Workbook

Sheet CONTENTS
A1: TABLE OF CONTENTS
A4: Bioenergy
A6: Ethanol
A7: Biodiesel
A8: Fats
A9: Renewable Diesel
A10: Renewable Jet Fuel
A11: Wood Pellets
A12: Waste to Energy
A13: Biogas
A14: Trade
A16: Biobased products
... A38: Canola

Sheet AG SUMMARY
A1: AGRICULTURE
A3: LAND USE | B3: 2010 | C3: 2011 | D3: 2012 | E3: 2013 | F3: 2014 | G3: 2015 | H3: 2016 | I3: 2017 | J3: 2018 | K3: 2019 | L3: 2020 | M3: 2021 | N3: 2022 | O3: 2023 | P3: 2024 | Q3: Source Name | R3: Source URL | S3: Comments
A4: Number of Farms in the United States (million farms) | B4: 2.14952 | C4: 2.13124 | D4: 2.10981 | E4: 2.10201 | F4: 2.085 | G4: 2.068 | H4: 2.06 | I4: 2.042 | J4: 2.0232 | K4: 2.0076 | L4: 1.9922 | M4: 1.95955 | N4: 1.90065 | O4: 1.89495 | P4: 1.88 | Q4: USDA | R4: https://esmis.nal.usda.gov/sites/default/release-files/5712m6524/z316rz25j/db78w849h/fnlo0225.pdf | S4: Retrieved January 2026
A5: Acreage of Agriculture in the United States (million acres) | B5: 915.66 | C5: 914.42 | D5: 914.6 | E5: 914.03 | F5: 913 | G5: 912 | H5: 911 | I5: 900.37 | J5: 898.86 | K5: 894.93 | L5: 893.11 | M5: 888.8 | N5: 879.66 | O5: 878.56 | P5: 876.46 | Q5: USDA | R5: https://esmis.nal.usda.gov/sites/default/release-files/5712m6524/z316rz25j/db78w849h/fnlo0225.pdf | S5: Retrieved January 2026
A6: U.S. Farmland Used as Permanent Pasture (million acres) | D6: 415.3 | I6: 401 | N6: 393 | Q6: USDA | R6: https://www.nass.usda.gov/Publications/Highlights/2024/Census22_HL_FarmsFarmland.pdf | S6: Retrieved January 2026
A7: U.S. Farmland Used as Cropland (million acres) | D7: 389.7 | I7: 396.43382 | N7: 382 | Q7: USDA | R7: https://www.nass.usda.gov/Publications/Highlights/2024/Census22_HL_FarmsFarmland.pdf | S7: Retrieved January 2026
A8: U.S. Cropland Harvested (million acres) | D8: 315 | I8: 320.04186 | N8: 301 | Q8: USDA | R8: https://www.nass.usda.gov/Publications/Highlights/2024/Census22_HL_FarmsFarmland.pdf | S8: Retrieved January 2026
A9: U.S. Farmland Used as Woodland (million acres) | D9: 77 | I9: 73 | N9: 72 | Q9: USDA | R9: https://www.nass.usda.gov/Publications/Highlights/2024/Census22_HL_FarmsFarmland.pdf | S9: Retrieved January 2026
A10: U.S. Farmland Used for other purposes (million acres) | D10: 32.5 | I10: 30 | N10: 33 | Q10: USDA | R10: https://www.nass.usda.gov/Publications/Highlights/2024/Census22_HL_FarmsFarmland.pdf | S10: Retrieved January 2026
A11: Average Farm Size (acres) | B11: 426 | C11: 429 | D11: 433 | E11: 435 | F11: 438 | G11: 441 | H11: 442 | I11: 441 | J11: 444 | K11: 446 | L11: 448 | M11: 454 | N11: 463 | O11: 464 | P11: 466 | Q11: USDA | R11: https://esmis.nal.usda.gov/sites/default/release-files/5712m6524/z316rz25j/db78w849h/fnlo0225.pdf | S11: Retrieved January 2026
A13: PRODUCTION + CONSUMPTION | B13: 2010 | C13: 2011 | D13: 2012 | E13: 2013 | F13: 2014 | G13: 2015 | H13: 2016 | I13: 2017 | J13: 2018 | K13: 2019 | L13: 2020 | M13: 2021 | N13: 2022 | O13: 2023 | P13: 2024 | Q13: Source Name | R13: Source URL | S13: Comments
A14: Agriculture Production (billion dollars) | B14: 191.09883 | C14: 211.35933 | D14: 223.86721 | E14: 210.17749 | F14: 194.80349 | G14: 179.1653 | H14: 185.66011 | I14: 187.8716 | J14: 185.33296 | K14: 174.04985 | L14: 206.44286 | M14: 257.23451 | N14: 263.01477 | O14: 233.4698 | Q14: USDA | R14: https://quickstats.nass.usda.gov/results/FE8787AE-F141-38C3-A8D7-17EC943640FB | S14: Retrieved January 2026
A15: Agriculture Exports (billion dollars) | B15: 118.719 | C15: 142.129 | D15: 145.918 | E15: 148.483 | F15: 154.542 | G15: 137.216 | H15: 138.903 | I15: 142.866 | J15: 144.733 | K15: 141.082 | L15: 149.672 | M15: 176.631 | N15: 195.68 | O15: 174.172 | P15: 175.979 | Q15: USDA | R15: https://www.ers.usda.gov/data-products/foreign-agricultural-trade-of-the-united-states-fatus/calendar-year | S15: Retrieved January 2026
A16: Agriculture Imports (billion dollars) | B16: 85.582 | C16: 102.033 | D16: 108.762 | E16: 111.002 | F16: 118.73 | G16: 121.122 | H16: 122.569 | I16: 129.21 | J16: 137.991 | K16: 141.562 | L16: 146.282 | M16: 170.595 | N16: 198.243 | O16: 194.842 | P16: 213 | Q16: USDA | R16: https://www.ers.usda.gov/data-products/foreign-agricultural-trade-of-the-united-states-fatus/calendar-year | S16: Retrieved January 2026
A18: ECONOMICS | B18: 2010 | C18: 2011 | D18: 2012 | E18: 2013 | F18: 2014 | G18: 2015 | H18: 2016 | I18: 2017 | J18: 2018 | K18: 2019 | L18: 2020 | M18: 2021 | N18: 2022 | O18: 2023 | P18: 2024 | Q18: Source Name | R18: Source URL | S18: Comments
A19: Net cash income (billion dollars) | B19: 96.335985 | C19: 123.21526 | D19: 135.27696 | E19: 135.55843 | F19: 131.55399 | G19: 106.19768 | H19: 95.56963 | I19: 101.26836 | J19: 103.47687 | K19: 109.15947 | L19: 120.87738 | M19: 155.19729 | N19: 210.04299 | O19: 156.74038 | P19: 140.55826 | Q19: USDA | R19: https://www.ers.usda.gov/data-products/farm-income-and-wealth-statistics/data-files-us-and-state-level-farm-income-and-wealth-statistics | S19: Retrieved January 2026
A20: Net farm income (billion dollars) | B20: 77.098341 | C20: 113.59305 | D20: 96.455951 | E20: 123.75284 | F20: 92.429956 | G20: 81.364081 | H20: 62.31452 | I20: 75.727325 | J20: 82.395831 | K20: 82.000034 | L20: 98.866384 | M20: 146.33148 | N20: 181.95228 | O20: 147.28189 | P20: 127.82734 | Q20: USDA | R20: https://www.ers.usda.gov/data-products/farm-income-and-wealth-statistics/data-files-us-and-state-level-farm-income-and-wealth-statistics | S20: Retrieved January 2026
A21: Total Farm Assets (billion dollars) | B21: 2170.8321 | C21: 2318.7202 | D21: 2638.2372 | E21: 2776.1096 | F21: 2949.2385 | G21: 2909.6532 | H21: 2914.4409 | I21: 3005.9449 | J21: 3019.1396 | K21: 3049.0815 | L21: 3130.5056 | M21: 3424.1307 | N21: 3788.4202 | O21: 4014.3413 | P21: 4218.2092 | Q21: USDA | R21: https://www.ers.usda.gov/data-products/farm-income-and-wealth-statistics/data-files-us-and-state-level-farm-income-and-wealth-statistics | S21: Retrieved January 2026
A22: Total Farm Debt (billion dollars) | B22: 278.93053 | C22: 294.47213 | D22: 297.52112 | E22: 315.33249 | F22: 345.20135 | G22: 356.73804 | H22: 374.16421 | I22: 390.42522 | J22: 402.6055 | K22: 420.4948 | L22: 441.25379 | M22: 474.30511 | N22: 496.14235 | O22: 519.29942 | P22: 563.47872 | Q22: USDA | R22: https://www.ers.usda.gov/data-products/farm-income-and-wealth-statistics/data-files-us-and-state-level-farm-income-and-wealth-statistics | S22: Retrieved January 2026
A23: Total Farm Equity (billion dollars) | B23: 1891.9016 | C23: 2024.248 | D23: 2340.7161 | E23: 2460.7771 | F23: 2604.0371 | G23: 2552.9151 | H23: 2540.2767 | I23: 2615.5196 | J23: 2616.5341 | K23: 2628.5867 | L23: 2689.2518 | M23: 2949.8256 | N23: 3292.2779 | O23: 3495.0419 | P23: 3654.7305 | Q23: USDA | R23: https://www.ers.usda.gov/data-products/farm-income-and-wealth-statistics/data-files-us-and-state-level-farm-income-and-wealth-statistics | S23: Retrieved January 2026
A24: Value Added of Farms (billion dollars) | B24: 117 | C24: 151.1 | D24: 148.8 | E24: 184.5 | F24: 167.1 | G24: 146.3 | H24: 130.3 | I24: 138.7 | J24: 136.8 | K24: 122.6 | L24: 120.5 | M24: 185.7 | N24: 247.1 | O24: 218.2 | P24: 215.8 | Q24: Census Bureau | R24: https://apps.bea.gov/iTable/?reqid=1603&step=2&Categories=GDPxInd&isURI=1&_gl=1*bg4lgp*_ga*MTU2MDMwOTkxNy4xNzY3ODk4NTU4*_ga_J4698JNNFT*czE3Njc5NzYxNDUkbzMkZzEkdDE3Njc5NzYxNjYkajM5JGwwJGgw#eyJhcHBpZCI6MTYwMywic3RlcHMiOlsxLDIsNCw0XSwiZGF0YSI6W1siY2F0ZWdvcmllcyIsIkdEUHhJbmQiXSxbIlRhYmxlX0xpc3QiLCJUVkExMDUiXSxbIlNjYWxlIiwiLTkiXSxbIkZpcnN0X1llYXIiLCIyMDEwIl0sWyJMYXN0X1llYXIiLCIyMDI1Il0sWyJSb3dzIixbIjIyUiIsIkdEUCIsIlBWVCIsIjExIiwiMTExQ0EiLCIxMTNGRiIsIjIxIiwiMjExIiwiMjEyIiwiMjEzIiwiMjIiLCIyMyIsIjMxRyIsIjMzREciLCIzMjEiLCIzMjciLCIzMzEiLCIzMzIiLCIzMzMiLCIzMzQiLCIzMzUiLCIzMzYxTVYiLCIzMzY0T1QiLCIzMzciLCIzMzkiLCIzMU5EIiwiMzExRlQiLCIzMTNUVCIsIjMxNUFMIiwiMzIyIiwiMzIzIiwiMzI0IiwiMzI1IiwiMzI2IiwiNDIiLCI0NFJUIiwiNDQxIiwiNDQ1IiwiNDUyIiwiNEEwIiwiNDhUVyIsIjQ4MSIsIjQ4MiIsIjQ4MyIsIjQ4NCIsIjQ4NSIsIjQ4NiIsIjQ4N09TIiwiNDkzIiwiNTEiLCI1MTEiLCI1MTIiLCI1MTMiLCI1MTQiLCJGSVJFIiwiNTIiLCI1MjFDSSIsIjUyMyIsIjUyNCIsIjUyNSIsIjUzIiwiNTMxIiwiSFMiLCJPUkUiLCI1MzJSTCIsIlBST0YiLCI1NCIsIjU0MTEiLCI1NDE1IiwiNTQxMk9QIiwiNTUiLCI1NiIsIjU2MSIsIjU2MiIsIjYiLCI2MSIsIjYyIiwiNjIxIiwiNjIyIiwiNjIzIiwiNjI0IiwiNyIsIjcxIiwiNzExQVMiLCI3MTMiLCI3MiIsIjcyMSIsIjcyMiIsIjgxIiwiRyIsIkdGIiwiR0ZHIiwiR0ZHRCIsIkdGR04iLCJHRkUiLCJHU0wiLCJHU0xHIiwiR1NMRSIsIiIsIlBHT09EIiwiUFNFUlYiLCJJQ1QiXV0sWyJTZXJpZXMiLCJBIl0sWyJDb2x1bW5zIixbIjIwMjAiXV1dfQ== | S24: Retrieved January 2026
A25: Gross Output of Farms (billion dollars) | B25: 320.9 | C25: 380.3 | D25: 404.2 | E25: 437.6 | F25: 442.2 | G25: 403.2 | H25: 379.8 | I25: 395.5 | J25: 395.1 | K25: 388.1 | L25: 390.9 | M25: 475.4 | N25: 576.7 | O25: 570 | P25: 565.7 | Q25: Census Bureau | R25: https://apps.bea.gov/iTable/?reqid=1603&step=2&Categories=GDPxInd&isURI=1&_gl=1*bg4lgp*_ga*MTU2MDMwOTkxNy4xNzY3ODk4NTU4*_ga_J4698JNNFT*czE3Njc5NzYxNDUkbzMkZzEkdDE3Njc5NzYxNjYkajM5JGwwJGgw#eyJhcHBpZCI6MTYwMywic3RlcHMiOlsxLDIsNCw0XSwiZGF0YSI6W1siY2F0ZWdvcmllcyIsIkdEUHhJbmQiXSxbIlRhYmxlX0xpc3QiLCJUVkExMDUiXSxbIlNjYWxlIiwiLTkiXSxbIkZpcnN0X1llYXIiLCIyMDEwIl0sWyJMYXN0X1llYXIiLCIyMDI1Il0sWyJSb3dzIixbIjIyUiIsIkdEUCIsIlBWVCIsIjExIiwiMTExQ0EiLCIxMTNGRiIsIjIxIiwiMjExIiwiMjEyIiwiMjEzIiwiMjIiLCIyMyIsIjMxRyIsIjMzREciLCIzMjEiLCIzMjciLCIzMzEiLCIzMzIiLCIzMzMiLCIzMzQiLCIzMzUiLCIzMzYxTVYiLCIzMzY0T1QiLCIzMzciLCIzMzkiLCIzMU5EIiwiMzExRlQiLCIzMTNUVCIsIjMxNUFMIiwiMzIyIiwiMzIzIiwiMzI0IiwiMzI1IiwiMzI2IiwiNDIiLCI0NFJUIiwiNDQxIiwiNDQ1IiwiNDUyIiwiNEEwIiwiNDhUVyIsIjQ4MSIsIjQ4MiIsIjQ4MyIsIjQ4NCIsIjQ4NSIsIjQ4NiIsIjQ4N09TIiwiNDkzIiwiNTEiLCI1MTEiLCI1MTIiLCI1MTMiLCI1MTQiLCJGSVJFIiwiNTIiLCI1MjFDSSIsIjUyMyIsIjUyNCIsIjUyNSIsIjUzIiwiNTMxIiwiSFMiLCJPUkUiLCI1MzJSTCIsIlBST0YiLCI1NCIsIjU0MTEiLCI1NDE1IiwiNTQxMk9QIiwiNTUiLCI1NiIsIjU2MSIsIjU2MiIsIjYiLCI2MSIsIjYyIiwiNjIxIiwiNjIyIiwiNjIzIiwiNjI0IiwiNyIsIjcxIiwiNzExQVMiLCI3MTMiLCI3MiIsIjcyMSIsIjcyMiIsIjgxIiwiRyIsIkdGIiwiR0ZHIiwiR0ZHRCIsIkdGR04iLCJHRkUiLCJHU0wiLCJHU0xHIiwiR1NMRSIsIiIsIlBHT09EIiwiUFNFUlYiLCJJQ1QiXV0sWyJTZXJpZXMiLCJBIl0sWyJDb2x1bW5zIixbIjIwMjAiXV1dfQ== | S25: Retrieved January 2026
A26: Value Addes as percentage of GDP farms (%) | B26: 0.8 | C26: 1 | D26: 0.9 | E26: 1.1 | F26: 0.9 | G26: 0.8 | H26: 0.7 | I26: 0.7 | J26: 0.7 | K26: 0.6 | L26: 0.6 | M26: 0.8 | N26: 0.9 | O26: 0.8 | P26: 0.7 | Q26: Census Bureau | R26: https://apps.bea.gov/iTable/?reqid=1603&step=2&Categories=GDPxInd&isURI=1&_gl=1*bg4lgp*_ga*MTU2MDMwOTkxNy4xNzY3ODk4NTU4*_ga_J4698JNNFT*czE3Njc5NzYxNDUkbzMkZzEkdDE3Njc5NzYxNjYkajM5JGwwJGgw#eyJhcHBpZCI6MTYwMywic3RlcHMiOlsxLDIsNCw0XSwiZGF0YSI6W1siY2F0ZWdvcmllcyIsIkdEUHhJbmQiXSxbIlRhYmxlX0xpc3QiLCJUVkExMDUiXSxbIlNjYWxlIiwiLTkiXSxbIkZpcnN0X1llYXIiLCIyMDEwIl0sWyJMYXN0X1llYXIiLCIyMDI1Il0sWyJSb3dzIixbIjIyUiIsIkdEUCIsIlBWVCIsIjExIiwiMTExQ0EiLCIxMTNGRiIsIjIxIiwiMjExIiwiMjEyIiwiMjEzIiwiMjIiLCIyMyIsIjMxRyIsIjMzREciLCIzMjEiLCIzMjciLCIzMzEiLCIzMzIiLCIzMzMiLCIzMzQiLCIzMzUiLCIzMzYxTVYiLCIzMzY0T1QiLCIzMzciLCIzMzkiLCIzMU5EIiwiMzExRlQiLCIzMTNUVCIsIjMxNUFMIiwiMzIyIiwiMzIzIiwiMzI0IiwiMzI1IiwiMzI2IiwiNDIiLCI0NFJUIiwiNDQxIiwiNDQ1IiwiNDUyIiwiNEEwIiwiNDhUVyIsIjQ4MSIsIjQ4MiIsIjQ4MyIsIjQ4NCIsIjQ4NSIsIjQ4NiIsIjQ4N09TIiwiNDkzIiwiNTEiLCI1MTEiLCI1MTIiLCI1MTMiLCI1MTQiLCJGSVJFIiwiNTIiLCI1MjFDSSIsIjUyMyIsIjUyNCIsIjUyNSIsIjUzIiwiNTMxIiwiSFMiLCJPUkUiLCI1MzJSTCIsIlBST0YiLCI1NCIsIjU0MTEiLCI1NDE1IiwiNTQxMk9QIiwiNTUiLCI1NiIsIjU2MSIsIjU2MiIsIjYiLCI2MSIsIjYyIiwiNjIxIiwiNjIyIiwiNjIzIiwiNjI0IiwiNyIsIjcxIiwiNzExQVMiLCI3MTMiLCI3MiIsIjcyMSIsIjcyMiIsIjgxIiwiRyIsIkdGIiwiR0ZHIiwiR0ZHRCIsIkdGR04iLCJHRkUiLCJHU0wiLCJHU0xHIiwiR1NMRSIsIiIsIlBHT09EIiwiUFNFUlYiLCJJQ1QiXV0sWyJTZXJpZXMiLCJBIl0sWyJDb2x1bW5zIixbIjIwMjAiXV1dfQ== | S26: Retrieved January 2026
A27: Full time and part time employees by farms (Thousands) | B27: 754 | C27: 763 | D27: 780 | E27: 789 | F27: 803 | G27: 817 | H27: 820 | I27: 819 | J27: 814 | K27: 813 | L27: 809 | M27: 811 | N27: 814 | O27: 813 | P27: 811 | Q27: Census Bureau | R27: https://apps.bea.gov/iTable/?reqid=1603&step=2&Categories=GDPxInd&isURI=1&_gl=1*bg4lgp*_ga*MTU2MDMwOTkxNy4xNzY3ODk4NTU4*_ga_J4698JNNFT*czE3Njc5NzYxNDUkbzMkZzEkdDE3Njc5NzYxNjYkajM5JGwwJGgw#eyJhcHBpZCI6MTYwMywic3RlcHMiOlsxLDIsNCw0XSwiZGF0YSI6W1siY2F0ZWdvcmllcyIsIkdEUHhJbmQiXSxbIlRhYmxlX0xpc3QiLCJUVkExMDUiXSxbIlNjYWxlIiwiLTkiXSxbIkZpcnN0X1llYXIiLCIyMDEwIl0sWyJMYXN0X1llYXIiLCIyMDI1Il0sWyJSb3dzIixbIjIyUiIsIkdEUCIsIlBWVCIsIjExIiwiMTExQ0EiLCIxMTNGRiIsIjIxIiwiMjExIiwiMjEyIiwiMjEzIiwiMjIiLCIyMyIsIjMxRyIsIjMzREciLCIzMjEiLCIzMjciLCIzMzEiLCIzMzIiLCIzMzMiLCIzMzQiLCIzMzUiLCIzMzYxTVYiLCIzMzY0T1QiLCIzMzciLCIzMzkiLCIzMU5EIiwiMzExRlQiLCIzMTNUVCIsIjMxNUFMIiwiMzIyIiwiMzIzIiwiMzI0IiwiMzI1IiwiMzI2IiwiNDIiLCI0NFJUIiwiNDQxIiwiNDQ1IiwiNDUyIiwiNEEwIiwiNDhUVyIsIjQ4MSIsIjQ4MiIsIjQ4MyIsIjQ4NCIsIjQ4NSIsIjQ4NiIsIjQ4N09TIiwiNDkzIiwiNTEiLCI1MTEiLCI1MTIiLCI1MTMiLCI1MTQiLCJGSVJFIiwiNTIiLCI1MjFDSSIsIjUyMyIsIjUyNCIsIjUyNSIsIjUzIiwiNTMxIiwiSFMiLCJPUkUiLCI1MzJSTCIsIlBST0YiLCI1NCIsIjU0MTEiLCI1NDE1IiwiNTQxMk9QIiwiNTUiLCI1NiIsIjU2MSIsIjU2MiIsIjYiLCI2MSIsIjYyIiwiNjIxIiwiNjIyIiwiNjIzIiwiNjI0IiwiNyIsIjcxIiwiNzExQVMiLCI3MTMiLCI3MiIsIjcyMSIsIjcyMiIsIjgxIiwiRyIsIkdGIiwiR0ZHIiwiR0ZHRCIsIkdGR04iLCJHRkUiLCJHU0wiLCJHU0xHIiwiR1NMRSIsIiIsIlBHT09EIiwiUFNFUlYiLCJJQ1QiXV0sWyJTZXJpZXMiLCJBIl0sWyJDb2x1bW5zIixbIjIwMjAiXV1dfQ== | S27: Retrieved January 2026
A29: ENVIRONMENTAL | B29: 2010 | C29: 2011 | D29: 2012 | E29: 2013 | F29: 2014 | G29: 2015 | H29: 2016 | I29: 2017 | J29: 2018 | K29: 2019 | L29: 2020 | M29: 2021 | N29: 2022 | O29: 2023 | P29: 2024 | Q29: Source Name | R29: Source URL | S29: Comments
A30: Fertilizer Consumption in US (million metric tons) | B30: 19.7923 | C30: 20.3628 | D30: 20.8613 | E30: 21.0868 | F30: 19.9778 | G30: 20.0757 | H30: 20.714 | I30: 20.99 | J30: 19.689 | K30: 20.55 | L30: 20.1804 | M30: 18.7322 | N30: 20.5066 | O30: 20.1377 | Q30: IFA | R30: https://www.ifastat.org/databases/plant-nutrition | S30: Retrieved January 2026
A31: Nitrogen products (million metric tons) | B31: 11.737 | C31: 12.2314 | D31: 12.1879 | E31: 12.0607 | F31: 11.8167 | G31: 11.6831 | H31: 11.7514 | I31: 11.8153 | J31: 11.602 | K31: 11.949 | L31: 11.8626 | M31: 11.1641 | N31: 12.0008 | O31: 11.6201 | Q31: IFA | R31: https://www.ifastat.org/databases/plant-nutrition | S31: Retrieved January 2026
A32: Phosphate products (million metric tons) | B32: 3.8902 | C32: 3.9456 | D32: 4.2886 | E32: 4.2601 | F32: 3.8741 | G32: 3.9198 | H32: 4.0908 | I32: 4.2974 | J32: 3.767 | K32: 4.087 | L32: 3.7708 | M32: 3.5238 | N32: 3.895 | O32: 3.8874 | Q32: IFA | R32: https://www.ifastat.org/databases/plant-nutrition | S32: Retrieved January 2026
A33: Potash products (million metric tons) | B33: 4.1651 | C33: 4.1858 | D33: 4.3848 | E33: 4.766 | F33: 4.287 | G33: 4.4728 | H33: 4.8718 | I33: 4.8773 | J33: 4.32 | K33: 4.514 | L33: 4.547 | M33: 4.0443 | N33: 4.6108 | O33: 4.6302 | Q33: IFA | R33: https://www.ifastat.org/databases/plant-nutrition | S33: Retrieved January 2026
A34: WATER | B34: 2010 | C34: 2011 | D34: 2012 | E34: 2013 | F34: 2014 | G34: 2015 | H34: 2016 | I34: 2017 | J34: 2018 | K34: 2019 | L34: 2020 | M34: 2021 | N34: 2022 | O34: 2023 | P34: 2024 | Q34: Source Name | R34: Source URL | S34: Comments
A35: Irrigated Land in the U.S. (million acres) | B35: 62.38349 | G35: 63.5 | Q35: USGS | R35: [2010] https://pubs.usgs.gov/circ/1405/pdf/circ1405.pdf [2015] https://pubs.usgs.gov/circ/1441/circ1441.pdf | S35: Retrieved June 2018 Retrieved October 2018
A36: Withdrawals (million acre-feet year) | B36: 129.16531 | G36: 132 | Q36: USGS | R36: [2010] https://pubs.usgs.gov/circ/1405/pdf/circ1405.pdf [2015] https://pubs.usgs.gov/circ/1441/circ1441.pdf | S36: Retrieved June 2018 Retrieved October 2018
A37: Groundwater withdrawals (million acre-feet year) | B37: 55.40511 | G37: 64.1 | Q37: USGS | R37: [2010] https://pubs.usgs.gov/circ/1405/pdf/circ1405.pdf [2015] https://pubs.usgs.gov/circ/1441/circ1441.pdf | S37: Retrieved June 2018 Retrieved October 2018
A38: Surface water withdrawals (million acre-feet year) | B38: 73.86284 | G38: 68.3 | Q38: USGS | R38: [2010] https://pubs.usgs.gov/circ/1405/pdf/circ1405.pdf [2015] https://pubs.usgs.gov/circ/1441/circ1441.pdf | S38: Retrieved June 2018 Retrieved October 2018

Sheet CORN
A1: CORN
A3: PHYSICAL | B3: 2010 | C3: 2011 | D3: 2012 | E3: 2013 | F3: 2014 | G3: 2015 | H3: 2016 | I3: 2017 | J3: 2018 | K3: 2019 | L3: 2020 | M3: 2021 | N3: 2022 | O3: 2023 | P3: 2024 | Q3: Source Name | R3: Source URL | S3: Comments
A4: Number of Farms Growing Corn in the United States (thousand farms) | D4: 376.179 | I4: 328.101 | N4: 306.053 | Q4: USDA | R4: https://quickstats.nass.usda.gov/results/453C1E4E-CA2D-37D4-AE93-56531E28FED8 | S4: Retrieved January 2026
A5: Planted Acreage of Corn in the United States (million acres) | B5: 90.909 | C5: 94.641 | D5: 88.162 | E5: 92.901 | F5: 90.432 | G5: 89.37 | H5: 88.821 | I5: 90.167 | J5: 94.004 | K5: 88.019 | L5: 90.597 | M5: 95.365 | N5: 97.291 | O5: 91.936 | P5: 88.192 | Q5: USDA-NASS | R5: https://quickstats.nass.usda.gov/results/5C42EA33-506B-37F7-871A-178A7B2FDB70 | S5: Retrieved January 2026
A6: Yield of Corn grown in U.S. (metric tons per acre) | B6: 4.0525247 | C6: 4.0525247 | D6: 5.4363136 | E6: 5.4363136 | F6: 6.1529186 | G6: 5.312761 | H6: 5.0656558 | I6: 3.2123671 | J6: 3.6818669 | K6: 4.8185507 | L6: 4.7938402 | M6: 4.6949981 | N6: 5.5351557 | O6: 4.7691296 | P6: 4.7691296 | Q6: USDA-PSD | R6: https://apps.fas.usda.gov/psdonline/app/index.html#/app/downloads | S6: Retrieved January 2026 1 acre=0.404686 Ha
A7: Planted acreage of corn for ethanol production in the United States (million acres) | B7: =B19/B6 -> 28.32282 | C7: =C19/C6 -> 30.960583 | D7: =D19/D6 -> 22.99367 | E7: =E19/E6 -> 21.343172 | F7: =F19/F6 -> 20.818129 | G7: =G19/G6 -> 24.46981 | H7: =H19/H6 -> 25.779554 | I7: =I19/I6 -> 42.273756 | ... P7: =P19/P6 -> 28.771382 | Q7: Calculation
A9: PRODUCTION | B9: 2010 | C9: 2011 | D9: 2012 | E9: 2013 | F9: 2014 | G9: 2015 | H9: 2016 | I9: 2017 | J9: 2018 | K9: 2019 | L9: 2020 | M9: 2021 | N9: 2022 | O9: 2023 | P9: 2024 | Q9: Source Name | R9: Source URL | S9: Comments
A10: Total Volume of Corn Grown in the US (million metric tons) | B10: 315.618 | C10: 312.789 | D10: 273.192 | E10: 351.316 | F10: 361.136 | G10: 345.506 | H10: 384.778 | I10: 371.096 | J10: 363.787 | K10: 344.651 | L10: 357.819 | M10: 381.469 | N10: 346.739 | O10: 389.667 | P10: 378.268 | Q10: USDA | R10: https://apps.fas.usda.gov/psdonline/app/index.html#/app/downloads | S10: Retrieved January 2026
A11: Total Volume of Corn consumption (million metric tons) | B11: 284.549 | C11: 277.961 | D11: 262.973 | E11: 293.002 | F11: 301.837 | G11: 298.845 | H11: 313.785 | I11: 313.991 | J11: 309.503 | K11: 306.45 | L11: 308.215 | M11: 315.665 | N11: 305.931 | O11: 322.873 | P11: 312.102 | Q11: USDA | R11: https://apps.fas.usda.gov/psdonline/app/index.html#/app/downloads | S11: Retrieved January 2026
A12: Corn imports (million metric tons) | B12: 0.703 | C12: 0.746 | D12: 4.063 | E12: 0.909 | F12: 0.804 | G12: 1.716 | H12: 1.45 | I12: 0.915 | J12: 0.71 | K12: 1.064 | L12: 0.616 | M12: 0.615 | N12: 0.982 | O12: 0.722 | P12: 0.55 | Q12: USDA | R12: https://apps.fas.usda.gov/psdonline/app/index.html#/app/downloads | S12: Retrieved January 2026
A13: Corn exports (million metric tons) | B13: 46.508 | C13: 39.096 | D13: 18.545 | E13: 48.79 | F13: 47.421 | G13: 48.228 | H13: 58.313 | I13: 61.906 | J13: 52.538 | K13: 45.175 | L13: 69.775 | M13: 62.802 | N13: 42.214 | O13: 57.275 | P13: 72.603 | Q13: USDA | R13: https://apps.fas.usda.gov/psdonline/app/index.html#/app/downloads | S13: Retrieved January 2026
A14: Beginning stocks (million metric tons) | B14: 43.38 | C14: 28.644 | D14: 25.122 | E14: 20.859 | F14: 31.292 | G14: 43.974 | H14: 44.123 | I14: 58.253 | J14: 54.367 | K14: 56.823 | L14: 50.913 | M14: 31.358 | N14: 34.975 | O14: 34.551 | P14: 44.792 | Q14: USDA | R14: https://apps.fas.usda.gov/psdonline/app/index.html#/app/downloads | S14: Retrieved January 2026
A15: Ending stocks (million metric tons) | B15: 28.644 | C15: 25.122 | D15: 20.859 | E15: 31.292 | F15: 43.974 | G15: 44.123 | H15: 58.253 | I15: 54.367 | J15: 56.823 | K15: 50.913 | L15: 31.358 | M15: 34.975 | N15: 34.551 | O15: 44.792 | P15: 38.905 | Q15: USDA | R15: https://apps.fas.usda.gov/psdonline/app/index.html#/app/downloads | S15: Retrieved January 2026
A16: Uses
A17: Total Volume of Corn Consumed for Feed (million metric tons) | B17: 127.3894 | C17: 119.25295 | D17: 112.80173 | E17: 107.71598 | F17: 125.10442 | G17: 132.186 | H17: 127.94635 | I17: 136.69875 | J17: 132.61495 | K17: 134.80273 | L17: 144.45947 | M17: 141.68495 | N17: 141.76263 | O17: 137.14748 | P17: 145.79458 | Q17: USDA | R17: https://www.ers.usda.gov/data-products/feed-grains-database/feed-grains-yearbook-tables.aspx | S17: Retrieved January 2026 1 bushel of corn=0.025 metric tons
A18: Total Volume of Corn Consumed for Food, alcohol and industrial use (million metric tons): | B18: 148.46665 | C18: 160.06305 | D18: 159.99335 | E18: 150.33023 | F18: 162.52742 | G18: 164.15252 | H18: 165.4148 | I18: 171.39798 | J18: 175.67863 | K18: 169.08925 | L18: 156.40533 | M18: 160.8963 | N18: 168.19043 | O18: 163.16168 | P18: 171.235 | Q18: USDA | R18: https://www.ers.usda.gov/data-products/feed-grains-database/feed-grains-yearbook-tables.aspx | S18: Retrieved January 2026 1 bushel of corn=0.025 metric tons
A19: Corn Processed into Fuel Alcohol (million metric tons) | B19: 114.77893 | C19: 125.46852 | D19: 125.0008 | E19: 116.02818 | F19: 128.09225 | G19: 130.00225 | H19: 130.59035 | I19: 135.79883 | J19: 140.12068 | K19: 134.45065 | L19: 121.41688 | M19: 125.68988 | N19: 132.99038 | O19: 129.3913 | P19: 137.21445 | Q19: USDA | R19: https://www.ers.usda.gov/data-products/feed-grains-database/feed-grains-yearbook-tables.aspx | S19: Retrieved January 2026 1 bushel of corn=0.025 metric tons
A20: Corn Processed into High Fructose Corn Syrup (million metric tons) | B20: 12.803125 | C20: 13.026225 | D20: 12.7901 | E20: 12.287175 | F20: 11.94345 | G20: 11.952475 | H20: 11.80645 | I20: 11.6744 | J20: 11.481275 | K20: 11.035475 | L20: 10.45515 | M20: 10.51435 | N20: 10.384925 | O20: 10.222675 | P20: 10.44365 | Q20: USDA | R20: https://www.ers.usda.gov/data-products/feed-grains-database/feed-grains-yearbook-tables.aspx | S20: Retrieved January 2026 1 bushel of corn=0.025 metric tons
A21: Corn Processed into Glucose and Dextrose (million metric tons) | B21: 6.4321 | C21: 6.808925 | D21: 7.358975 | E21: 7.298 | F21: 7.67865 | G21: 7.451725 | H21: 8.425975 | I21: 9.2836 | J21: 9.2893 | K21: 8.8778 | L21: 8.904775 | M21: 9.117825 | N21: 9.2758 | O21: 8.594925 | P21: 8.409275 | Q21: USDA | R21: https://www.ers.usda.gov/data-products/feed-grains-database/feed-grains-yearbook-tables.aspx | S21: Retrieved January 2026 1 bushel of corn=0.025 metric tons
A22: Corn Processed into Starch (million metric tons) | B22: 6.260925 | C22: 6.459375 | D22: 6.35025 | E22: 6.234725 | F22: 6.263675 | G22: 6.161175 | H22: 5.939525 | I22: 5.88365 | J22: 5.894875 | K22: 5.762825 | L22: 5.806025 | M22: 6.29425 | N22: 6.154325 | O22: 5.482775 | P22: 5.567625 | Q22: USDA | R22: https://www.ers.usda.gov/data-products/feed-grains-database/feed-grains-yearbook-tables.aspx | S22: Retrieved January 2026 1 bushel of corn=0.025 metric tons
A23: Corn Used as Cereal (million metric tons) | B23: 4.841575 | C23: 4.925 | D23: 5.080725 | E23: 4.9855 | F23: 5.01195 | G23: 5.030225 | H23: 5.0775 | I23: 5.1075 | J23: 5.1675 | K23: 5.2125 | L23: 5.4975 | M23: 5.355 | N23: 5.36 | O23: 5.42 | P23: 5.475 | Q23: USDA | R23: https://www.ers.usda.gov/data-products/feed-grains-database/feed-grains-yearbook-tables.aspx | S23: Retrieved January 2026 1 bushel of corn=0.025 metric tons
A24: Corn Processed into Alcoholic Beverages (million metric tons) | B24: 3.35 | C24: 3.375 | D24: 3.4125 | E24: 3.5 | F24: 3.53745 | G24: 3.554675 | H24: 3.575 | I24: 3.65 | J24: 3.725 | K24: 3.75 | L24: 4.325 | M24: 3.925 | N24: 4.025 | O24: 4.05 | P24: 4.125 | Q24: USDA | R24: https://www.ers.usda.gov/data-products/feed-grains-database/feed-grains-yearbook-tables.aspx | S24: Retrieved January 2026 1 bushel of corn=0.025 metric tons
A25: Corn Saved for Seed (million metric tons) | B25: 0.693875 | C25: 0.7394 | D25: 0.774675 | E25: 0.774075 | F25: 0.74305 | G25: 0.731375 | H25: 0.763875 | I25: 0.7326 | J25: 0.738275 | K25: 0.723475 | L25: 0.744425 | M25: 0.764675 | N25: 0.7279 | O25: 0.79055 | P25: 0.743275 | Q25: USDA | R25: https://www.ers.usda.gov/data-products/feed-grains-database/feed-grains-yearbook-tables.aspx | S25: Retrieved January 2026 1 bushel of corn=0.025 metric tons
A26: Corn into Biofuels
A27: Ethanol production as percent of total corn use | B27: =B19/B10 -> 0.36366407 | C27: =C19/C10 -> 0.40112832 | D27: =D19/D10 -> 0.45755659 | E27: =E19/E10 -> 0.33026727 | F27: =F19/F10 -> 0.35469255 | G27: =G19/G10 -> 0.37626626 | H27: =H19/H10 -> 0.33939142 | I27: =I19/I10 -> 0.36593988 | ... P27: =P19/P10 -> 0.36274401 | Q27: Calculation
A28: Corn Oil Going to Biodiesel (million metric tons) | B28: 0.050801438 | C28: 0.13788962 | D28: 0.25899662 | E28: 0.484428 | F28: 0.43997674 | G28: 0.47354198 | H28: 0.59238105 | I28: 0.71620956 | J28: 0.94573932 | K28: 0.79832192 | L28: 0.68764547 | P28: 1.9663213 | Q28: EIA | R28: https://www.eia.gov/biofuels/biodiesel/production/archive/
A30: ECONOMICS | B30: 2010 | C30: 2011 | D30: 2012 | E30: 2013 | F30: 2014 | G30: 2015 | H30: 2016 | I30: 2017 | J30: 2018 | K30: 2019 | L30: 2020 | M30: 2021 | N30: 2022 | O30: 2023 | P30: 2024 | Q30: Source Name | R30: Source URL | S30: Comments
A31: Corn Prices (dollars per metric ton) | B31: 207.2 | C31: 248.8 | D31: 275.6 | E31: 178.4 | F31: 148 | G31: 144.4 | H31: 134.4 | I31: 134.4 | J31: 144.4 | K31: 142.4 | L31: 181.2 | M31: 240 | N31: 261.6 | O31: 182 | P31: 169.6 | Q31: USDA-NASS | R31: https://quickstats.nass.usda.gov/results/B064DE81-3626-3F18-B562-BBF6B877613A | S31: Retrieved January 2026 1 bushel of corn=0.025 metric tons
A32: Corn Oil Price (dollars per metric ton) | B32: 866.1952 | C32: 1339.5271 | D32: 1236.5714 | E32: 1028.6757 | F32: 869.28167 | G32: 826.29158 | H32: 865.31335 | I32: 824.72078 | J32: 670.08966 | K32: 593.79603 | L32: 871.67 | M32: 1199.3868 | N32: 1416.8477 | O32: 1358.4097 | P32: 1036.1714 | Q32: USDA-ERS (Oil Crops Outlook 2018) | R32: https://www.ers.usda.gov/publications/pub-details/?pubid=86740 | S32: Retrieved April 2018 1 metric ton = 2,204.622 pounds
A33: Direct Value of All Corn Grown in the United States (billion dollars) | B33: 64.529628 | C33: 76.651242 | D33: 74.155299 | E33: 61.935222 | F33: 52.958412 | G33: 49.339261 | H33: 51.304297 | I33: 49.567854 | J33: 52.029758 | K33: 48.737123 | L33: 64.197149 | M33: 90.264369 | N33: 89.452876 | O33: 70.085591 | P33: 64.672613 | Q33: USDA-NASS | R33: https://quickstats.nass.usda.gov/results/6470F0BD-2744-3376-97E7-7B7F46D09C66 | S33: Retrieved January 2026
A34: Value of Corn Used for Starch Ethanol (billion dollars) | B34: =B19*B31/1000 -> 23.782193 | C34: =C19*C31/1000 -> 31.216569 | D34: =D19*D31/1000 -> 34.45022 | E34: =E19*E31/1000 -> 20.699426 | F34: =F19*F31/1000 -> 18.957653 | G34: =G19*G31/1000 -> 18.772325 | H34: =H19*H31/1000 -> 17.551343 | I34: =I19*I31/1000 -> 18.251362 | ... P34: =P19*P31/1000 -> 23.271571 | Q34: Calculation
A35: Value of Corn Used for Biodiesel (billion dollars) | B35: =B28*B32/1000 -> 0.044003962 | C35: =C28*C32/1000 -> 0.18470688 | D35: =D28*D32/1000 -> 0.3202678 | E35: =E28*E32/1000 -> 0.49831931 | F35: =F28*F32/1000 -> 0.38246371 | G35: =G28*G32/1000 -> 0.39128375 | H35: =H28*H32/1000 -> 0.51259523 | I35: =I28*I32/1000 -> 0.59067291 | ... P35: =P28*P32/1000 -> 2.0374459 | Q35: Calculation
A37: ENVIRONMENTAL | B37: 2010 | C37: 2011 | D37: 2012 | E37: 2013 | F37: 2014 | G37: 2015 | H37: 2016 | I37: 2017 | J37: 2018 | K37: 2019 | L37: 2020 | M37: 2021 | N37: 2022 | O37: 2023 | P37: 2024 | Q37: Source Name | R37: Source URL | S37: Comments
A38: Fertilizer Use
A39: Nitrogen (million metric tons) | B39: 5.0895233 | C39: NA | D39: NA | E39: NA | F39: 5.7309119 | G39: NA | H39: 5.5545123 | Q39: USDA | R39: https://www.ers.usda.gov/data-products/fertilizer-use-and-price.aspx | S39: Retrieved April 2018 1 short ton=0.907185 metric tons
A40: Phosphate (million metric tons) | B40: 1.7539742 | C40: NA | D40: NA | E40: NA | F40: 2.0753131 | G40: NA | H40: 1.8878973 | Q40: USDA | R40: https://www.ers.usda.gov/data-products/fertilizer-use-and-price.aspx | S40: Retrieved April 2018 1 short ton=0.907185 metric tons
A41: Potash (million metric tons) | B41: 1.8060687 | C41: NA | D41: NA | E41: NA | F41: 2.1842772 | G41: NA | H41: 2.0403951 | Q41: USDA | R41: https://www.ers.usda.gov/data-products/fertilizer-use-and-price.aspx | S41: Retrieved April 2018 1 short ton=0.907185 metric tons

Sheet SORGHUM
A1: SORGHUM
A3: PHYSICAL | B3: 2010 | C3: 2011 | D3: 2012 | E3: 2013 | F3: 2014 | G3: 2015 | H3: 2016 | I3: 2017 | J3: 2018 | K3: 2019 | L3: 2020 | M3: 2021 | N3: 2022 | O3: 2023 | P3: 2024 | Q3: Source Name | R3: Source URL | S3: Comments
A4: Number of Farms Growing Sorghum in the United States (thousand farms) | D4: 20.037 | I4: 15.339 | N4: 13.591 | Q4: USDA | R4: https://quickstats.nass.usda.gov/results/4FF74281-332C-3441-88F0-C0D86B06FC6F | S4: Retrieved January 2026
A5: Planted Acreage of Sorghum Planted in the United States (million acres) | B5: 5.369 | C5: 5.451 | D5: 6.259 | E5: 8.076 | F5: 7.138 | G5: 8.459 | H5: 6.69 | I5: 5.629 | J5: 5.69 | K5: 5.265 | L5: 5.88 | M5: 7.305 | N5: 6.325 | O5: 7.195 | P5: 6.315 | Q5: USDA-NASS | R5: https://quickstats.nass.usda.gov/results/22AB96F9-09A2-3278-8198-B3E4D37A2F10 | S5: Retrieved January 2026
A7: PRODUCTION | B7: 2010 | C7: 2011 | D7: 2012 | E7: 2013 | F7: 2014 | G7: 2015 | H7: 2016 | I7: 2017 | J7: 2018 | K7: 2019 | L7: 2020 | M7: 2021 | N7: 2022 | O7: 2023 | P7: 2024 | Q7: Source Name | R7: Source URL | S7: Comments
A8: Total Volume of Sorghum Grown in the US (million metric tons) | B8: 9.540125 | C8: 8.6366 | D8: 5.324825 | E8: 6.19355 | F8: 9.808275 | G8: 10.814375 | H8: 14.918775 | I8: 12.006525 | J8: 9.046775 | K8: 9.12465 | L8: 8.5365 | M8: 9.324 | N8: 11.19525 | O8: 4.694625 | P8: 7.943625 | Q8: USDA | R8: https://www.ers.usda.gov/data-products/feed-grains-database/feed-grains-yearbook-tables.aspx | S8: Retrieved January 2026 1 bushel of sorghum=0.025 metric tons
A9: Total Volume of Sorghum consumption (million metric tons) | B9: 5.773725 | C9: 5.19325 | D9: 3.85465 | E9: 4.72045 | F9: 4.064 | G9: 2.420625 | H9: 6.03175 | I9: 6.18445 | J9: 4.0535 | K9: 6.114625 | L9: 4.296425 | M9: 2.596075 | N9: 3.125625 | O9: 2.544775 | P9: 1.880725 | Q9: USDA | R9: https://www.ers.usda.gov/data-products/feed-grains-database/feed-grains-yearbook-tables.aspx | S9: Retrieved January 2026 1 bushel of sorghum=0.025 metric tons
A10: Sorghum imports (million metric tons) | B10: 0.000125 | C10: 0.00075 | D10: 0.002625 | E10: 0.239325 | F10: 0.00225 | G10: 0.0094 | H10: 0.114675 | I10: 0.043525 | J10: 0.05045 | K10: 0.000975 | L10: 0.00125 | M10: 0.000725 | N10: 0.000325 | O10: 0.0002 | P10: 0.000525 | Q10: USDA | R10: https://www.ers.usda.gov/data-products/feed-grains-database/feed-grains-yearbook-tables.aspx | S10: Retrieved January 2026 1 bushel of sorghum=0.025 metric tons
A11: Sorghum exports (million metric tons) | B11: 4.103325 | C11: 3.78885 | D11: 1.58525 | E11: 1.9074 | F11: 5.27455 | G11: 8.793725 | H11: 8.546125 | I11: 5.944925 | J11: 5.00885 | K11: 2.290825 | L11: 5.080475 | M11: 6.973075 | N11: 7.395975 | O11: 2.72605 | P11: 5.851575 | Q11: USDA | R11: https://www.ers.usda.gov/data-products/feed-grains-database/feed-grains-yearbook-tables.aspx | S11: Retrieved January 2026 1 bushel of sorghum=0.025 metric tons
A12: Beginning stocks (million metric tons) | B12: 1.3678 | C12: 1.031 | D12: 0.68625 | E12: 0.5738 | F12: 0.378825 | G12: 0.8508 | H12: 0.460225 | I12: 0.9158 | J12: 0.836475 | K12: 0.87135 | L12: 1.591525 | M12: 0.752375 | N12: 0.50795 | O12: 1.181925 | P12: 0.605925 | Q12: USDA | R12: https://www.ers.usda.gov/data-products/feed-grains-database/feed-grains-yearbook-tables.aspx | S12: Retrieved January 2026 1 bushel of sorghum=0.025 metric tons
A13: Ending stocks (million metric tons) | B13: 1.031 | C13: 0.68625 | D13: 0.5738 | E13: 0.378825 | F13: 0.8508 | G13: 0.460225 | H13: 0.9158 | I13: 0.836475 | J13: 0.87135 | K13: 1.591525 | L13: 0.752375 | M13: 0.50795 | N13: 1.181925 | O13: 0.605925 | P13: 0.817775 | Q13: USDA | R13: https://www.ers.usda.gov/data-products/feed-grains-database/feed-grains-yearbook-tables.aspx | S13: Retrieved January 2026 1 bushel of sorghum=0.025 metric tons
A14: Uses
A15: Total Volume of Sorghum Consumed for Feed (million metric tons) | B15: 3.523725 | C15: 3.06825 | D15: 1.72965 | E15: 2.33705 | F15: 2.316825 | G15: 2.045375 | H15: 2.60805 | I15: 3.3191 | J15: 2.543425 | K15: 3.47425 | L15: 2.417375 | M15: 2.4265 | N15: 1.9988 | O15: 1.06195 | P15: 1.273525 | Q15: USDA | R15: https://www.ers.usda.gov/data-products/feed-grains-database/feed-grains-yearbook-tables.aspx | S15: Retrieved January 2026 1 bushel of sorghum=0.025 metric tons
A16: Total Volume of Sorghum Consumed for Food, alcohol and industrial use (million metric tons): | B16: 2.231425 | C16: 2.10875 | D16: 2.10565 | E16: 2.358675 | F16: 1.72525 | G16: 0.349275 | H16: 3.403475 | I16: 2.84805 | J16: 1.49245 | K16: 2.62405 | L16: 1.860425 | M16: 0.14695 | N16: 1.10395 | O16: 1.459675 | P16: 0.587625 | Q16: USDA | R16: https://www.ers.usda.gov/data-products/feed-grains-database/feed-grains-yearbook-tables.aspx | S16: Retrieved January 2026 1 bushel of sorghum=0.025 metric tons
A17: Sorghum Saved for Seed (million metric tons) | B17: 0.018575 | C17: 0.01625 | D17: 0.01935 | E17: 0.024725 | F17: 0.021925 | G17: 0.025975 | H17: 0.020225 | I17: 0.0173 | J17: 0.017625 | K17: 0.016325 | L17: 0.018625 | M17: 0.022625 | N17: 0.022875 | O17: 0.02315 | P17: 0.019575 | Q17: USDA | R17: https://www.ers.usda.gov/data-products/feed-grains-database/feed-grains-yearbook-tables.aspx | S17: Retrieved January 2026 1 bushel of sorghum=0.025 metric tons
A18: Sorghum into Biofuels
A19: Ethanol production as percent of total Sorghum use | Q19: Calculation
A21: ECONOMICS | B21: 2010 | C21: 2011 | D21: 2012 | E21: 2013 | F21: 2014 | G21: 2015 | H21: 2016 | I21: 2017 | J21: 2018 | K21: 2019 | L21: 2020 | M21: 2021 | N21: 2022 | O21: 2023 | P21: 2024 | Q21: Source Name | R21: Source URL | S21: Comments
A22: Sorghum Prices (dollars per metric ton) | B22: 198 | C22: 236 | D22: 249 | E22: 168 | F22: 159 | G22: 130 | H22: 110 | I22: 125 | J22: 185 | K22: 188 | L22: 190 | M22: 212 | N22: 296 | O22: 296 | P22: 252 | Q22: USDA-NASS | R22: https://quickstats.nass.usda.gov/results/10684D48-7FE1-37D9-A4A7-34DDD9A43959 | S22: Retrieved January 2026 1 cwt = 0.04536 metric tons
A23: Direct Value of All Sorghum Grown in the United States (billion dollars) | B23: 1.616773 | C23: 1.259635 | D23: 1.606237 | E23: 1.716927 | F23: 1.72133 | G23: 2.064638 | H23: 1.352438 | I23: 1.168526 | J23: 1.180847 | K23: 1.125759 | L23: 1.767844 | M23: 2.666217 | N23: 1.246906 | O23: 1.556703 | P23: 1.454711 | Q23: USDA-NASS | R23: https://quickstats.nass.usda.gov/results/356755E1-3FFF-3783-93D1-9A40207DD05C | S23: Retrieved January 2026

Sheet BARLEY
A1: BARLEY
A3: PHYSICAL | B3: 2010 | C3: 2011 | D3: 2012 | E3: 2013 | F3: 2014 | G3: 2015 | H3: 2016 | I3: 2017 | J3: 2018 | K3: 2019 | L3: 2020 | M3: 2021 | N3: 2022 | O3: 2023 | P3: 2024 | Q3: Source Name | R3: Source URL | S3: Comments
A4: Number of Farms Growing Barley in the United States (thousand farms) | D4: 18.667 | I4: 11.188 | N4: 9.112 | Q4: USDA | R4: https://quickstats.nass.usda.gov/results/F560C69D-E59A-302C-8EBF-A1DD58243BD2 | S4: Retrieved January 2026
A5: Planted Acreage of barley Planted in the United States (million acres) | B5: 2.872 | C5: 2.564 | D5: 3.66 | E5: 3.528 | F5: 3.031 | G5: 3.583 | H5: 3.059 | I5: 2.486 | J5: 2.494 | K5: 2.767 | L5: 2.727 | M5: 2.707 | N5: 2.927 | O5: 3.109 | P5: 2.381 | Q5: USDA-NASS | R5: https://quickstats.nass.usda.gov/results/616E13D1-D39B-350E-9E93-142A3459195C | S5: Retrieved January 2026
A7: PRODUCTION | B7: 2010 | C7: 2011 | D7: 2012 | E7: 2013 | F7: 2014 | G7: 2015 | H7: 2016 | I7: 2017 | J7: 2018 | K7: 2019 | L7: 2020 | M7: 2021 | N7: 2022 | O7: 2023 | P7: 2024 | Q7: Source Name | R7: Source URL | S7: Comments
A8: Total Volume of barley Grown in the US (million metric tons) | B8: 4.758663 | C8: 3.785061 | D8: 3.250548 | E8: 4.59879 | F8: 4.551645 | G8: 3.812382 | H8: 4.581927 | I8: 4.198194 | J8: 3.008418 | K8: 3.176649 | L8: 3.620589 | M8: 3.58491 | N8: 2.532453 | O8: 3.65232 | P8: 3.908667 | Q8: USDA | R8: https://www.ers.usda.gov/data-products/feed-grains-database/feed-grains-yearbook-tables.aspx | S8: Retrieved January 2026 1 bushel of barley=0.021 metric tons
A9: Total Volume of barley consumption (million metric tons) | B9: 4.426212 | C9: 4.374405 | D9: 4.022823 | E9: 4.473273 | F9: 4.606602 | G9: 4.084248 | H9: 4.251156 | I9: 4.21932 | J9: 3.342969 | K9: 3.353049 | L9: 3.686445 | M9: 3.722817 | N9: 3.406368 | O9: 3.498138 | P9: 3.823176 | Q9: USDA | R9: https://www.ers.usda.gov/data-products/feed-grains-database/feed-grains-yearbook-tables.aspx | S9: Retrieved January 2026 1 bushel of barley=0.021 metric tons
A10: Barley imports (million metric tons) | B10: 0.348516 | C10: 0.199374 | D10: 0.341376 | E10: 0.48909 | F10: 0.393708 | G10: 0.494949 | H10: 0.390201 | I10: 0.202335 | J10: 0.191793 | K10: 0.123333 | L10: 0.148953 | M10: 0.136731 | N10: 0.3087 | O10: 0.492429 | P10: 0.279258 | Q10: USDA | R10: https://www.ers.usda.gov/data-products/feed-grains-database/feed-grains-yearbook-tables.aspx | S10: Retrieved January 2026 1 bushel of barley=0.021 metric tons
A11: Barley exports (million metric tons) | B11: 0.118881 | C11: 0.159138 | D11: 0.185745 | E11: 0.185997 | F11: 0.299733 | G11: 0.300279 | H11: 0.226821 | I11: 0.091875 | J11: 0.106785 | K11: 0.103551 | L11: 0.120267 | M11: 0.289359 | N11: 0.154266 | O11: 0.044688 | P11: 0.104811 | Q11: USDA | R11: https://www.ers.usda.gov/data-products/feed-grains-database/feed-grains-yearbook-tables.aspx | S11: Retrieved January 2026 1 bushel of barley=0.021 metric tons
A12: Beginning stocks (million metric tons) | B12: 1.863393 | C12: 2.425479 | D12: 1.876371 | E12: 1.259727 | F12: 1.688337 | G12: 1.727355 | H12: 1.650159 | I12: 2.14431 | J12: 2.233644 | K12: 1.984101 | L12: 1.827483 | M12: 1.790313 | N12: 1.499778 | O12: 0.780297 | P12: 1.38222 | Q12: USDA | R12: https://www.ers.usda.gov/data-products/feed-grains-database/feed-grains-yearbook-tables.aspx | S12: Retrieved January 2026 1 bushel of barley=0.021 metric tons
A13: Ending stocks (million metric tons) | B13: 2.425479 | C13: 1.876371 | D13: 1.259727 | E13: 1.688337 | F13: 1.727355 | G13: 1.650159 | H13: 2.14431 | I13: 2.233644 | J13: 1.984101 | K13: 1.827483 | L13: 1.790313 | M13: 1.499778 | N13: 0.780297 | O13: 1.38222 | P13: 1.642158 | Q13: USDA | R13: https://www.ers.usda.gov/data-products/feed-grains-database/feed-grains-yearbook-tables.aspx | S13: Retrieved January 2026 1 bushel of barley=0.021 metric tons
A14: Uses
A15: Total Volume of barley Consumed for Feed (million metric tons) | B15: 0.988029 | C15: 1.045527 | D15: 0.767823 | E15: 1.390263 | F15: 1.383627 | G15: 0.721434 | H15: 0.928074 | I15: 0.948234 | J15: 0.155925 | K15: 0.236733 | L15: 0.710115 | M15: 0.643293 | N15: 0.615384 | O15: 0.73332 | P15: 1.18251 | Q15: USDA | R15: https://www.ers.usda.gov/data-products/feed-grains-database/feed-grains-yearbook-tables.aspx | S15: Retrieved January 2026 1 bushel of barley=0.021 metric tons
A16: Total Volume of barley Consumed for Food, alcohol and industrial use (million metric tons): | B16: 3.333288 | C16: 3.228288 | D16: 3.128412 | E16: 2.961483 | F16: 3.11493 | G16: 3.23925 | H16: 3.214722 | I16: 3.183285 | J16: 3.096975 | K16: 3.01854 | L16: 2.880255 | M16: 2.983428 | N16: 2.687979 | O16: 2.655408 | P16: 2.556603 | Q16: USDA | R16: https://www.ers.usda.gov/data-products/feed-grains-database/feed-grains-yearbook-tables.aspx | S16: Retrieved January 2026 1 bushel of barley=0.021 metric tons
A17: Barley Saved for Seed (million metric tons) | B17: 0.104895 | C17: 0.10059 | D17: 0.126588 | E17: 0.121527 | F17: 0.108045 | G17: 0.123564 | H17: 0.10836 | I17: 0.087801 | J17: 0.090069 | K17: 0.097776 | L17: 0.096075 | M17: 0.096096 | N17: 0.103005 | O17: 0.10941 | P17: 0.084063 | Q17: USDA | R17: https://www.ers.usda.gov/data-products/feed-grains-database/feed-grains-yearbook-tables.aspx | S17: Retrieved January 2026 1 bushel of barley=0.021 metric tons
A19: ECONOMICS | B19: 2010 | C19: 2011 | D19: 2012 | E19: 2013 | F19: 2014 | G19: 2015 | H19: 2016 | I19: 2017 | J19: 2018 | K19: 2019 | L19: 2020 | M19: 2021 | N19: 2022 | O19: 2023 | P19: 2024 | Q19: Source Name | R19: Source URL | S19: Comments
A20: Barley Prices (dollars per metric ton) | B20: 190.47619 | C20: 228.09524 | D20: 284.7619 | E20: 298.09524 | F20: 269.04762 | G20: 249.52381 | H20: 246.19048 | I20: 222.85714 | J20: 215.2381 | K20: 223.80952 | L20: 224.28571 | M20: 239.52381 | N20: 314.28571 | O20: 350 | P20: 325.2381 | Q20: USDA-NASS | R20: https://quickstats.nass.usda.gov/results/775E91AB-2C7E-3E11-8F6F-1E6167569EC2 | S20: Retrieved January 2026 1 bushel of barley=0.021 metric tons
A21: Direct Value of All barley Grown in the United States (billion dollars) | B21: 0.691573 | C21: 0.808741 | D21: 1.371381 | E21: 1.265798 | F21: 0.914955 | G21: 1.149831 | H21: 0.949876 | I21: 0.624184 | J21: 0.688963 | K21: 0.788419 | L21: 0.787351 | M21: 0.66527 | N21: 1.160718 | O21: 1.329492 | P21: 0.899879 | Q21: USDA-NASS | R21: https://quickstats.nass.usda.gov/results/BCCC15CB-5216-3401-B519-C2BB83E644E4 | S21: Retrieved January 2026

Sheet WHEAT
A1: WHEAT
A3: PHYSICAL | B3: 2010 | C3: 2011 | D3: 2012 | E3: 2013 | F3: 2014 | G3: 2015 | H3: 2016 | I3: 2017 | J3: 2018 | K3: 2019 | L3: 2020 | M3: 2021 | N3: 2022 | O3: 2023 | P3: 2024 | Q3: Source Name | R3: Source URL | S3: Comments
A4: Number of Farms Growing Wheat in the United States (thousand farms) | D4: 147.632 | I4: 104.792 | N4: 97.014 | Q4: USDA | R4: https://quickstats.nass.usda.gov/results/924115B3-CA65-385F-877C-351EC14F9F6B | S4: Retrieved January 2026
A5: Planted Acreage of Wheat in the United States (million acres) | B5: 52.62 | C5: 54.277 | D5: 55.294 | E5: 56.236 | F5: 56.841 | G5: 54.999 | H5: 50.116 | I5: 46.052 | J5: 47.82 | K5: 45.485 | L5: 44.45 | M5: 46.74 | N5: 45.769 | O5: 49.575 | P5: 46.274 | Q5: USDA | R5: https://quickstats.nass.usda.gov/results/7539B9E8-3C98-3BA5-AB49-19F9CC39402E | S5: Retrieved January 2026
A7: PRODUCTION | B7: 2010 | C7: 2011 | D7: 2012 | E7: 2013 | F7: 2014 | G7: 2015 | H7: 2016 | I7: 2017 | J7: 2018 | K7: 2019 | L7: 2020 | M7: 2021 | N7: 2022 | O7: 2023 | P7: 2024 | Q7: Source Name | R7: Source URL | S7: Comments
A8: Total Volume of Wheat Grown in the US (million metric tons) | B8: 58.868 | C8: 54.244 | D8: 61.298 | E8: 58.105 | F8: 55.147 | G8: 56.117 | H8: 62.832 | I8: 47.38 | J8: 51.311 | K8: 52.581 | L8: 49.523 | M8: 44.804 | N8: 44.898 | O8: 49.095 | P8: 53.851 | Q8: USDA | R8: https://apps.fas.usda.gov/psdonline/app/index.html#/app/downloads | S8: Retrieved April 2018
A9: Total Volume of Wheat consumed in the US (million metric tons) | B9: 29.424 | C9: 31.993 | D9: 37.81 | E9: 34.26 | F9: 31.328 | G9: 31.943 | H9: 31.865 | I9: 29.245 | J9: 29.991 | K9: 30.437 | L9: 30.185 | M9: 30.411 | N9: 30.361 | O9: 30.18 | P9: 31.235 | Q9: USDA | R9: https://apps.fas.usda.gov/psdonline/app/index.html#/app/downloads | S9: Retrieved June 2018
A10: Wheat Imports (million metric tons) | B10: 2.638 | C10: 3.079 | D10: 3.383 | E10: 4.694 | F10: 4.116 | G10: 3.069 | H10: 3.212 | I10: 4.299 | J10: 3.662 | K10: 2.828 | L10: 2.726 | M10: 2.617 | N10: 3.309 | O10: 3.75 | P10: 4.054 | Q10: USDA | R10: https://apps.fas.usda.gov/psdonline/app/index.html#/app/downloads | S10: Retrieved June 2018
A11: Wheat Exports (million metric tons) | B11: 35.147 | C11: 28.606 | D11: 27.544 | E11: 32.012 | F11: 23.523 | G11: 21.168 | H11: 28.6 | I11: 24.658 | J11: 25.503 | K11: 26.373 | L11: 27.048 | M11: 21.656 | N11: 20.7 | O11: 19.212 | P11: 22.477 | Q11: USDA | R11: https://apps.fas.usda.gov/psdonline/app/index.html#/app/downloads | S11: Retrieved June 2018
A12: Beginning stocks (million metric tons) | B12: 26.552 | C12: 23.487 | D12: 20.211 | E12: 19.538 | F12: 16.065 | G12: 20.477 | H12: 26.552 | I12: 32.131 | J12: 29.907 | K12: 29.386 | L12: 27.985 | M12: 23.001 | N12: 18.355 | O12: 15.501 | P12: 18.954 | Q12: USDA | R12: https://apps.fas.usda.gov/psdonline/app/index.html#/app/downloads | S12: Retrieved April 2018
A13: Ending stocks (million metric tons) | B13: 23.487 | C13: 20.211 | D13: 19.538 | E13: 16.065 | F13: 20.477 | G13: 26.552 | H13: 32.131 | I13: 29.907 | J13: 29.386 | K13: 27.985 | L13: 23.001 | M13: 18.355 | N13: 15.501 | O13: 18.954 | P13: 23.147 | Q13: USDA | R13: https://apps.fas.usda.gov/psdonline/app/index.html#/app/downloads | S13: Retrieved April 2018
A15: ECONOMICS | B15: 2010 | C15: 2011 | D15: 2012 | E15: 2013 | F15: 2014 | G15: 2015 | H15: 2016 | I15: 2017 | J15: 2018 | K15: 2019 | L15: 2020 | M15: 2021 | N15: 2022 | O15: 2023 | P15: 2024 | Q15: Source Name | R15: Source URL | S15: Comments
A16: Wheat Prices (dollars per metric ton) | B16: 189.62963 | C16: 275.55556 | D16: 281.48148 | E16: 271.11111 | F16: 234.44444 | G16: 195.55556 | H16: 152.22222 | I16: 164.44444 | J16: 190.37037 | K16: 175.55556 | L16: 180 | M16: 253.33333 | N16: 344.44444 | O16: 284.07407 | P16: 214.81481 | Q16: USDA-NASS | R16: https://quickstats.nass.usda.gov/results/FDBAF890-6232-3032-8271-F98ED7B43DEE | S16: Retrieved January 2026 1 bushel of wheat=0.027 metric tons
A17: Direct Value of All wheat Grown in the United States (billion dollars) | B17: 12.579125 | C17: 14.269225 | D17: 17.383149 | E17: 14.604442 | F17: 11.914954 | G17: 10.018323 | H17: 9.17919 | I17: 8.255119 | J17: 9.66325 | K17: 8.919117 | L17: 9.345872 | M17: 12.208186 | N17: 14.213326 | O17: 12.259414 | P17: 10.928966 | Q17: USDA-NASS | R17: https://quickstats.nass.usda.gov/results/25621CF1-71CE-3AF9-9CE4-69B2C52D0D72 | S17: Retrieved January 2026
A40: Feed
A41: Fuel Alcohol
A42: High Fructose wheat Syrup
A43: Glucose and Dextrose
A44: Starch
A45: Cereal
A46: Alcoholic Beverages
A47: Seed

Sheet SOY
A1: SOY
A3: PHYSICAL | B3: 2010 | C3: 2011 | D3: 2012 | E3: 2013 | F3: 2014 | G3: 2015 | H3: 2016 | I3: 2017 | J3: 2018 | K3: 2019 | L3: 2020 | M3: 2021 | N3: 2022 | O3: 2023 | P3: 2024 | Q3: Source Name | R3: Source URL | S3: Comments
A4: Number of Farms Growing Soy in the United States (thousand farms) | D4: 302.963 | I4: 303.191 | N4: 270.851 | Q4: USDA | R4: https://quickstats.nass.usda.gov/results/110FC2E2-86FA-3DD3-9E05-1D109EDE0FFD | S4: Retrieved January 2026
A5: Acreage of Soybeans planted in the United States (million acres) | B5: 77.404 | C5: 75.046 | D5: 77.198 | E5: 76.82 | F5: 83.296 | G5: 82.66 | H5: 83.453 | I5: 90.162 | J5: 89.167 | K5: 76.1 | L5: 83.354 | M5: 87.195 | N5: 87.45 | O5: 83.6 | P5: 87.05 | Q5: USDA | R5: https://www.ers.usda.gov/data-products/oil-crops-yearbook/oil-crops-yearbook/ | S5: Retrieved January 2026
A6: Acreage of Soybeans harvested in the United States (million acres) | B6: 76.61 | C6: 73.776 | D6: 76.144 | E6: 76.233 | F6: 82.611 | G6: 81.742 | H6: 82.706 | I6: 89.542 | J6: 87.594 | K6: 74.918 | L6: 82.603 | M6: 86.292 | N6: 86.174 | O6: 82.271 | P6: 86.05 | Q6: USDA | R6: https://www.ers.usda.gov/data-products/oil-crops-yearbook/oil-crops-yearbook/ | S6: Retrieved January 2026
A7: Yield of Soy grown in the United States (metric tons per acre) | B7: 1.1740669 | C7: 1.1334829 | D7: 1.0786823 | E7: 1.1889747 | F7: 1.2838229 | G7: 1.2970448 | H7: 1.4026237 | I7: 1.3302594 | J7: 1.3649342 | K7: 1.2797844 | L7: 1.37816 | M7: 1.3968999 | N7: 1.3379939 | O7: 1.3659192 | P7: 1.3700788 | Q7: USDA | R7: https://www.ers.usda.gov/data-products/oil-crops-yearbook/oil-crops-yearbook/ | S7: Retrieved January 2026 1 bushel of soy=0.027 metric tons
A9: PRODUCTION | B9: 2010 | C9: 2011 | D9: 2012 | E9: 2013 | F9: 2014 | G9: 2015 | H9: 2016 | I9: 2017 | J9: 2018 | K9: 2019 | L9: 2020 | M9: 2021 | N9: 2022 | O9: 2023 | P9: 2024 | Q9: Source Name | R9: Source URL | S9: Comments
A10: Total Volume of Soybean Grown in the US (million metric tons) | B10: 90.745137 | C10: 89.945262 | D10: 83.623833 | E10: 82.135188 | F10: 90.639108 | G10: 106.05789 | H10: 106.02303 | I10: 116.00539 | J10: 119.11409 | K10: 119.56005 | L10: 95.87889 | M10: 113.84015 | N10: 120.54128 | O10: 115.30029 | P10: 112.37554 | Q10: USDA | R10: https://www.ers.usda.gov/data-products/oil-crops-yearbook/oil-crops-yearbook/ | S10: Retrieved January 2026 1 bushel of soy=0.027 metric tons
A11: Total volume of soy consumption (million metric tons) | B11: 50.322168 | C11: 47.969535 | D11: 48.429982 | E11: 48.163878 | F11: 49.647279 | G11: 54.547376 | H11: 54.042181 | I11: 55.27871 | J11: 58.40647 | K11: 59.449418 | L11: 61.292336 | M11: 60.801767 | N11: 62.394346 | O11: 62.790047 | P11: 65.062208 | Q11: USDA | R11: https://www.ers.usda.gov/data-products/oil-crops-yearbook/oil-crops-yearbook/ | S11: Retrieved January 2026 1 bushel of soy=0.027 metric tons
A12: Soybean Imports (million metric tons) | B12: 0.39387888 | C12: 0.39012561 | D12: 0.43556405 | E12: 1.0939412 | F12: 1.9379802 | G12: 0.89761126 | H12: 0.63560456 | I12: 0.6015791 | J12: 0.5888835 | K12: 0.3795471 | L12: 0.4152735 | M12: 0.535005 | N12: 0.4297104 | O12: 0.6617808 | P12: 0.5625477 | Q12: USDA | R12: https://www.ers.usda.gov/data-products/oil-crops-yearbook/oil-crops-yearbook/ | S12: Retrieved January 2026 1 bushel of soy=0.027 metric tons
A13: Soybean Exports (million metric tons) | B13: 40.474299 | C13: 40.634396 | D13: 36.861777 | E13: 35.843202 | F13: 44.241091 | G13: 49.745413 | H13: 52.451243 | I13: 58.496879 | J13: 57.610734 | K13: 47.34261 | L13: 45.437625 | M13: 61.175566 | N13: 58.106443 | O13: 53.447691 | P13: 45.763156 | Q13: USDA | R13: https://www.ers.usda.gov/data-products/oil-crops-yearbook/oil-crops-yearbook/ | S13: Retrieved January 2026 1 bushel of soy=0.027 metric tons
A14: Beginning stocks (million metric tons) | B14: 3.731346 | C14: 4.073895 | D14: 5.805351 | E14: 4.57299 | F14: 3.795039 | G14: 2.483757 | H14: 5.14647 | I14: 5.311683 | J14: 8.143065 | K14: 11.828835 | L14: 24.976404 | M14: 14.540607 | N14: 6.938433 | O14: 7.408638 | P14: 7.132968 | Q14: USDA | R14: https://www.ers.usda.gov/data-products/oil-crops-yearbook/oil-crops-yearbook/ | S14: Retrieved January 2026 1 bushel of soy=0.027 metric tons
A15: Ending stocks (million metric tons) | B15: 4.073895 | C15: 5.805351 | D15: 4.57299 | E15: 3.795039 | F15: 2.483757 | G15: 5.14647 | H15: 5.311683 | I15: 8.143065 | J15: 11.828835 | K15: 24.976404 | L15: 14.540607 | M15: 6.938433 | N15: 7.408638 | O15: 7.132968 | P15: 9.245691 | Q15: USDA | R15: https://www.ers.usda.gov/data-products/oil-crops-yearbook/oil-crops-yearbook/ | S15: Retrieved January 2026 1 bushel of soy=0.027 metric tons
A16: Uses
A17: Total Volume of Soy Consumed for Crush (million metric tons) | B17: 47.295529 | C17: 44.49715 | D17: 45.981513 | E17: 45.600381 | F17: 46.814976 | G17: 50.584332 | H17: 50.928394 | I17: 51.332348 | J17: 55.483164 | K17: 56.483738 | L17: 58.442963 | M17: 57.795787 | N17: 59.504549 | O17: 59.722321 | P17: 61.703186 | Q17: USDA | R17: https://www.ers.usda.gov/data-products/oil-crops-yearbook/oil-crops-yearbook/ | S17: Retrieved January 2026 1 bushel of soy=0.027 metric tons
A18: Total Volume of Soy Consumed for Seed, feed and residual (million metric tons) | B18: 3.0266383 | C18: 3.4723853 | D18: 2.4484685 | E18: 2.5634972 | F18: 2.8323029 | G18: 3.9630434 | H18: 3.1137876 | I18: 3.9463625 | J18: 2.9233062 | K18: 2.96568 | L18: 2.8493721 | M18: 3.0059802 | N18: 2.8897965 | O18: 3.0677265 | P18: 3.3590214 | Q18: USDA | R18: https://www.ers.usda.gov/data-products/oil-crops-yearbook/oil-crops-yearbook/ | S18: Retrieved January 2026 1 bushel of soy=0.027 metric tons
A19: Soy into Biofuels
A20: Soybean Oil Going to Biodiesel (million metric tons) | B20: 0.76040337 | C20: 1.2414827 | D20: 2.2108098 | E20: 2.1268952 | F20: 2.3031477 | G20: 2.2854666 | H20: 2.5719647 | I20: 2.8124096 | J20: 3.3265158 | K20: 3.9296079 | L20: 3.9271222 | M20: 4.0460451 | N20: 4.7077231 | O20: 5.6745918 | P20: 5.8917321 | Q20: USDA | R20: https://www.ers.usda.gov/data-products/us-bioenergy-statistics/us-bioenergy-statistics/ | S20: Retrieved January 2026 1 metric ton = 2,204.622 pounds
A21: Percent Soybean Oil Used for Biodiesel | B21: 0.10600782 | C21: 0.16543333 | D21: 0.26331679 | E21: 0.24958621 | F21: 0.26854149 | G21: 0.26575634 | H21: 0.28122906 | I21: 0.31216398 | J21: 0.34301393 | K21: 0.37873745 | L21: 0.38794729 | M21: 0.38261702 | N21: 0.4180388 | O21: 0.47015357 | P21: 0.47836682 | Q21: USDA | R21: https://www.ers.usda.gov/data-products/us-bioenergy-statistics/us-bioenergy-statistics/ | S21: Retrieved January 2026
A23: ECONOMICS | B23: 2010 | C23: 2011 | D23: 2012 | E23: 2013 | F23: 2014 | G23: 2015 | H23: 2016 | I23: 2017 | J23: 2018 | K23: 2019 | L23: 2020 | M23: 2021 | N23: 2022 | O23: 2023 | P23: 2024 | Q23: Source Name | R23: Source URL | S23: Comments
A24: Average Soy Price (dollar per metric tons) | B24: 355.18519 | C24: 418.51852 | D24: 462.96296 | E24: 533.33333 | F24: 481.48148 | G24: 374.07407 | H24: 331.48148 | I24: 350.74074 | J24: 345.55556 | K24: 314.07407 | L24: 317.40741 | M24: 400 | N24: 492.59259 | O24: 525.92593 | P24: 459.25926 | Q24: 368.51852 | R24: https://www.ers.usda.gov/data-products/oil-crops-yearbook/oil-crops-yearbook/ | S24: Retrieved January 2026 1 bushel of soy=0.027 metric tons
A25: Soybean Oil Price (dollars per metric ton) | B25: 792.56161 | C25: 1172.8589 | D25: 1144.1988 | E25: 1039.0383 | F25: 842.82699 | G25: 696.66055 | H25: 658.30013 | I25: 717.60446 | J25: 662.26845 | K25: 623.02618 | L25: 653.67042 | M25: 1253.7685 | N25: 1608.9331 | O25: 1438.7363 | P25: 1042.3453 | Q25: USDA-ERS (Oil Crops Outlook 2018) | R25: https://www.ers.usda.gov/publications/pub-details/?pubid=86740 | S25: Retrieved January 2026 1 metric ton = 2,204.622 pounds
A26: Direct Value of All Soy Grown in the United States (billion dollars) | B26: 37.571277 | C26: 38.542177 | D26: 43.723144 | E26: 43.582901 | F26: 39.474861 | G26: 35.195882 | H26: 40.694573 | I26: 41.30874 | J26: 37.557828 | K26: 30.518566 | L26: 45.732122 | M26: 59.140279 | N26: 60.695837 | O26: 51.555913 | P26: 44.097484 | Q26: USDA | R26: https://www.ers.usda.gov/data-products/oil-crops-yearbook/oil-crops-yearbook/ | S26: Retrieved January 2026
A27: Value of Soybeans Used for Biodiesel (billion dollars) | B27: =B25*B20/1000 -> 0.60266652 | C27: =C25*C20/1000 -> 1.456084 | D27: =D25*D20/1000 -> 2.529606 | E27: =E25*E20/1000 -> 2.2099257 | F27: =F25*F20/1000 -> 1.941155 | G27: =G25*G20/1000 -> 1.5921944 | H27: =H25*H20/1000 -> 1.6931247 | I27: =I25*I20/1000 -> 2.0181976 | ... P27: =P25*P20/1000 -> 6.1412191 | Q27: Calculation
A29: ENVIRONMENTAL | B29: 2010 | C29: 2011 | D29: 2012 | E29: 2013 | F29: 2014 | G29: 2015 | H29: 2016 | I29: 2017 | J29: 2018 | K29: 2019 | L29: 2020 | M29: 2021 | N29: 2022 | O29: 2023 | P29: 2024 | Q29: Source Name | R29: Source URL | S29: Comments
A30: Fertilizer Use
A31: Nitrogen (million metric tons) | B31: 0.10111644 | C31: 0.1514999 | D31: 0.15171724 | E31: NA | F31: NA | G31: 0.18415856 | H31: NA | Q31: USDA | R31: https://www.ers.usda.gov/data-products/fertilizer-use-and-price.aspx | S31: Retrieved April 2018 1 short ton=0.907185 metric tons
A32: Phosphate (million metric tons) | B32: 0.5006668 | C32: 0.6350295 | D32: 0.62808386 | E32: NA | F32: NA | G32: 0.75426642 | H32: NA | Q32: USDA | R32: https://www.ers.usda.gov/data-products/fertilizer-use-and-price.aspx | S32: Retrieved April 2018 1 short ton=0.907185 metric tons
A33: Potash (million metric tons) | B33: 0.70219748 | C33: 1.0369125 | D33: 1.0464284 | E33: NA | F33: NA | G33: 1.2080519 | H33: NA | Q33: USDA | R33: https://www.ers.usda.gov/data-products/fertilizer-use-and-price.aspx | S33: Retrieved April 2018 1 short ton=0.907185 metric tons
A56: Feed
A57: Fuel Alcohol
A58: High Fructose Corn Syrup
A59: Glucose and Dextrose
A60: Starch
A61: Cereal
A62: Alcoholic Beverages
A63: Seed

Sheet CANOLA
A1: CANOLA
A3: PHYSICAL | B3: 2010 | C3: 2011 | D3: 2012 | E3: 2013 | F3: 2014 | G3: 2015 | H3: 2016 | I3: 2017 | J3: 2018 | K3: 2019 | L3: 2020 | M3: 2021 | N3: 2022 | O3: 2023 | P3: 2024 | Q3: Source Name | R3: Source URL | S3: Comments
A4: Number of Farms Growing Canola in the United States (thousand farms) | D4: 3.995 | I4: 4.208 | N4: 4.058 | Q4: USDA | R4: https://quickstats.nass.usda.gov/results/D152A1E1-36F0-3C4E-889E-CC202E0A2E27 | S4: Retrieved January 2026
A5: Planted Acreage of Canola Planted in the United States (million acres) | B5: 0.82 | C5: 1.4488 | D5: 1.0615 | E5: 1.7544 | F5: 1.348 | G5: 1.715 | H5: 1.777 | I5: 1.709 | J5: 2.077 | K5: 1.9827 | L5: 2.036 | M5: 1.831 | N5: 2.1455 | O5: 2.206 | P5: 2.3445 | Q5: USDA | R5: https://www.ers.usda.gov/data-products/oil-crops-yearbook/oil-crops-yearbook/ | S5: Retrieved January 2026
A7: PRODUCTION | B7: 2010 | C7: 2011 | D7: 2012 | E7: 2013 | F7: 2014 | G7: 2015 | H7: 2016 | I7: 2017 | J7: 2018 | K7: 2019 | L7: 2020 | M7: 2021 | N7: 2022 | O7: 2023 | P7: 2024 | Q7: Source Name | R7: Source URL | S7: Comments
A8: Total Volume of Canola Grown in the U.S. (million metric tons) | B8: 0.66441322 | C8: 1.1102257 | D8: 0.69309387 | E8: 1.0848164 | F8: 0.99928922 | G8: 1.1369727 | H8: 1.3047933 | I8: 1.3966068 | J8: 1.3859111 | K8: 1.6366479 | L8: 1.5408378 | M8: 1.5869419 | N8: 1.2315263 | O8: 1.7303751 | P8: 1.8857745 | Q8: USDA | R8: https://www.ers.usda.gov/data-products/oil-crops-yearbook/oil-crops-yearbook/ | S8: Retrieved January 2026 1 metric ton = 2,204.622 pounds
A9: Total volume of Canola consumption (million metric tons) | B9: 1.1122088 | C9: 1.2900171 | D9: 1.1666399 | E9: 1.2641623 | F9: 1.6845972 | G9: 1.7354449 | H9: 1.5412284 | I9: 1.9948218 | J9: 1.7573008 | K9: 1.7177303 | L9: 1.8240732 | M9: 2.0721031 | N9: 1.6482055 | O9: 1.9209016 | P9: 2.099862 | Q9: USDA | R9: https://www.ers.usda.gov/data-products/oil-crops-yearbook/oil-crops-yearbook/ | S9: Retrieved January 2026 1 metric ton = 2,204.622 pounds
A10: Canola imports (million metric tons) | B10: 0.56798946 | C10: 0.48218677 | D10: 0.62196824 | E10: 0.39403404 | F10: 0.92739364 | G10: 0.77686287 | H10: 0.35880981 | I10: 0.69734721 | J10: 0.65144274 | K10: 0.56363236 | L10: 0.56295116 | M10: 0.44023962 | N10: 0.50313004 | O10: 0.57764746 | P10: 0.31650139 | Q10: USDA | R10: https://www.ers.usda.gov/data-products/oil-crops-yearbook/oil-crops-yearbook/ | S10: Retrieved January 2026 1 metric ton = 2,204.622 pounds
A11: Canola exports (million metric tons) | B11: 0.1770181 | C11: 0.29373134 | D11: 0.15285243 | E11: 0.17712824 | F11: 0.15948254 | G11: 0.15956182 | H11: 0.17580293 | I11: 0.11849242 | J11: 0.15353834 | K11: 0.18087925 | L11: 0.18296655 | M11: 0.15573434 | N11: 0.12873324 | O11: 0.14874604 | P11: 0.16774425 | Q11: USDA | R11: https://www.ers.usda.gov/data-products/oil-crops-yearbook/oil-crops-yearbook/ | S11: Retrieved January 2026 1 metric ton = 2,204.622 pounds
A12: Beginning stocks (million metric tons) | B12: 0.20409712 | C12: 0.12196649 | D12: 0.10190137 | E12: 0.070070969 | F12: 0.080913644 | G12: 0.12890963 | H12: 0.10944824 | I12: 0.16080988 | J12: 0.10814779 | K12: 0.087739304 | L12: 0.13834254 | M12: 0.21858486 | N12: 0.2124532 | O12: 0.10924458 | P12: 0.22082697 | Q12: USDA | R12: https://www.ers.usda.gov/data-products/oil-crops-yearbook/oil-crops-yearbook/ | S12: Retrieved January 2026 1 metric ton = 2,204.622 pounds
A13: Ending stocks (million metric tons) | B13: 1.4364998 | C13: 1.714379 | D13: 1.4169635 | E13: 1.5489214 | F13: 2.0075965 | G13: 2.0427452 | H13: 1.7730513 | I13: 2.2547639 | J13: 2.1455016 | K13: 2.2880196 | L13: 2.2421315 | M13: 2.2457664 | N13: 1.9471096 | O13: 2.4172671 | P13: 2.4231029 | Q13: USDA | R13: https://www.ers.usda.gov/data-products/oil-crops-yearbook/oil-crops-yearbook/ | S13: Retrieved January 2026 1 metric ton = 2,204.622 pounds
A14: Uses
A15: Volume of Canola Crushed (million metric tons) | B15: 1.1122088 | C15: 1.2900171 | D15: 1.1666399 | E15: 1.2641623 | F15: 1.6845972 | G15: 1.7354449 | H15: 1.5412284 | I15: 1.9948218 | J15: 1.7573008 | K15: 1.7177303 | L15: 1.8240732 | M15: 2.0721031 | N15: 1.6482055 | O15: 1.9209016 | P15: 2.099862 | Q15: USDA | R15: https://www.ers.usda.gov/data-products/oil-crops-yearbook/oil-crops-yearbook/ | S15: Retrieved January 2026 1 metric ton = 2,204.622 pounds
A16: Canola into Biofuels
A17: Canola Oil Going to Biodiesel (million metric tons) | B17: 0.14106727 | C17: 0.29256716 | D17: 0.43726317 | E17: 0.19459118 | F17: 0.44193517 | G17: 0.42419063 | H17: 0.45725299 | I17: 0.58711652 | J17: 0.62793985 | K17: 0.49895175 | L17: 0.59765348 | M17: 0.52163137 | N17: 0.60554598 | O17: 1.3219055 | P17: 1.9671847 | Q17: USDA | R17: https://www.ers.usda.gov/data-products/oil-crops-yearbook/oil-crops-yearbook/ | S17: Retrieved January 2026 1 metric ton = 2,204.622 pounds
A18: Percent Canola Oil Used for Biodiesel | B18: 0.109114 | C18: 0.17660604 | D18: 0.25135883 | E18: 0.11894239 | F18: 0.2141788 | G18: 0.18664297 | H18: 0.18953252 | I18: 0.22131427 | J18: 0.24690202 | K18: 0.2083132 | L18: 0.23400013 | M18: 0.20586231 | N18: 0.23648189 | O18: 0.36784459 | P18: 0.47876285 | Q18: Calculation (Oil for biodiesel/total oil)
A20: ECONOMICS | B20: 2010 | C20: 2011 | D20: 2012 | E20: 2013 | F20: 2014 | G20: 2015 | H20: 2016 | I20: 2017 | J20: 2018 | K20: 2019 | L20: 2020 | M20: 2021 | N20: 2022 | O20: 2023 | P20: 2024 | Q20: Source Name | R20: Source URL | S20: Comments
A21: Average Canola Price (dollar per metric tons) | B21: 318.8832 | C21: 379.90406 | D21: 472.41956 | E21: 521.62993 | F21: 405.49345 | G21: 332.6621 | H21: 307.07271 | I21: 326.75686 | J21: 344.47259 | K21: 311.00954 | L21: 291.32539 | M21: 362.18833 | N21: 647.60847 | O21: 586.58762 | P21: 478.3248 | Q21: USDA | R21: https://www.ers.usda.gov/data-products/oil-crops-yearbook/oil-crops-yearbook/ | S21: Retrieved January 2026 1 cwt = 0.0508023 metric ton
A22: Canola Oil Price (dollars per metric ton) | B22: 945.34191 | C22: 1293.6722 | D22: 1260.8233 | E22: 1238.3362 | F22: 963.41981 | G22: 833.56758 | H22: 777.57018 | I22: 853.8501 | J22: 843.70884 | K22: 795.64808 | L22: 834.89035 | M22: 1553.3767 | N22: 1995.6238 | O22: 1612.4605 | P22: 1223.1243 | Q22: USDA | R22: https://www.ers.usda.gov/data-products/oil-crops-yearbook/oil-crops-yearbook/ | S22: Retrieved January 2026 1 metric ton = 2,204.622 pounds
A23: Total Volume of Canola Grown in the U.S. (billion dollars) | B23: 0.471068 | C23: 0.364197 | D23: 0.630253 | E23: 0.454935 | F23: 0.422492 | G23: 0.448253 | H23: 0.509325 | I23: 0.526211 | J23: 0.567556 | K23: 0.501152 | L23: 0.644009 | M23: 0.887509 | N23: 1.131398 | O23: 0.997526 | P23: 0.95222 | Q23: USDA-NASS | R23: https://quickstats.nass.usda.gov/results/3E507DA6-3070-3BED-B57D-AF15AA455D65 | S23: Retrieved January 2026
A24: Value of Canola Used for Biodiesel (billion dollars) | B24: =+B17*B22/1000 -> 0.1333568 | C24: =+C17*C22/1000 -> 0.378486 | D24: =+D17*D22/1000 -> 0.5513116 | E24: =+E17*E22/1000 -> 0.2409693 | F24: =+F17*F22/1000 -> 0.4257691 | G24: =+G17*G22/1000 -> 0.35359156 | H24: =+H17*H22/1000 -> 0.35554629 | I24: =+I17*I22/1000 -> 0.5013095 | ... P24: =+P17*P22/1000 -> 2.4061114 | Q24: Calculation
A47: Feed
A48: Fuel Alcohol
A49: High Fructose Corn Syrup
A50: Glucose and Dextrose
A51: Starch
A52: Cereal
A53: Alcoholic Beverages
A54: Seed

Sheet SUNFLOWERS
A1: SUNFLOWERS
A3: PHYSICAL | B3: 2010 | C3: 2011 | D3: 2012 | E3: 2013 | F3: 2014 | G3: 2015 | H3: 2016 | I3: 2017 | J3: 2018 | K3: 2019 | L3: 2020 | M3: 2021 | N3: 2022 | O3: 2023 | P3: 2024 | Q3: Source Name | R3: Source URL | S3: Comments
A4: Number of Farms Growing Sunflowers in the United States (thousand farms) | D4: 4.953 | I4: 3.389 | N4: 3.623 | Q4: USDA | R4: https://quickstats.nass.usda.gov/results/2EE254E7-6090-3BDD-AEDA-0C962B3A0E6C | S4: Retrieved January 2026
A5: Planted Acreage of Sunflower Planted in the United States (million acres) | B5: 1.463 | C5: 1.2895 | D5: 1.658 | E5: 1.279 | F5: 1.174 | G5: 1.5505 | H5: 1.418 | I5: 1.216 | J5: 1.161 | K5: 1.193 | L5: 1.484 | M5: 1.176 | N5: 1.544 | O5: 1.161 | P5: 0.594 | Q5: USDA | R5: https://www.ers.usda.gov/data-products/oil-crops-yearbook/oil-crops-yearbook/ | S5: Retrieved April 2018
A7: PRODUCTION | B7: 2010 | C7: 2011 | D7: 2012 | E7: 2013 | F7: 2014 | G7: 2015 | H7: 2016 | I7: 2017 | J7: 2018 | K7: 2019 | L7: 2020 | M7: 2021 | N7: 2022 | O7: 2023 | P7: 2024 | Q7: Source Name | R7: Source URL | S7: Comments
A8: Total Volume of Sunflowers Grown in the US (million metric tons) | B8: 1.3773155 | C8: 1.240834 | D8: 0.92454625 | E8: 1.2410563 | F8: 0.91705744 | G8: 1.0035054 | H8: 1.3267717 | I8: 1.2027617 | J8: 0.96966736 | K8: 0.95304093 | L8: 0.88429445 | M8: 1.3506261 | N8: 0.86155132 | O8: 1.2739395 | P8: 1.0240712 | Q8: USDA | R8: https://www.ers.usda.gov/data-products/oil-crops-yearbook/oil-crops-yearbook/ | S8: Retrieved January 2026 1 metric ton = 2,204.622 pounds
A9: Total volume of Sunflowers consumption (million metric tons) | B9: 1.290888 | C9: 1.1803066 | D9: 0.89335224 | E9: 1.0909739 | F9: 0.92565755 | G9: 0.94561154 | H9: 1.2201502 | I9: 1.1119719 | J9: 1.0804488 | K9: 1.0494251 | L9: 1.0619222 | M9: 1.3712287 | N9: 1.0310567 | O9: 1.332018 | P9: 1.0493212 | Q9: USDA | R9: https://www.ers.usda.gov/data-products/oil-crops-yearbook/oil-crops-yearbook/ | S9: Retrieved January 2026 1 metric ton = 2,204.622 pounds
A10: Sunflowers imports (million metric tons) | B10: 0.046478262 | C10: 0.040649599 | D10: 0.044082387 | E10: 0.053476741 | F10: 0.065244291 | G10: 0.074913976 | H10: 0.07154832 | I10: 0.079756076 | J10: 0.096961021 | K10: 0.11523014 | L10: 0.18105344 | M10: 0.17014137 | N10: 0.17392156 | O10: 0.14015663 | P10: 0.15686412 | Q10: USDA | R10: https://www.ers.usda.gov/data-products/oil-crops-yearbook/oil-crops-yearbook/ | S10: Retrieved January 2026 1 metric ton = 2,204.622 pounds
A11: Sunflowers exports (million metric tons) | B11: 0.17917947 | C11: 0.16046288 | D11: 0.1060404 | E11: 0.13641522 | F11: 0.11974978 | G11: 0.1158126 | H11: 0.098872278 | I11: 0.090010525 | J11: 0.078512922 | K11: 0.064377618 | L11: 0.044858213 | M11: 0.058683217 | N11: 0.049776814 | O11: 0.049726514 | P11: 0.038348311 | Q11: USDA | R11: https://www.ers.usda.gov/data-products/oil-crops-yearbook/oil-crops-yearbook/ | S11: Retrieved January 2026 1 metric ton = 2,204.622 pounds
A12: Beginning stocks (million metric tons) | B12: 0.22288991 | C12: 0.17661622 | D12: 0.11733032 | E12: 0.086566314 | F12: 0.15371025 | G12: 0.090604648 | H12: 0.10759985 | I12: 0.18689735 | J12: 0.26743269 | K12: 0.1750994 | L12: 0.12956779 | M12: 0.08813529 | N12: 0.17899082 | O12: 0.13363016 | P12: 0.16598174 | Q12: USDA | R12: https://www.ers.usda.gov/data-products/oil-crops-yearbook/oil-crops-yearbook/ | S12: Retrieved January 2026 1 metric ton = 2,204.622 pounds
A13: Ending stocks (million metric tons) | B13: 1.4700674 | C13: 1.3407695 | D13: 0.99939264 | E13: 1.2273891 | F13: 1.0454073 | G13: 1.0614241 | H13: 1.3190225 | I13: 1.2019825 | J13: 1.1589617 | K13: 1.1138027 | L13: 1.1067804 | M13: 1.4299119 | N13: 1.0808335 | O13: 1.3817445 | P13: 1.0876695 | Q13: USDA | R13: https://www.ers.usda.gov/data-products/oil-crops-yearbook/oil-crops-yearbook/ | S13: Retrieved January 2026 1 metric ton = 2,204.622 pounds
A14: Uses
A15: Volume of Sunflowers Crushed (million metric tons) | B15: 0.77632356 | C15: 0.58784136 | D15: 0.34938098 | E15: 0.45079293 | F15: 0.46274599 | G15: 0.36604915 | H15: 0.49500005 | I15: 0.50800001 | J15: 0.47500011 | K15: 0.48500015 | L15: 0.38900011 | M15: 0.50400014 | N15: 0.4350001 | O15: 0.41100012 | P15: 0.37800013 | Q15: USDA | R15: https://www.ers.usda.gov/data-products/oil-crops-yearbook/oil-crops-yearbook/ | S15: Retrieved January 2026 1 metric ton = 2,204.622 pounds
A16: Volume of Sunflowers Nonoil use and seed (million metric tons) | B16: 0.5145644 | C16: 0.59246528 | D16: 0.54397126 | E16: 0.64018095 | F16: 0.46291156 | G16: 0.57956239 | H16: 0.72515016 | I16: 0.60397194 | J16: 0.60544864 | K16: 0.56442492 | L16: 0.67292207 | M16: 0.86722857 | N16: 0.59605662 | O16: 0.9210179 | P16: 0.67132106 | Q16: USDA | R16: https://www.ers.usda.gov/data-products/oil-crops-yearbook/oil-crops-yearbook/ | S16: Retrieved January 2026 1 metric ton = 2,204.622 pounds
A18: ECONOMICS | B18: 2010 | C18: 2011 | D18: 2012 | E18: 2013 | F18: 2014 | G18: 2015 | H18: 2016 | I18: 2017 | J18: 2018 | K18: 2019 | L18: 2020 | M18: 2021 | N18: 2022 | O18: 2023 | P18: 2024 | Q18: Source Name | R18: Source URL | S18: Comments
A19: Average Sunflowers Price (dollar per metric tons) | B19: 297.23064 | C19: 458.64065 | D19: 572.80871 | E19: 499.97736 | F19: 421.24077 | G19: 427.14602 | H19: 385.8093 | I19: 342.50418 | J19: 338.56735 | K19: 342.50418 | L19: 383.84089 | M19: 419.27236 | N19: 647.60847 | O19: 547.21932 | P19: 417.30394 | Q19: USDA | R19: https://www.ers.usda.gov/data-products/oil-crops-yearbook/oil-crops-yearbook/ | S19: Retrieved January 2026 1 cwt = 0.0508023 metric ton
A20: Sunflower Oil Price (dollars per metric ton) | B20: 1164.0404 | C20: 1898.6205 | D20: 1834.2455 | E20: 1452.1845 | F20: 1303.3725 | G20: 1470.9238 | H20: 1274.492 | I20: 1180.3546 | J20: 1203.0622 | K20: 1174.6226 | L20: 1433.6657 | M20: 1741.6514 | N20: 2455.7284 | O20: 1766.1227 | P20: 1293.0108 | Q20: USDA-ERS (Oil Crops Outlook 2018) | R20: https://www.ers.usda.gov/publications/pub-details/?pubid=86740 | S20: Retrieved January 2026 1 metric ton = 2,204.622 pounds
A21: Total Volume of Sunflowers Grown in the US (billion dollars) | B21: 0.633778 | C21: 0.589282 | D21: 0.69997 | E21: 0.443296 | F21: 0.496469 | G21: 0.574481 | H21: 0.464015 | I21: 0.375077 | J21: 0.369423 | K21: 0.385263 | L21: 0.630923 | M21: 0.616357 | N21: 0.763085 | O21: 0.458081 | P21: 0.22733 | Q21: USDA | R21: https://www.ers.usda.gov/data-products/oil-crops-yearbook/oil-crops-yearbook/ | S21: Retrieved January 2026
A44: Feed
A45: Fuel Alcohol
A46: High Fructose Corn Syrup
A47: Glucose and Dextrose
A48: Starch
A49: Cereal
A50: Alcoholic Beverages
A51: Seed

Sheet PEANUTS
A1: PEANUTS
A3: PHYSICAL | B3: 2010 | C3: 2011 | D3: 2012 | E3: 2013 | F3: 2014 | G3: 2015 | H3: 2016 | I3: 2017 | J3: 2018 | K3: 2019 | L3: 2020 | M3: 2021 | N3: 2022 | O3: 2023 | P3: 2024 | Q3: Source Name | R3: Source URL | S3: Comments
A4: Number of Farms Growing Peanuts in the United States (thousand farms) | D4: 6.561 | I4: 6.379 | N4: 4.919 | Q4: USDA | R4: https://quickstats.nass.usda.gov/results/D8B4A523-8516-3545-ACC8-8CB860F8EAAE | S4: Retrieved January 2026
A5: Planted Acreage of Peanuts Planted in the United States (million acres) | B5: 1.288 | C5: 1.1406 | D5: 1.638 | E5: 1.067 | F5: 1.3535 | G5: 1.625 | H5: 1.671 | I5: 1.8716 | J5: 1.4196 | K5: 1.4294 | L5: 1.6585 | M5: 1.5783 | N5: 1.4485 | O5: 1.645 | P5: 1.801 | Q5: USDA | R5: https://www.ers.usda.gov/data-products/oil-crops-yearbook/oil-crops-yearbook/ | S5: Retrieved January 2026
A7: PRODUCTION | B7: 2010 | C7: 2011 | D7: 2012 | E7: 2013 | F7: 2014 | G7: 2015 | H7: 2016 | I7: 2017 | J7: 2018 | K7: 2019 | L7: 2020 | M7: 2021 | N7: 2022 | O7: 2023 | P7: 2024 | Q7: Source Name | R7: Source URL | S7: Comments
A8: Total Volume of Peanuts Grown in the U.S. (million metric tons) | B8: 1.6745047 | C8: 1.8855114 | D8: 1.659509 | E8: 3.0635093 | F8: 1.8929186 | G8: 2.3535395 | H8: 2.7221705 | I8: 2.5317583 | J8: 3.2274966 | K8: 2.490935 | L8: 2.4788104 | M8: 2.7953772 | N8: 2.8844809 | O8: 2.5137062 | P8: 2.6660171 | Q8: USDA | R8: https://www.ers.usda.gov/data-products/oil-crops-yearbook/oil-crops-yearbook/ | S8: Retrieved January 2026 1 metric ton = 2,204.622 pounds
A9: Total volume of Peanuts consumption (million metric tons) | B9: 1.5751449 | C9: 1.7819003 | D9: 1.7594699 | E9: 1.7758804 | F9: 1.8496252 | G9: 1.7941497 | H9: 2.2051249 | I9: 2.1612022 | J9: 2.1494288 | K9: 2.1342641 | L9: 1.9376978 | M9: 2.2699879 | N9: 2.218059 | O9: 2.1658849 | P9: 2.3037922 | Q9: USDA | R9: https://www.ers.usda.gov/data-products/oil-crops-yearbook/oil-crops-yearbook/ | S9: Retrieved January 2026 1 metric ton = 2,204.622 pounds
A10: Peanuts imports (million metric tons) | B10: 0.032653444 | C10: 0.029415927 | D10: 0.11519154 | E10: 0.053927748 | F10: 0.039831681 | G10: 0.040671643 | H10: 0.042772412 | I10: 0.073343503 | J10: 0.077289304 | K10: 0.053117904 | L10: 0.051908037 | M10: 0.054891859 | N10: 0.048548277 | O10: 0.046779765 | P10: 0.047315912 | Q10: USDA | R10: https://www.ers.usda.gov/data-products/oil-crops-yearbook/oil-crops-yearbook/ | S10: Retrieved January 2026 1 metric ton = 2,204.622 pounds
A11: Peanuts exports (million metric tons) | B11: 0.26870434 | C11: 0.27491493 | D11: 0.24774578 | E11: 0.53986906 | F11: 0.49724234 | G11: 0.48972958 | H11: 0.70048249 | I11: 0.60234539 | J11: 0.57680532 | K11: 0.5440476 | L11: 0.73041474 | M11: 0.64833178 | N11: 0.53711883 | O11: 0.54300334 | P11: 0.6601343 | Q11: USDA | R11: https://www.ers.usda.gov/data-products/oil-crops-yearbook/oil-crops-yearbook/ | S11: Retrieved January 2026 1 metric ton = 2,204.622 pounds
A12: Beginning stocks (million metric tons) | B12: 0.96619738 | C12: 0.82950637 | D12: 0.68761856 | E12: 0.45510341 | F12: 1.256791 | G12: 0.84267371 | H12: 0.95300555 | I12: 0.81234107 | J12: 0.65389532 | K12: 1.2324471 | L12: 1.0981883 | M12: 0.96079419 | N12: 0.89274352 | O12: 1.0705949 | P12: 0.92219256 | Q12: USDA | R12: https://www.ers.usda.gov/data-products/oil-crops-yearbook/oil-crops-yearbook/ | S12: Retrieved January 2026 1 metric ton = 2,204.622 pounds
A13: Ending stocks (million metric tons) | B13: 1.8438419 | C13: 2.0566977 | D13: 2.0071897 | E13: 2.1364542 | F13: 2.0743833 | G13: 2.431518 | H13: 1.9912398 | I13: 2.4399171 | J13: 2.293742 | K13: 2.0912692 | L13: 1.9898268 | M13: 2.4045215 | N13: 2.2912291 | O13: 1.9758299 | P13: 1.9771308 | Q13: USDA | R13: https://www.ers.usda.gov/data-products/oil-crops-yearbook/oil-crops-yearbook/ | S13: Retrieved January 2026 1 metric ton = 2,204.622 pounds
A14: Uses
A15: Volume of Peanuts Crushed (million metric tons) | B15: 0.19762771 | C15: 0.26671602 | D15: 0.274468 | E15: 0.29827798 | F15: 0.30073763 | G15: 0.3064255 | H15: 0.32160112 | I15: 0.39913087 | J15: 0.31977473 | K15: 0.29416131 | L15: 0.35114922 | M15: 0.39594552 | N15: 0.38212097 | O15: 0.36047123 | P15: 0.29675636 | Q15: USDA | R15: https://www.ers.usda.gov/data-products/oil-crops-yearbook/oil-crops-yearbook/ | S15: Retrieved January 2026 1 metric ton = 2,204.622 pounds
A16: Volume of Peanuts Food (million metric tons) | B16: 0.94140921 | C16: 1.0062649 | D16: 0.99188667 | E16: 1.0207051 | F16: 1.0501434 | G16: 1.0761672 | H16: 1.1067105 | I16: 1.1093225 | J16: 1.1190393 | K16: 1.1135353 | L16: 1.1473107 | M16: 1.1885252 | N16: 1.1846198 | O16: 1.1753717 | P16: 1.1311193 | Q16: USDA | R16: https://www.ers.usda.gov/data-products/oil-crops-yearbook/oil-crops-yearbook/ | S16: Retrieved January 2026 1 metric ton = 2,204.622 pounds
A17: Peanut candy | B17: 0.14315152 | C17: 0.17937406 | D17: 0.17902298 | E17: 0.17323333 | F17: 0.17949834 | G17: 0.17048546 | H17: 0.17123344 | I17: 0.18493012 | J17: 0.17214017 | K17: 0.17278971 | L17: 0.17946251 | M17: 0.19649899 | N17: 0.2223202 | O17: 0.20038764 | P17: 0.18608224 | Q17: USDA | R17: https://www.ers.usda.gov/data-products/oil-crops-yearbook/oil-crops-yearbook/ | S17: Retrieved January 2026 1 metric ton = 2,204.622 pounds
A18: Snack peanuts | B18: 0.16010137 | C18: 0.17924932 | D18: 0.17693192 | E18: 0.18163159 | F18: 0.19495224 | G18: 0.19435395 | H18: 0.2293781 | I18: 0.21332092 | J18: 0.23806575 | K18: 0.21213433 | L18: 0.21837304 | M18: 0.22931278 | N18: 0.2201552 | O18: 0.20666717 | P18: 0.18404833 | Q18: USDA | R18: https://www.ers.usda.gov/data-products/oil-crops-yearbook/oil-crops-yearbook/ | S18: Retrieved January 2026 1 metric ton = 2,204.622 pounds
A19: Peanut butter | B19: 0.54060106 | C19: 0.55031157 | D19: 0.54328951 | E19: 0.55694763 | F19: 0.55255277 | G19: 0.59137349 | H19: 0.58950423 | I19: 0.60699521 | J19: 0.59627773 | K19: 0.60891935 | L19: 0.63968517 | M19: 0.6571884 | N19: 0.63916626 | O19: 0.67139537 | P19: 0.65897601 | Q19: USDA | R19: https://www.ers.usda.gov/data-products/oil-crops-yearbook/oil-crops-yearbook/ | S19: Retrieved January 2026 1 metric ton = 2,204.622 pounds
A20: Other uses | B20: 0.0071849052 | C20: 0.0076611773 | D20: 0.0089180821 | E20: 0.0093730354 | F20: 0.013200902 | G20: 0.024121595 | H20: 0.027845136 | I20: 0.025749993 | J20: 0.043519025 | K20: 0.051097648 | L20: 0.041534104 | M20: 0.032965288 | N20: 0.027294021 | O20: 0.020571327 | P20: 0.024810602 | Q20: USDA | R20: https://www.ers.usda.gov/data-products/oil-crops-yearbook/oil-crops-yearbook/ | S20: Retrieved January 2026 1 metric ton = 2,204.622 pounds
A21: Clean in-shell | B21: 0.090370343 | C21: 0.089668791 | D21: 0.083724181 | E21: 0.099519517 | F21: 0.10993912 | G21: 0.095832699 | H21: 0.088749644 | I21: 0.078326285 | J21: 0.069036596 | K21: 0.068594246 | L21: 0.068255918 | M21: 0.072559706 | N21: 0.075684122 | O21: 0.076350205 | P21: 0.077202163 | Q21: USDA | R21: https://www.ers.usda.gov/data-products/oil-crops-yearbook/oil-crops-yearbook/ | S21: Retrieved January 2026 1 metric ton = 2,204.622 pounds
A22: Volume of Peanuts Seed, loss, shrinkage, and residual (million metric tons) | B22: 0.19323249 | C22: 0.24335623 | D22: 0.2270538 | E22: 0.2101289 | F22: 0.24839251 | G22: 0.13515678 | H22: 0.47883855 | I22: 0.35171617 | J22: 0.38954324 | K22: 0.40947205 | L22: 0.10733808 | M22: 0.34566248 | N22: 0.32892228 | O22: 0.30923886 | P22: 0.59028505 | Q22: USDA | R22: https://www.ers.usda.gov/data-products/oil-crops-yearbook/oil-crops-yearbook/ | S22: Retrieved January 2026 1 metric ton = 2,204.622 pounds
A24: ECONOMICS | B24: 2010 | C24: 2011 | D24: 2012 | E24: 2013 | F24: 2014 | G24: 2015 | H24: 2016 | I24: 2017 | J24: 2018 | K24: 2019 | L24: 2020 | M24: 2021 | N24: 2022 | O24: 2023 | P24: 2024 | Q24: Source Name | R24: Source URL | S24: Comments
A25: Average Peanuts Price (dollar per metric tons) | B25: 478.40297 | C25: 496.03995 | D25: 701.0698 | E25: 663.59122 | F25: 548.95088 | G25: 485.01684 | H25: 425.49205 | I25: 434.31053 | J25: 504.85844 | K25: 473.99373 | L25: 451.94751 | M25: 462.97062 | N25: 535.72315 | O25: 590.8387 | P25: 593.04332 | Q25: USDA | R25: https://www.ers.usda.gov/data-products/oil-crops-yearbook/oil-crops-yearbook/ | S25: Retrieved January 2026 1 metric ton = 2,204.622 pounds
A26: Peanut Oil Price (dollars per metric ton) | B26: 1400.9917 | C26: 1866.09 | D26: 2359.0583 | E26: 1820.6217 | F26: 1394.985 | G26: 1377.9592 | H26: 1380.6308 | I26: 1460.7925 | J26: 1446.21 | K26: 1411.785 | L26: 1707.9167 | M26: 2075.095 | N26: 2202.5525 | O26: 2034.655 | P26: 1795.515 | Q26: Index Mundi | R26: https://www.indexmundi.com/commodities/?commodity=peanut-oil&months=240 | S26: Retrieved January 2026
A27: Total Volume of Peanuts Grown in the U.S. (billion dollars) | B27: 0.938611 | C27: 1.168587 | D27: 2.026326 | E27: 1.0550953 | F27: 1.158251 | G27: 1.16056 | H27: 1.088165 | I27: 1.634017 | J27: 1.175137 | K27: 1.130914 | L27: 1.295647 | M27: 1.561993 | N27: 1.501234 | O27: 1.61005 | P27: 1.684567 | Q27: USDA | R27: https://www.ers.usda.gov/data-products/oil-crops-yearbook/oil-crops-yearbook/ | S27: Retrieved January 2026
A50: Feed
A51: Fuel Alcohol
A52: High Fructose Corn Syrup
A53: Glucose and Dextrose
A54: Starch
A55: Cereal
A56: Alcoholic Beverages
A57: Seed

Sheet COTTON
A1: COTTON
A3: PHYSICAL | B3: 2010 | C3: 2011 | D3: 2012 | E3: 2013 | F3: 2014 | G3: 2015 | H3: 2016 | I3: 2017 | J3: 2018 | K3: 2019 | L3: 2020 | M3: 2021 | N3: 2022 | O3: 2023 | P3: 2024 | Q3: Source Name | R3: Source URL | S3: Comments
A4: Number of Farms Growing Cotton in the United States (thousand farms) | D4: 18.155 | I4: 16.149 | N4: 14.283 | Q4: USDA | R4: https://quickstats.nass.usda.gov/results/EBCC6EA4-210F-34A1-B822-4B50728DA70D | S4: Retrieved January 2026
A5: Planted Acreage of Cotton Planted in the United States (million acres) | B5: 10.9742 | C5: 14.7354 | D5: 12.2644 | E5: 10.407 | F5: 11.1484 | G5: 8.5805 | H5: 10.0735 | I5: 12.7175 | J5: 14.0813 | K5: 13.7227 | L5: 12.086 | M5: 11.2065 | N5: 13.749 | O5: 10.23 | P5: 11.182 | Q5: USDA | R5: https://www.ers.usda.gov/data-products/oil-crops-yearbook/oil-crops-yearbook/ | S5: Retrieved January 2026
A7: PRODUCTION | B7: 2010 | C7: 2011 | D7: 2012 | E7: 2013 | F7: 2014 | G7: 2015 | H7: 2016 | I7: 2017 | J7: 2018 | K7: 2019 | L7: 2020 | M7: 2021 | N7: 2022 | O7: 2023 | P7: 2024 | Q7: Source Name | R7: Source URL | S7: Comments
A8: Total Volume of Cotton Grown in the US (million metric tons) | B8: 3.7637291 | C8: 5.5302905 | D8: 4.8715835 | E8: 5.1401102 | F8: 3.8128986 | G8: 4.6493231 | H8: 3.667749 | I8: 4.8706763 | J8: 5.8259421 | K8: 5.1083587 | L8: 5.3932148 | M8: 4.0533026 | N8: 4.8289458 | O8: 4.0052218 | P8: 3.3057821 | Q8: USDA | R8: https://www.ers.usda.gov/data-products/oil-crops-yearbook/oil-crops-yearbook/ | S8: Retrieved January 2026 1 short ton=0.907185 metric tons
A9: Total volume of Cotton consumption (million metric tons) | B9: 3.6742584 | C9: 5.030561 | D9: 4.9863523 | E9: 4.9102495 | F9: 3.7566572 | G9: 4.4860571 | H9: 3.6013312 | I9: 4.5991334 | J9: 5.3456544 | K9: 4.7340406 | L9: 5.1042009 | M9: 3.855331 | N9: 4.5856436 | O9: 3.9379634 | P9: 2.9881975 | Q9: USDA | R9: https://www.ers.usda.gov/data-products/oil-crops-yearbook/oil-crops-yearbook/ | S9: Retrieved January 2026 1 short ton=0.907185 metric tons
A10: Cotton imports (million metric tons) | B10: 0.021953877 | C10: 0.0002721555 | D10: 0.064954446 | E10: 0 | F10: 0.082190961 | G10: 0.0544311 | H10: 0.014877834 | I10: 0.046357154 | J10: 0 | K10: 0.00045731196 | L10: 0.00098728944 | M10: 0.00084567786 | N10: 0.022467072 | O10: 0.091752509 | P10: 0.021903528 | Q10: USDA | R10: https://www.ers.usda.gov/data-products/oil-crops-yearbook/oil-crops-yearbook/ | S10: Retrieved January 2026 1 short ton=0.907185 metric tons
A11: Cotton exports (million metric tons) | B11: 0.26791406 | C11: 0.24961858 | D11: 0.12037348 | E11: 0.17361523 | F11: 0.1986059 | G11: 0.20696517 | H11: 0.12347969 | I11: 0.30994397 | J11: 0.43372182 | K11: 0.35127764 | L11: 0.3090303 | M11: 0.25379897 | N11: 0.26579704 | O11: 0.16828354 | P11: 0.35315551 | Q11: USDA | R11: https://www.ers.usda.gov/data-products/oil-crops-yearbook/oil-crops-yearbook/ | S11: Retrieved January 2026 1 short ton=0.907185 metric tons
A12: Beginning stocks (million metric tons) | B12: 0.46638381 | C12: 0.3098944 | D12: 0.56027746 | E12: 0.39008955 | F12: 0.44633502 | G12: 0.38616144 | H12: 0.39689344 | I12: 0.35470934 | J12: 0.36266535 | K12: 0.40922943 | L12: 0.43270547 | M12: 0.41368262 | N12: 0.3587288 | O12: 0.35872036 | P12: 0.34948431 | Q12: USDA | R12: https://www.ers.usda.gov/data-products/oil-crops-yearbook/oil-crops-yearbook/ | S12: Retrieved January 2026 1 short ton=0.907185 metric tons
A13: Ending stocks (million metric tons) | B13: 0.3098944 | C13: 0.56027746 | D13: 0.39008955 | E13: 0.44633502 | F13: 0.38616144 | G13: 0.39689344 | H13: 0.35470934 | I13: 0.36266535 | J13: 0.40923115 | K13: 0.43272724 | L13: 0.41367636 | M13: 0.35870095 | N13: 0.35870095 | O13: 0.34944766 | P13: 0.33581694 | Q13: USDA | R13: https://www.ers.usda.gov/data-products/oil-crops-yearbook/oil-crops-yearbook/ | S13: Retrieved January 2026 1 short ton=0.907185 metric tons
A14: Uses
A15: Volume of Cottonseed Crushed (million metric tons) | B15: 1.7242837 | C15: 2.3247079 | D15: 2.177244 | E15: 2.2679625 | F15: 1.81437 | G15: 1.7236515 | H15: 1.3607775 | I15: 1.6052094 | J15: 1.6815363 | K15: 1.5970166 | L15: 1.5531098 | M15: 1.417697 | N15: 1.4124725 | O15: 1.2608239 | P15: 1.244588 | Q15: USDA | R15: https://www.ers.usda.gov/data-products/oil-crops-yearbook/oil-crops-yearbook/ | S15: Retrieved January 2026 1 short ton=0.907185 metric tons
A16: Volume of Cottonseed Other (million metric tons) | B16: 1.9499746 | C16: 2.7058531 | D16: 2.8091083 | E16: 2.642287 | F16: 1.9422872 | G16: 2.7624056 | H16: 2.2405537 | I16: 2.993924 | J16: 3.6641181 | K16: 3.1370457 | L16: 3.551085 | M16: 2.4376061 | N16: 3.1731517 | O16: 2.6771029 | P16: 1.7436096 | Q16: USDA | R16: https://www.ers.usda.gov/data-products/oil-crops-yearbook/oil-crops-yearbook/ | S16: Retrieved January 2026 1 short ton=0.907185 metric tons
A18: ECONOMICS | B18: 2010 | C18: 2011 | D18: 2012 | E18: 2013 | F18: 2014 | G18: 2015 | H18: 2016 | I18: 2017 | J18: 2018 | K18: 2019 | L18: 2020 | M18: 2021 | N18: 2022 | O18: 2023 | P18: 2024 | Q18: Source Name | R18: Source URL | S18: Comments
A19: Average Cotton Price (dollar per metric tons) | B19: 174.16514 | C19: 177.47207 | D19: 286.60086 | E19: 277.78237 | F19: 271.1685 | G19: 213.84833 | H19: 250.2246 | I19: 214.95064 | J19: 156.52816 | K19: 170.8582 | L19: 177.47207 | M19: 213.84833 | N19: 267.86157 | O19: 337.30716 | P19: 245.81535 | Q19: USDA | R19: https://www.ers.usda.gov/data-products/oil-crops-yearbook/oil-crops-yearbook/ | S19: Retrieved January 2026 1 short ton=0.907185 metric tons
A20: Cottonseed Oil Price (dollars per metric ton) | B20: 887.81965 | C20: 1201.519 | D20: 1173.2998 | E20: 1071.4463 | F20: 1337.3237 | G20: 1008.3941 | H20: 1011.2601 | I20: 902.13132 | J20: 702.61303 | K20: 774.70417 | L20: 885.81712 | M20: 1784.421 | N20: 2362.2525 | O20: 2260.3989 | P20: 1740.3286 | Q20: USDA | R20: https://www.ers.usda.gov/data-products/oil-crops-yearbook/oil-crops-yearbook/ | S20: Retrieved January 2026 1 metric ton = 2,204.622 pounds
A21: Total Volume of Cotton Grown in the US (billion dollars) | B21: 0.988656 | C21: 1.413343 | D21: 1.456245 | E21: 1.054003 | F21: 1.015607 | G21: 0.932894 | H21: 1.055924 | I21: 0.911925 | J21: 0.878254 | K21: 0.968027 | L21: 0.875057 | M21: 1.3016 | N21: 1.35587 | O21: 0.835248 | P21: 0.998681 | Q21: USDA | R21: https://www.ers.usda.gov/data-products/oil-crops-yearbook/oil-crops-yearbook/ | S21: Retrieved January 2026
A44: Feed
A45: Fuel Alcohol
A46: High Fructose Corn Syrup
A47: Glucose and Dextrose
A48: Starch
A49: Cereal
A50: Alcoholic Beverages
A51: Seed

Sheet ETHANOL
A1: ETHANOL
A3: PHYSICAL | B3: 2010 | C3: 2011 | D3: 2012 | E3: 2013 | F3: 2014 | G3: 2015 | H3: 2016 | I3: 2017 | J3: 2018 | K3: 2019 | L3: 2020 | M3: 2021 | N3: 2022 | O3: 2023 | P3: 2024 | Q3: Source Name | R3: Source URL | S3: Comments
A4: Number of Ethanol Plants installed in the United States | B4: 204 | C4: 209 | D4: 211 | E4: 210 | F4: 213 | G4: 214 | H4: 213 | I4: 209 | J4: 210 | K4: 205 | L4: 208 | M4: 208 | N4: 199 | O4: 198 | P4: 198 | Q4: RFA | R4: http://www.ethanolrfa.org/pocket-guide/ | S4: Retrieved January 2026
A5: Number Ethanol Plants in the United States-Starch | H5: 203 | I5: 202 | J5: 204 | K5: 199 | L5: 201 | M5: 199 | N5: 195 | O5: 197 | P5: 195 | Q5: Ethanol producer RFA | R5: https://ethanolproducer.com/plants/list/ethanol | S5: Retrieved January 2026
A6: Number Ethanol Plants in the United States-Cellulosic | H6: 10 | I6: 7 | J6: 6 | K6: 6 | L6: 11 | M6: 11 | N6: 8 | O6: 9 | P6: 3 | Q6: Ethanol producer RFA | R6: https://ethanolproducer.com/plants/list/ethanol | S6: Retrieved January 2026
A7: Number Ethanol Plants in the United States-Corn | J7: 196 | K7: 197 | L7: 199 | M7: 198 | N7: 190 | O7: 195 | P7: 194 | Q7: Ethanol producer RFA | R7: https://ethanolproducer.com/plants/list/ethanol | S7: Retrieved January 2026
A8: Number Ethanol Plants in the United States-Sorghum | J8: 13 | K8: 14 | L8: 9 | M8: 10 | N8: 12 | O8: 10 | P8: 1 | Q8: Ethanol producer RFA | R8: https://ethanolproducer.com/plants/list/ethanol | S8: Retrieved January 2026
A9: Number Ethanol Plants in the United States-Other (Tobacco, crop residue, waste stream) | J9: 5 | K9: 4 | L9: 8 | M9: 9 | N9: 5 | O9: 7 | P9: 3 | Q9: Ethanol producer RFA | R9: https://ethanolproducer.com/plants/list/ethanol | S9: Retrieved January 2026
A10: Number of Ethanol Plants Operational in the United States | C10: 193 | D10: 194 | E10: 192 | F10: 198 | G10: 199 | H10: 200 | I10: 201 | J10: 199 | K10: 200 | L10: 201 | M10: 197 | N10: 192 | O10: 187 | P10: 194 | Q10: Ethanol producer RFA | R10: https://ethanolproducer.com/plants/list/ethanol | S10: Retrieved January 2026
A11: Number of Existing Plants Under Construction | E11: 7 | F11: 3 | G11: 3 | H11: 3 | I11: 7 | J11: 9 | K11: 4 | L11: 1 | M11: 5 | N11: 4 | O11: 2 | P11: 2 | Q11: Ethanol producer RFA | R11: https://ethanolproducer.com/plants/list/ethanol | S11: Retrieved January 2026
A12: Number Proposed Ethanol Plants in the United States | I12: 11 | J12: 1 | K12: 1 | N12: 0 | O12: 1 | P12: 1 | Q12: Ethanol producer RFA | R12: https://ethanolproducer.com/plants/list/ethanol | S12: Retrieved January 2026
A13: Number of States which have an Ethanol Production Facility | B13: 29 | C13: 29 | D13: 29 | E13: 28 | F13: 29 | G13: 29 | H13: 28 | I13: 28 | J13: 27 | K13: 26 | L13: 25 | M13: 24 | N13: 22 | O13: 22 | P13: 24 | Q13: RFA | R13: http://www.ethanolrfa.org/pocket-guide/ | S13: Retrieved January 2026
A14: Ethanol plant capacities (billion gallons) | B14: 14.46 | C14: 13.614 | D14: 13.728 | E14: 13.852 | F14: 13.681 | G14: 14.369 | H14: 14.903 | I14: 15.584 | J14: 16.542 | K14: 16.868 | L14: 17.378 | M14: 17.546 | N14: 17.38 | O14: 17.663 | P14: 18.268 | Q14: Ethanol producer RFA | R14: https://ethanolproducer.com/plants/list/ethanol | S14: Retrieved January 2026
A16: PRODUCTION | B16: 2010 | C16: 2011 | D16: 2012 | E16: 2013 | F16: 2014 | G16: 2015 | H16: 2016 | I16: 2017 | J16: 2018 | K16: 2019 | L16: 2020 | M16: 2021 | N16: 2022 | O16: 2023 | P16: 2024 | Q16: Source Name | R16: Source URL | S16: Comments
A17: Total Volume of Ethanol Produced in US (billion gallons) | B17: 13.298 | C17: 13.929 | D17: 13.218 | E17: 13.293 | F17: 14.313 | G17: 14.807 | H17: 15.413 | I17: 15.936 | J17: 16.091 | K17: 15.778 | L17: 13.941 | M17: 15.016 | N17: 15.361 | O17: 15.62 | P17: 16.225 | Q17: EIA | R17: https://www.eia.gov/totalenergy/data/monthly/pdf/mer.pdf | S17: Retrieved January 2026
A18: Total Volume of Ethanol Consumed (billion gallons) | B18: 12.858 | C18: 12.893 | D18: 12.882 | E18: 13.216 | F18: 13.444 | G18: 13.947 | H18: 14.356 | I18: 15.485 | J18: 14.42 | K18: 14.552 | L18: 12.681 | M18: 13.944 | N18: 14.023 | O18: 14.249 | P18: 14.245 | Q18: EIA | R18: https://www.eia.gov/totalenergy/data/monthly/pdf/mer.pdf | S18: Retrieved January 2026
A19: Total Volume of Ethanol Consumed: Transportation (billion gallons) | B19: 13.420745 | C19: 13.472314 | D19: 13.472314 | E19: 13.820403 | F19: 14.091138 | G19: 14.310305 | H19: 14.735838 | I19: 14.903437 | J19: 14.86476 | K19: 14.980791 | L19: 12.943816 | M19: 14.310394 | N19: 14.400639 | O19: 14.619808 | P19: 14.619808 | Q19: EIA | R19: https://www.eia.gov/totalenergy/data/monthly/pdf/mer.pdf | S19: Retrieved January 2026, Table 10.2c 1 gallon of ethanol = 77566 BTUs
A20: Total Volume of Ethanol Consumed: Industrial sector (billion gallons) | B20: 0.21916683 | C20: 0.21916683 | D20: 0.21916683 | E20: 0.232059 | F20: 0.18049033 | G20: 0.232059 | H20: 0.23206044 | I20: 0.23206044 | J20: 0.23206044 | K20: 0.23206044 | L20: 0.24495269 | M20: 0.24495269 | N20: 0.24495269 | O20: 0.24495269 | P20: 0.03867674 | Q20: EIA | R20: https://www.eia.gov/totalenergy/data/monthly/pdf/mer.pdf | S20: Retrieved January 2026, Table 10.2b 1 gallon of ethanol = 77566 BTUs
A21: Total Volume of Ethanol Imported into the US (billion gallons) | B21: 0.015666 | C21: 0.171864 | D21: 0.49413 | E21: 0.376992 | F21: 0.074676 | G21: 0.091518 | H21: 0.036204 | I21: 0.076608 | J21: 0.054348 | K21: 0.195048 | L21: 0.15414 | M21: 0.060774 | N21: 0.06909 | O21: 0.027258 | P21: 0.004 | Q21: RFA | R21: https://ethanolrfa.org/file/2909/2024%20Ethanol%20Trade%20Summary.pdf | S21: Retrieved January 2026
A22: Total Volume of Ethanol Exported From the US (billion gallons) | B22: 0.398496 | C22: 1.195194 | D22: 0.741552 | E22: 0.618954 | F22: 0.846258 | G22: 0.832062 | H22: 1.170288 | I22: 1.389864 | J22: 1.709568 | K22: 1.46664 | L22: 1.317204 | M22: 1.242444 | N22: 1.313592 | O22: 1.43346 | P22: 1.914 | Q22: RFA | R22: https://ethanolrfa.org/file/2909/2024%20Ethanol%20Trade%20Summary.pdf | S22: Retrieved January 2026
A23: CORN FOR ETHANOL | B23: 2010 | C23: 2011 | D23: 2012 | E23: 2013 | F23: 2014 | G23: 2015 | H23: 2016 | I23: 2017 | J23: 2018 | K23: 2019 | L23: 2020 | M23: 2021 | N23: 2022 | O23: 2023 | P23: 2024 | Q23: Source Name | R23: Source URL | S23: Comments
A24: Total corn used for Fuel ethanol use (million metric tons) | B24: 125.46852 | C24: 125.0008 | D24: 116.02818 | E24: 128.09225 | F24: 130.00225 | G24: 130.59035 | H24: 135.79883 | I24: 140.12068 | J24: 134.45065 | K24: 121.41688 | L24: 125.68988 | M24: 132.99038 | N24: 129.40353 | O24: 135 | P24: 137.7826 | Q24: USDA | R24: https://www.ers.usda.gov/data-products/us-bioenergy-statistics/#:~:text=Ethanol%2C%20made%20mostly%20from%20corn,all%20biofuel%20production%20in%202012.&text=ERS%20analysts%20track%20U.S.%20ethanol,production%2C%20consumption%2C%20and%20trade. | S24: Retrieved January 2026 1 bushel of corn=0.025 metric tons
A26: ECONOMICS | B26: 2010 | C26: 2011 | D26: 2012 | E26: 2013 | F26: 2014 | G26: 2015 | H26: 2016 | I26: 2017 | J26: 2018 | K26: 2019 | L26: 2020 | M26: 2021 | N26: 2022 | O26: 2023 | P26: 2024 | Q26: Source Name | R26: Source URL | S26: Comments
A27: Price for Ethanol Per gallon (dollar per gallon) | B27: 1.84 | C27: 2.56 | D27: 2.5 | E27: 2.5 | F27: 2.39 | G27: 1.82 | H27: 1.55 | I27: 1.6 | J27: 1.24 | K27: 1.3 | L27: 1.8 | M27: 2.33 | N27: 2.42 | O27: 1.83 | P27: 1.5796296 | Q27: USDA | R27: https://www.ers.usda.gov/data-products/us-bioenergy-statistics/ | S27: Retrieved January 2026
A28: Price for Ethanol Per gallon (dollar per gge) | B28: 2.76 | C28: 3.84 | D28: 3.75 | E28: 3.75 | F28: 3.585 | G28: 2.73 | H28: 2.325 | I28: 2.4 | J28: 1.86 | K28: 1.81 | L28: 2.66 | M28: 3.82 | N28: 3.42 | O28: 3.05 | P28: =+P27*1.5 -> 2.3694444 | Q28: USDA | R28: https://www.ers.usda.gov/data-products/us-bioenergy-statistics/ | S28: Retrieved January 2026 1.5 gallons ethanol = 1 gallon gasoline
A29: Price for E85 Per gallon (dollar per gge) | B29: 3.37 | C29: 4.38 | D29: 4.7075 | E29: 4.5025 | F29: 4.435 | G29: 2.95 | H29: 2.455 | I29: 2.675 | J29: 2.925 | K29: 2.905 | L29: 2.59 | M29: =(2.65+3.12+3.4+3.55)/4 -> 3.18 | N29: =(3.87+4.6+5.1+4.13)/4 -> 4.425 | O29: =(3.96+3.84+3.88+3.6)/4 -> 3.82 | P29: 3.66 | Q29: AFD | R29: https://www.afdc.energy.gov/fuels/prices.html | S29: Retrieved January 2026
A30: Price for gasoline Per gallon (dollar per gge) | B30: 2.745 | C30: 3.4775 | D30: 3.65 | E30: 3.495 | F30: 3.5075 | G30: 2.4725 | H30: 2.13 | I30: 2.3625 | J30: 2.74 | K30: 2.6175 | L30: 2.225 | M30: =(2.32+2.82+3.09+3.25)/4 -> 2.87 | N30: =(3.28+4.13+4.7+4.05)/4 -> 4.04 | O30: =(3.31+3.69+3.59+3.72)/4 -> 3.5775 | P30: 3.23 | Q30: AFD | R30: https://www.afdc.energy.gov/fuels/prices.html | S30: Retrieved January 2026
A31: Number of direct jobs working with ethanol production | B31: 70400 | C31: 90200 | D31: 70000 | E31: 86504 | F31: 83949 | G31: 85967 | H31: 74420 | I31: 71906 | J31: 71637 | K31: 68542 | L31: 62180 | M31: 73193 | N31: 78802 | O31: 72463 | P31: 55810 | Q31: RFA | R31: http://www.ethanolrfa.org/pocket-guide/ | S31: Retrieved January 2026
A32: Number of indirect and induced jobs working with ethanol production | B32: 329600 | C32: 311400 | D32: 295000 | E32: 300277 | F32: 295265 | G32: 271440 | H32: 264756 | I32: 285587 | J32: 294516 | K32: 277389 | L32: 242600 | M32: 334220 | N32: 342876 | O32: 322002 | P32: 258089 | Q32: RFA | R32: http://www.ethanolrfa.org/pocket-guide/ | S32: Retrieved January 2026
A33: GDP contribution/influence (billion dollars) | B33: 54 | C33: 42.4 | D33: 40.6 | E33: 44 | F33: 53 | G33: 44 | H33: 42 | I33: 45 | J33: 46 | K33: 42.8 | L33: 34.7 | M33: 52.1 | N33: 57 | O33: 54.2 | P33: 53 | Q33: RFA | R33: http://www.ethanolrfa.org/pocket-guide/ | S33: Retrieved January 2026
A34: Household income from industry (billion dollars) | B34: 36 | C34: 29.9 | D34: 29.9 | E34: 31 | F34: 27 | G34: 24 | H34: 23 | I34: 24 | J34: 25 | K34: 22.9 | L34: 18.6 | M34: 28.7 | N34: 34.8 | O34: 32.5 | P34: 28.3 | Q34: RFA | R34: http://www.ethanolrfa.org/pocket-guide/ | S34: Retrieved January 2026
A35: Tax Revenue (billion dollars) | D35: 7.9 | E35: 8.3 | F35: 10.3 | G35: 8.7 | H35: 8.5 | I35: 10.7 | J35: 8.8 | K35: 7.9 | L35: 6.3 | M35: 10.4 | N35: 12.3 | O35: 10.4 | P35: 10.3 | Q35: RFA | R35: "[2013-2014] http://www.ethanolrfa.org/pocket-guide/ [2019-2021] https://ethanolrfa.org/library/reports-studies-and-white-papers/ethanol-and-the-economy" | S35: Retrieved January 2026
A36: Crude oil (dollar per barrel) | B36: 79.48 | C36: 94.88 | D36: 94.05 | E36: 97.98 | F36: 93.17 | G36: 48.66 | H36: 43.29 | I36: 50.8 | J36: 65.23 | K36: 56.99 | L36: 39.68 | M36: 68.17 | N36: 94.53 | O36: 77.64 | P36: 76.6 | Q36: Macrotrends | R36: https://www.macrotrends.net/1369/crude-oil-price-history-chart | S36: Retrieved January 2026

Sheet BIODIESEL
A1: BIODIESEL
A3: PHYSICAL | B3: 2010 | C3: 2011 | D3: 2012 | E3: 2013 | F3: 2014 | G3: 2015 | H3: 2016 | I3: 2017 | J3: 2018 | K3: 2019 | L3: 2020 | M3: 2021 | N3: 2022 | O3: 2023 | P3: 2024 | Q3: Source Name | R3: Source URL | S3: Comments
A4: Number of Biodiesel Plants in the United States | C4: 103 | D4: 112 | E4: 115 | F4: 98 | G4: 94 | H4: 96 | I4: 95 | J4: 100 | K4: 91 | L4: 85 | M4: 75 | N4: 72 | O4: 59 | P4: 48 | Q4: EIA | R4: https://www.eia.gov/biofuels/biodiesel/capacity/archive/2024/index.php | S4: Retrieved January 2026
A5: Number of Proposed Biodiesel Plants | H5: 6 | I5: 0 | J5: 0 | K5: 0 | M5: 9 | O5: 3 | P5: 7 | Q5: Biodiesel Magazine | R5: http://www.biodieselmagazine.com/plants/listplants/USA/proposed/ | S5: Retrieved January 2026
A6: Number of Existing Plants Under Construction | G6: 16 | H6: 15 | I6: 10 | J6: 12 | K6: 12 | M6: 14 | O6: 3 | P6: 3 | Q6: Biodiesel Magazine | R6: http://www.biodieselmagazine.com/plants/listplants/USA/construction/ | S6: Retrieved January 2026
A7: Number of States which have a Biodiesel Production Facility | C7: 35 | D7: 37 | E7: 38 | F7: 35 | G7: 36 | H7: 37 | I7: 36 | J7: 38 | K7: 37 | L7: 33 | M7: 32 | N7: 29 | O7: 29 | P7: 26 | Q7: EIA | R7: https://www.eia.gov/biofuels/biodiesel/capacity/archive/2024/index.php | S7: Retrieved January 2026
A8: Plant capacity (billion gallons) | K8: 2.563 | L8: 2.514 | M8: 2.409 | N8: 2.255 | O8: 2.086 | P8: 1.986 | Q8: EIA | R8: https://www.eia.gov/biofuels/biodiesel/capacity/archive/2024/index.php | S8: Retrieved January 2026
A10: PRODUCTION | B10: 2010 | C10: 2011 | D10: 2012 | E10: 2013 | F10: 2014 | G10: 2015 | H10: 2016 | I10: 2017 | J10: 2018 | K10: 2019 | L10: 2020 | M10: 2021 | N10: 2022 | O10: 2023 | P10: 2024 | Q10: Source Name | R10: Source URL | S10: Comments
A11: Total Production of Biodiesel in US (billion gallons) | B11: 0.3435 | C11: 0.9675 | D11: 0.9696 | E11: 1.358 | F11: 1.268 | G11: 1.266 | H11: 1.569 | I11: 1.596 | J11: 1.857 | K11: 1.725 | L11: 1.815 | M11: 1.709 | N11: 1.622 | O11: 1.699 | P11: 1.671 | Q11: EIA | R11: [2010-2019] https://www.eia.gov/biofuels/biodiesel/production/archive/ [2020-2021] https://www.eia.gov/totalenergy/data/monthly/pdf/mer.pdf | S11: Retrieved January 2026
A12: Total Volume of Biodiesel Consumed in US (billion gallons) | B12: 0.25863034 | C12: 0.88561299 | D12: 0.90128755 | E12: 1.4263855 | F12: 1.4185509 | G12: 1.4969239 | H12: 2.0847212 | I12: 1.9828363 | J12: 1.9044633 | K12: 1.813 | L12: 1.876 | M12: 1.71 | N12: 1.658 | O12: 1.939 | P12: 1.931 | Q12: EIA | R12: https://www.eia.gov/totalenergy/data/monthly/pdf/sec10_5.pdf | S12: Retrieved January 2026 1 gallon of biodiesel = 127,595 BTUs
A13: Total Volume of Biodiesel Imported into the US (million gallons) | B13: 23.688 | C13: 37.38 | D13: 35.826 | E13: 342.384 | F13: 192.276 | G13: 352.758 | H13: 708.918 | I13: 393.708 | J13: 166.698 | K13: 171.276 | L13: 196.728 | M13: 210.21 | N13: 249.9 | O13: 501.018 | P13: 429.702 | Q13: EIA | R13: https://www.eia.gov/totalenergy/data/monthly/pdf/sec10_8.pdf | S13: Retrieved January 2026 1 barrel of biodiesel = 42 gallons
A14: Total Volume of Biodiesel Exported from the US (million gallons) | B14: 108.696 | C14: 75.558 | D14: 128.352 | E14: 196.35 | F14: 82.908 | G14: 87.822 | H14: 88.116 | I14: 93.156 | J14: 103.74 | K14: 114.66 | L14: 145.236 | M14: 186.984 | N14: 238.182 | O14: 251.16 | P14: 180.726 | Q14: EIA | R14: https://www.eia.gov/totalenergy/data/monthly/pdf/sec10_8.pdf | S14: Retrieved January 2026 1 barrel of biodiesel = 42 gallons
A15: Number of Biodiesel stations | B15: 644 | C15: 627 | D15: 675 | E15: 757 | F15: 783 | G15: 713 | H15: 716 | I15: 704 | J15: 680 | K15: 611 | L15: 712 | M15: 730 | N15: 1193 | O15: 1700 | P15: 1816 | Q15: AFDC | R15: https://afdc.energy.gov/stations/states?count=total&include_temporarily_unavailable=false&date= | S15: Retrieved January 2026
A17: ECONOMICS | B17: 2010 | C17: 2011 | D17: 2012 | E17: 2013 | F17: 2014 | G17: 2015 | H17: 2016 | I17: 2017 | J17: 2018 | K17: 2019 | L17: 2020 | M17: 2021 | N17: 2022 | O17: 2023 | P17: 2024 | Q17: Source Name | R17: Source URL | S17: Comments
A18: Price Per Gallon of Biodiesel (dollar per gallon) | B18: 3.436375 | C18: 5.1727083 | D18: 4.51625 | E18: 4.6016667 | F18: 3.455 | G18: 2.8358333 | H18: 3.2391667 | I18: 3.2725 | J18: 3.1016667 | K18: =AVERAGE(3.03, 3.11, 2.95, 2.87, 2.83, 2.8, 2.87, 2.89, 2.9, 2.93, 2.97, 3.17 ) -> 2.9433333 | L18: =AVERAGE(3.25, 3.1, 2.97, 2.71, 2.67, 2.8, 2.88, 3.12, 2.99, 3.09, 3.39, 3.51 ) -> 3.04 | M18: =AVERAGE(4.13, 4.42, 4.91, 5.41, 6.05, 5.97, 5.88, 5.56, 5.28, 5.45, 5.57, 5.45 ) -> 5.34 | N18: =AVERAGE(5.46, 5.93, 6.48, 6.78, 7.09, 6.97, 6.57, 6.71, 6.79, 6.81, 6.72, 5.87 ) -> 6.515 | O18: =AVERAGE(5.73, 5.54, 5.09, 5.12, 4.99, 5.33, 5.66, 5.65, 5.47, 4.45, 4.49, 4.56 ) -> 5.1733333 | P18: 4.6 | Q18: USDA | R18: https://www.ers.usda.gov/data-products/us-bioenergy-statistics/ | S18: Retrieved January 2026
A19: Price Per Gallon of B99/100 (dollar per gge) | B19: 3.6275 | C19: 4.125 | D19: 4.2275 | E19: 4.2125 | F19: 4.18 | G19: 3.615 | H19: 3 | I19: 3.12 | J19: 3.4625 | K19: 3.535 | L19: =AVERAGE(3.65,3.44,3.08,3.26 ) -> 3.3575 | M19: =AVERAGE(3.11,3.49,3.56,3.73 ) -> 3.4725 | N19: =AVERAGE(3.88,4.96,5.48,5.15 ) -> 4.8675 | O19: =AVERAGE(5.11,4.85,4.44,4.76 ) -> 4.79 | P19: 4.245 | Q19: AFDC | R19: https://www.afdc.energy.gov/fuels/prices.html | S19: Retrieved January 2026
A20: Price Per Gallon of B20 (dollar per gge) | B20: 2.8 | C20: 3.53 | D20: 3.6875 | E20: 3.6675 | F20: 3.5975 | G20: 2.635 | H20: 2.1675 | I20: 2.3025 | J20: 2.6675 | K20: 2.485 | L20: =AVERAGE(2.6,2.13,2.11,2.06 ) -> 2.225 | M20: =AVERAGE(2.18,2.53,2.74,2.96 ) -> 2.6025 | N20: =AVERAGE(3.08,4.16,4.8,4.4 ) -> 4.11 | O20: =AVERAGE(4.01,3.62,3.4,3.98 ) -> 3.7525 | P20: 3.385 | Q20: AFDC | R20: https://www.afdc.energy.gov/fuels/prices.html | S20: Retrieved January 2026
A21: Price Per Gallon of Diesel (dollar per gge) | B21: 2.67 | C21: 4.1675 | D21: 3.5525 | E21: 3.535 | F21: 3.485 | G21: 2.555 | H21: 2.0725 | I21: 2.3075 | J21: 2.8025 | K21: =AVERAGE(2.65,2.75,2.71,2.74) -> 2.7125 | L21: =AVERAGE(2.71,2.33,2.2,2.13 ) -> 2.3425 | M21: =AVERAGE(2.35,2.77,2.9,3.1 ) -> 2.78 | N21: =AVERAGE(3.22,4.5,5.02,4.6 ) -> 4.335 | O21: =AVERAGE(4.08,3.78,3.45,4.02 ) -> 3.8325 | P21: 3.455 | Q21: AFDC | R21: https://www.afdc.energy.gov/fuels/prices.html | S21: Retrieved January 2026
A22: Average Soy Price (dollar per metric tons) | B22: 418.51852 | C22: 462.96296 | D22: 533.33333 | E22: 481.48148 | F22: 374.07407 | G22: 331.48148 | H22: 350.74074 | I22: 345.55556 | J22: 314.07407 | K22: 329.81481 | L22: =AVERAGE(317.407,400) -> 358.7035 | M22: =AVERAGE(400,492.59259) -> 446.29629 | N22: =AVERAGE(529.62,492.59259) -> 511.10629 | O22: 529.62 | P22: 455.576 | Q22: USDA | R22: https://www.ers.usda.gov/data-products/oil-crops-yearbook/oil-crops-yearbook/ | S22: Retrieved January 2026 1 bushel of soy=0.027 metric tons
A23: Number of direct jobs working with biodiesel production | F23: 49500 | G23: 49500 | H23: 61100 | I23: 62200 | J23: 72300 | K23: 67300 | L23: 70860 | M23: 63900 | N23: 63180 | O23: 66261 | P23: 107,4 | Q23: Clean Fuels Alliance | R23: https://cleanfuels.org/new-study-shows-clean-fuels-industry-contributes-42-4-billion-to-us-economy/ | S23: Retrieved January 2026

Sheet RENEWABLE DIESEL
A1: RENEWABLE DIESEL
A3: PHYSICAL | B3: 2010 | C3: 2011 | D3: 2012 | E3: 2013 | F3: 2014 | G3: 2015 | H3: 2016 | I3: 2017 | J3: 2018 | K3: 2019 | L3: 2020 | M3: 2021 | N3: 2022 | O3: 2023 | P3: 2024 | Q3: Source Name | R3: Source URL | S3: Comments
A4: Number of Renewable Diesel Plants | M4: 6 | N4: 11 | O4: 17 | P4: 19 | Q4: EIA | R4: https://www.eia.gov/biofuels/renewable/capacity/ | S4: Retrieved January 2026
A5: Number of States which have Renewable Diesel Plants in the United States | M5: 5 | N5: 6 | O5: 11 | P5: 10 | Q5: EIA | R5: https://www.eia.gov/biofuels/renewable/capacity/ | S5: Retrieved January 2026
A6: Renewable Diesel plant capacities (billion gallons) | M6: 0.791 | N6: 1.75 | O6: 3 | P6: 4.719 | Q6: EIA | R6: https://www.eia.gov/biofuels/renewable/capacity/ | S6: Retrieved January 2026
A8: PRODUCTION | B8: 2010 | C8: 2011 | D8: 2012 | E8: 2013 | F8: 2014 | G8: 2015 | H8: 2016 | I8: 2017 | J8: 2018 | K8: 2019 | L8: 2020 | M8: 2021 | N8: 2022 | O8: 2023 | P8: 2024 | Q8: Source Name | R8: Source URL | S8: Comments
A9: Total Production of Renewable diesel in the US (million gallons) | B9: 8.776593 | C9: 62.04129 | D9: 52.401102 | E9: 113.28586 | F9: 159.14121 | G9: 176.84762 | H9: 241.48744 | I9: 258.34213 | J9: 305.48445 | K9: 492.00796 | L9: 534 | M9: 861 | N9: 1499 | O9: 2593 | P9: 3194 | Q9: EIA | R9: https://www.eia.gov/totalenergy/data/monthly/pdf/mer.pdf | S9: Retrieved January 2026
A10: Total Consumption of Renewable diesel in the US (million gallons) | B10: 8.776593 | C10: 62.04129 | D10: 102.67402 | E10: 416.6854 | F10: 487.8927 | G10: 513.14457 | H10: 591.17347 | I10: 602.72382 | J10: 615.33108 | K10: 912.38458 | L10: 966 | M10: 1209 | N10: 1718 | O10: 2868 | P10: 3671 | Q10: EIA | R10: https://www.eia.gov/totalenergy/data/monthly/pdf/mer.pdf | S10: Retrieved January 2026
A11: Total Volume of Renewable diesel Exported from the US (million gallons) | H11: 0 | I11: 0 | J11: 0 | K11: 0 | L11: 0 | M11: 0 | N11: 0 | O11: 0 | P11: - | Q11: EIA | R11: https://www.eia.gov/totalenergy/data/monthly/pdf/mer.pdf | S11: Retrieved January 2026
A12: Total Volume of Renewable diesel Imported into the US (million gallons) | D12: 25.368 | E12: 206.682 | F12: 120.666 | G12: 204.708 | H12: 222.768 | I12: 189.378 | J12: 173.082 | K12: 258.006 | L12: 279.636 | M12: 392.28 | N12: 262.668 | O12: 362.124 | P12: 520.548 | Q12: EIA | R12: https://www.eia.gov/totalenergy/data/monthly/pdf/mer.pdf | S12: Retrieved January 2026

Sheet FATS
A1: ANIMAL FATS AND RECYCLED GREASES
A3: PRODUCTION | B3: 2010 | C3: 2011 | D3: 2012 | E3: 2013 | F3: 2014 | G3: 2015 | H3: 2016 | I3: 2017 | J3: 2018 | K3: 2019 | L3: 2020 | M3: 2021 | N3: 2022 | O3: 2023 | P3: 2024 | R3: Source Name | S3: Source URL | T3: Comments
A4: Production
A5: Poultry Fat (Thousand metric tons) | C5: 1004.9 | D5: 1025.2 | E5: 1040.2 | F5: 1056.5 | G5: 1088.8 | H5: 1113.3192 | I5: 1095.307 | J5: 1025.564 | K5: 1133.8828 | L5: 1146.5185 | M5: 957.10648 | N5: 917.95192 | O5: 1039.6036 | P5: 1010.659 | Q5: =+(P5-O5)/O5 -> -0.027842001 | R5: NASS | S5: https://www.nass.usda.gov/ | T5: Retrieved January 2026
A6: Tallow (Thousand metric tons) | C6: 2646.2 | D6: 2608.7 | E6: 2589.3 | F6: 2441.4 | G6: 2385.7 | H6: 2559.5277 | I6: 2594.9247 | J6: 2770.7838 | K6: 2767.4195 | L6: 2601.9476 | M6: 2860.8006 | N6: 2834.1543 | O6: 2793.1328 | P6: 2895.3358 | Q6: =+(P6-O6)/O6 -> 0.036590816 | R6: NASS | S6: https://www.nass.usda.gov/ | T6: Retrieved January 2026
A7: White Grease (Thousand metric tons) | C7: 721.5 | D7: 720 | E7: 718 | F7: 707.3 | G7: 758.7 | H7: 620.28774 | I7: 592.27659 | J7: 587.38097 | K7: 610.88613 | L7: 596.55306 | M7: 565.86571 | N7: 617.36524 | O7: 608.62406 | P7: 567.61431 | Q7: =+(P7-O7)/O7 -> -0.067381088 | R7: NASS | S7: https://www.nass.usda.gov/ | T7: Retrieved January 2026
A8: Yellow Grease (Thousand metric tons) | C8: 906.4 | D8: 885.9 | E8: 896.4 | F8: 933.2 | G8: 926.4 | H8: 916.37024 | I8: 913.01094 | J8: 992.2218 | K8: 1007.6961 | L8: 946.68066 | M8: 999.79951 | N8: 979.47811 | R8: NASS | S8: https://www.nass.usda.gov/ | T8: Retrieved January 2026
A9: TOTAL (Thousand metric tons) | C9: =SUM(C5:C8) -> 5279 | D9: =SUM(D5:D8) -> 5239.8 | E9: =SUM(E5:E8) -> 5243.9 | F9: =SUM(F5:F8) -> 5138.4 | G9: =SUM(G5:G8) -> 5159.6 | H9: =SUM(H5:H8) -> 5209.5048 | I9: =SUM(I5:I8) -> 5195.5192 | J9: =SUM(J5:J8) -> 5375.9506 | ... P9: =SUM(P5:P8) -> 4473.6091 | R9: Calculation
A10: Consumption | B10: 2010 | C10: 2011 | D10: 2012 | E10: 2013 | F10: 2014 | G10: 2015 | H10: 2016 | I10: 2017 | J10: 2018 | K10: 2019 | L10: 2020 | M10: 2021 | N10: 2022 | O10: 2023 | P10: 2024
A11: Poultry Fat (Thousand metric tons) | H11: 1113.3178 | I11: 1078.4479 | J11: 1010.5628 | K11: 1131.2302 | L11: 1146.2301 | M11: 958.4287 | N11: 916.82656 | O11: 1037.8346 | P11: 1013.2698 | R11: NASS | S11: https://www.nass.usda.gov/ | T11: Retrieved January 2026
A12: Tallow (Thousand metric tons) | H12: 3029.8287 | I12: 2605.3841 | J12: 2824.8398 | K12: 2834.7186 | L12: 2608.9389 | M12: 2858.3249 | N12: 2828.9412 | O12: 2821.8629 | P12: 2894.5983 | R12: NASS | S12: https://www.nass.usda.gov/ | T12: Retrieved January 2026
A13: White Grease (Thousand metric tons) | H13: 619.51391 | I13: 591.86836 | J13: 585.63962 | K13: 611.07664 | L13: 596.6025 | M13: 567.44603 | N13: 617.21148 | O13: 608.32605 | P13: 567.79212 | R13: NASS | S13: https://www.nass.usda.gov/ | T13: Retrieved January 2026
A14: Yellow Grease (Thousand metric tons) | H14: 923.05756 | I14: 884.68817 | J14: 989.27481 | K14: 1005.7452 | L14: 948.48822 | M14: 998.11804 | N14: 976.073 | R14: NASS | S14: https://www.nass.usda.gov/ | T14: Retrieved January 2026
A15: TOTAL (Thousand metric tons) | H15: =SUM(H11:H14) -> 5685.718 | I15: =SUM(I11:I14) -> 5160.3885 | J15: =SUM(J11:J14) -> 5410.3171 | K15: =SUM(K11:K14) -> 5582.7707 | L15: =SUM(L11:L14) -> 5300.2596 | M15: =SUM(M11:M14) -> 5382.3177 | N15: =SUM(N11:N14) -> 5339.0522 | O15: =SUM(O11:O14) -> 4468.0235 | P15: =SUM(P11:P14) -> 4475.6602 | R15: Calculation
A16: Consumtpion for Biofuels | B16: 2010 | C16: 2011 | D16: 2012 | E16: 2013 | F16: 2014 | G16: 2015 | H16: 2016 | I16: 2017 | J16: 2018 | K16: 2019 | L16: 2020 | M16: 2021 | N16: 2022 | O16: 2023 | P16: 2024
A17: Poultry Going to Biodiesel (Thousand metric tons) | B17: 45.35925 | C17: 108.8622 | D17: 79.83228 | E17: 73.028392 | F17: 79.83228 | G17: 89.357722 | H17: 99.79035 | I17: 72.121207 | J17: 51.255952 | K17: 73.934229 | L17: 78.471502 | M17: 139.70649 | N17: 73.481985 | O17: 76.801 | P17: 96.615202 | Q17: =+(P17-O17)/O17 -> 0.25799406 | R17: EIA | S17: https://www.eia.gov/dnav/pet/PET_PNP_FEEDBIOFUEL_DCU_NUS_M.htm | T17: Retrieved January 2026 1 metric ton = 2,204.622 pounds
A18: Tallow Going to Biodiesel (Thousand metric tons) | B18: 77.110725 | C18: 195.49837 | D18: 174.63311 | E18: 210.92051 | F18: 172.36515 | G18: 195.04477 | H18: 150.59271 | I18: 156.48941 | J18: 219.53877 | K18: 132.44659 | L18: 166.92204 | M18: 734.81985 | N18: 898.56674 | O18: 1904.018 | P18: 3298.0711 | Q18: =+(P18-O18)/O18 -> 0.7321638 | R18: EIA | S18: https://www.eia.gov/dnav/pet/PET_PNP_FEEDBIOFUEL_DCU_NUS_M.htm | T18: Retrieved January 2026 1 metric ton = 2,204.622 pounds
A19: White Grease Going to Biodiesel (Thousand metric tons) | B19: 151.0463 | C19: 241.7648 | D19: 185.06574 | E19: 212.28129 | F19: 193.684 | G19: 267.16598 | H19: 262.17646 | I19: 268.07317 | J19: 280.32016 | K19: 243.12115 | L19: 277.59861 | M19: 315.24679 | N19: 301.18542 | O19: 270.27 | P19: 314.79319 | Q19: =+(P19-O19)/O19 -> 0.16473598 | R19: EIA | S19: https://www.eia.gov/dnav/pet/PET_PNP_FEEDBIOFUEL_DCU_NUS_M.htm | T19: Retrieved January 2026 1 metric ton = 2,204.622 pounds
A20: Yellow Grease to Biodiesel (Thousand metric tons) | B20: 111.58375 | C20: 213.64207 | D20: 303.90697 | E20: 474.45775 | F20: 487.15834 | G20: 568.80499 | H20: 630.03998 | I20: 667.23456 | J20: 756.59229 | K20: 655.42921 | L20: 477.6329 | M20: 1539.4929 | N20: 2272.0448 | O20: 3092.8 | P20: 3350.6878 | Q20: =+(P20-O20)/O20 -> 0.083383272 | R20: EIA | S20: https://www.eia.gov/dnav/pet/PET_PNP_FEEDBIOFUEL_DCU_NUS_M.htm | T20: Retrieved January 2026 1 metric ton = 2,204.622 pounds
A21: Other fats Going to Biodiesel (Thousand metric tons) | B21: 37.194585 | C21: 127.0059 | D21: 152.86067 | E21: 148.32475 | F21: 97.97598 | G21: 80.739465 | H21: 31.297882 | I21: 29.02992 | J21: 100.24394 | K21: W | L21: 16.782922 | M21: 35.833807 | N21: 28.130672 | O21: 35.7 | P21: 97.068795 | Q21: =+(P21-O21)/O21 -> 1.7190139 | R21: EIA | S21: https://www.eia.gov/dnav/pet/PET_PNP_FEEDBIOFUEL_DCU_NUS_M.htm | T21: Retrieved January 2026 1 metric ton = 2,204.622 pounds
A22: TOTAL (Thousand metric tons) | B22: =SUM(B17:B21) -> 422.29462 | C22: =SUM(C17:C21) -> 886.77333 | D22: =SUM(D17:D21) -> 896.29878 | E22: =SUM(E17:E21) -> 1119.0127 | F22: =SUM(F17:F21) -> 1031.0157 | G22: =SUM(G17:G21) -> 1201.1129 | H22: =SUM(H17:H21) -> 1173.8974 | I22: =SUM(I17:I21) -> 1192.9483 | ... P22: =SUM(P17:P21) -> 7157.236 | Q22: =+(P22-O22)/O22 -> 0.33044291 | R22: Calculation
A23: Exports | B23: 2010 | C23: 2011 | D23: 2012 | E23: 2013 | F23: 2014 | G23: 2015 | H23: 2016 | I23: 2017 | J23: 2018 | K23: 2019 | L23: 2020 | M23: 2021 | N23: 2022 | O23: 2023 | P23: 2024
A24: Poultry Fat (Thousand metric tons) | D24: 14.5 | E24: 14.9 | F24: 18.4 | G24: 16.4 | H24: 14.7 | I24: 16.1 | J24: 14.8 | K24: 12.9 | L24: 19 | M24: 17 | N24: 17 | O24: 19.2 | P24: 23.799 | Q24: =+(P24-O24)/O24 -> 0.23953125 | R24: Render Magazine | S24: https://rendermagazine.com/archives/2020s/ | T24: Retrieved January 2026
A25: Tallow (Thousand metric tons) | C25: =598.4+60 -> 658.4 | D25: =486.7+75.4 -> 562.1 | E25: 453.4 | F25: 443.3 | G25: 407.9 | H25: 403.4 | I25: 402.3 | J25: 445.4 | K25: =301+121.4 -> 422.4 | L25: 299.7 | M25: 187.7 | N25: 214.6 | O25: =108.4+45.7 -> 154.1 | P25: 177.747 | Q25: =+(P25-O25)/O25 -> 0.1534523 | R25: Render Magazine | S25: https://rendermagazine.com/archives/2020s/ | T25: Retrieved January 2026
A26: White Grease (Thousand metric tons) | C26: =34.8+2.5 -> 37.3 | D26: =24.8+1.4 -> 26.2 | E26: 29.9 | F26: 22 | G26: 20 | H26: 19.5 | I26: 18 | J26: 17.2 | K26: 22.5 | L26: 18.1 | M26: 81.3 | N26: 26.7 | O26: 0.107 | R26: Render Magazine | S26: https://rendermagazine.com/archives/2020s/ | T26: Retrieved January 2026
A27: Yellow Grease (Thousand metric tons) | C27: 566.2 | D27: 452.1 | E27: 361 | F27: 333.1 | G27: 253 | H27: 286.2 | I27: 300.2 | J27: 360.7 | K27: 448.2 | L27: 766.3 | M27: 761.1 | N27: 489.9 | O27: 192.4 | P27: 151.598 | Q27: =+(P27-O27)/O27 -> -0.21206861 | R27: Render Magazine | S27: https://rendermagazine.com/archives/2020s/ | T27: Retrieved January 2026
A28: TOTAL (Thousand metric tons) | C28: =SUM(C24:C27) -> 1261.9 | D28: =SUM(D24:D27) -> 1054.9 | E28: =SUM(E24:E27) -> 859.2 | F28: =SUM(F24:F27) -> 816.8 | G28: =SUM(G24:G27) -> 697.3 | H28: =SUM(H24:H27) -> 723.8 | I28: =SUM(I24:I27) -> 736.6 | J28: =SUM(J24:J27) -> 838.1 | ... P28: =SUM(P24:P27) -> 353.144 | Q28: =+(P28-O28)/O28 -> -0.034616615 | R28: Calculation
A29: Imports | B29: 2010 | C29: 2011 | D29: 2012 | E29: 2013 | F29: 2014 | G29: 2015 | H29: 2016 | I29: 2017 | J29: 2018 | K29: 2019 | L29: 2020 | M29: 2021 | N29: 2022 | O29: 2023 | P29: 2024 | Q29: =+(P29-O29)/O29 -> 0.00049431537
A30: Poultry Fat (Thousand metric tons) | D30: 0.5 | E30: 0.4 | F30: 4.4 | G30: 6.4 | H30: 5.8 | I30: 19.5 | J30: 5.69 | K30: 3.5 | L30: 2.1 | M30: 1.3 | N30: 3 | O30: 2.3 | P30: 0.728 | R30: Render Magazine | S30: https://rendermagazine.com/archives/2020s/ | T30: Retrieved January 2026
A31: Tallow (Thousand metric tons) | D31: 62.6 | E31: 59.5 | F31: 62.6 | G31: 64 | H31: 78.9 | I31: 99.8 | J31: 139.3 | K31: 192 | L31: 243.1 | M31: 333.3 | N31: 554.1 | O31: 795 | P31: 879.6 | Q31: =+(P31-O31)/O31 -> 0.10641509 | R31: Render Magazine | S31: https://rendermagazine.com/archives/2020s/ | T31: Retrieved January 2026
A32: White Grease (Thousand metric tons) | D32: 17.7 | E32: 21.8 | F32: 20.8 | G32: 34.4 | H32: 28.8 | I32: 27 | J32: 35.8 | K32: 27.2 | L32: 23 | M32: 45.3 | N32: 70.5 | O32: 71.5 | Q32: =+P33+P31 -> 3328.635 | R32: Render Magazine | S32: https://rendermagazine.com/archives/2020s/ | T32: Retrieved January 2026
A33: Yellow Grease (Thousand metric tons) | D33: 16.1 | E33: 20.6 | F33: 17.2 | G33: 22.4 | H33: 23 | I33: 38.7 | J33: 62.9 | K33: 88 | L33: 83 | M33: 129.5 | N33: 395.6 | O33: 1405.6 | P33: 2449.035 | Q33: =+(P33-O33)/O33 -> 0.74234135 | R33: Render Magazine | S33: https://rendermagazine.com/archives/2020s/ | T33: Retrieved January 2026
A34: TOTAL (Thousand metric tons) | D34: =SUM(D30:D33) -> 96.9 | E34: =SUM(E30:E33) -> 102.3 | F34: =SUM(F30:F33) -> 105 | G34: =SUM(G30:G33) -> 127.2 | H34: =SUM(H30:H33) -> 136.5 | I34: =SUM(I30:I33) -> 185 | J34: =SUM(J30:J33) -> 243.69 | K34: =SUM(K30:K33) -> 310.7 | ... P34: =SUM(P30:P33) -> 3329.363 | Q34: =+(P34-O34)/O34 -> 0.46384233 | R34: Calculation
A35: Percent into Biodiesel | B35: 2010 | C35: 2011 | D35: 2012 | E35: 2013 | F35: 2014 | G35: 2015 | H35: 2016 | I35: 2017 | J35: 2018 | K35: 2019 | L35: 2020 | M35: 2021 | N35: 2022 | O35: 2023 | P35: 2024
A36: Poultry Fat (%) | C36: =C17/(C5)*100 -> 10.833138 | D36: =D17/(D5)*100 -> 7.7869957 | E36: =E17/(E5)*100 -> 7.0206107 | F36: =F17/(F5)*100 -> 7.5562972 | G36: =G17/(G5)*100 -> 8.2069914 | H36: =H17/(H5)*100 -> 8.9633188 | I36: =I17/(I5)*100 -> 6.5845653 | J36: =J17/(J5)*100 -> 4.9978306 | ... P36: =P17/(P5)*100 -> 9.5596245 | Q36: =+(P36-O36)/O36 -> 0.29402223 | R36: Calculation
A37: Tallow (%) | C37: =C18/(C6)*100 -> 7.3878908 | D37: =D18/(D6)*100 -> 6.6942581 | E37: =E18/(E6)*100 -> 8.1458507 | F37: =F18/(F6)*100 -> 7.0600946 | G37: =G18/(G6)*100 -> 8.1755784 | H37: =H18/(H6)*100 -> 5.8836133 | I37: =I18/(I6)*100 -> 6.0305956 | J37: =J18/(J6)*100 -> 7.9233452 | ... P37: =P18/(P6)*100 -> 113.90979 | Q37: =+(P37-O37)/O37 -> 0.67101982 | R37: Calculation
A38: White Grease (%) | C38: =C19/(C7)*100 -> 33.508635 | D38: =D19/(D7)*100 -> 25.703575 | E38: =E19/(E7)*100 -> 29.565639 | F38: =F19/(F7)*100 -> 27.383571 | G38: =G19/(G7)*100 -> 35.213652 | H38: =H19/(H7)*100 -> 42.26691 | I38: =I19/(I7)*100 -> 45.261483 | J38: =J19/(J7)*100 -> 47.72374 | ... P38: =P19/(P7)*100 -> 55.458995 | Q38: =+(P38-O38)/O38 -> 0.24888737 | R38: Calculation
A39: Yellow Grease (%) | C39: =C20/(C8)*100 -> 23.570396 | D39: =D20/(D8)*100 -> 34.304885 | E39: =E20/(E8)*100 -> 52.929245 | F39: =F20/(F8)*100 -> 52.202994 | G39: =G20/(G8)*100 -> 61.399503 | H39: =H20/(H8)*100 -> 68.753867 | I39: =I20/(I8)*100 -> 73.080676 | J39: =J20/(J8)*100 -> 76.252335 | ... N39: =N20/(N8)*100 -> 231.96484 | R39: Calculation
A41: ECONOMICS | B41: 2010 | C41: 2011 | D41: 2012 | E41: 2013 | F41: 2014 | G41: 2015 | H41: 2016 | I41: 2017 | J41: 2018 | K41: 2019 | L41: 2020 | M41: 2021 | N41: 2022 | O41: 2023 | P41: 2024 | R41: Source Name | S41: Source URL | T41: Comments
A42: Price
A43: Poultry Fat (dollar per metric ton) | C43: 992 | D43: 864 | E43: 793 | F43: 660 | G43: 502 | H43: 546 | I43: 605 | J43: 566 | K43: 564 | L43: 558 | M43: 1038 | N43: 1376 | O43: 1095 | P43: 791 | R43: Render Magazine | S43: https://rendermagazine.com/archives/2020s/ | T43: Retrieved January 2026
A44: Tallow (dollar per metric ton) | C44: 1180 | D44: 1034 | E44: 966 | F44: 803 | G44: 563 | H44: 746 | I44: 731 | J44: 662 | K44: 748 | L44: 828 | M44: 1444 | N44: 1817 | O44: 1557 | P44: 1188 | R44: Render Magazine | S44: https://rendermagazine.com/archives/2020s/ | T44: Retrieved January 2026
A45: White Grease (dollar per metric ton) | C45: 1020 | D45: 926 | E45: 846 | F45: 711 | G45: 498 | H45: 537 | I45: 549 | J45: 463 | K45: 512 | L45: 534 | M45: 1066 | N45: 1462 | O45: 1174 | P45: 883 | R45: Render Magazine | S45: https://rendermagazine.com/archives/2020s/ | T45: Retrieved January 2026
A46: Yellow Grease (dollar per metric ton) | C46: 932 | D46: 788 | E46: 727 | F46: 612 | G46: 462 | H46: 505 | I46: 524 | J46: 408 | K46: 466 | L46: 461 | M46: 893 | N46: 1266 | O46: 1027 | P46: 748 | R46: Render Magazine | S46: https://rendermagazine.com/archives/2020s/ | T46: Retrieved January 2026

Sheet RENEWABLE JET FUEL
A1: RENEWABLE JET FUEL
A3: PRODUCTION | B3: 2010 | C3: 2011 | D3: 2012 | E3: 2013 | F3: 2014 | G3: 2015 | H3: 2016 | I3: 2017 | J3: 2018 | K3: 2019 | L3: 2020 | M3: 2021 | N3: 2022 | O3: 2023 | P3: 2024 | Q3: Source Name | R3: Source URL | S3: Comments
A4: Total production of renewable jet fuel (million gallons) | H4: 1.943717 | I4: 1.711017 | J4: 1.828178 | K4: 2.428702 | L4: 4.608399 | M4: 5.080073 | N4: 7.893137 | O4: 14.016105 | P4: 38.714566 | Q4: EPA | R4: https://www.epa.gov/fuels-registration-reporting-and-compliance-help/rins-generated-transactions | S4: Retrieved January 2026
A5: Total consumption of renewable jet fuel (million gallons) | H5: 1.943717 | I5: 1.711017 | J5: 1.828178 | K5: 2.428702 | L5: 4.608399 | M5: 5.080073 | N5: 15.819877 | O5: 26.300097 | P5: 103.03825 | Q5: EPA | R5: https://www.epa.gov/fuels-registration-reporting-and-compliance-help/rins-generated-transactions | S5: Retrieved January 2026
A6: Total consumption of jet fuel major US Airlines (million gallons) | H6: 17138 | I6: 17662 | J6: 18325 | K6: 18746 | L6: 11067 | M6: 14617 | N6: 17510 | O6: 19254.123 | P6: 19938.316 | Q6: US Department of Transportation | R6: https://data.bts.gov/stories/s/Fuel-Consumption/bwcv-dxgx/ | S6: Retrieved January 2026
A7: Airline off-take agreement (million gallons) | E7: 14.91804 | F7: 392.31828 | G7: 912.35592 | H7: 633.10068 | I7: 39.51972 | J7: 0 | K7: 255.177 | L7: 108.87552 | M7: 2412.2732 | N7: 5683.2498 | O7: 3076.5186 | P7: 498.83832 | Q7: ICAO | R7: https://www.icao.int/environmental-protection/GFAAF/Pages/Offtake-Agreements.aspx#InplviewHashef347ce3-9fcc-4b72-be6a-207e60680777=ShowInGrid%3DTrue | S7: Retrieved January 2026 1 liter = 0.26172 gallons
A8: Airline off-take agreement (cumulative by year) | E8: 2 | F8: 4 | G8: 6 | H8: 12 | I8: 14 | J8: 19 | K8: 23 | L8: 28 | M8: 51 | N8: 94 | O8: 122 | P8: 145 | Q8: ICAO | R8: https://www.icao.int/environmental-protection/GFAAF/Pages/Offtake-Agreements.aspx#InplviewHashef347ce3-9fcc-4b72-be6a-207e60680777=ShowInGrid%3DTrue | S8: Retrieved January 2026
A9: Number of Eligible Producers | E9: 1 | F9: 2 | G9: 2 | H9: 6 | I9: 2 | J9: 5 | K9: 4 | L9: 5 | M9: 23 | N9: 43 | O9: 28 | P9: 23 | Q9: ICAO | R9: https://www.icao.int/environmental-protection/GFAAF/Pages/Production-Facilities.aspx | S9: Retrieved January 2026
A10: Number of Facilities in Service | D10: 4 | E10: 5 | F10: 6 | G10: 6 | H10: 6 | I10: 7 | J10: 7 | K10: 7 | L10: 10 | M10: 11 | N10: 11 | O10: 14 | P10: 15 | Q10: ICAO | R10: https://www.icao.int/environmental-protection/GFAAF/Pages/Production-Facilities.aspx | S10: Retrieved January 2026
A11: Number of Airports with SAF (Ongoing Delivery) | F11: 0 | G11: 0 | H11: 2 | I11: 5 | J11: 9 | K11: 10 | L11: 13 | M11: 43 | N11: 58 | O11: 74 | P11: 96 | Q11: ICAO | R11: https://www.icao.int/environmental-protection/GFAAF/Pages/Airports.aspx | S11: Retrieved January 2026
A12: Number of Airports with SAF (Batch Delivery) | F12: 1 | G12: 1 | H12: 3 | I12: 5 | J12: 9 | K12: 14 | L12: 15 | M12: 24 | N12: 33 | O12: 56 | P12: 62 | Q12: ICAO | R12: https://www.icao.int/environmental-protection/GFAAF/Pages/Airports.aspx | S12: Retrieved January 2026
A13: Number of States with SAF available at airports | G13: 1 | H13: 2 | I13: 2 | J13: 3 | K13: 3 | L13: 4 | M13: 5 | N13: 6 | O13: 7 | P13: 19 | Q13: ICAO | R13: https://www.icao.int/environmental-protection/GFAAF/Pages/Airports.aspx | S13: Retrieved January 2026
A14: Domestic CO2 emissions from aviation sector (Million metric tons) | B14: 288.14 | C14: 296.04 | D14: 301.89 | E14: 311.24 | F14: 321.69 | G14: 338.84 | H14: 356.18 | I14: 380.57 | J14: 395.41 | K14: 403.72 | L14: 279.79 | M14: 321.13 | N14: 347.73 | O14: 395.69 | Q14: IEA | R14: https://www.iea.org/energy-system/transport/aviation#tracking | S14: Retrieved January 2025
A15: International CO2 emissions form aviation sector (Million metric tons) | B15: 465.88 | C15: 479.74 | D15: 481.25 | E15: 490.26 | F15: 505.94 | G15: 534.97 | H15: 559.09 | I15: 595.24 | J15: 622.53 | K15: 632.73 | L15: 302.56 | M15: 343.88 | N15: 436.72 | O15: 544.91 | Q15: IEA | R15: https://www.iea.org/energy-system/transport/aviation#tracking | S15: Retrieved January 2025
F18: =+F4/1000+'RENEWABLE DIESEL'!F9/1000+BIODIESEL!F11+ETHANOL!F17 -> 15.740141 | G18: =+G4/1000+'RENEWABLE DIESEL'!G9/1000+BIODIESEL!G11+ETHANOL!G17 -> 16.249848 | H18: =+H4/1000+'RENEWABLE DIESEL'!H9/1000+BIODIESEL!H11+ETHANOL!H17 -> 17.225431 | I18: =+I4/1000+'RENEWABLE DIESEL'!I9/1000+BIODIESEL!I11+ETHANOL!I17 -> 17.792053 | J18: =+J4/1000+'RENEWABLE DIESEL'!J9/1000+BIODIESEL!J11+ETHANOL!J17 -> 18.255313 | K18: =+K4/1000+'RENEWABLE DIESEL'!K9/1000+BIODIESEL!K11+ETHANOL!K17 -> 17.997437 | L18: =+L4/1000+'RENEWABLE DIESEL'!L9/1000+BIODIESEL!L11+ETHANOL!L17 -> 16.294608 | M18: =+M4/1000+'RENEWABLE DIESEL'!M9/1000+BIODIESEL!M11+ETHANOL!M17 -> 17.59108 | ... P18: =+P4/1000+'RENEWABLE DIESEL'!P9/1000+BIODIESEL!P11+ETHANOL!P17 -> 21.128715
F20: =+$P$18-F18 -> 5.3885734 | G20: =+$P$18-G18 -> 4.8788669 | H20: =+$P$18-H18 -> 3.9032834 | I20: =+$P$18-I18 -> 3.3366614 | J20: =+$P$18-J18 -> 2.8734019 | K20: =+$P$18-K18 -> 3.1312779 | L20: =+$P$18-L18 -> 4.8341062 | M20: =+$P$18-M18 -> 3.5376345 | ... P20: =+$P$18-P18 -> 0
F21: =+F20/F18 -> 0.34234594 | G21: =+G20/G18 -> 0.30024078 | H21: =+H20/H18 -> 0.22660004 | I21: =+I20/I18 -> 0.18753662 | J21: =+J20/J18 -> 0.15740086 | K21: =+K20/K18 -> 0.17398466 | L21: =+L20/L18 -> 0.29666906 | M21: =+M20/M18 -> 0.20110388 | ... P21: =+P20/P18 -> 0
O26: =+P11-O11 -> 22
O27: =+O26/O11 -> 0.2972973

Sheet WOOD PELLETS
A1: WOOD PELLETS
A3: PHYSICAL | B3: 2010 | C3: 2011 | D3: 2012 | E3: 2013 | F3: 2014 | G3: 2015 | H3: 2016 | I3: 2017 | J3: 2018 | K3: 2019 | L3: 2020 | M3: 2021 | N3: 2022 | O3: 2023 | P3: 2024 | Q3: Source Name | R3: Source URL | S3: Comments
A4: Total Operational Capacity of Pellet Mill Facilities (million metric tons) | G4: 9.4225 | H4: 11.158927 | I4: 13.019865 | J4: 12.355042 | K4: 13.0586 | L4: 13.99425 | M4: 13.3658 | N4: 12.8441 | O4: 13.9023 | P4: 15.2906 | Q4: Biomass Industry Directory | R4: Biomass Industry Directory, published by BBI International | S4: Retrieved January 2026
A5: Number of WP Plants in the United States | E5: 123 | F5: 122 | G5: 137 | H5: 147 | I5: 148 | J5: 140 | K5: 126 | L5: 124 | M5: 116 | N5: 123 | O5: 118 | P5: 129 | Q5: Biomass Industry Directory | R5: Biomass Industry Directory, published by BBI International | S5: Retrieved January 2026
A6: Number of Proposed WP Plants | E6: 11 | F6: 15 | G6: 22 | H6: 18 | I6: 7 | J6: 0 | K6: 3 | L6: 1 | M6: 3 | N6: 3 | O6: 5 | P6: 6 | Q6: Biomass Industry Directory | R6: Biomass Industry Directory, published by BBI International | S6: Retrieved January 2026
A7: Number of Existing Plants Under Construction | E7: 7 | F7: 9 | G7: 9 | H7: 11 | I7: 4 | J7: 4 | K7: 2 | L7: 5 | M7: 4 | N7: 4 | O7: 1 | P7: 4 | Q7: Biomass Industry Directory | R7: Biomass Industry Directory, published by BBI International | S7: Retrieved January 2026
A8: Number of Existing Plants that Were Put on Standby | H8: 13 | I8: 11 | J8: 6 | K8: 0 | L8: 5 | M8: 1 | N8: 1 | O8: 1 | P8: 2 | Q8: Biomass Industry Directory | R8: Biomass Industry Directory, published by BBI International | S8: Retrieved January 2026
A9: Number of States which have an WP Production Facility | E9: 36 | F9: 36 | G9: 36 | H9: 38 | I9: 37 | J9: 40 | K9: 38 | L9: 37 | M9: 36 | N9: 36 | O9: 35 | P9: 36 | Q9: Biomass Industry Directory | R9: Biomass Industry Directory, published by BBI International | S9: Retrieved January 2026
A11: PRODUCTION + CONSUMPTION | B11: 2010 | C11: 2011 | D11: 2012 | E11: 2013 | F11: 2014 | G11: 2015 | H11: 2016 | I11: 2017 | J11: 2018 | K11: 2019 | L11: 2020 | M11: 2021 | N11: 2022 | O11: 2023 | P11: 2024 | Q11: Source Name | R11: Source URL | S11: Comments
A12: Wood pellets Production (million metric tons) | D12: 3.474 | E12: 4.704 | F12: 5.947 | G12: 6.517 | H12: 6.393 | I12: 6.9 | J12: 7.468361 | K12: 8.592713 | L12: 8.412359 | M12: 8.4486 | N12: 9.544 | O12: 9.820703 | P12: 9.716 | Q12: FAOSTAT | R12: http://www.fao.org/faostat/en/#data/FO | S12: Retrieved January 2026
A13: Wood pellets Imports (million metric tons) | D13: 0.086 | E13: 0.152442 | F13: 0.219987 | G13: 0.207 | H13: 0.204847 | I13: 0.211617 | J13: 0.221 | K13: 0.211615 | L13: 0.204958 | M13: 0.195951 | N13: 0.19442 | O13: 0.17687225 | P13: 0.160379 | Q13: FAOSTAT | R13: http://www.fao.org/faostat/en/#data/FO | S13: Retrieved January 2026
A14: Wood pellets Exports (million metric tons) | D14: 1.898125 | E14: 2.882517 | F14: 4.005057 | G14: 4.669 | H14: 4.709 | I14: 5.203981 | J14: 6.017 | K14: 6.858462 | L14: 7.25686 | M14: 7.52255 | N14: 8.97716 | O14: 9.54 | P14: 10.00402 | Q14: FAOSTAT | R14: http://www.fao.org/faostat/en/#data/FO | S14: Retrieved January 2026
A15: Wood pellets Consumption (million metric tons) | D15: =+D12+D13-D14 -> 1.661875 | E15: =+E12+E13-E14 -> 1.973925 | F15: =+F12+F13-F14 -> 2.16193 | G15: =+G12+G13-G14 -> 2.055 | H15: 1.5657913 | I15: 1.715935 | J15: 1.9029739 | K15: 2.0141902 | L15: 1.9794541 | M15: 1.5609515 | N15: 1.6379896 | O15: 1.6228687 | P15: 1.3984565 | Q15: EIA | R15: https://www.eia.gov/biofuels/biomass/?year=2024&month=12#table_data
A16: Electricity Net Generation from Wood (trillion BTUs) | B16: 126.83607 | C16: 127.78123 | D16: 128.97548 | E16: 136.58114 | F16: 144.47001 | G16: 143.06762 | H16: 139.7169 | I16: 140.32085 | J16: 139.67936 | K16: 131.51411 | L16: 123.5843 | M16: 124.41686 | N16: 121.01496 | O16: 107.87481 | P16: 107.70079 | Q16: EIA | R16: https://www.eia.gov/totalenergy/data/monthly/pdf/mer.pdf | S16: Retrieved January 2026 1 kwh= 3412.14 BTUs
A17: Industrial Sector | B17: 87.712471 | C17: 91.073429 | D17: 91.189442 | E17: 94.485569 | F17: 92.943281 | G17: 93.212841 | H17: 93.69054 | I17: 93.533582 | J17: 93.748547 | K17: 90.193097 | L17: 85.01688 | M17: 83.300574 | N17: 79.465328 | O17: 72.746825 | P17: 74.384652 | Q17: EIA | R17: https://www.eia.gov/totalenergy/data/monthly/pdf/mer.pdf | S17: Retrieved January 2026 1 kwh= 3412.14 BTUs
A18: Electric Power Sector | B18: 39.055354 | C18: 36.622499 | D18: 37.704147 | E18: 41.976146 | F18: 51.274228 | G18: 49.690995 | H18: 45.790919 | I18: 46.545002 | J18: 45.671494 | K18: 41.013923 | L18: 38.253502 | M18: 40.59423 | N18: 40.952504 | O18: 34.75947 | P18: 32.937387 | Q18: EIA | R18: https://www.eia.gov/totalenergy/data/monthly/pdf/mer.pdf | S18: Retrieved January 2026 1 kwh= 3412.14 BTUs
A19: Heating from Wood in the US (trillion BTUs) | B19: =+B20-B16 -> 2090.1639 | C19: =+C20-C16 -> 2085.2188 | D19: =+D20-D16 -> 2022.0245 | E19: =+E20-E16 -> 2201.4189 | F19: =+F20-F16 -> 2253.53 | G19: =+G20-G16 -> 2161.9324 | H19: =+H20-H16 -> 2077.2831 | I19: =+I20-I16 -> 2035.6792 | ... P19: =+P20-P16 -> 1812.2992 | Q19: Estimation
A20: Energy Consumption from Wood in US (trillion BTUs) | B20: 2217 | C20: 2213 | D20: 2151 | E20: 2338 | F20: 2398 | G20: 2305 | H20: 2217 | I20: 2176 | J20: 2254 | K20: 2229 | L20: 1960 | M20: 1992 | N20: 2135 | O20: 1969 | P20: 1920 | Q20: EIA | R20: https://www.eia.gov/totalenergy/data/monthly/pdf/mer.pdf | S20: Retrieved January 2026
A21: Residential Sector | B21: 541 | C21: 524 | D21: 438 | E21: 572 | F21: 579 | G21: 513 | H21: 445 | I21: 430 | J21: 526 | K21: 547 | L21: 345 | M21: 357 | N21: 450 | O21: 382 | P21: 358 | Q21: EIA | R21: https://www.eia.gov/totalenergy/data/monthly/pdf/mer.pdf | S21: Retrieved January 2026
A22: Commercial Sector | B22: 72 | C22: 69 | D22: 61 | E22: 70 | F22: 73 | G22: 73 | H22: 74 | I22: 74 | J22: 74 | K22: 74 | L22: 73 | M22: 73 | N22: 73 | O22: 72 | P22: 72 | Q22: EIA | R22: https://www.eia.gov/totalenergy/data/monthly/pdf/mer.pdf | S22: Retrieved January 2026
A23: Industrial Sector | B23: 1409 | C23: 1438 | D23: 1462 | E23: 1489 | F23: 1495 | G23: 1476 | H23: 1474 | I23: 1442 | J23: 1432 | K23: 1407 | L23: 1356 | M23: 1366 | N23: 1415 | O23: 1341 | P23: 1328 | Q23: EIA | R23: https://www.eia.gov/totalenergy/data/monthly/pdf/mer.pdf | S23: Retrieved January 2026
A24: Electric Power Sector | B24: 196 | C24: 182 | D24: 190 | E24: 207 | F24: 251 | G24: 244 | H24: 224 | I24: 229 | J24: 221 | K24: 201 | L24: 185 | M24: 197 | N24: 198 | O24: 174 | P24: 162 | Q24: EIA | R24: https://www.eia.gov/totalenergy/data/monthly/pdf/mer.pdf | S24: Retrieved January 2026
A25: Wood pellet production worldwide (million metric tons) | B25: 15.7 | C25: 18.3 | D25: 18.053589 | E25: 21.19902 | F25: 25.093777 | G25: 27.381663 | H25: 29.304248 | I25: 33.410286 | J25: 37.627758 | K25: 41.975705 | L25: 42.988148 | M25: 45.334052 | N25: 47.431272 | O25: 46.81716 | P25: 47.725818 | Q25: FAOSTAT | R25: http://www.fao.org/faostat/en/#data/FO | S25: Retrieved January 2026
A26: Average Annual Densified Biomass Capacity (million metric tons) | H26: 10.003977 | I26: 10.867589 | J26: 10.730605 | K26: 10.806215 | L26: 12.010147 | M26: 12.96185 | N26: 13.244444 | O26: 13.26499 | Q26: EIA | R26: http://www.eia.gov/biofuels/biomass/ | S26: Retrieved January 2026
A27: Wood Pellets Exported from US (in million $) | D27: 258.234 | E27: 370.981 | F27: 519.399 | G27: 682.978 | H27: 612.496 | I27: 666.545 | J27: 809.855 | K27: 942.627 | L27: 981.593 | M27: 1059.261 | N27: 1556.111 | O27: 1764.333 | P27: 1859.544 | Q27: FAOSTAT | R27: http://www.fao.org/faostat/en/#data/FO | S27: Retrieved January 2026
A28: Wood Pellets Imported from US (in million $) | D28: 18.348 | E28: 30.262 | F28: 44.906 | G28: 45.782 | H28: 34.745 | I28: 41.134 | J28: 41.139 | K28: 42.323 | L28: 42.118 | M28: 42.997 | N28: 46.788 | O28: 46.855 | P28: 43.858 | Q28: FAOSTAT | R28: http://www.fao.org/faostat/en/#data/FO | S28: Retrieved January 2026
A30: ECONOMICS | B30: 2010 | C30: 2011 | D30: 2012 | E30: 2013 | F30: 2014 | G30: 2015 | H30: 2016 | I30: 2017 | J30: 2018 | K30: 2019 | L30: 2020 | M30: 2021 | N30: 2022 | O30: 2023 | P30: 2024 | Q30: Source Name | R30: Source URL | S30: Comments
A31: Total Jobs Created in the Wood Pellet Industry | B31: 26549 | C31: 25477 | D31: 25484 | E31: 25085 | F31: 26895 | G31: 23416 | H31: 23596 | I31: 24432 | J31: 25040 | K31: 24738 | L31: 24306 | M31: 25517 | N31: 26939 | O31: 27349 | P31: 27393 | Q31: NAICS | R31: https://data.bls.gov/cew/apps/data_views/data_views.htm#tab=Tables | S31: Retrieved January 2026

Sheet WASTE TO ENERGY
A1: WASTE TO ENERGY
A3: PHYSICAL | B3: 2010 | C3: 2011 | D3: 2012 | E3: 2013 | F3: 2014 | G3: 2015 | H3: 2016 | I3: 2017 | J3: 2018 | K3: 2019 | L3: 2020 | M3: 2021 | N3: 2022 | O3: 2023 | P3: 2024 | Q3: Source Name | R3: Source URL | S3: Comments
A4: Number of WTE Plants in the United States | B4: 86 | C4: 85 | D4: 85 | E4: 84 | F4: 84 | G4: 78 | H4: 77 | I4: 76 | J4: 75 | K4: 75 | L4: 64 | M4: 98 | N4: 60 | O4: 61 | P4: 56 | Q4: EIA | R4: https://www.eia.gov/electricity/data/eia860m/ | S4: Retrieved January 2026
A5: Number of WTE Plants Proposed in US | B5: 2 | C5: 0 | D5: 2 | E5: 2 | F5: 1 | G5: 0 | H5: 0 | I5: 0 | J5: 0 | K5: 0 | L5: 1 | M5: 2 | N5: 2 | O5: 3 | P5: 2 | Q5: EIA | R5: https://www.eia.gov/electricity/data/eia860m/ | S5: Retrieved January 2026
A6: Number of WTE Existing Plants that Were Put on Standby | B6: 2 | C6: 2 | D6: 2 | E6: 2 | F6: 2 | G6: 2 | H6: 1 | I6: 1 | J6: 1 | K6: 0 | L6: 2 | M6: 2 | N6: 0 | O6: 0 | P6: 2 | Q6: EIA | R6: https://www.eia.gov/electricity/data/eia860m/ | S6: Retrieved January 2026
A7: Number of WTE Existing Plants that Were Closed-Shut Down | B7: 11 | C7: 10 | D7: 11 | E7: 13 | F7: 8 | G7: 9 | H7: 11 | I7: 11 | J7: 20 | K7: 16 | L7: 11 | M7: 13 | N7: 2 | O7: 0 | P7: 4 | Q7: EIA | R7: https://www.eia.gov/electricity/data/eia860m/ | S7: Retrieved January 2026
A8: Number of WTE Fuel Switching Plants in US | B8: 20 | C8: 20 | D8: 16 | E8: 13 | F8: 15 | G8: 15 | H8: 15 | I8: 10 | J8: 16 | K8: 13 | L8: 14 | M8: 13 | N8: 14 | O8: 14 | P8: 14 | Q8: EIA | R8: https://www.eia.gov/electricity/data/eia860m/ | S8: Retrieved January 2026
A9: Number of States which have an WTE Fuel Switching Production Facility | B9: 9 | C9: 9 | D9: 7 | E9: 5 | F9: 7 | G9: 7 | H9: 7 | I9: 8 | J9: 6 | K9: 6 | L9: 8 | M9: 8 | N9: 8 | O9: 8 | P9: 8 | Q9: EIA | R9: https://www.eia.gov/electricity/data/eia860m/ | S9: Retrieved January 2026
A11: PRODUCTION | B11: 2010 | C11: 2011 | D11: 2012 | E11: 2013 | F11: 2014 | G11: 2015 | H11: 2016 | I11: 2017 | J11: 2018 | K11: 2019 | L11: 2020 | M11: 2021 | N11: 2022 | O11: 2023 | P11: 2024 | Q11: Source Name | R11: Source URL | S11: Comments
A12: Municipal solid waste generation in the United States (million metric tons) | B12: =+SUM(B13:B15) -> 251.05 | C12: =+SUM(C13:C15) -> 250.5 | D12: =+SUM(D13:D15) -> 251.84 | E12: =+SUM(E13:E15) -> 255.02 | F12: =+SUM(F13:F15) -> 258.95 | G12: =+SUM(G13:G15) -> 262.11 | H12: =+SUM(H13:H15) -> 266.78 | I12: 268.7 | J12: 292.4 | Q12: EPA | R12: [2010-2018]https://www.epa.gov/facts-and-figures-about-materials-waste-and-recycling/advancing-sustainable-materials-management | S12: Retrieved February 2024 1 ton = 0.9072 metric tons
A13: Recycled and composted | B13: =65.26+20.17 -> 85.43 | C13: 87 | D13: 86.89 | E13: 87.56 | F13: 89.57 | G13: =67.56+23.39 -> 90.95 | H13: 93.7 | I13: =67.18+26.99 -> 94.17 | J13: 93.9 | Q13: EPA | R13: [2010-2018]https://www.epa.gov/facts-and-figures-about-materials-waste-and-recycling/advancing-sustainable-materials-management | S13: Retrieved February 2024 1 ton = 0.9072 metric tons
A14: Combusted with Energy recovery | B14: 29.31 | C14: 31.8 | D14: 32.5 | E14: 33.16 | F14: 33.21 | G14: 33.55 | H14: 33.9 | I14: 34.03 | J14: 34.55 | Q14: EPA | R14: [2010-2018]https://www.epa.gov/facts-and-figures-about-materials-waste-and-recycling/advancing-sustainable-materials-management | S14: Retrieved February 2024 1 ton = 0.9072 metric tons
A15: Landfilled | B15: 136.31 | C15: 131.7 | D15: 132.45 | E15: 134.3 | F15: 136.17 | G15: 137.61 | H15: 139.18 | I15: 139.59 | J15: 146.12 | Q15: EPA | R15: [2010-2018]https://www.epa.gov/facts-and-figures-about-materials-waste-and-recycling/advancing-sustainable-materials-management | S15: Retrieved February 2024 1 ton = 0.9072 metric tons
A16: Biogenic Municipal Solid Waste: Consumption for Electricity Generation (million metric tons) | B16: 17.633246 | C16: 15.396998 | D16: 16.968 | E16: 17.007 | F16: 15.155683 | G16: 15.087643 | H16: 15.416957 | I16: 14.830906 | J16: 15.225538 | K16: 14.115125 | L16: 14.076115 | M16: 13.810306 | N16: 13.235141 | O16: 12.624595 | P16: 12.370579 | Q16: EIA | R16: http://www.eia.gov/electricity/annual/html/epa_05_07_a.html | S16: Retrieved January 2026 1 ton = 0.9072 metric tons
A17: Biogenic Municipal Solid Waste: Consumption for Heating Generation (million metric tons) | B17: 2.0747664 | C17: 1.8180288 | D17: 1.986 | E17: 1.865 | F17: 1.773576 | G17: 1.8016992 | H17: 2.0248704 | I17: 1.9268928 | J17: 1.85976 | K17: 1.5123024 | L17: 1.49688 | M17: 1.5531264 | N17: 1.4941584 | O17: 1.5123024 | P17: 1.4614992 | Q17: EIA | R17: http://www.eia.gov/electricity/annual/html/epa_05_07_b.html | S17: Retrieved January 2026 1 ton = 0.9072 metric tons
A18: Biogenic Municipal Solid Waste: Consumption for Energy Generation (million metric tons) | B18: 19.70892 | C18: 17.251315 | D18: 18.954 | E18: 18.871 | F18: 16.929259 | G18: 16.889342 | H18: 17.441827 | I18: 16.758706 | J18: 17.085298 | K18: 15.62652 | L18: 15.572995 | M18: 15.362525 | N18: 14.729299 | O18: 14.137805 | P18: 13.832078 | Q18: EIA | R18: http://www.eia.gov/electricity/annual/html/epa_05_07_c.html | S18: Retrieved January 2026 1 ton = 0.9072 metric tons
A19: Electric utilities | B19: 0.3646944 | C19: 0.3519936 | D19: 0.418 | E19: 0.456 | F19: 0.4027968 | G19: 0.4100544 | H19: 0.4209408 | I19: 0.3828384 | J19: 0.4236624 | K19: 0.2694384 | L19: 0.254016 | M19: 0.2286144 | N19: 0.2485728 | O19: 0.2567376 | P19: 0.2567376 | Q19: EIA | R19: http://www.eia.gov/electricity/annual/html/epa_05_07_c.html | S19: Retrieved January 2026 1 ton = 0.9072 metric tons
A20: Independent power producers | B20: 15.985771 | C20: 13.940942 | D20: 14.757 | E20: 14.574 | F20: 13.117205 | G20: 13.110854 | H20: 13.461034 | I20: 12.877704 | J20: 13.255099 | K20: 12.414125 | L20: 12.45767 | M20: 12.079368 | N20: 7.0280784 | O20: 6.7205376 | P20: 6.4755936 | Q20: EIA | R20: http://www.eia.gov/electricity/annual/html/epa_05_07_c.html | S20: Retrieved January 2026 1 ton = 0.9072 metric tons
A21: Commercial sector | B21: 3.2196528 | C21: 2.8150416 | D21: 3.577 | E21: 3.646 | F21: 3.2214672 | G21: 3.1770144 | H21: 3.35664 | I21: 3.3013008 | J21: 3.2269104 | K21: 2.7642384 | L21: 2.6816832 | M21: 2.8912464 | N21: 7.452648 | O21: 7.1596224 | P21: 7.1006544 | Q21: EIA | R21: http://www.eia.gov/electricity/annual/html/epa_05_07_c.html | S21: Retrieved January 2026 1 ton = 0.9072 metric tons
A22: Industrial Sector | B22: 0.1378944 | C22: 0.1433376 | D22: 0.203 | E22: 0.195 | F22: 0.1868832 | G22: 0.1914192 | H22: 0.2032128 | I22: 0.1959552 | J22: 0.1787184 | K22: 0.1787184 | L22: 0.1796256 | M22: 0.163296 | N22: 0 | O22: 0 | P22: 0 | Q22: EIA | R22: http://www.eia.gov/electricity/annual/html/epa_05_07_c.html | S22: Retrieved January 2026 1 ton = 0.9072 metric tons
A23: Biogenic Municipal Solid Waste: Consumption for Electricity Generation (Trillion BTUs) | B23: 144.934 | C23: 135.241 | D23: 135.735 | E23: 135.764 | F23: 134.408 | G23: 133.117 | H23: 135.957 | I23: 130.942 | J23: 134.465 | K23: 115.114 | L23: 114.814 | M23: 113.173 | N23: 108.508 | O23: 103.306 | P23: 100.831 | Q23: EIA | R23: http://www.eia.gov/electricity/annual/html/epa_05_07_d.html | S23: Retrieved January 2026
A24: Biogenic Municipal Solid Waste: Consumption for Heating Generation (Trillion BTUs) | B24: 17.502 | C24: 16.766 | D24: 16.31 | E24: 15.168 | F24: 15.783 | G24: 16.623 | H24: 18.259 | I24: 17.72 | J24: 16.724 | K24: 12.308 | L24: 11.939 | M24: 12.721 | N24: 12.244 | O24: 12.535 | P24: 12.179 | Q24: EIA | R24: http://www.eia.gov/electricity/annual/html/epa_05_07_e.html | S24: Retrieved January 2026
A25: Biogenic Municipal Solid Waste: Consumption for Energy Generation (Trillion BTUs) | B25: 162.436 | D25: 152.045 | E25: 150.932 | F25: 150.191 | G25: 149.74 | H25: 154.216 | I25: 148.662 | J25: 151.188 | K25: 127.422 | L25: 126.752 | M25: 125.894 | N25: 120.753 | O25: 115.841 | P25: 113.01 | Q25: EIA | R25: http://www.eia.gov/electricity/annual/html/epa_05_07_f.html | S25: Retrieved January 2026
A26: Electric utilities | B26: 3.322 | C26: 3.433 | D26: 3.91 | E26: 4.459 | F26: 4.429 | G26: 4.295 | H26: 4.434 | I26: 4.172 | J26: 4.568 | K26: 2.454 | L26: 2.284 | M26: 2.029 | N26: 2.212 | O26: 2.275 | P26: 2.273 | Q26: EIA | R26: http://www.eia.gov/electricity/annual/html/epa_05_07_f.html | S26: Retrieved January 2026
A27: Independent power producers | B27: 130.467 | C27: 121.648 | D27: 117.598 | E27: 115.574 | F27: 115.709 | G27: 114.886 | H27: 17.88 | I27: 112.857 | J27: 116.339 | K27: 101 | L27: 101.362 | M27: 98.516 | N27: 57.217 | O27: 54.557 | P27: 52.395 | Q27: EIA | R27: http://www.eia.gov/electricity/annual/html/epa_05_07_f.html | S27: Retrieved January 2026
A28: Commercial sector | B28: 27.509 | C28: 25.664 | D28: 28.923 | E28: 29.342 | F28: 28.411 | G28: 28.821 | H28: 30.095 | I28: 29.794 | J28: 28.686 | K28: 22.473 | L28: 21.629 | M28: 23.994 | N28: 61.324 | O28: 59.009 | P28: 58.341 | Q28: EIA | R28: http://www.eia.gov/electricity/annual/html/epa_05_07_f.html | S28: Retrieved January 2026
A29: Industrial Sector | B29: 1.138 | C29: 1.262 | D29: 1.614 | E29: 1.557 | F29: 1.643 | G29: 1.739 | H29: 1.806 | I29: 1.839 | J29: 1.596 | K29: 1.495 | L29: 1.478 | M29: 1.355 | N29: 0 | O29: 0 | P29: 0 | Q29: EIA | R29: http://www.eia.gov/electricity/annual/html/epa_05_07_f.html | S29: Retrieved January 2026
A31: ECONOMICS | B31: 2010 | C31: 2011 | D31: 2012 | E31: 2013 | F31: 2014 | G31: 2015 | H31: 2016 | I31: 2017 | J31: 2018 | K31: 2019 | L31: 2020 | M31: 2021 | N31: 2022 | O31: 2023 | P31: 2024 | Q31: Source Name | R31: Source URL | S31: Comments
A32: Revenue from waste electricity generation in the U.S. (million dollars) | B32: 1732.7 | C32: 1734.3 | D32: 1709 | E32: 1678.2 | F32: 1721.8 | G32: 1699.5 | H32: 1685.4 | I32: 1615.8 | J32: 1600.5 | K32: 1524.9 | L32: 1509.1 | M32: 1518.2 | N32: 1496.7 | O32: 1426.1 | P32: 1383.4 | Q32: IBIS World | R32: https://www.ibisworld.com/united-states/industry/waste-to-energy-plant-operation/4496/#:~:text=The%20market%20size%20of%20the,industry%20in%20the%20United%20States? | S32: Retrieved January 2026
A33: Jobs in WTE Facilities | B33: 2836 | C33: 2951 | D33: 3072 | E33: 2966 | F33: 2863 | G33: 2567 | H33: 2478 | I33: 2393 | J33: 2406 | K33: 2420 | L33: 2434 | M33: 2184 | N33: 1931 | O33: 1897 | P33: 1866 | Q33: IBIS World | R33: https://www.ibisworld.com/united-states/industry/waste-to-energy-plant-operation/4496/#:~:text=The%20market%20size%20of%20the,industry%20in%20the%20United%20States? | S33: Retrieved January 2026

Sheet BIOGAS
A1: BIOGAS
A3: PHYSICAL | B3: 2010 | C3: 2011 | D3: 2012 | E3: 2013 | F3: 2014 | G3: 2015 | H3: 2016 | I3: 2017 | J3: 2018 | K3: 2019 | L3: 2020 | M3: 2021 | N3: 2022 | O3: 2023 | P3: 2024 | Q3: Source Name | R3: Source URL | S3: Comments
A4: Number of anaerobic digestion (AD) Plants | B4: 133 | C4: 158 | D4: 183 | E4: 209 | F4: 218 | G4: 225 | H4: 229 | I4: 234 | J4: 245 | K4: 257 | L4: 282 | M4: 341 | N4: 400 | O4: 429 | P4: 400 | Q4: EPA | R4: https://www.epa.gov/agstar/livestock-anaerobic-digester-database | S4: Retrieved January 2026
A5: Used for Electricity | B5: 25 | C5: 38 | D5: 50 | E5: 61 | F5: 64 | G5: 65 | H5: 68 | I5: 71 | J5: 75 | K5: 95 | L5: 97 | M5: 101 | N5: 100 | O5: 100 | P5: 91 | Q5: EPA | R5: https://www.epa.gov/agstar/livestock-anaerobic-digester-database | S5: Retrieved January 2026
A6: Used for Boiler/Furnace | B6: 14 | C6: 14 | D6: 14 | E6: 14 | F6: 14 | G6: 14 | H6: 14 | I6: 14 | J6: 14 | K6: 11 | L6: 29 | M6: 29 | N6: 15 | O6: 15 | P6: 28 | Q6: EPA | R6: https://www.epa.gov/agstar/livestock-anaerobic-digester-database | S6: Retrieved January 2026
A7: Used for "Flare Full Time" | B7: 13 | C7: 13 | D7: 13 | E7: 13 | F7: 13 | G7: 13 | H7: 13 | I7: 13 | J7: 13 | K7: 11 | L7: 10 | M7: 10 | N7: 12 | O7: 12 | P7: 13 | Q7: EPA | R7: https://www.epa.gov/agstar/livestock-anaerobic-digester-database | S7: Retrieved January 2026
A8: Used for Cogeneration | B8: 81 | C8: 93 | D8: 106 | E8: 121 | F8: 127 | G8: 133 | H8: 134 | I8: 136 | J8: 143 | K8: 107 | L8: 119 | M8: 119 | N8: 101 | O8: 101 | P8: 109 | Q8: EPA | R8: https://www.epa.gov/agstar/livestock-anaerobic-digester-database | S8: Retrieved January 2026
A9: Number of Existing AD Plants Under Construction | B9: 0 | C9: 1 | D9: 4 | E9: 1 | F9: 0 | G9: 0 | H9: 0 | I9: 1 | J9: 3 | K9: 6 | L9: 7 | M9: 15 | N9: 24 | O9: 29 | P9: 73 | Q9: EPA | R9: https://www.epa.gov/agstar/livestock-anaerobic-digester-database | S9: Retrieved January 2026
A10: Number of AD Plants that Shut Down | B10: 3 | C10: 8 | D10: 1 | E10: 3 | F10: 5 | G10: 4 | H10: 9 | I10: 4 | J10: 2 | K10: 3 | L10: 1 | M10: 0 | N10: 2 | O10: 0 | P10: 0 | Q10: EPA | R10: https://www.epa.gov/agstar/livestock-anaerobic-digester-database | S10: Retrieved January 2026
A11: Number of States which have an AD Production Facility | B11: 29 | C11: 34 | D11: 35 | E11: 36 | F11: 36 | G11: 36 | H11: 36 | I11: 36 | J11: 36 | K11: 36 | L11: 35 | M11: 35 | N11: 34 | O11: 35 | P11: 38 | Q11: EPA | R11: https://www.epa.gov/agstar/livestock-anaerobic-digester-database | S11: Retrieved January 2026
A12: Number of landfill Plants | B12: 359 | C12: 394 | D12: 425 | E12: 451 | F12: 474 | G12: 483 | H12: 490 | I12: 497 | J12: 514 | K12: 565 | L12: 545 | M12: 549 | N12: 516 | O12: 535 | P12: 542 | Q12: EPA | R12: [2010-2019] https://www.epa.gov/lmop/landfill-technical-data [2020-2021] https://www.epa.gov/lmop/landfill-gas-energy-project-data | S12: Retrieved February 2024
A13: Number of States which have a landfill Facility | B13: 46 | C13: 46 | D13: 48 | E13: 48 | F13: 49 | G13: 49 | H13: 49 | I13: 49 | J13: 49 | K13: 49 | L13: 49 | M13: 49 | N13: 49 | O13: 45 | P13: 45 | Q13: EPA | R13: [2010-2019] https://www.epa.gov/lmop/landfill-technical-data [2020-2021] https://www.epa.gov/lmop/landfill-gas-energy-project-data | S13: Retrieved February 2024
A15: PRODUCTION | B15: 2010 | C15: 2011 | D15: 2012 | E15: 2013 | F15: 2014 | G15: 2015 | H15: 2016 | I15: 2017 | J15: 2018 | K15: 2019 | L15: 2020 | M15: 2021 | N15: 2022 | O15: 2023 | P15: 2024 | Q15: Source Name | R15: Source URL | S15: Comments
A16: Biogas potential from landfills (billion cubic feet) | J16: 125.12775 | L16: 344.75903 | M16: 346.13106 | N16: 434.8368 | O16: 435.8735 | P16: 497 | Q16: EPA | R16: https://www.epa.gov/lmop/landfill-gas-energy-project-data | S16: Retrieved January 2026
A17: Biogas potential from wastewater (billion cubic feet) | J17: 132 | L17: 147 | O17: 147.08 | Q17: American biogas Council | R17: [2018] https://americanbiogascouncil.org/biogas-market-snapshot/ [2020] https://americanbiogascouncil.org/resources/state-profiles/ | S17: Retrieved January 2026
A18: Biogas potential from animal manure (billion cubic feet) | J18: 1124 | L18: 1157 | O18: 1277.889 | Q18: American biogas Council | R18: [2018] https://americanbiogascouncil.org/biogas-market-snapshot/ [2020] https://americanbiogascouncil.org/resources/state-profiles/ | S18: Retrieved January 2026
A19: Anaerobic digestion: Biogas generated (trillion BTU) | B19: 0.94784545 | C19: 1.3818346 | D19: 1.6778589 | E19: 2.084233 | F19: 2.1646239 | G19: 2.1646239 | H19: 2.1866801 | I19: 2.1870213 | J19: 2.3303905 | K19: 2.3785148 | L19: 2.4109288 | M19: 2.4109288 | N19: 2.4109288 | O19: 2.4109288 | P19: 2.2488247 | Q19: EPA | R19: https://www.epa.gov/agstar/livestock-anaerobic-digester-database | S19: Retrieved January 2026 1 kwh = 3412 BTUs
A20: Anaerobic digestion: Biogas generated (billion cubic feet) | B20: 5.3880716 | C20: 5.5375621 | D20: 5.9042283 | E20: 7.1320504 | F20: 7.1768724 | G20: 7.8956304 | H20: 7.8956304 | I20: 7.8956304 | J20: 9.7217619 | K20: 10.652238 | L20: 12.763316 | M20: 17.167976 | N20: 18.214614 | O20: 18.251769 | P20: 23.1447 | Q20: EPA | R20: https://www.epa.gov/agstar/livestock-anaerobic-digester-database | S20: Retrieved January 2026
A21: Anaerobic digestion: Total Methane Emission Reductions (million metric tons of CO2) | B21: 1.8173376 | C21: 2.3786015 | D21: 3.02899 | E21: 3.5291747 | F21: 3.7230252 | G21: 3.8045922 | H21: 4.0303677 | I21: 4.2102567 | J21: 4.9356798 | K21: 5.7714269 | L21: 7.404395 | M21: 9.7669786 | N21: 10.486236 | O21: 10.504499 | P21: 18.182939 | Q21: EPA | R21: https://www.epa.gov/agstar/livestock-anaerobic-digester-database | S21: Retrieved January 2026
A22: Agriculture: total methane emissions (million metric tons of CO2) | B22: 271.1 | C22: 264.86 | D22: 264.39 | E22: 259.24 | F22: 258.46 | G22: 266.56 | H22: 274.03 | I22: 277.5 | J22: 281.21 | K22: 280.37 | L22: 281.02 | M22: 278.23 | N22: 274.3 | Q22: EPA | R22: https://www3.epa.gov/climatechange/ghgemissions/inventoryexplorer/index.html#iallsectors/methane/inventsect/all | S22: Retrieved February 2024
A23: Landfill gas: energy consumption (trillion BTU) | B23: 106.681 | C23: 114.173 | D23: 125.927 | E23: 133.18 | F23: 141.632 | G23: 138.841 | H23: 137.6 | I23: 139.831 | J23: 135.921 | K23: 129.5 | L23: 126.872 | M23: 116.049 | N23: 105.993 | O23: 97.56 | P23: 91.336 | Q23: EIA | R23: https://www.eia.gov/electricity/annual/html/epa_05_06_f.html | S23: Retrieved January 2026
A24: Landfill gas: energy consumption (billion cubic feet) | B24: 219.954 | C24: 235.99 | D24: 259.564 | E24: 272.798 | F24: 287.692 | G24: 284.052 | H24: 277.72 | I24: 282.051 | J24: 273.856 | K24: 261.064 | L24: 256.512 | M24: 235.906 | N24: 216.146 | O24: 197.712 | P24: 184.874 | Q24: EIA | R24: https://www.eia.gov/electricity/annual/html/epa_05_06_c.html | S24: Retrieved January 2026
A25: Landfill gas: Total Methane Emission Reductions (million metric tons of CO2) | B25: 64.16877 | C25: 71.99401 | D25: 80.27265 | E25: 89.39436 | F25: 96.57712 | G25: 99.47028 | H25: 105.34576 | I25: 108.25581 | J25: 115.48526 | K25: 90.05205 | L25: 93.5948 | M25: 94.3788 | N25: 94.8533 | O25: 95.1357 | P25: 89.30906 | Q25: EPA | R25: https://www.epa.gov/lmop/landfill-technical-data | S25: Retrieved January 2026
A26: Waste: total methane emissions (million metric tons of CO2) | B26: 163.1 | C26: 153.87 | D26: 155.63 | E26: 151.69 | F26: 151.39 | G26: 150.22 | H26: 146.27 | I26: 147.9 | J26: 150.23 | K26: 152.36 | L26: 147.6 | M26: 145.28 | N26: 143.17 | Q26: EPA | R26: https://www3.epa.gov/climatechange/ghgemissions/inventoryexplorer/index.html#iallsectors/methane/inventsect/all | S26: Retrieved April 2024
A28: ECONOMICS IN THEORY | B28: 2010 | C28: 2011 | D28: 2012 | E28: 2013 | F28: 2014 | G28: 2015 | H28: 2016 | I28: 2107 | J28: 2018 | K28: 2019 | L28: 2020 | M28: 2021 | N28: 2022 | O28: 2023 | P28: 2024 | Q28: Source Name | R28: Source URL | S28: Comments
A29: In theory, if 11,000 biogas systems made it would generate: | Q29: EPA
A30: Short Term Construction Jobs | F30: 275000 | L30: 372870 | Q30: EPA | R30: [2014] https://19january2017snapshot.epa.gov/sites/production/files/2015-12/documents/biogas-roadmap.pdf [2020] https://americanbiogascouncil.org/resources/state-profiles/ | S30: Retrieved February 2024
A31: Permanent Jobs | F31: 18000 | L31: 24826 | Q31: EPA | R31: [2014] https://19january2017snapshot.epa.gov/sites/production/files/2015-12/documents/biogas-roadmap.pdf [2020] https://americanbiogascouncil.org/resources/state-profiles/ | S31: Retrieved February 2024
A32: In theory, if 2,647 dairy operations were installed it would have a market potential of (billion dollars): | F32: 2.9 | Q32: EPA | R32: https://19january2017snapshot.epa.gov/sites/production/files/2015-12/documents/biogas-roadmap.pdf | S32: Retrieved February 2024
A34: Renewable Natural Gas | B34: 2010 | C34: 2011 | D34: 2012 | E34: 2013 | F34: 2014 | G34: 2015 | H34: 2016 | I34: 2017 | J34: 2018 | K34: 2019 | L34: 2020 | M34: 2021 | N34: 2022 | O34: 2023 | P34: 2024 | Q34: Source Name | R34: Source URL | S34: Comments
A35: Ag RNG projects | B35: 7 | C35: 5 | D35: 6 | E35: 6 | F35: 5 | G35: 6 | H35: 5 | I35: 7 | J35: 14 | K35: 29 | L35: 53 | M35: 97 | N35: 109 | O35: 135 | Q35: EPA | R35: https://www.epa.gov/lmop/renewable-natural-gas | S35: Retriaved May 8 2023
A36: Landfill RNG projects | B36: 30 | C36: 32 | D36: 33 | E36: 38 | F36: 39 | G36: 41 | H36: 41 | I36: 45 | J36: 58 | K36: 63 | L36: 70 | M36: 76 | N36: 82 | O36: 102 | Q36: EPA | R36: https://www.epa.gov/lmop/renewable-natural-gas | S36: Retriaved May 8 2024

Sheet TRADE
A1: 2024 Top Exports | M1: 2023 Top Exports
A2: Ethanol | B2: million gallons | D2: Biodiesel | E2: million gallons | G2: Wood Pellets | H2: million metric tons | J2: Poultry Fat | K2: metric tons | M2: Ethanol | N2: million gallons | P2: Biodiesel | Q2: million gallons | S2: Wood Pellets | T2: million metric tons | V2: Poultry Fat | W2: metric tons
A3: Canada | B3: 698.796 | D3: Canada | E3: 154.224 | G3: United Kingdom | H3: 7.0043052 | J3: Canada | K3: 6624 | M3: Canada | N3: 625.632 | P3: Canada | Q3: 230.664 | S3: United Kingdom | T3: 5.287793 | V3: Canada | W3: 6477
A4: United Kingdom | B4: 242.424 | D4: Peru | E4: 24.864 | G4: Japan | H4: 1.1500328 | J4: Guatemala | K4: 6479 | M4: United Kingdom | N4: 160.062 | P4: Peru | Q4: 26.628 | S4: Netherlands | T4: 1.4244955 | V4: Guatemala | W4: 4957
A5: India | B5: 189.714 | D5: Germany | E5: 0.672 | G5: Netherlands | H5: 0.65937796 | J5: Mexico | K5: 4219 | M5: Netherlands | N5: 114.324 | P5: Germany | Q5: 0.714 | S5: Japan | T5: 1.3936382 | V5: Mexico | W5: 3048
A6: Netherlands | B6: 140.112 | D6: Singapore | E6: 0.42 | G6: Denmark | H6: 0.64864761 | J6: Dominican Republic | K6: 1641 | M6: Korea | N6: 99.456 | Q6: =+Q3+Q4+Q5 -> 258.006 | S6: Denmark | T6: 1.3936382 | V6: Dominican Republic | W6: 1232
A7: Colombia | B7: 133.77 | D7: Bahama Islands | E7: 0.294 | G7: France | H7: 0.37844593 | J7: Indonesia | K7: 1184 | M7: India | N7: 83.874 | S7: France | T7: 0.32424067 | V7: Indonesia | W7: 1171
T8: =+T4+T3+T5+T6+T7 -> 9.8238056
A12: Inedible tallow | B12: metric tons | D12: Edible tallow | E12: metric tons | G12: Yellow grease | H12: metric tons | J12: White grease | K12: metric tons | M12: Inedible tallow | N12: metric tons | P12: Edible tallow | Q12: metric tons | S12: Yellow grease | T12: metric tons | V12: White grease | W12: metric tons
A13: Canada | B13: 69650 | D13: Mexico | E13: 53998 | G13: Mexico | H13: 48884 | J13: Mexico | K13: 208 | M13: Canada | N13: 45420 | P13: Mexico | Q13: 43177 | S13: Singapore | T13: 78264 | V13: Mexico | W13: 107
A14: Mexico | B14: 24825 | D14: Canada | E14: 1314 | G14: Canada | H14: 38430 | M14: Mexico | N14: 38946 | P14: Canada | Q14: 1504 | S14: Mexico | T14: 62095
A15: Singapore | B15: 22428 | D15: China | E15: 387 | G15: Singapore | H15: 18421 | J15: Tallow | K15: metric tons | M15: Singapore | N15: 21950 | P15: China | Q15: 1001 | S15: Canada | T15: 24459 | V15: Tallow | W15: metric tons
A16: Trinidad and Tabago | B16: 756 | G16: Netherlands | H16: 17993 | J16: Mexico | K16: =+B14+E13 -> 78823 | M16: Trinidad and Tabago | N16: 1977 | P16: Jamaica | Q16: 49 | S16: Ecuador | T16: 4931 | V16: Mexico | W16: =+N14+Q13 -> 82123
A17: Honduras | B17: 40 | G17: Ecuador | H17: 2972 | J17: Canada | K17: =+E14+B13 -> 70964 | M17: Honduras | N17: 60 | S17: Dominican Republic | T17: 4370 | V17: Canada | W17: =+Q14+N13 -> 46924
J18: Singapore | K18: =+B15 -> 22428 | V18: Singapore | W18: =+N15 -> 21950
J19: Trinidad and Tabago | K19: =B16 -> 756 | V19: Trinidad and Tabago | W19: 1977
J20: China | K20: =E15 -> 387 | V20: China | W20: 1001
A21: 2024 Top Imports | M21: 2023 Top Imports
A22: Ethanol | B22: million gallons | D22: Biodiesel | E22: million gallons | G22: Wood Pellets | H22: Thousand metric tons | M22: Ethanol | N22: million gallons | P22: Biodiesel | Q22: million gallons | S22: Wood Pellets | T22: Thousand metric tons
A23: Brazil | B23: 4 | D23: Germany | E23: 129.906 | G23: Canada | H23: 160.07799 | M23: Brazil | N23: 27.258 | P23: Canada | Q23: 140.07 | S23: Canada | T23: 176.51179
D24: Canada | E24: 128.772 | G24: Portugal | H24: 0.079113 | P24: Germany | Q24: 174.72 | S24: Japan | T24: 0.150213
D25: Spain | E25: 89.46 | G25: Japan | H25: 0.071656 | P25: South Korea | Q25: 33.054 | S25: Ukraine | T25: 0.062274
D26: Italy | E26: 40.026 | G26: Ukraine | H26: 0.069439 | P26: Italy | Q26: 44.73 | S26: China | T26: 0.048161
D27: South Korea | E27: 17.388 | G27: Mexico | H27: 0.044312 | P27: Spain | Q27: 84.462 | S27: Thailand | T27: 0.028172
A30: 2022 Top Exports | M30: 2021 Top Exports
A31: Ethanol | B31: million gallons | D31: Biodiesel | E31: million gallons | G31: Wood Pellets | H31: million metric tons | J31: Poultry Fat | K31: metric tons | M31: Ethanol | N31: million gallons | P31: Biodiesel | Q31: million gallons | S31: Wood Pellets | T31: million metric tons | V31: Poultry Fat | W31: metric tons
A32: Canada | B32: 501.815 | D32: Canada | E32: 190.553 | G32: United Kingdom | H32: 5.287589 | J32: Canada | K32: 5418 | M32: Canada | N32: 374.766 | P32: Canada | Q32: 141.792 | S32: United Kingdom | T32: 5.404957 | V32: Canada | W32: 5525
A33: Brazil | B33: 60.731 | D33: Netherlands | E33: 7.265 | G33: Netherlands | H33: 1.756709 | J33: Peru | K33: 4308 | M33: South Korea | N33: 150.864 | P33: Peru | Q33: 27.342 | S33: Netherlands | T33: 1.1673211 | V33: Peru | W33: 4016
A34: India | B34: 72.869 | D34: Peru | E34: 36.749 | G34: Japan | H34: 0.64670067 | J34: Guatemala | K34: 3600 | M34: India | N34: 149.184 | P34: Netherlands | Q34: 8.358 | S34: Denmark | T34: 0.44624637 | V34: Guatemala | W34: 3773
A35: South Korea | B35: 153.845 | D35: Norway | E35: 1.931 | G35: Denmark | H35: 0.5611442 | J35: Mexico | K35: 1461 | M35: China | N35: 100.338 | P35: Singapore | Q35: 7.098 | S35: France | T35: 0.24152277 | V35: Mexico | W35: 1718
A36: Netherlands | B36: 94.163 | D36: Germany | E36: 1.133 | G36: Belgium | H36: 0.42933387 | J36: Dominican Republic | K36: 1068 | M36: Brazil | N36: 69.552 | P36: Mexico | Q36: 1.554 | S36: Belgium | T36: 0.2212456 | V36: Chile | W36: 587
A37: Mexico | B37: 63.293
A38: Singapore | B38: 43.679
A39: United Kingdom | B39: 66.821
A41: Inedible tallow | B41: metric tons | D41: Edible tallow | E41: metric tons | G41: Yellow grease | H41: metric tons | J41: White grease | K41: metric tons | M41: Inedible tallow | N41: metric tons | P41: Edible tallow | Q41: metric tons | S41: Yellow grease | T41: metric tons | V41: White grease | W41: metric tons
A42: Canada | B42: 111420 | D42: Mexico | E42: 64808 | G42: Singapore | H42: 276041 | J42: Canada | K42: 102 | M42: Mexico | N42: 97086 | P42: Mexico | Q42: 108885 | S42: Singapore | T42: 501047 | V42: Ghana | W42: 77
A43: Mexico | B43: 50498 | D43: Canada | E43: 3228 | G43: United Kingdom | H43: 25971 | J43: Mexico | K43: 26469 | M43: Canada | N43: 60869 | P43: Honduras | Q43: 1675 | S43: United Kingdom | T43: 93990 | V43: Japan | W43: 15
A44: Singapore | B44: 48587 | G44: *EU27 | H44: 31177 | M44: Honduras | N44: 11650 | P44: Guatemala | Q44: 1500 | S44: Mexico | T44: 92240 | V44: Mexico | W44: 12
A45: Guatemala | B45: 3000 | G45: Mexico | H45: 96212 | M45: Brazil | N45: 3000 | P45: Canada | Q45: 1344 | S45: *EU27 | T45: 36942
G46: Dominican Republic | H46: 9833 | M46: Guatemala | N46: 3800 | S46: Dominican Republic | T46: 11309
G47: Canada | H47: 25335 | M47: Morocco | N47: 7500 | S47: Canada | T47: 9417
G48: *EU27 =the 27 European Union countries after the UK left the EU, So EU28 = 76,665 + 77,345 | M48: Colombia | N48: 2400 | S48: *EU27 =the 27 European Union countries after the UK left the EU, So EU28 = 76,665 + 77,345
A50: 2022 Top Imports | M50: 2021 Top Imports
A51: Ethanol | B51: million gallons | D51: Biodiesel | E51: million gallons | G51: Wood Pellets | H51: Thousand metric tons | M51: Ethanol | N51: million gallons | P51: Biodiesel | Q51: million gallons | S51: Wood Pellets | T51: Thousand metric tons
A52: Brazil | B52: 68.795 | D52: Canada | E52: 123.353 | G52: Canada | H52: 194.09566 | M52: Brazil | N52: 60.774 | P52: Canada | Q52: 129.15 | S52: Canada | T52: 28.560177
A53: Canada | B53: 0.293 | D53: Germany | E53: 76.859 | G53: Japan | H53: 0.10447 | P53: Germany | Q53: 27.174 | S53: Viet Nam | T53: 0.456887
D54: Spain | E54: 20.579 | G54: China | H54: 0.050596 | P54: Spain | Q54: 26.88 | S54: Japan | T54: 27.003
D55: South Korea | E55: 12.515 | G55: Ukraine | H55: 0.037325 | P55: South Korea | Q55: 23.646 | S55: Germany | T55: 1.312694
D56: Italy | E56: 12.431 | G56: Malaysia | H56: 0.035948 | P56: Italy | Q56: 3.36 | S56: Ukraine | T56: 0.072214
D57: Belgium | E57: 4.157

Sheet BIOPRODUCTS
A1: BIOPRODUCTS SUMMARY
A3: USDA BIOPREFFERED PROGRAM | B3: 2010 | C3: 2011 | D3: 2012 | E3: 2013 | F3: 2014 | G3: 2015 | H3: 2016 | I3: 2017 | J3: 2018 | K3: 2019 | L3: 2020 | M3: 2021 | N3: 2022 | O3: 2023 | P3: 2024 | Q3: Source Name | R3: Source URL | S3: Comments
A4: USDA BioPreferred product certifications | I4: 1297 | J4: 1550 | K4: 2216 | L4: =K4+658 -> 2874 | M4: =L4+1357 -> 4231 | N4: 8424 | O4: 10469 | P4: 11533 | Q4: USDA | R4: https://www.biopreferred.gov/BioPreferred/faces/catalog/Catalog.xhtml | S4: Retrieved January 2026
A5: Baby and Kids | I5: 53 | J5: 46 | K5: 58 | L5: 52 | N5: 238 | O5: =35+18+42+10+12+17+27+41+9+9+6+51 -> 277 | P5: 343 | Q5: USDA | R5: https://www.biopreferred.gov/BioPreferred/faces/catalog/Catalog.xhtml | S5: Retrieved January 2026
A6: Construction | I6: 57 | J6: 106 | K6: 116 | L6: 74 | N6: 562 | O6: =67+79+28+107+31+41+107+279+9 -> 748 | P6: 797 | Q6: USDA | R6: https://www.biopreferred.gov/BioPreferred/faces/catalog/Catalog.xhtml | S6: Retrieved January 2026
A7: Custodial Services | I7: 148 | J7: 176 | K7: 341 | L7: 212 | N7: 821 | O7: 927 | P7: 1091 | Q7: USDA | R7: https://www.biopreferred.gov/BioPreferred/faces/catalog/Catalog.xhtml | S7: Retrieved January 2026
A8: Films and Packaging | I8: 85 | J8: 106 | K8: 60 | L8: 95 | N8: 378 | O8: =120+19+219+22+33 -> 413 | P8: 477 | Q8: USDA | R8: https://www.biopreferred.gov/BioPreferred/faces/catalog/Catalog.xhtml | S8: Retrieved January 2026
A9: Food Services/Cafeteria | I9: 68 | J9: 88 | K9: 138 | L9: 351 | N9: 601 | O9: =10+42+84+361+185 -> 682 | P9: 805 | Q9: USDA | R9: https://www.biopreferred.gov/BioPreferred/faces/catalog/Catalog.xhtml | S9: Retrieved January 2026
A10: Grounds Maintenance | I10: 110 | J10: 72 | K10: 82 | L10: 48 | N10: 414 | O10: =23+3+28+6+107+29+85+38+26+2+27+64+48 -> 486 | P10: 521 | Q10: USDA | R10: https://www.biopreferred.gov/BioPreferred/faces/catalog/Catalog.xhtml | S10: Retrieved January 2026
A11: Household Supplies | I11: 218 | J11: 207 | K11: 404 | L11: 375 | N11: 1130 | O11: =15+65+7+17+29+42+258+67+83+21+167+498 -> 1269 | P11: 1531 | Q11: USDA | R11: https://www.biopreferred.gov/BioPreferred/faces/catalog/Catalog.xhtml | S11: Retrieved January 2026
A12: Intermediates | I12: 157 | J12: 373 | K12: 345 | L12: 330 | N12: 2074 | O12: =5+30+613+159+662+214+190+72+263+345+429+15+233 -> 3230 | P12: 3096 | Q12: USDA | R12: https://www.biopreferred.gov/BioPreferred/faces/catalog/Catalog.xhtml | S12: Retrieved January 2026
A13: Miscellaneous | I13: 63 | J13: 43 | K13: 114 | L13: 84 | N13: 223 | O13: =126+3+27+30+21+3+2+51 -> 263 | P13: 367 | Q13: USDA | R13: https://www.biopreferred.gov/BioPreferred/faces/catalog/Catalog.xhtml | S13: Retrieved January 2026
A14: Office Supplies | I14: 9 | J14: 21 | K14: 16 | L14: 20 | N14: 103 | O14: =4+7+5+2+81+1+13+1 -> 114 | P14: 108 | Q14: USDA | R14: https://www.biopreferred.gov/BioPreferred/faces/catalog/Catalog.xhtml | S14: Retrieved January 2026
A15: Operations and Maintenance | I15: 164 | J15: 121 | K15: 113 | L15: 62 | N15: 783 | O15: =90+34+3+50+8+8+36+2+38+48+55+58+4+22+252+22+74+3+39+6+54+3+17+2 -> 928 | P15: 933 | Q15: USDA | R15: https://www.biopreferred.gov/BioPreferred/faces/catalog/Catalog.xhtml | S15: Retrieved January 2026
A16: Personal Care and Toiletries | I16: 160 | J16: 186 | K16: 423 | L16: 209 | N16: 1041 | O16: =1035+7 -> 1042 | P16: 1282 | Q16: USDA | R16: https://www.biopreferred.gov/BioPreferred/faces/catalog/Catalog.xhtml | S16: Retrieved January 2026
A17: Safety Equipment | I17: 1 | J17: 0 | K17: 0 | L17: 0 | N17: 20 | O17: =1+10+20 -> 31 | P17: 63 | Q17: USDA | R17: https://www.biopreferred.gov/BioPreferred/faces/catalog/Catalog.xhtml | S17: Retrieved January 2026
A18: Vehicles and Equipment Maintenance | I18: 4 | J18: 5 | K18: 6 | L18: 2 | N18: 36 | O18: =1+12+6+17+22+1 -> 59 | P18: 119 | Q18: USDA | R18: https://www.biopreferred.gov/BioPreferred/faces/catalog/Catalog.xhtml | S18: Retrieved January 2026

Sheet BIOPLASTICS
A1: PLASTICS
A3: US/GLOBAL PLASTICS | B3: 2010 | C3: 2011 | D3: 2012 | E3: 2013 | F3: 2014 | G3: 2015 | H3: 2016 | I3: 2017 | J3: 2018 | K3: 2019 | L3: 2020 | M3: 2021 | N3: 2022 | O3: 2023 | P3: 2024 | Q3: Source Name | R3: Source URL | S3: Comments
A4: U.S. Plastic and Rubber Products Value Added (billion dollars) | B4: 61.8 | C4: 62.9 | D4: 67.5 | E4: 69 | F4: 67.1 | G4: 78.3 | H4: 79.8 | I4: 77.2 | J4: 80.8 | K4: 84.8 | L4: 80 | M4: 83 | N4: 95.2 | O4: 101.8 | P4: 101.5 | Q4: Bureau of Economic Analysis | R4: https://apps.bea.gov/iTable/?reqid=19&step=2&isuri=1&categories=survey&_gl=1*1r7rqrk*_ga*MTM3MDkyNjc3LjE3MDg2OTk4NjU.*_ga_J4698JNNFT*MTcwODk1ODU4NC4yLjEuMTcwODk2MDEzMy42MC4wLjA. | S4: Retrieved January 2026
A5: Value Added of Manufacturing US Plastic and Rubber Products as Percentage of GDP (%) | B5: 0.4 | C5: 0.4 | D5: 0.4 | E5: 0.4 | F5: 0.4 | G5: 0.4 | H5: 0.4 | I5: 0.4 | J5: 0.4 | K5: 0.4 | L5: 0.4 | M5: 0.3 | N5: 0.4 | O5: 0.4 | P5: 0.3 | Q5: Bureau of Economic Analysis | R5: https://www.bea.gov/iTable/iTable.cfm?ReqID=51&step=1#reqid=51&step=51&isuri=1&5114=a&5102=5 | S5: Retrieved January 2026
A6: Gross Output of US Plastic and Rubber Products (billion dollars) | B6: 186.6 | C6: 201 | D6: 216.5 | E6: 224.5 | F6: 231.2 | G6: 233.541 | H6: 230.789 | I6: 237.8 | J6: 252.8 | K6: 250.3 | L6: 234.6 | M6: 275.2 | N6: 301.2 | O6: 296.1 | P6: 298.4 | Q6: Bureau of Economic Analysis | R6: https://www.bea.gov/iTable/iTable.cfm?ReqID=51&step=1#reqid=51&step=51&isuri=1&5114=a&5102=5 | S6: Retrieved January 2026
A7: Compensation of Employees, Plastics and Rubber Products (billion dollars) | B7: 36.098 | C7: 37.729 | D7: 39.04 | E7: 40.03 | F7: 42.102 | G7: 43.56 | H7: 44.897 | I7: 47.155 | J7: 49.309 | K7: 50.626 | L7: 50.565 | M7: 54.545 | N7: 58.746 | O7: 60.544 | P7: 62.338 | Q7: Bureau of Economic Analysis | R7: https://apps.bea.gov/iTable/iTable.cfm?reqid=19&step=2&isuri=1&1921=survey# | S7: Retrieved January 2026
A8: Full and Part Time Employees (thousands) | B8: 624 | C8: 634 | D8: 646 | E8: 658 | F8: 674 | G8: 688 | H8: 702 | I8: 715 | J8: 730 | K8: 731 | L8: 693 | M8: 722 | N8: 749 | O8: 736 | P8: 722 | Q8: Bureau of Economic Analysis | R8: https://apps.bea.gov/iTable/iTable.cfm?reqid=19&step=2&isuri=1&1921=survey | S8: Retrieved January 2026
A9: Global Plastic Production (million metric tons) | B9: 265 | C9: 279 | D9: 288 | E9: 299 | F9: 311 | G9: 322 | H9: 335 | I9: 348 | J9: 365.5 | K9: 374.8 | L9: 380.4 | M9: 394 | N9: 400.3 | O9: 413.8 | P9: 430.9 | Q9: Plastics Europe | R9: https://plasticseurope.org/resources/market-data/ | S9: Retrieved January 2026
A11: GLOBAL BIOPLASTIC | B11: 2010 | C11: 2011 | D11: 2012 | E11: 2013 | F11: 2014 | G11: 2015 | H11: 2016 | I11: 2017 | J11: 2018 | K11: 2019 | L11: 2020 | M11: 2021 | N11: 2022 | O11: 2023 | P11: 2024 | Q11: Source Name | R11: Source URL | S11: Comments
A12: Global production capacity of biodegradable bioplastics (million metric tons) | B12: 0.342 | C12: 0.486 | D12: 0.571 | E12: 0.591 | F12: 0.663 | G12: 0.459 | H12: 0.862 | I12: 0.88 | J12: 1.077 | K12: 1.174 | L12: 1.239 | M12: 1.05 | N12: 1.142 | O12: 1.011 | P12: 1.39 | Q12: European Plastics | R12: https://docs.european-bioplastics.org/publications/market_data/2024/EUBP_Market_Data_Report_2024.pdf | S12: Retrieved January 2026
A13: Global production capacity of non-biodegradable bioplastics (million metric tons) | B13: 0.674 | C13: 0.675 | D13: 0.921 | E13: 0.99 | F13: 1.034 | G13: 1.177 | H13: 1.177 | I13: 1.174 | J13: 0.934 | K13: 0.941 | L13: 0.848 | M13: 0.742 | N13: 1.075 | O13: 1.008 | P13: 1.079 | Q13: European Plastics | R13: https://docs.european-bioplastics.org/publications/market_data/2024/EUBP_Market_Data_Report_2024.pdf | S13: Retrieved January 2026
A14: Global production capacities of biodegradable and non-biodegradable bioplastics (million metric tons) | B14: =+B13+B12 -> 1.016 | C14: =+C13+C12 -> 1.161 | D14: =+D13+D12 -> 1.492 | E14: =+E13+E12 -> 1.581 | F14: =+F13+F12 -> 1.697 | G14: =+G13+G12 -> 1.636 | H14: =+H13+H12 -> 2.039 | I14: =+I13+I12 -> 2.054 | ... P14: =+P13+P12 -> 2.469 | Q14: European Plastics | R14: https://docs.european-bioplastics.org/publications/market_data/2024/EUBP_Market_Data_Report_2024.pdf | S14: Retrieved January 2026
A15: Packaging | I15: 58 | J15: 57.742471 | K15: 53 | L15: 47.287373 | M15: 64.636872 | N15: 48.274775 | O15: 42.844 | P15: 45.4 | Q15: European Plastics | R15: https://docs.european-bioplastics.org/publications/market_data/2024/EUBP_Market_Data_Report_2024.pdf | S15: Retrieved January 2026
A16: Textiles | I16: 11 | J16: 11.335072 | K16: 11 | L16: 11.419095 | M16: 13.575419 | N16: 14.815315 | O16: 20.715596 | P16: 19.9 | Q16: European Plastics | R16: https://docs.european-bioplastics.org/publications/market_data/2024/EUBP_Market_Data_Report_2024.pdf | S16: Retrieved January 2026
A17: Consumer Goods | I17: 7 | J17: 6.8057861 | K17: 8 | L17: 12.248282 | M17: 15.055866 | N17: 14.072073 | O17: 13.366975 | P17: 13.2 | Q17: European Plastics | R17: https://docs.european-bioplastics.org/publications/market_data/2024/EUBP_Market_Data_Report_2024.pdf | S17: Retrieved January 2026
A18: Agriculture & Horticulture | I18: 5 | J18: 5.6675362 | K18: 8 | L18: 7.7469794 | M18: 11.899441 | N18: 4.3873874 | O18: 4.5366972 | P18: 5.3 | Q18: European Plastics | R18: https://docs.european-bioplastics.org/publications/market_data/2024/EUBP_Market_Data_Report_2024.pdf | S18: Retrieved January 2026
A19: Automotive & Transport | I19: 7 | J19: 7.3511975 | K19: 7 | L19: 5.7332386 | M19: 6.5921788 | N19: 7.1621622 | O19: 9.7285321 | P19: 8.4 | Q19: European Plastics | R19: https://docs.european-bioplastics.org/publications/market_data/2024/EUBP_Market_Data_Report_2024.pdf | S19: Retrieved January 2026
A20: Building & Construction | I20: 4 | J20: 3.6281717 | K20: 4 | L20: 3.5299692 | M20: 4.301676 | N20: 0.94144144 | O20: 0.63761468 | Q20: European Plastics | R20: https://docs.european-bioplastics.org/publications/market_data/2024/EUBP_Market_Data_Report_2024.pdf | S20: Retrieved January 2026
A21: Electronics | I21: 2 | J21: 1.6125207 | K21: 2 | L21: 3 | M21: 3.5195531 | N21: 2.5990991 | O21: 3.5366972 | P21: 2.95 | Q21: European Plastics | R21: https://docs.european-bioplastics.org/publications/market_data/2024/EUBP_Market_Data_Report_2024.pdf | S21: Retrieved January 2026
A22: Others | I22: 6 | J22: 5.8572445 | K22: 7 | L22: 5 | M22: 10.083799 | N22: 6.0045045 | O22: 3.40366 | P22: 3.7 | Q22: European Plastics | R22: https://docs.european-bioplastics.org/publications/market_data/2024/EUBP_Market_Data_Report_2024.pdf | S22: Retrieved January 2026
A23: Percentage of Bioplastic in Total Global Plastic Consumption | B23: =+B14/B9*100 -> 0.38339623 | C23: =+C14/C9*100 -> 0.41612903 | D23: =+D14/D9*100 -> 0.51805556 | E23: =+E14/E9*100 -> 0.52876254 | F23: =+F14/F9*100 -> 0.54565916 | G23: =+G14/G9*100 -> 0.50807453 | H23: =+H14/H9*100 -> 0.60865672 | I23: =+I14/I9*100 -> 0.59022989 | ... P23: =+P14/P9*100 -> 0.57298677 | Q23: Calculation | S23: Retrieved January 2026
A24: Land Used for Bioplastics (million ha) | E24: 0.554 | F24: 0.683 | G24: 0.749 | H24: 0.751 | I24: 0.898 | J24: 0.81 | K24: 0.79 | P24: 0.62 | Q24: European Plastics | R24: https://www.european-bioplastics.org/bioplastics/feedstock/ | S24: Retrieved January 2026
A25: Land Used for Bioplastics/Total Amount of Arable Land (%) | E25: 0.039571429 | F25: 0.048785714 | G25: 0.0535 | H25: 0.053642857 | I25: 0.064142857 | J25: 0.057857143 | K25: 0.02 | P25: 0.013 | Q25: European Plastics | R25: https://www.european-bioplastics.org/bioplastics/feedstock/ | S25: Retrieved January 2026
A27: GLOBAL BIO-BASED STRUCTURAL POLYMERS | B27: 2010 | C27: 2011 | D27: 2012 | E27: 2013 | F27: 2014 | G27: 2015 | H27: 2016 | I27: 2017 | J27: 2018 | K27: 2019 | L27: 2020 | M27: 2021 | N27: 2022 | O27: 2023 | P27: 2024 | Q27: Source Name | R27: Source URL | S27: Comments
A28: Total Production Capacity | F28: 1.7 | I28: 2.05 | J28: 2.01 | K28: 2.11 | L28: =L14 -> 2.087 | M28: =M14 -> 1.792 | N28: =N14 -> 2.217 | O28: 2.18 | P28: 2.47 | Q28: Nova Institute for Ecology and Innovation | R28: https://www.european-bioplastics.org/market/# | S28: Retrieved January 2026
A29: Starch Blends (%) | F29: 10 | I29: 18.8 | J29: 18.2 | K29: 21.3 | L29: 18.7 | M29: 16.4 | N29: 17.9 | O29: 10.6 | P29: 5.7 | Q29: Nova Institute for Ecology and Innovation | R29: https://www.european-bioplastics.org/market/# | S29: Retrieved January 2026
A30: Polylactic Acid (PLA) (%) | F30: 12.2 | I30: 10.3 | J30: 10.3 | K30: 13.9 | L30: 18.7 | M30: 18.9 | N30: 20.7 | O30: 31 | P30: 37.1 | Q30: Nova Institute for Ecology and Innovation | R30: https://www.european-bioplastics.org/market/# | S30: Retrieved January 2026
A31: Poly (butylene adipate-co-terephthalate) (PBAT) (%) | F31: 13 | I31: 5 | J31: 7.2 | K31: 13.4 | L31: 13.5 | M31: 19.2 | N31: 4.5 | O31: 4.6 | P31: 4.6 | Q31: Nova Institute for Ecology and Innovation | R31: https://www.european-bioplastics.org/market/# | S31: Retrieved January 2026
A32: Polyethylene (PE) (%) | F32: 11.8 | I32: 9.7 | J32: 9.5 | K32: 11.8 | L32: 10.5 | M32: 9.5 | N32: 14.8 | O32: 12.3 | P32: 11 | Q32: Nova Institute for Ecology and Innovation | R32: https://www.european-bioplastics.org/market/# | S32: Retrieved January 2026
A33: Polyamides (PA) (%) | F33: 5.5 | I33: 11.9 | J33: 11.6 | K33: 11.6 | L33: 11.9 | M33: 9.1 | N33: 11.1 | O33: 18.3 | P33: 14.4 | Q33: Nova Institute for Ecology and Innovation | R33: https://www.european-bioplastics.org/market/# | S33: Retrieved January 2026
A34: Polyethylene Terephthalate (PET) (%) | F34: 35.4 | I34: 26.3 | J34: 26.6 | K34: 9.8 | L34: 7.8 | M34: 6.2 | N34: 4.2 | O34: 2.2 | P34: 2.7 | Q34: Nova Institute for Ecology and Innovation | R34: https://www.european-bioplastics.org/market/# | S34: Retrieved January 2026
A35: Polytrimethylene Terephthalate (PTT) (%) | F35: 7.1 | J35: 9.2 | K35: 9.2 | L35: 9.2 | M35: 8.1 | N35: 13.3 | O35: 13.5 | P35: 13.2 | Q35: Nova Institute for Ecology and Innovation | R35: https://www.european-bioplastics.org/market/# | S35: Retrieved January 2026
A36: Polybutylene Succinate (PBS) (%) | F36: 1.6 | I36: 4.9 | J36: 4.6 | K36: 4.3 | L36: 4.1 | M36: 3.5 | N36: 0.9 | O36: 0.9 | P36: 1.3 | Q36: Nova Institute for Ecology and Innovation | R36: https://www.european-bioplastics.org/market/# | S36: Retrieved January 2026
A37: Other (%) | F37: 1.4 | I37: 10.7 | J37: 1.4 | K37: 2.6 | L37: 2.5 | M37: 1 | N37: 1.1 | O37: 1.1 | P37: 5.3 | Q37: Nova Institute for Ecology and Innovation | R37: https://www.european-bioplastics.org/market/# | S37: Retrieved January 2026
A38: Polyhydroxyalkanoates (PHA) (%) | F38: 2 | I38: 2.4 | J38: 1.4 | K38: 1.2 | L38: 1.7 | M38: 1.8 | N38: 3.9 | O38: 4.8 | P38: 4.1 | Q38: Nova Institute for Ecology and Innovation | R38: https://www.european-bioplastics.org/market/# | S38: Retrieved January 2026
A39: Polyproprylene (PP) (%) | F39: 0 | I39: 0 | J39: 0 | K39: 0.9 | L39: 1.4 | M39: 1.9 | N39: 3.9 | O39: 0.5 | P39: 0.6 | Q39: Nova Institute for Ecology and Innovation | R39: https://www.european-bioplastics.org/market/# | S39: Retrieved January 2026
A41: US BIOPLASTIC | B41: 2010 | C41: 2011 | D41: 2012 | E41: 2013 | F41: 2014 | G41: 2015 | H41: 2016 | I41: 2017 | J41: 2018 | K41: 2019 | L41: 2020 | M41: 2021 | N41: 2022 | O41: 2023 | P41: 2024 | Q41: Source Name | R41: Source URL | S41: Comments
A42: Revenue (million dollars) | B42: 1210.3 | C42: 1260.7 | D42: 1337.4 | E42: 1368.2 | F42: 1378.6 | G42: 1194.7 | H42: 1118.4 | I42: 1204.2 | J42: 1262.7 | K42: 1084 | L42: 989.4 | M42: 1235.9 | N42: 1319.8 | O42: 1295 | P42: 1263.9 | Q42: IBIS World | R42: Key Success Factors - OD4512 Bioplastics Manufacturing in the US - MyIBISWorld | S42: Retrieved January 2026
A43: Employment | B43: 572 | C43: 566 | D43: 685 | E43: 702 | F43: 696 | G43: 751 | H43: 686 | I43: 717 | J43: 736 | K43: 733 | L43: 738 | M43: 704 | N43: 930 | O43: 927 | P43: 923 | Q43: IBIS World | R43: Key Success Factors - OD4512 Bioplastics Manufacturing in the US - MyIBISWorld | S43: Retrieved January 2026
A44: Exports (million dollars) | B44: 617.1 | C44: 654.2 | D44: 594.8 | E44: 587.7 | F44: 575 | G44: 518.2 | H44: 483 | I44: 498.8 | J44: 534.3 | K44: 512 | L44: 454.4 | M44: 533.7 | N44: 535.5 | O44: 443.6 | P44: 433.3 | Q44: IBIS World | R44: Key Success Factors - OD4512 Bioplastics Manufacturing in the US - MyIBISWorld | S44: Retrieved January 2026
A45: Imports (million dollars) | B45: 211.6 | C45: 239.7 | D45: 231.4 | E45: 236.1 | F45: 257.8 | G45: 234.5 | H45: 225.4 | I45: 237.1 | J45: 258.3 | K45: 219.7 | L45: 186.6 | M45: 278.3 | N45: 263.9 | O45: 185.8 | P45: 186.9 | Q45: IBIS World | R45: Key Success Factors - OD4512 Bioplastics Manufacturing in the US - MyIBISWorld | S45: Retrieved January 2026
O50: Biodegradable | P50: Starch Blends | Q50: 5.7
O51: Biodegradable | P51: PLA | Q51: 37.1
O52: Biodegradable | P52: PBTA | Q52: 4.6
O53: Biodegradable | P53: PBS | Q53: 11
O54: Biodegradable | P54: PHA | Q54: 14.4
O55: Biobased | P55: PE | Q55: 2.7
O56: Biobased | P56: PA | Q56: 13.2
O57: Biobased | P57: PET | Q57: 1.3
O58: Biobased | P58: PTT | Q58: 5.3
O59: Biobased | P59: Other | Q59: 4.1
O60: Biobased | P60: PP | Q60: 0.6

Sheet ENZYMES
A1: ENZYMES
A3: GLOBAL | B3: 2010 | C3: 2011 | D3: 2012 | E3: 2013 | F3: 2014 | G3: 2015 | H3: 2016 | I3: 2017 | J3: 2018 | K3: 2019 | L3: 2020 | M3: 2021 | N3: 2022 | O3: 2023 | P3: 2024 | Q3: Source Name | R3: Source URL | S3: Comments
A4: Global Industrial Enzyme Market (billion dollars) By market: | B4: 3.63 | C4: 4.03 | D4: 4.49 | E4: 4.77 | F4: 4.6 | G4: 4.9 | H4: 5 | I4: 5.2541 | J4: 5.5 | K4: 5.6 | L4: 5.93 | M4: 6.4 | N4: 7 | O4: 7.4 | P4: 7.9 | Q4: BBC Research | R4: https://www.bccresearch.com/market-research/biotechnology/global-markets-for-enzymes-in-industrial-applications.html | S4: Retrieved January 2026
A5: * Food (billion dollars) | C5: 1.2048 | D5: 1.3472 | E5: 1.3472 | H5: 1.5 | I5: 1.9259 | P5: 3.9 | Q5: BBC Research | R5: “Global Markets for Enzymes in Industrial Applications.” BCC Research (September 2018) | S5: Retrieved January 2026
A6: * Feed (billion dollars) | C6: 1.0029 | D6: 1.1002 | E6: 1.2149 | H6: 1.2 | I6: 0.5962 | P6: 1.9 | Q6: BBC Research | R6: “Global Markets for Enzymes in Industrial Applications.” BCC Research (September 2018) | S6: Retrieved January 2026
A7: * Technical (billion dollars) | C7: 0.9684 | D7: 1.1052 | E7: 1.1518 | H7: 1.2 | I7: 1.2983 | Q7: BBC Research | R7: “Global Markets for Enzymes in Industrial Applications.” BCC Research (September 2018) | S7: Retrieved January 2026
A8: * Biofuel (billion dollars) | I8: 0.7193 | M8: 1.3 | P8: 1.6 | Q8: BBC Research | R8: “Global Markets for Enzymes in Industrial Applications.” BCC Research (September 2018) | S8: Retrieved January 2026
A9: * Other (billion dollars) | I9: 0.7144 | Q9: BBC Research | R9: “Global Markets for Enzymes in Industrial Applications.” BCC Research (September 2018) | S9: Retrieved January 2026
A10: * Detergent (billion dollars) | C10: 0.8319 | D10: 0.9669 | E10: 1.0535 | H10: 1.1 | Q10: BBC Research | R10: “Global Markets for Enzymes in Industrial Applications.” BCC Research (September 2018) | S10: Retrieved January 2026

Sheet APPAREL AND TEXTILES
A1: APPAREL AND TEXTILES
A3: US TEXTILE MILLS AND TEXTILE PRODUCT MILLS (NAICS) | B3: 2010 | C3: 2011 | D3: 2012 | E3: 2013 | F3: 2014 | G3: 2015 | H3: 2016 | I3: 2017 | J3: 2018 | K3: 2019 | L3: 2020 | M3: 2021 | N3: 2022 | O3: 2023 | P3: 2024 | Q3: Source Name | R3: Source URL | S3: Comments
A4: U.S. Textile Mills and Textile Product Mills Value Added (billion dollars) | B4: 15.6 | C4: 15.1 | D4: 16 | E4: 16.8 | F4: 17.8 | G4: 17.9 | H4: 18.2 | I4: 17.3 | J4: 16.6 | K4: 16.7 | L4: 15.8 | M4: 17 | N4: 16.7 | O4: 16.2 | P4: 16.3 | Q4: Bureau of Economic Analysis | R4: https://apps.bea.gov/iTable/?reqid=150&step=2&isuri=1&categories=gdpxind&_gl=1*14rxqpt*_ga*MTM3MDkyNjc3LjE3MDg2OTk4NjU.*_ga_J4698JNNFT*MTcwODk1ODU4NC4yLjEuMTcwODk2MjUwMS42MC4wLjA.#eyJhcHBpZCI6MTUwLCJzdGVwcyI6WzEsMiwzXSwiZGF0YSI6W1siY2F0ZWdvcmllcyIsIkdkcHhJbmQiXSxbIlRhYmxlX0xpc3QiLCIxNSJdXX0= | S4: Retrieved January 2026
A5: Value Added of Manufacturing US Textile Mills and Textile Product Mills as a Percentage of GDP (%) | B5: 0.1 | C5: 0.1 | D5: 0.1 | E5: 0.1 | F5: 0.1 | G5: 0.1 | H5: 0.1 | I5: 0.1 | J5: 0.1 | K5: 0.1 | L5: 0.1 | M5: 0.1 | N5: 0.1 | O5: 0.1 | P5: 0.1 | Q5: Bureau of Economic Analysis | R5: https://apps.bea.gov/iTable/?reqid=150&step=2&isuri=1&categories=gdpxind&_gl=1*14rxqpt*_ga*MTM3MDkyNjc3LjE3MDg2OTk4NjU.*_ga_J4698JNNFT*MTcwODk1ODU4NC4yLjEuMTcwODk2MjUwMS42MC4wLjA.#eyJhcHBpZCI6MTUwLCJzdGVwcyI6WzEsMiwzXSwiZGF0YSI6W1siY2F0ZWdvcmllcyIsIkdkcHhJbmQiXSxbIlRhYmxlX0xpc3QiLCIxNSJdXX0= | S5: Retrieved January 2026
A6: Gross Output of US Textile Mills and Textile Product Mills (billion dollars) | B6: 49.8 | C6: 52.9 | D6: 51.7 | E6: 54 | F6: 55.8 | G6: 53.5 | H6: 51.5 | I6: 49.7 | J6: 50.7 | K6: 49.9 | L6: 45.8 | M6: 51.1 | N6: 50.3 | O6: 47.3 | P6: 46.8 | Q6: Bureau of Economic Analysis | R6: https://apps.bea.gov/iTable/?reqid=150&step=2&isuri=1&categories=gdpxind&_gl=1*14rxqpt*_ga*MTM3MDkyNjc3LjE3MDg2OTk4NjU.*_ga_J4698JNNFT*MTcwODk1ODU4NC4yLjEuMTcwODk2MjUwMS42MC4wLjA.#eyJhcHBpZCI6MTUwLCJzdGVwcyI6WzEsMiwzXSwiZGF0YSI6W1siY2F0ZWdvcmllcyIsIkdkcHhJbmQiXSxbIlRhYmxlX0xpc3QiLCIxNSJdXX0= | S6: Retrieved January 2026
A7: Compensation of Employees, Textile Mills & Textile Product Mills (billion dollars) | B7: 10.9 | C7: 11 | D7: 11.2 | E7: 11.5 | F7: 12.1 | G7: 12 | H7: 12 | I7: 12.3 | J7: 12.544 | K7: 12.376 | L7: 11.524 | M7: 12.329 | N7: 13.009 | O7: 12.595 | P7: 12.641 | Q7: Bureau of Economic Analysis | R7: https://apps.bea.gov/iTable/?reqid=150&step=2&isuri=1&categories=gdpxind&_gl=1*14rxqpt*_ga*MTM3MDkyNjc3LjE3MDg2OTk4NjU.*_ga_J4698JNNFT*MTcwODk1ODU4NC4yLjEuMTcwODk2MjUwMS42MC4wLjA.#eyJhcHBpZCI6MTUwLCJzdGVwcyI6WzEsMiwzXSwiZGF0YSI6W1siY2F0ZWdvcmllcyIsIkdkcHhJbmQiXSxbIlRhYmxlX0xpc3QiLCIxNSJdXX0= | S7: Retrieved January 2026
A8: Full and Part Time Employees (thousands) | B8: 240 | C8: 240 | D8: 236 | E8: 233 | F8: 235 | G8: 234 | H8: 230 | I8: 229 | J8: 228 | K8: 221 | L8: 199 | M8: 202 | N8: 202 | O8: 192 | P8: 182 | Q8: Bureau of Economic Analysis | R8: https://apps.bea.gov/iTable/?reqid=150&step=2&isuri=1&categories=gdpxind&_gl=1*14rxqpt*_ga*MTM3MDkyNjc3LjE3MDg2OTk4NjU.*_ga_J4698JNNFT*MTcwODk1ODU4NC4yLjEuMTcwODk2MjUwMS42MC4wLjA.#eyJhcHBpZCI6MTUwLCJzdGVwcyI6WzEsMiwzXSwiZGF0YSI6W1siY2F0ZWdvcmllcyIsIkdkcHhJbmQiXSxbIlRhYmxlX0xpc3QiLCIxNSJdXX0= | S8: Retrieved January 2026
A10: US APPAREL AND LEATHER AND ALLIED PRODUCTS (NAICS) | B10: 2010 | C10: 2011 | D10: 2012 | E10: 2013 | F10: 2014 | G10: 2015 | H10: 2016 | I10: 2017 | J10: 2018 | K10: 2019 | L10: 2020 | M10: 2021 | N10: 2022 | O10: 2023 | P10: 2024 | Q10: Source Name | R10: Source URL | S10: Comments
A11: Apparel and Leather and Allied Products Value Added (billion dollars) | B11: 10.4 | C11: 10.1 | D11: 10 | E11: 10.2 | F11: 9.9 | G11: 9.7 | H11: 9.6 | I11: 9.4 | J11: 9.3 | K11: 9.6 | L11: 9.4 | M11: 11 | N11: 11.7 | O11: 11.7 | P11: 12.5 | Q11: Bureau of Economic Analysis | R11: https://apps.bea.gov/iTable/?reqid=150&step=2&isuri=1&categories=gdpxind&_gl=1*14rxqpt*_ga*MTM3MDkyNjc3LjE3MDg2OTk4NjU.*_ga_J4698JNNFT*MTcwODk1ODU4NC4yLjEuMTcwODk2MjUwMS42MC4wLjA.#eyJhcHBpZCI6MTUwLCJzdGVwcyI6WzEsMiwzXSwiZGF0YSI6W1siY2F0ZWdvcmllcyIsIkdkcHhJbmQiXSxbIlRhYmxlX0xpc3QiLCIxNSJdXX0= | S11: Retrieved January 2026
A12: Valued Added of Manufacturing US Apparel and Leather and Allied Products as a Percentage of GDP (%) | B12: 0.1 | C12: 0.1 | D12: 0.1 | E12: 0.1 | F12: 0.1 | G12: 0.1 | H12: 0.1 | I12: 0 | J12: 0 | K12: 0 | L12: 0 | M12: 0 | N12: 0 | O12: 0 | P12: 0 | Q12: Bureau of Economic Analysis | R12: https://apps.bea.gov/iTable/?reqid=150&step=2&isuri=1&categories=gdpxind&_gl=1*14rxqpt*_ga*MTM3MDkyNjc3LjE3MDg2OTk4NjU.*_ga_J4698JNNFT*MTcwODk1ODU4NC4yLjEuMTcwODk2MjUwMS42MC4wLjA.#eyJhcHBpZCI6MTUwLCJzdGVwcyI6WzEsMiwzXSwiZGF0YSI6W1siY2F0ZWdvcmllcyIsIkdkcHhJbmQiXSxbIlRhYmxlX0xpc3QiLCIxNSJdXX0= | S12: Retrieved January 2026
A13: Gross Output of US Apparel and Leather and Allied Products (billion dollars) | B13: 23.3 | C13: 24.9 | D13: 19.2 | E13: 19.6 | F13: 19.1 | G13: 18.6 | H13: 18.5 | I13: 15.7 | J13: 16.9 | K13: 17.3 | L13: 17.1 | M13: 19.1 | N13: 17.4 | O13: 19.8 | P13: 21.9 | Q13: Bureau of Economic Analysis | R13: https://apps.bea.gov/iTable/?reqid=150&step=2&isuri=1&categories=gdpxind&_gl=1*14rxqpt*_ga*MTM3MDkyNjc3LjE3MDg2OTk4NjU.*_ga_J4698JNNFT*MTcwODk1ODU4NC4yLjEuMTcwODk2MjUwMS42MC4wLjA.#eyJhcHBpZCI6MTUwLCJzdGVwcyI6WzEsMiwzXSwiZGF0YSI6W1siY2F0ZWdvcmllcyIsIkdkcHhJbmQiXSxbIlRhYmxlX0xpc3QiLCIxNSJdXX0= | S13: Retrieved January 2026
A14: Compensation of Employees, Apparel and Leather and Allied Products (billion dollars) | B14: 8.4 | C14: 8.1 | D14: 8.2 | E14: 8.2 | F14: 8.4 | G14: 8.2 | H14: 8.1 | I14: 7.885 | J14: 7.762 | K14: 7.644 | L14: 6.744 | M14: 7.294 | N14: 7.914 | O14: 7.844 | P14: 7.74 | Q14: Bureau of Economic Analysis | R14: https://apps.bea.gov/iTable/?reqid=150&step=2&isuri=1&categories=gdpxind&_gl=1*14rxqpt*_ga*MTM3MDkyNjc3LjE3MDg2OTk4NjU.*_ga_J4698JNNFT*MTcwODk1ODU4NC4yLjEuMTcwODk2MjUwMS42MC4wLjA.#eyJhcHBpZCI6MTUwLCJzdGVwcyI6WzEsMiwzXSwiZGF0YSI6W1siY2F0ZWdvcmllcyIsIkdkcHhJbmQiXSxbIlRhYmxlX0xpc3QiLCIxNSJdXX0= | S14: Retrieved January 2026
A15: Full and Part Time Employees (thousands) | B15: 187 | C15: 181 | D15: 178 | E15: 174 | F15: 170 | G15: 166 | H15: 159 | I15: 149 | J15: 142 | K15: 137 | L15: 114 | M15: 117 | N15: 118 | O15: 115 | P15: 108 | Q15: Bureau of Economic Analysis | R15: https://apps.bea.gov/iTable/?reqid=150&step=2&isuri=1&categories=gdpxind&_gl=1*14rxqpt*_ga*MTM3MDkyNjc3LjE3MDg2OTk4NjU.*_ga_J4698JNNFT*MTcwODk1ODU4NC4yLjEuMTcwODk2MjUwMS42MC4wLjA.#eyJhcHBpZCI6MTUwLCJzdGVwcyI6WzEsMiwzXSwiZGF0YSI6W1siY2F0ZWdvcmllcyIsIkdkcHhJbmQiXSxbIlRhYmxlX0xpc3QiLCIxNSJdXX0= | S15: Retrieved January 2026
... A21: Value of the U.S. textiles imports worldwide (billion dollars) | B21: 6.5358656 | C21: 7.330905 | D21: 7.7750181 | E21: 8.0410699 | F21: 8.4601825 | G21: 8.6507927 | H21: 8.2525303 | I21: 8.1829452 | J21: 8.7653571 | K21: 8.2144911 | L21: 8.2874789 | M21: 9.8263712 | N21: 10.257758 | O21: 8.7231181 | P21: 9.135 | Q21: ITA | R21: https://www.trade.gov/data-visualization/tradestats-express-us-trade-product | S21: Retrieved January 2026

Sheet FOREST PRODUCTS
A1: FOREST PRODUCTS
A3: US WOOD PRODUCTS (NAICS) | B3: 2010 | C3: 2011 | D3: 2012 | E3: 2013 | F3: 2014 | G3: 2015 | H3: 2016 | I3: 2017 | J3: 2018 | K3: 2019 | L3: 2020 | M3: 2021 | N3: 2022 | O3: 2023 | P3: 2024 | Q3: Source Name | R3: Source URL | S3: Comments
A4: U.S. Wood Products Real Value Added (billion dollars) | B4: 23.3 | C4: 23.6 | D4: 25.8 | E4: 30.5 | F4: 30.9 | G4: 32.5 | H4: 33.7 | I4: 35.7 | J4: 36.9 | K4: 36.8 | L4: 43 | M4: 59.9 | N4: 64.6 | O4: 62.3 | P4: 60.2 | Q4: Bureau of Economic Analysis | R4: https://apps.bea.gov/iTable/?reqid=19&step=2&isuri=1&categories=survey&_gl=1*1r7rqrk*_ga*MTM3MDkyNjc3LjE3MDg2OTk4NjU.*_ga_J4698JNNFT*MTcwODk1ODU4NC4yLjEuMTcwODk2MDEzMy42MC4wLjA. | S4: Retrieved January 2026
A5: Value Added of Manufacturing US Wood Products as Percentage of GDP (%) | B5: 0.2 | C5: 0.2 | D5: 0.2 | E5: 0.2 | F5: 0.2 | G5: 0.2 | H5: 0.2 | I5: 0.2 | J5: 0.2 | K5: 0.2 | L5: 0.2 | M5: 0.3 | N5: 0.2 | O5: 0.2 | P5: 0.2 | Q5: Bureau of Economic Analysis | R5: https://apps.bea.gov/iTable/?reqid=150&step=2&isuri=1&categories=gdpxind&_gl=1*14rxqpt*_ga*MTM3MDkyNjc3LjE3MDg2OTk4NjU.*_ga_J4698JNNFT*MTcwODk1ODU4NC4yLjEuMTcwODk2MjUwMS42MC4wLjA.#eyJhcHBpZCI6MTUwLCJzdGVwcyI6WzEsMiwzXSwiZGF0YSI6W1siY2F0ZWdvcmllcyIsIkdkcHhJbmQiXSxbIlRhYmxlX0xpc3QiLCIxNSJdXX0= | S5: Retrieved January 2026
A6: Gross Output of US Wood Products (billion dollars) | B6: 71.9 | C6: 73 | D6: 80.8 | E6: 90.6 | F6: 97.6 | G6: 101 | H6: 103.2 | I6: 108.5 | J6: 120.4 | K6: 112.4 | L6: 123.7 | M6: 163.4 | N6: 179.3 | O6: 173.3 | P6: 174.2 | Q6: Bureau of Economic Analysis | R6: https://apps.bea.gov/iTable/?reqid=19&step=2&isuri=1&categories=survey&_gl=1*1r7rqrk*_ga*MTM3MDkyNjc3LjE3MDg2OTk4NjU.*_ga_J4698JNNFT*MTcwODk1ODU4NC4yLjEuMTcwODk2MDEzMy42MC4wLjA. | S6: Retrieved January 2026
A7: Compensation of Employees, Wood Products (billion dollars) | B7: 15.9 | C7: 16.3 | D7: 16.7 | E7: 17.7 | F7: 19.4 | G7: 20.4 | H7: 21.1 | I7: 22.261 | J7: 23.537 | K7: 24.637 | L7: 25.435 | M7: 28.224 | N7: 31.296 | O7: 31.644 | P7: 32.297 | Q7: Bureau of Economic Analysis | R7: [Table 6.2D] https://apps.bea.gov/iTable/?reqid=19&step=2&isuri=1&categories=survey&_gl=1*1r7rqrk*_ga*MTM3MDkyNjc3LjE3MDg2OTk4NjU.*_ga_J4698JNNFT*MTcwODk1ODU4NC4yLjEuMTcwODk2MDEzMy42MC4wLjA. | S7: Retrieved January 2026
A8: Full and Part Time Employees (thousands) | B8: 342 | C8: 338 | D8: 341 | E8: 355 | F8: 371 | G8: 381 | H8: 391 | I8: 398 | J8: 406 | K8: 407 | L8: 395 | M8: 410 | N8: 427 | O8: 419 | P8: 412 | Q8: Bureau of Economic Analysis | R8: [6.4D] https://apps.bea.gov/iTable/?reqid=19&step=2&isuri=1&categories=survey&_gl=1*1r7rqrk*_ga*MTM3MDkyNjc3LjE3MDg2OTk4NjU.*_ga_J4698JNNFT*MTcwODk1ODU4NC4yLjEuMTcwODk2MDEzMy42MC4wLjA. | S8: Retrieved January 2026
A10: US PAPER PRODUCTS (NAICS) | B10: 2010 | C10: 2011 | D10: 2012 | E10: 2013 | F10: 2014 | G10: 2015 | H10: 2016 | I10: 2017 | J10: 2018 | K10: 2019 | L10: 2020 | M10: 2021 | N10: 2022 | O10: 2023 | P10: 2024 | Q10: Source Name | R10: Source URL | S10: Comments
A11: U.S. Paper Products Value Added (billion dollars) | B11: 56.3 | C11: 53.7 | D11: 53 | E11: 56.3 | F11: 56.7 | G11: 59.7 | H11: 58.7 | I11: 55.9 | J11: 60.2 | K11: 62.7 | L11: 65.1 | M11: 64.6 | N11: 70.1 | O11: 73.7 | P11: 74.4 | Q11: Bureau of Economic Analysis | R11: https://apps.bea.gov/iTable/?reqid=19&step=2&isuri=1&categories=survey&_gl=1*1r7rqrk*_ga*MTM3MDkyNjc3LjE3MDg2OTk4NjU.*_ga_J4698JNNFT*MTcwODk1ODU4NC4yLjEuMTcwODk2MDEzMy42MC4wLjA. | S11: Retrieved January 2026
A12: Value Added of Manufacturing US Paper Products as Percentage of GDP (%) | B12: 0.4 | C12: 0.3 | D12: 0.3 | E12: 0.3 | F12: 0.3 | G12: 0.3 | H12: 0.3 | I12: 0.3 | J12: 0.3 | K12: 0.3 | L12: 0.3 | M12: 0.3 | N12: 0.3 | O12: 0.3 | P12: 0.3 | Q12: Bureau of Economic Analysis | R12: https://apps.bea.gov/iTable/?reqid=150&step=2&isuri=1&categories=gdpxind&_gl=1*14rxqpt*_ga*MTM3MDkyNjc3LjE3MDg2OTk4NjU.*_ga_J4698JNNFT*MTcwODk1ODU4NC4yLjEuMTcwODk2MjUwMS42MC4wLjA.#eyJhcHBpZCI6MTUwLCJzdGVwcyI6WzEsMiwzXSwiZGF0YSI6W1siY2F0ZWdvcmllcyIsIkdkcHhJbmQiXSxbIlRhYmxlX0xpc3QiLCIxNSJdXX0= | S12: Retrieved January 2026
A13: Gross Output of US Paper Products (billion dollars) | B13: 169.4 | C13: 175.6 | D13: 179 | E13: 183.8 | F13: 184.6 | G13: 182.9 | H13: 179.3 | I13: 185.3 | J13: 190.2 | K13: 190.9 | L13: 180.2 | M13: 196.7 | N13: 217.4 | O13: 217.5 | P13: 218.8 | Q13: Bureau of Economic Analysis | R13: https://apps.bea.gov/iTable/?reqid=19&step=2&isuri=1&categories=survey&_gl=1*1r7rqrk*_ga*MTM3MDkyNjc3LjE3MDg2OTk4NjU.*_ga_J4698JNNFT*MTcwODk1ODU4NC4yLjEuMTcwODk2MDEzMy42MC4wLjA. | S13: Retrieved January 2026
A14: Compensation of Employees, Paper Products (billion dollars) | B14: 28.9 | C14: 29.2 | D14: 29.1 | E14: 29.4 | F14: 29.8 | G14: 30.2 | H14: 30 | I14: 30.386 | J14: 31.315 | K14: 32.452 | L14: 32.016 | M14: 32.518 | N14: 34.515 | O14: 35.313 | P14: 36.515 | Q14: Bureau of Economic Analysis | R14: [6.2D] https://apps.bea.gov/iTable/?reqid=19&step=2&isuri=1&categories=survey&_gl=1*1r7rqrk*_ga*MTM3MDkyNjc3LjE3MDg2OTk4NjU.*_ga_J4698JNNFT*MTcwODk1ODU4NC4yLjEuMTcwODk2MDEzMy42MC4wLjA. | S14: Retrieved January 2026
A15: Full and Part Time Employees (thousands) | B15: 394 | C15: 388 | D15: 380 | E15: 377 | F15: 373 | G15: 372 | H15: 370 | I15: 368 | J15: 367 | K15: 373 | L15: 355 | M15: 354 | N15: 365 | O15: 361 | P15: 357 | Q15: Bureau of Economic Analysis | R15: [6.4D] https://apps.bea.gov/iTable/?reqid=19&step=2&isuri=1&categories=survey&_gl=1*1r7rqrk*_ga*MTM3MDkyNjc3LjE3MDg2OTk4NjU.*_ga_J4698JNNFT*MTcwODk1ODU4NC4yLjEuMTcwODk2MDEzMy42MC4wLjA. | S15: Retrieved January 2026
A17: Forest Products | B17: 2010 | C17: 2011 | D17: 2012 | E17: 2013 | F17: 2014 | G17: 2015 | H17: 2016 | I17: 2017 | J17: 2018 | K17: 2019 | L17: 2020 | M17: 2021 | N17: 2022 | O17: 2023 | P17: 2024 | Q17: Source Name | R17: Source URL | S17: Comments
A18: Wood fuel (million m3) | B18: 40.436676 | C18: 40.436676 | D18: 40.436 | E18: 41.880843 | F18: 41.880843 | G18: 44.345 | H18: 62.156 | I18: 64.37 | J18: 71.608562 | K18: 71.426931 | L18: 60.52536 | M18: 71.11054 | N18: 72.369 | O18: 66.026 | P18: =39.614809+24.423893 -> 64.038702 | Q18: FAOSTAT | R18: http://www.fao.org/faostat/en/#data/FO | S18: Retrieved January 2026
A19: Wood residues ( million m3) | B19: 11.757 | C19: 11.654 | D19: 12.328 | E19: 13.198 | F19: 13.8 | G19: 13.8 | H19: 13.8 | I19: 14.275 | J19: 14.818026 | K19: 15.288915 | L19: 13.241628 | M19: 16.27606 | N19: 16.362 | O19: 14.361 | P19: 13.796 | Q19: FAOSTAT | R19: http://www.fao.org/faostat/en/#data/FO | S19: Retrieved January 2026
A20: Roundwood (million m3) | B20: 376.57168 | C20: 395.14068 | D20: 387.512 | E20: 396.81784 | F20: 398.69275 | G20: 399.02341 | H20: 436.632 | I20: 436.69138 | J20: 464.11815 | K20: 459.12888 | L20: 430 | M20: 453.446 | N20: 456.32969 | O20: 389.0263 | P20: 381.23483 | Q20: FAOSTAT | R20: http://www.fao.org/faostat/en/#data/FO | S20: Retrieved January 2026
A21: Sawnwood (million m3) | B21: 60.0134 | C21: 63.1738 | D21: 67.474 | E21: 71.115 | F21: 75.8333 | G21: 76.362 | H21: 78.165 | I21: 80.374 | J21: 81.9976 | K21: 82.4717 | L21: 79.133603 | M21: 80.705 | N21: 81.637 | O21: 77.872 | P21: 75.537207 | Q21: FAOSTAT | R21: http://www.fao.org/faostat/en/#data/FO | S21: Retrieved January 2026
A22: Wood-based panels (million m3) | B22: 32.19228 | C22: 31.649823 | D22: 31.059 | E22: 33.06239 | F22: 35.05954 | G22: 35.258505 | H22: 35.95673 | I22: 36.20091 | J22: 34.244962 | K22: 34.353377 | L22: 33.110844 | M22: 34.651024 | N22: 33.322828 | O22: 31.394901 | P22: 32.9997 | Q22: FAOSTAT | R22: http://www.fao.org/faostat/en/#data/FO | S22: Retrieved January 2026
A23: Wood fuel (million tonnes) | B23: =+B18*1.38 -> 55.802613 | C23: =+C18*1.38 -> 55.802613 | D23: =+D18*1.38 -> 55.80168 | E23: =+E18*1.38 -> 57.795563 | F23: =+F18*1.38 -> 57.795563 | G23: =+G18*1.38 -> 61.1961 | H23: =+H18*1.38 -> 85.77528 | I23: =+I18*1.38 -> 88.8306 | ... P23: =+P18*1.38 -> 88.373409 | Q23: Calculation | S23: Retrieved January 2026
A24: Wood residues ( mililon tonnes) | B24: =+B19*1.48 -> 17.40036 | C24: =+C19*1.48 -> 17.24792 | D24: =+D19*1.48 -> 18.24544 | E24: =+E19*1.48 -> 19.53304 | F24: =+F19*1.48 -> 20.424 | G24: =+G19*1.48 -> 20.424 | H24: =+H19*1.48 -> 20.424 | I24: =+I19*1.48 -> 21.127 | ... P24: =+P19*1.48 -> 20.41808 | Q24: Calculation | S24: Retrieved January 2026
A25: Roundwood (million tonnes) | B25: =+B20*1.43 -> 538.4975 | C25: =+C20*1.43 -> 565.05117 | D25: =+D20*1.43 -> 554.14216 | E25: =+E20*1.43 -> 567.44952 | F25: =+F20*1.43 -> 570.13063 | G25: =+G20*1.43 -> 570.60348 | H25: =+H20*1.43 -> 624.38376 | I25: =+I20*1.43 -> 624.46867 | ... P25: =+P20*1.43 -> 545.16581 | Q25: Calculation | S25: Retrieved January 2026
A26: Sawnwood (million tonnes) | B26: =+B21*1.82 -> 109.22439 | C26: =+C21*1.82 -> 114.97632 | D26: =+D21*1.82 -> 122.80268 | E26: =+E21*1.82 -> 129.4293 | F26: =+F21*1.82 -> 138.01661 | G26: =+G21*1.82 -> 138.97884 | H26: =+H21*1.82 -> 142.2603 | I26: =+I21*1.82 -> 146.28068 | ... P26: =+P21*1.82 -> 137.47772 | Q26: Calculation | S26: Retrieved January 2026
A27: Wood-based panels (million tonnes) | B27: =+B22*1.3 -> 41.849964 | C27: =+C22*1.3 -> 41.14477 | D27: =+D22*1.3 -> 40.3767 | E27: =+E22*1.3 -> 42.981107 | F27: =+F22*1.3 -> 45.577402 | G27: =+G22*1.3 -> 45.836056 | H27: =+H22*1.3 -> 46.743749 | I27: =+I22*1.3 -> 47.061183 | ... P27: =+P22*1.3 -> 42.89961 | Q27: Calculation | S27: Retrieved January 2026
A28: Wood pulp (million tonnes) | B28: 50.905939 | C28: 51.114622 | D28: 50.20053 | E28: 49.0551 | F28: 50.10664 | G28: 49.36821 | H28: 49.53443 | I28: 49.247516 | J28: 53.233456 | K28: 52.061998 | L28: 45.363116 | M28: 44.521 | N28: 42.728673 | O28: 38.415 | P28: 36.85108 | Q28: FAOSTAT | R28: http://www.fao.org/faostat/en/#data/FO | S28: Retrieved January 2026
A29: Paper and paperboard (million tonnes) | B29: 75.772845 | C29: 76.430822 | D29: 74.492 | E29: 71.732298 | F29: 73.093 | G29: 72.397 | H29: 71.902239 | I29: 72.044539 | J29: 70.891067 | K29: 68.15681 | L29: 66 | M29: 67 | N29: 65.507164 | O29: 60.674376 | P29: 62.458 | Q29: FAOSTAT | R29: http://www.fao.org/faostat/en/#data/FO | S29: Retrieved January 2026
A30: Wood pellets (million tonnes) | D30: 3.474 | E30: 4.704 | F30: 5.947 | G30: 6.517 | H30: 6.393 | I30: 6.9 | J30: 7.468361 | K30: 8.592713 | L30: 8.523943 | M30: 8.560184 | N30: 8.655584 | O30: 9.932283 | P30: 9.82758 | Q30: FAOSTAT | R30: http://www.fao.org/faostat/en/#data/FO | S30: Retrieved January 2026
