Workbook

Sheet CONTENTS
A1: TABLE OF CONTENTS
A4: Bioenergy
A6: Ethanol
A7: Biobutanol
A8: Biodiesel
A9: Fats
A10: Renewable Diesel
A11: Renewable Jet Fuel
A12: Wood Pellets
A13: Waste to Energy
A14: Biogas
A15: Trade
... A26: Funding

Sheet ETHANOL
A1: ETHANOL
A3: PHYSICAL | B3: 2010 | C3: 2011 | D3: 2012 | E3: 2013 | F3: 2014 | G3: 2015 | H3: 2016 | I3: 2017 | J3: 2018 | K3: 2019 | L3: 2020 | M3: 2021 | N3: 2022 | O3: 2023 | P3: Source Name | Q3: Source URL | R3: Comments
A4: Number of Ethanol Plants installed in the United States | B4: 204 | C4: 209 | D4: 211 | E4: 210 | F4: 213 | G4: 214 | H4: 213 | I4: 209 | J4: 210 | K4: 205 | L4: 208 | M4: 208 | N4: 199 | O4: 198 | P4: RFA | Q4: http://www.ethanolrfa.org/pocket-guide/ | R4: Retrieved January 2024
A5: Number Ethanol Plants in the United States-Starch | H5: 203 | I5: 202 | J5: 204 | K5: 199 | L5: 201 | M5: 199 | N5: 195 | O5: 197 | P5: Ethanol producer RFA | Q5: [2016-2019, 2022] http://ethanolproducer.com/plants/listplants/US/Existing/Sugar-Starch/ [2020-2021] http://www.ethanolrfa.org/pocket-guide/ | R5: Retrieved January 2024
A6: Number Ethanol Plants in the United States-Cellulosic | H6: 10 | I6: 7 | J6: 6 | K6: 6 | L6: 11 | M6: 11 | N6: 8 | O6: 9 | P6: Ethanol producer RFA | Q6: [2016-2019, 2022] http://ethanolproducer.com/plants/listplants/US/Existing/Cellulosic [2020-2021] http://www.ethanolrfa.org/pocket-guide/ | R6: Retrieved January 2024
A7: Number Ethanol Plants in the United States-Corn | J7: 196 | K7: 197 | L7: 199 | M7: 198 | N7: 190 | O7: 195 | P7: Ethanol producer RFA | Q7: [2018-2019, 2022] http://ethanolproducer.com/plants/listplants/US/Existing/Cellulosic [2020-2021] http://www.ethanolrfa.org/pocket-guide/ | R7: Retrieved January 2024
A8: Number Ethanol Plants in the United States-Sorghum | J8: 13 | K8: 14 | L8: 9 | M8: 10 | N8: 12 | O8: 10 | P8: Ethanol producer RFA | Q8: [2018-2019, 2022] http://ethanolproducer.com/plants/listplants/US/Existing/Cellulosic [2020-2021] http://www.ethanolrfa.org/pocket-guide/ | R8: Retrieved January 2024
A9: Number Ethanol Plants in the United States-Other (Tobacco, crop residue, waste stream) | J9: 5 | K9: 4 | L9: 8 | M9: 9 | N9: 5 | O9: 7 | P9: Ethanol producer RFA | Q9: [2018-2019, 2022] http://ethanolproducer.com/plants/listplants/US/Existing/Cellulosic [2020-2021] http://www.ethanolrfa.org/pocket-guide/ | R9: Retrieved January 2024
A10: Number of Ethanol Plants Operational in the United States | C10: 193 | D10: 194 | E10: 192 | F10: 198 | G10: 199 | H10: 200 | I10: 201 | J10: 199 | K10: 200 | L10: 201 | M10: 197 | N10: 192 | O10: 187 | P10: EIA RFA | Q10: [2011-2012] http://www.eia.gov/petroleum/ethanolcapacity/ [2013-2021] http://www.ethanolrfa.org/pocket-guide/ | R10: Retrieved January 2024
A11: Number of Existing Plants Under Construction | E11: 7 | F11: 3 | G11: 3 | H11: 3 | I11: 7 | J11: 9 | K11: 4 | L11: 1 | M11: 5 | N11: 4 | O11: 2 | P11: RFA | Q11: http://www.ethanolrfa.org/pocket-guide/ | R11: Retrieved January 2024
A12: Number Proposed Ethanol Plants in the United States | I12: 11 | J12: 1 | K12: 1 | N12: 0 | O12: 1 | P12: Ethanol producer | Q12: http://ethanolproducer.com/plants/listplants/US/Existing/Sugar-Starch/ | R12: Retrieved January 2024
A13: Number of States which have an Ethanol Production Facility | B13: 29 | C13: 29 | D13: 29 | E13: 28 | F13: 29 | G13: 29 | H13: 28 | I13: 28 | J13: 27 | K13: 26 | L13: 25 | M13: 24 | N13: 22 | O13: 22 | P13: RFA | Q13: http://www.ethanolrfa.org/pocket-guide/ | R13: Retrieved January 2024
A14: Ethanol plant capacities (billion gallons) | B14: 14.46 | C14: 13.614 | D14: 13.728 | E14: 13.852 | F14: 13.681 | G14: 14.369 | H14: 14.903 | I14: 15.584 | J14: 16.542 | K14: 16.868 | L14: 17.378 | M14: 17.546 | N14: 17.38 | O14: 17.663 | P14: EIA EIA | Q14: [2010-2021] https://www.eia.gov/petroleum/ethanolcapacity/index.php [2022] https://www.eia.gov/biofuels/update/ | R14: Retrieved January 2024
A16: PRODUCTION | B16: 2010 | C16: 2011 | D16: 2012 | E16: 2013 | F16: 2014 | G16: 2015 | H16: 2016 | I16: 2017 | J16: 2018 | K16: 2019 | L16: 2020 | M16: 2021 | N16: 2022 | O16: 2023 | P16: Source Name | Q16: Source URL | R16: Comments
A17: Total Volume of Ethanol Produced in US (billion gallons) | B17: 13.298 | C17: 13.929 | D17: 13.218 | E17: 13.293 | F17: 14.313 | G17: 14.807 | H17: 15.413 | I17: 15.936 | J17: 16.091 | K17: 15.778 | L17: 13.941 | M17: 15.016 | N17: 15.361 | O17: 15.62 | P17: EIA | Q17: https://www.eia.gov/totalenergy/data/monthly/pdf/mer.pdf | R17: Retrieved January 2024
A18: Total Volume of Ethanol Consumed (billion gallons) | B18: 12.858 | C18: 12.893 | D18: 12.882 | E18: 13.216 | F18: 13.444 | G18: 13.947 | H18: 14.356 | I18: 15.485 | J18: 14.42 | K18: 14.552 | L18: 12.681 | M18: 13.944 | N18: 14.023 | O18: 14.249 | P18: EIA | Q18: https://www.eia.gov/totalenergy/data/monthly/pdf/sec10_7.pdf | R18: Retrieved January 2024
A19: Total Volume of Ethanol Consumed: Transportation (billion gallons) | B19: 13.420745 | C19: 13.472314 | D19: 13.472314 | E19: 13.820403 | F19: 14.091138 | G19: 14.310305 | H19: 14.735838 | I19: 14.903437 | J19: 14.86476 | K19: 14.980791 | L19: 12.943816 | M19: 14.310394 | N19: 14.400639 | O19: 14.619808 | P19: EIA | Q19: https://www.eia.gov/totalenergy/data/monthly/pdf/mer.pdf | R19: Retrieved January 2024, Table 10.2c 1 gallon of ethanol = 77566 BTUs
A20: Total Volume of Ethanol Consumed: Industrial sector (billion gallons) | B20: 0.21916683 | C20: 0.21916683 | D20: 0.21916683 | E20: 0.232059 | F20: 0.18049033 | G20: 0.232059 | H20: 0.23206044 | I20: 0.23206044 | J20: 0.23206044 | K20: 0.23206044 | L20: 0.24495269 | M20: 0.24495269 | N20: 0.24495269 | O20: 0.24495269 | P20: EIA | Q20: https://www.eia.gov/totalenergy/data/monthly/pdf/sec10_5.pdf | R20: Retrieved January 2024, Table 10.2b 1 gallon of ethanol = 77566 BTUs
A21: Total Volume of Ethanol Imported into the US (billion gallons) | B21: 0.015666 | C21: 0.171864 | D21: 0.49413 | E21: 0.376992 | F21: 0.074676 | G21: 0.091518 | H21: 0.036204 | I21: 0.076608 | J21: 0.054348 | K21: 0.195048 | L21: 0.15414 | M21: 0.060774 | N21: 0.06909 | O21: 0.027258 | P21: EIA | Q21: https://www.eia.gov/dnav/pet/hist/LeafHandler.ashx?n=PET&s=MFEIMUS1&f=A | R21: Retrieved January 2024 1 barrel of ethanol = 42 gallons
A22: Total Volume of Ethanol Exported From the US (billion gallons) | B22: 0.398496 | C22: 1.195194 | D22: 0.741552 | E22: 0.618954 | F22: 0.846258 | G22: 0.832062 | H22: 1.170288 | I22: 1.389864 | J22: 1.709568 | K22: 1.46664 | L22: 1.317204 | M22: 1.242444 | N22: 1.313592 | O22: 1.43346 | P22: EIA | Q22: https://www.eia.gov/dnav/pet/hist/LeafHandler.ashx?n=pet&s=m_epooxe_eex_nus-z00_mbbl&f=a | R22: Retrieved January 2024 1 barrel of ethanol = 42 gallons
A23: CORN FOR ETHANOL | B23: 2010 | C23: 2011 | D23: 2012 | E23: 2013 | F23: 2014 | G23: 2015 | H23: 2016 | I23: 2017 | J23: 2018 | K23: 2019 | L23: 2020 | M23: 2021 | N23: 2022 | O23: 2023 | P23: Source Name | Q23: Source URL | R23: Comments
A24: Total corn used for Fuel ethanol use (million metric tons) | B24: 125.46852 | C24: 125.0008 | D24: 116.02818 | E24: 128.09225 | F24: 130.00225 | G24: 130.59035 | H24: 135.79883 | I24: 140.12068 | J24: 134.45065 | K24: 121.41688 | L24: 125.68988 | M24: 132.99038 | N24: 129.40353 | O24: 135 | P24: USDA | Q24: https://www.ers.usda.gov/data-products/us-bioenergy-statistics/#:~:text=Ethanol%2C%20made%20mostly%20from%20corn,all%20biofuel%20production%20in%202012.&text=ERS%20analysts%20track%20U.S.%20ethanol,production%2C%20consumption%2C%20and%20trade. | R24: Retrieved January 2024 1 bushel of corn=0.025 metric tons
A26: ECONOMICS | B26: 2010 | C26: 2011 | D26: 2012 | E26: 2013 | F26: 2014 | G26: 2015 | H26: 2016 | I26: 2017 | J26: 2018 | K26: 2019 | L26: 2020 | M26: 2021 | N26: 2022 | O26: 2023 | P26: Source Name | Q26: Source URL | R26: Comments
... A28: Price for Ethanol Per gallon (dollar per gge) | B28: 2.76 | C28: 3.84 | D28: 3.75 | E28: 3.75 | F28: 3.585 | G28: 2.73 | H28: 2.325 | I28: 2.4 | J28: 1.86 | K28: 1.81 | L28: 2.66 | M28: 3.82 | N28: 3.42 | O28: 3.05 | P28: USDA | Q28: https://www.ers.usda.gov/data-products/us-bioenergy-statistics/ | R28: Retrieved January 2024 1.5 gallons ethanol = 1 gallon gasoline
A29: Price for E85 Per gallon (dollar per gge) | B29: 3.37 | C29: 4.38 | D29: 4.7075 | E29: 4.5025 | F29: 4.435 | G29: 2.95 | H29: 2.455 | I29: 2.675 | J29: 2.925 | K29: 2.905 | L29: 2.59 | M29: =(2.65+3.12+3.4+3.55)/4 -> 3.18 | N29: =(3.87+4.6+5.1+4.13)/4 -> 4.425 | O29: =(3.96+3.84+3.88+3.6)/4 -> 3.82 | P29: AFD | Q29: https://www.afdc.energy.gov/fuels/prices.html | R29: Retrieved January 2024
A30: Price for gasoline Per gallon (dollar per gge) | B30: 2.745 | C30: 3.4775 | D30: 3.65 | E30: 3.495 | F30: 3.5075 | G30: 2.4725 | H30: 2.13 | I30: 2.3625 | J30: 2.74 | K30: 2.6175 | L30: 2.225 | M30: =(2.32+2.82+3.09+3.25)/4 -> 2.87 | N30: =(3.28+4.13+4.7+4.05)/4 -> 4.04 | O30: =(3.31+3.69+3.59+3.72)/4 -> 3.5775 | P30: AFD | Q30: https://www.afdc.energy.gov/fuels/prices.html | R30: Retrieved January 2024
A31: Number of direct jobs working with ethanol production | B31: 70400 | C31: 90200 | D31: 70000 | E31: 86504 | F31: 83949 | G31: 85967 | H31: 74420 | I31: 71906 | J31: 71637 | K31: 68542 | L31: 62180 | M31: 73193 | N31: 78802 | O31: 72463 | P31: RFA | Q31: http://www.ethanolrfa.org/pocket-guide/ | R31: Retrieved January 2024
A32: Number of indirect and induced jobs working with ethanol production | B32: 329600 | C32: 311400 | D32: 295000 | E32: 300277 | F32: 295265 | G32: 271440 | H32: 264756 | I32: 285587 | J32: 294516 | K32: 277389 | L32: 242600 | M32: 334220 | N32: 342876 | O32: 322002 | P32: RFA | Q32: http://www.ethanolrfa.org/pocket-guide/ | R32: Retrieved January 2024
A33: GDP contribution/influence (billion dollars) | B33: 54 | C33: 42.4 | D33: 40.6 | E33: 44 | F33: 53 | G33: 44 | H33: 42 | I33: 45 | J33: 46 | K33: 42.8 | L33: 34.7 | M33: 52.1 | N33: 57 | O33: 54.2 | P33: RFA | Q33: http://www.ethanolrfa.org/pocket-guide/ | R33: Retrieved January 2024
A34: Household income from industry (billion dollars) | B34: 36 | C34: 29.9 | D34: 29.9 | E34: 31 | F34: 27 | G34: 24 | H34: 23 | I34: 24 | J34: 25 | K34: 22.9 | L34: 18.6 | M34: 28.7 | N34: 34.8 | O34: 32.5 | P34: RFA | Q34: http://www.ethanolrfa.org/pocket-guide/ | R34: Retrieved January 2024
A35: Tax Revenue (billion dollars) | D35: 7.9 | E35: 8.3 | F35: 10.3 | G35: 8.7 | H35: 8.5 | I35: 10.7 | J35: 8.8 | K35: 7.9 | L35: 6.3 | M35: 10.4 | N35: 12.3 | O35: 10.4 | P35: RFA | Q35: "[2013-2014] http://www.ethanolrfa.org/pocket-guide/ [2019-2021] https://ethanolrfa.org/library/reports-studies-and-white-papers/ethanol-and-the-economy" | R35: Retrieved January 2024
A36: Crude oil (dollar per barrel) | B36: 79.48 | C36: 94.88 | D36: 94.05 | E36: 97.98 | F36: 93.17 | G36: 48.66 | H36: 43.29 | I36: 50.8 | J36: 65.23 | K36: 56.99 | L36: 39.68 | M36: 68.17 | N36: 94.53 | O36: 77.64 | P36: Macrotrends | Q36: https://www.macrotrends.net/1369/crude-oil-price-history-chart | R36: Retrieved January 2024

Sheet BIOBUTANOL
A1: BIOBUTANOL
A3: PRODUCTION | B3: 2010 | C3: 2011 | D3: 2012 | E3: 2013 | F3: 2014 | G3: 2015 | H3: 2016 | I3: 2017 | J3: 2018 | K3: 2019 | L3: 2020 | M3: 2021 | N3: 2022 | O3: 2023 | P3: Source Name | Q3: Source URL | R3: Comments
A4: Total Volume of Biobutanol entering the commercial market in the US (thousand gallons) | E4: 12 | F4: 0 | G4: 0 | H4: 125 | I4: 0 | J4: 0 | K4: 0 | L4: 0.44 | M4: 0 | N4: 0 | O4: 0 | P4: EPA | Q4: https://www.epa.gov/fuels-registration-reporting-and-compliance-help/rins-generated-transactions | R4: Retrieved December 2023

Sheet BIODIESEL
A1: BIODIESEL
A3: PHYSICAL | B3: 2010 | C3: 2011 | D3: 2012 | E3: 2013 | F3: 2014 | G3: 2015 | H3: 2016 | I3: 2017 | J3: 2018 | K3: 2019 | L3: 2020 | M3: 2021 | N3: 2022 | O3: 2023 | P3: Source Name | Q3: Source URL | R3: Comments
A4: Number of Biodiesel Plants in the United States | C4: 103 | D4: 112 | E4: 115 | F4: 98 | G4: 94 | H4: 96 | I4: 95 | J4: 100 | K4: 91 | L4: 85 | M4: 75 | N4: 72 | O4: 59 | P4: EIA | Q4: https://www.eia.gov/biofuels/biodiesel/capacity/ | R4: Retrieved February 2024
A5: Number of Proposed Biodiesel Plants | H5: 6 | I5: 0 | J5: 0 | K5: 0 | M5: 9 | O5: 3 | P5: Biodiesel Magazine | Q5: http://www.biodieselmagazine.com/plants/listplants/USA/proposed/ | R5: Retrieved February 2024
A6: Number of Existing Plants Under Construction | G6: 16 | H6: 15 | I6: 10 | J6: 12 | K6: 12 | M6: 14 | O6: 3 | P6: Biodiesel Magazine | Q6: http://www.biodieselmagazine.com/plants/listplants/USA/construction/ | R6: Retrieved February 2024
A7: Number of States which have a Biodiesel Production Facility | C7: 35 | D7: 37 | E7: 38 | F7: 35 | G7: 36 | H7: 37 | I7: 36 | J7: 38 | K7: 37 | L7: 33 | M7: 32 | N7: 29 | O7: 29 | P7: EIA | Q7: https://www.eia.gov/biofuels/biodiesel/production/archive/ https://www.eia.gov/biofuels/biodiesel/capacity/ | R7: Retrieved February 2024
A8: Plant capacity (billion gallons) | K8: 2.563 | L8: 2.514 | M8: 2.409 | N8: 2.255 | O8: 2.086 | P8: EIA | Q8: https://www.eia.gov/biofuels/biodiesel/capacity/ | R8: Retrieved February 2024
A10: PRODUCTION | B10: 2010 | C10: 2011 | D10: 2012 | E10: 2013 | F10: 2014 | G10: 2015 | H10: 2016 | I10: 2017 | J10: 2018 | K10: 2019 | L10: 2020 | M10: 2021 | N10: 2022 | O10: 2023 | P10: Source Name | Q10: Source URL | R10: Comments
A11: Total Production of Biodiesel in US (billion gallons) | B11: 0.3435 | C11: 0.9675 | D11: 0.9696 | E11: 1.358 | F11: 1.268 | G11: 1.266 | H11: 1.569 | I11: 1.596 | J11: 1.857 | K11: 1.725 | L11: 1.815 | M11: 1.709 | N11: 1.622 | O11: 1.699 | P11: EIA | Q11: [2010-2019] https://www.eia.gov/biofuels/biodiesel/production/archive/ [2020-2021] https://www.eia.gov/totalenergy/data/monthly/pdf/mer.pdf | R11: Retrieved January 2024
A12: Total Volume of Biodiesel Consumed in US (billion gallons) | B12: 0.25863034 | C12: 0.88561299 | D12: 0.90128755 | E12: 1.4263855 | F12: 1.4185509 | G12: 1.4969239 | H12: 2.0847212 | I12: 1.9828363 | J12: 1.9044633 | K12: 1.813 | L12: 1.876 | M12: 1.71 | N12: 1.658 | O12: 1.939 | P12: EIA | Q12: https://www.eia.gov/totalenergy/data/monthly/pdf/sec10_5.pdf | R12: Retrieved January 2024 1 gallon of biodiesel = 127,595 BTUs
A13: Total Volume of Biodiesel Imported into the US (million gallons) | B13: 23.688 | C13: 37.38 | D13: 35.826 | E13: 342.384 | F13: 192.276 | G13: 352.758 | H13: 708.918 | I13: 393.708 | J13: 166.698 | K13: 171.276 | L13: 196.728 | M13: 210.21 | N13: 249.9 | O13: 501.018 | P13: EIA | Q13: https://www.eia.gov/totalenergy/data/monthly/pdf/sec10_8.pdf | R13: Retrieved January 2024 1 barrel of biodiesel = 42 gallons
A14: Total Volume of Biodiesel Exported from the US (million gallons) | B14: 108.696 | C14: 75.558 | D14: 128.352 | E14: 196.35 | F14: 82.908 | G14: 87.822 | H14: 88.116 | I14: 93.156 | J14: 103.74 | K14: 114.66 | L14: 145.236 | M14: 186.984 | N14: 238.182 | O14: 251.16 | P14: EIA | Q14: https://www.eia.gov/totalenergy/data/monthly/pdf/sec10_8.pdf | R14: Retrieved January 2024 1 barrel of biodiesel = 42 gallons
A15: Number of Biodiesel stations | B15: 644 | C15: 627 | D15: 675 | E15: 757 | F15: 783 | G15: 713 | H15: 716 | I15: 704 | J15: 680 | K15: 611 | L15: 712 | M15: 730 | N15: 1193 | O15: 1700 | P15: USDA | Q15: https://www.ers.usda.gov/data-products/us-bioenergy-statistics/ | R15: Retrieved January 2024
A17: ECONOMICS | B17: 2010 | C17: 2011 | D17: 2012 | E17: 2013 | F17: 2014 | G17: 2015 | H17: 2016 | I17: 2017 | J17: 2018 | K17: 2019 | L17: 2020 | M17: 2021 | N17: 2022 | O17: 2023 | P17: Source Name | Q17: Source URL | R17: Comments
A18: Price Per Gallon of Biodiesel (dollar per gallon) | B18: 3.436375 | C18: 5.1727083 | D18: 4.51625 | E18: 4.6016667 | F18: 3.455 | G18: 2.8358333 | H18: 3.2391667 | I18: 3.2725 | J18: 3.1016667 | K18: =AVERAGE(3.03, 3.11, 2.95, 2.87, 2.83, 2.8, 2.87, 2.89, 2.9, 2.93, 2.97, 3.17 ) -> 2.9433333 | L18: =AVERAGE(3.25, 3.1, 2.97, 2.71, 2.67, 2.8, 2.88, 3.12, 2.99, 3.09, 3.39, 3.51 ) -> 3.04 | M18: =AVERAGE(4.13, 4.42, 4.91, 5.41, 6.05, 5.97, 5.88, 5.56, 5.28, 5.45, 5.57, 5.45 ) -> 5.34 | N18: =AVERAGE(5.46, 5.93, 6.48, 6.78, 7.09, 6.97, 6.57, 6.71, 6.79, 6.81, 6.72, 5.87 ) -> 6.515 | O18: =AVERAGE(5.73, 5.54, 5.09, 5.12, 4.99, 5.33, 5.66, 5.65, 5.47, 4.45, 4.49, 4.56 ) -> 5.1733333 | P18: USDA | Q18: https://www.ers.usda.gov/data-products/us-bioenergy-statistics/ | R18: Retrieved February 2024
A19: Price Per Gallon of B99/100 (dollar per gge) | B19: 3.6275 | C19: 4.125 | D19: 4.2275 | E19: 4.2125 | F19: 4.18 | G19: 3.615 | H19: 3 | I19: 3.12 | J19: 3.4625 | K19: 3.535 | L19: =AVERAGE(3.65,3.44,3.08,3.26 ) -> 3.3575 | M19: =AVERAGE(3.11,3.49,3.56,3.73 ) -> 3.4725 | N19: =AVERAGE(3.88,4.96,5.48,5.15 ) -> 4.8675 | O19: =AVERAGE(5.11,4.85,4.44,4.76 ) -> 4.79 | P19: AFDC | Q19: https://www.afdc.energy.gov/fuels/prices.html | R19: Retrieved February 2024
A20: Price Per Gallon of B20 (dollar per gge) | B20: 2.8 | C20: 3.53 | D20: 3.6875 | E20: 3.6675 | F20: 3.5975 | G20: 2.635 | H20: 2.1675 | I20: 2.3025 | J20: 2.6675 | K20: 2.485 | L20: =AVERAGE(2.6,2.13,2.11,2.06 ) -> 2.225 | M20: =AVERAGE(2.18,2.53,2.74,2.96 ) -> 2.6025 | N20: =AVERAGE(3.08,4.16,4.8,4.4 ) -> 4.11 | O20: =AVERAGE(4.01,3.62,3.4,3.98 ) -> 3.7525 | P20: AFDC | Q20: https://www.afdc.energy.gov/fuels/prices.html | R20: Retrieved February 2024
A21: Price Per Gallon of Diesel (dollar per gge) | B21: 2.67 | C21: 4.1675 | D21: 3.5525 | E21: 3.535 | F21: 3.485 | G21: 2.555 | H21: 2.0725 | I21: 2.3075 | J21: 2.8025 | K21: =AVERAGE(2.65,2.75,2.71,2.74) -> 2.7125 | L21: =AVERAGE(2.71,2.33,2.2,2.13 ) -> 2.3425 | M21: =AVERAGE(2.35,2.77,2.9,3.1 ) -> 2.78 | N21: =AVERAGE(3.22,4.5,5.02,4.6 ) -> 4.335 | O21: =AVERAGE(4.08,3.78,3.45,4.02 ) -> 3.8325 | P21: AFDC | Q21: https://www.afdc.energy.gov/fuels/prices.html | R21: Retrieved February 2024
A22: Average Soy Price (dollar per metric tons) | B22: 418.51852 | C22: 462.96296 | D22: 533.33333 | E22: 481.48148 | F22: 374.07407 | G22: 331.48148 | H22: 350.74074 | I22: 345.55556 | J22: 314.07407 | K22: 329.81481 | L22: =AVERAGE(317.407,400) -> 358.7035 | M22: =AVERAGE(400,492.59259) -> 446.29629 | N22: =AVERAGE(529.62,492.59259) -> 511.10629 | O22: 529.62 | P22: USDA | Q22: https://www.ers.usda.gov/data-products/oil-crops-yearbook/oil-crops-yearbook/ | R22: Retrieved February 2024 1 bushel of soy=0.027 metric tons
A23: Number of direct jobs working with biodiesel production | F23: 49500 | G23: 49500 | H23: 61100 | I23: 62200 | J23: 72300 | K23: 67300 | L23: 70860 | M23: 63900 | N23: 63180 | O23: 66261 | P23: IRENA | Q23: https://www.irena.org/publicationsearch?keywords=jobs%20annual%20review | R23: Retrieved February 2024

Sheet FATS
A1: ANIMAL FATS AND RECYCLED GREASES
A3: PRODUCTION | B3: 2009 | C3: 2010 | D3: 2011 | E3: 2012 | F3: 2013 | G3: 2014 | H3: 2015 | I3: 2016 | J3: 2017 | K3: 2018 | L3: 2019 | M3: 2020 | N3: 2021 | O3: 2022 | P3: 2023 | Q3: Source Name | R3: Source URL | S3: Comments
A4: Production
A5: Poultry Fat (Thousand metric tons) | D5: 1004.9 | E5: 1025.2 | F5: 1040.2 | G5: 1056.5 | H5: 1088.8 | I5: 1113.3 | J5: 1095.3 | K5: 1025.6 | L5: 1133.9 | M5: 1146.5 | N5: 957.1 | O5: 918 | P5: 1039.6 | Q5: Render Magazine | R5: https://pubs.rendermagazine.com/archives/2024/2024-04.pdf | S5: Retrieved April 2024
A6: Tallow (Thousand metric tons) | D6: 2646.2 | E6: 2608.7 | F6: 2589.3 | G6: 2441.4 | H6: 2385.7 | I6: 2559.5 | J6: 2594.9 | K6: 2770.8 | L6: 2767.4 | M6: 2601.9 | N6: 2860.8 | O6: 2834.2 | P6: 2793.1 | Q6: Render Magazine | R6: https://pubs.rendermagazine.com/archives/2024/2024-04.pdf | S6: Retrieved April 2024
A7: White Grease (Thousand metric tons) | D7: 721.5 | E7: 720 | F7: 718 | G7: 707.3 | H7: 758.7 | I7: 787.6 | J7: 750.5 | K7: 736.8 | L7: 768.9 | M7: 734.2 | N7: 697.6 | O7: 745.9 | P7: 741 | Q7: Render Magazine | R7: https://pubs.rendermagazine.com/archives/2024/2024-04.pdf | S7: Retrieved April 2024
A8: Yellow Grease (Thousand metric tons) | D8: 906.4 | E8: 885.9 | F8: 896.4 | G8: 933.2 | H8: 926.4 | I8: 916.4 | J8: 913 | K8: 990.7 | L8: 1348.3 | M8: 1346 | N8: 1349.9 | O8: 1359.3 | Q8: Render Magazine | R8: https://pubs.rendermagazine.com/archives/2024/2024-04.pdf | S8: Retrieved April 2024
A9: Other fats (Thousand metric tons) | D9: 345.2 | E9: 348.6 | F9: 346.7 | G9: 333.9 | H9: 341.7 | I9: 336 | J9: 369.2 | K9: 285.9 | L9: 209.4 | M9: 207.2 | N9: 229.2 | O9: 175.6 | P9: 135.2 | Q9: Render Magazine | R9: https://pubs.rendermagazine.com/archives/2024/2024-04.pdf | S9: Retrieved April 2024
A10: Consumption for Feed & Food | B10: 2009 | C10: 2010 | D10: 2011 | E10: 2012 | F10: 2013 | G10: 2014 | H10: 2015 | I10: 2016 | J10: 2017 | K10: 2018 | L10: 2019 | M10: 2020 | N10: 2021 | O10: 2022 | P10: 2023
A11: Poultry Fat (Thousand metric tons) | D11: 896 | E11: 931.4 | F11: 952.6 | G11: 959 | H11: 983.7 | I11: 999.4 | J11: 1000.9 | K11: 979.4 | L11: 74.1 | M11: 78.5 | N11: 139.4 | O11: 73.3 | Q11: Render Magazine | R11: https://rendermagazine.com/wp-content/uploads/2019/07/Render_Apr19.pdf | S11: Retrieved January 2024
A12: Tallow (Thousand metric tons) | D12: 1792.3 | E12: 1934.5 | F12: 1990.3 | G12: 1899.6 | H12: 1846.8 | I12: 2084.4 | J12: 2116.1 | K12: 2150 | L12: 132.6 | M12: 166.9 | N12: 604.7 | O12: 794.6 | Q12: Render Magazine | R12: https://rendermagazine.com/wp-content/uploads/2019/07/Render_Apr19.pdf | S12: Retrieved January 2024
A13: White Grease (Thousand metric tons) | D13: 442.4 | E13: 526.4 | F13: 498.5 | G13: 492.5 | H13: 505.9 | I13: 534.8 | J13: 491.4 | K13: 475 | L13: 243.2 | M13: 277.6 | N13: 314.8 | O13: 300.2 | Q13: Render Magazine | R13: https://pubs.rendermagazine.com/2023-04/#p=18 | S13: Retrieved January 2024
A14: Yellow Grease (Thousand metric tons) | D14: 126.5 | E14: 146 | F14: 80.6 | G14: 123.7 | H14: 126.5 | I14: 23.1 | J14: 0 | K14: 0 | L14: 655.7 | M14: 477.6 | N14: 1535.2 | O14: 2273.1 | Q14: Render Magazine | R14: https://rendermagazine.com/wp-content/uploads/2019/07/Render_Apr19.pdf | S14: Retrieved January 2024
A15: TOTAL (Thousand metric tons) | D15: =SUM(D11:D14) -> 3257.2 | E15: =SUM(E11:E14) -> 3538.3 | F15: =SUM(F11:F14) -> 3522 | G15: =SUM(G11:G14) -> 3474.8 | H15: =SUM(H11:H14) -> 3462.9 | I15: =SUM(I11:I14) -> 3641.7 | J15: =SUM(J11:J14) -> 3608.4 | K15: =SUM(K11:K14) -> 3604.4 | ... O15: =SUM(O11:O14) -> 3441.2 | Q15: Calculation
A16: Consumtpion for Biofuels | B16: 2009 | C16: 2010 | D16: 2011 | E16: 2012 | F16: 2013 | G16: 2014 | H16: 2015 | I16: 2016 | J16: 2017 | K16: 2018 | L16: 2019 | M16: 2020 | N16: 2021 | O16: 2022 | P16: 2023
A17: Poultry Going to Biodiesel (Thousand metric tons) | B17: 61.234987 | C17: 45.35925 | D17: 108.8622 | E17: 79.83228 | F17: 73.028392 | G17: 79.83228 | H17: 89.357722 | I17: 99.79035 | J17: 72.121207 | K17: 51.255952 | L17: 73.934229 | M17: 78.471502 | N17: 139.70649 | O17: 73.481985 | P17: 76.801 | Q17: EIA | R17: https://www.eia.gov/biofuels/biodiesel/production/archive/2020/2020_09/table3.pdf Monthly Issues can be found here: https://www.eia.gov/biofuels/update/ | S17: Retrieved January 2024 1 metric ton = 2,204.622 pounds
A18: Tallow Going to Biodiesel (Thousand metric tons) | B18: 240.85762 | C18: 77.110725 | D18: 195.49837 | E18: 174.63311 | F18: 210.92051 | G18: 172.36515 | H18: 195.04477 | I18: 150.59271 | J18: 156.48941 | K18: 219.53877 | L18: 132.44659 | M18: 166.92204 | N18: 734.81985 | O18: 898.56674 | P18: 1904.018 | Q18: EIA | R18: https://www.eia.gov/biofuels/biodiesel/production/archive/2020/2020_09/table3.pdf | S18: Retrieved January 2024 1 metric ton = 2,204.622 pounds
A19: White Grease Going to Biodiesel (Thousand metric tons) | B19: 151.49989 | C19: 151.0463 | D19: 241.7648 | E19: 185.06574 | F19: 212.28129 | G19: 193.684 | H19: 267.16598 | I19: 262.17646 | J19: 268.07317 | K19: 280.32016 | L19: 243.12115 | M19: 277.59861 | N19: 315.24679 | O19: 301.18542 | P19: 270.27 | Q19: EIA | R19: https://www.eia.gov/biofuels/biodiesel/production/archive/2020/2020_09/table3.pdf | S19: Retrieved January 2024 1 metric ton = 2,204.622 pounds
A20: Yellow Grease to Biodiesel (Thousand metric tons) | B20: 70.76043 | C20: 111.58375 | D20: 213.64207 | E20: 303.90697 | F20: 474.45775 | G20: 487.15834 | H20: 568.80499 | I20: 630.03998 | J20: 667.23456 | K20: 756.59229 | L20: 655.42921 | M20: 477.6329 | N20: 1539.4929 | O20: 2272.0448 | P20: 3092.8 | Q20: EIA | R20: https://www.eia.gov/biofuels/biodiesel/production/archive/2020/2020_09/table3.pdf | S20: Retrieved January 2024 1 metric ton = 2,204.622 pounds
A21: Other fats Going to Biodiesel (Thousand metric tons) | B21: 37.648177 | C21: 37.194585 | D21: 127.0059 | E21: 152.86067 | F21: 148.32475 | G21: 97.97598 | H21: 80.739465 | I21: 31.297882 | J21: 29.02992 | K21: 100.24394 | L21: W | M21: 16.782922 | N21: 35.833807 | O21: 28.130672 | P21: 35.7 | Q21: EIA | R21: https://www.eia.gov/biofuels/biodiesel/production/archive/2020/2020_09/table3.pdf | S21: Retrieved January 2024 1 metric ton = 2,204.622 pounds
A22: TOTAL (Thousand metric tons) | B22: =SUM(B17:B21) -> 562.0011 | C22: =SUM(C17:C21) -> 422.29462 | D22: =SUM(D17:D21) -> 886.77333 | E22: =SUM(E17:E21) -> 896.29878 | F22: =SUM(F17:F21) -> 1119.0127 | G22: =SUM(G17:G21) -> 1031.0157 | H22: =SUM(H17:H21) -> 1201.1129 | I22: =SUM(I17:I21) -> 1173.8974 | ... P22: =SUM(P17:P21) -> 5379.589 | Q22: Calculation
A23: Exports | B23: 2009 | C23: 2010 | D23: 2011 | E23: 2012 | F23: 2013 | G23: 2014 | H23: 2015 | I23: 2016 | J23: 2017 | K23: 2018 | L23: 2019 | M23: 2020 | N23: 2021 | O23: 2022 | P23: 2023
A24: Poultry Fat (Thousand metric tons) | E24: 14.5 | F24: 14.9 | G24: 18.4 | H24: 16.4 | I24: 14.7 | J24: 16.1 | K24: 14.8 | L24: 12.9 | M24: 19 | N24: 17 | O24: 17 | P24: 19.2 | Q24: Render Magazine | R24: https://pubs.rendermagazine.com/archives/2024/2024-04.pdf | S24: Retrieved April 2024
A25: Tallow (Thousand metric tons) | D25: =598.4+60 -> 658.4 | E25: =486.7+75.4 -> 562.1 | F25: 453.4 | G25: 443.3 | H25: 407.9 | I25: 403.4 | J25: 402.3 | K25: 445.4 | L25: =301+121.4 -> 422.4 | M25: 299.7 | N25: 187.7 | O25: 214.6 | P25: =108.4+45.7 -> 154.1 | Q25: Render Magazine | R25: https://pubs.rendermagazine.com/archives/2024/2024-04.pdf | S25: Retrieved April 2024
A26: White Grease (Thousand metric tons) | D26: =34.8+2.5 -> 37.3 | E26: =24.8+1.4 -> 26.2 | F26: 29.9 | G26: 22 | H26: 20 | I26: 19.5 | J26: 18 | K26: 17.2 | L26: 22.5 | M26: 18.1 | N26: 81.3 | O26: 26.7 | P26: 0.107 | Q26: Render Magazine | R26: https://pubs.rendermagazine.com/archives/2024/2024-04.pdf | S26: Retrieved April 2024
A27: Yellow Grease (Thousand metric tons) | D27: 566.2 | E27: 452.1 | F27: 361 | G27: 333.1 | H27: 253 | I27: 286.2 | J27: 300.2 | K27: 360.7 | L27: 448.2 | M27: 766.3 | N27: 761.1 | O27: 489.9 | P27: 192.4 | Q27: Render Magazine | R27: https://pubs.rendermagazine.com/archives/2024/2024-04.pdf | S27: Retrieved April 2024
A28: TOTAL (Thousand metric tons) | D28: =SUM(D24:D27) -> 1261.9 | E28: =SUM(E24:E27) -> 1054.9 | F28: =SUM(F24:F27) -> 859.2 | G28: =SUM(G24:G27) -> 816.8 | H28: =SUM(H24:H27) -> 697.3 | I28: =SUM(I24:I27) -> 723.8 | J28: =SUM(J24:J27) -> 736.6 | K28: =SUM(K24:K27) -> 838.1 | ... P28: =SUM(P24:P27) -> 365.807 | Q28: Calculation
A29: Imports | B29: 2009 | C29: 2010 | D29: 2011 | E29: 2012 | F29: 2013 | G29: 2014 | H29: 2015 | I29: 2016 | J29: 2017 | K29: 2018 | L29: 2019 | M29: 2020 | N29: 2021 | O29: 2022 | P29: 2023
A30: Poultry Fat (Thousand metric tons) | E30: 0.5 | F30: 0.4 | G30: 4.4 | H30: 6.4 | I30: 5.8 | J30: 19.5 | K30: 5.69 | L30: 3.5 | M30: 2.1 | N30: 1.3 | O30: 3 | P30: 2.3 | Q30: Render Magazine | R30: https://pubs.rendermagazine.com/archives/2024/2024-04.pdf | S30: Retrieved April 2024
A31: Tallow (Thousand metric tons) | E31: 62.6 | F31: 59.5 | G31: 62.6 | H31: 64 | I31: 78.9 | J31: 99.8 | K31: 139.3 | L31: 192 | M31: 243.1 | N31: 333.3 | O31: 554.1 | P31: 795 | Q31: Render Magazine | R31: https://pubs.rendermagazine.com/archives/2024/2024-04.pdf | S31: Retrieved April 2024
A32: White Grease (Thousand metric tons) | E32: 17.7 | F32: 21.8 | G32: 20.8 | H32: 34.4 | I32: 28.8 | J32: 27 | K32: 35.8 | L32: 27.2 | M32: 23 | N32: 45.3 | O32: 70.5 | P32: 71.5 | Q32: Render Magazine | R32: https://pubs.rendermagazine.com/archives/2024/2024-04.pdf | S32: Retrieved April 2024
A33: Yellow Grease (Thousand metric tons) | E33: 16.1 | F33: 20.6 | G33: 17.2 | H33: 22.4 | I33: 23 | J33: 38.7 | K33: 62.9 | L33: 88 | M33: 83 | N33: 129.5 | O33: 395.6 | P33: 1405.6 | Q33: Render Magazine | R33: https://pubs.rendermagazine.com/archives/2024/2024-04.pdf | S33: Retrieved April 2024
A34: TOTAL (Thousand metric tons) | E34: =SUM(E30:E33) -> 96.9 | F34: =SUM(F30:F33) -> 102.3 | G34: =SUM(G30:G33) -> 105 | H34: =SUM(H30:H33) -> 127.2 | I34: =SUM(I30:I33) -> 136.5 | J34: =SUM(J30:J33) -> 185 | K34: =SUM(K30:K33) -> 243.69 | L34: =SUM(L30:L33) -> 310.7 | ... P34: =SUM(P30:P33) -> 2274.4 | Q34: Calculation
A35: Percent into Biodiesel | B35: 2009 | C35: 2010 | D35: 2011 | E35: 2012 | F35: 2013 | G35: 2014 | H35: 2015 | I35: 2016 | J35: 2017 | K35: 2018 | L35: 2019 | M35: 2020 | N35: 2021 | O35: 2022 | P35: 2023
A36: Poultry Fat (%) | D36: =D17/(D5)*100 -> 10.833138 | E36: =E17/(E5)*100 -> 7.7869957 | F36: =F17/(F5)*100 -> 7.0206107 | G36: =G17/(G5)*100 -> 7.5562972 | H36: =H17/(H5)*100 -> 8.2069914 | I36: =I17/(I5)*100 -> 8.9634734 | J36: =J17/(J5)*100 -> 6.5846076 | K36: =K17/(K5)*100 -> 4.9976553 | ... P36: =P17/(P5)*100 -> 7.3875529 | Q36: Calculation
A37: Tallow (%) | D37: =D18/(D6)*100 -> 7.3878908 | E37: =E18/(E6)*100 -> 6.6942581 | F37: =F18/(F6)*100 -> 8.1458507 | G37: =G18/(G6)*100 -> 7.0600946 | H37: =H18/(H6)*100 -> 8.1755784 | I37: =I18/(I6)*100 -> 5.8836769 | J37: =J18/(J6)*100 -> 6.0306529 | K37: =K18/(K6)*100 -> 7.923299 | ... P37: =P18/(P6)*100 -> 68.16863 | Q37: Calculation
A38: White Grease (%) | D38: =D19/(D7)*100 -> 33.508635 | E38: =E19/(E7)*100 -> 25.703575 | F38: =F19/(F7)*100 -> 29.565639 | G38: =G19/(G7)*100 -> 27.383571 | H38: =H19/(H7)*100 -> 35.213652 | I38: =I19/(I7)*100 -> 33.288022 | J38: =J19/(J7)*100 -> 35.719276 | K38: =K19/(K7)*100 -> 38.045625 | ... P38: =P19/(P7)*100 -> 36.473684 | Q38: Calculation
A39: Yellow Grease (%) | D39: =D20/(D8)*100 -> 23.570396 | E39: =E20/(E8)*100 -> 34.304885 | F39: =F20/(F8)*100 -> 52.929245 | G39: =G20/(G8)*100 -> 52.202994 | H39: =H20/(H8)*100 -> 61.399503 | I39: =I20/(I8)*100 -> 68.751635 | J39: =J20/(J8)*100 -> 73.081551 | K39: =K20/(K8)*100 -> 76.369465 | ... O39: =O20/(O8)*100 -> 167.14815 | Q39: Calculation
A41: ECONOMICS | B41: 2009 | C41: 2010 | D41: 2011 | E41: 2012 | F41: 2013 | G41: 2014 | H41: 2015 | I41: 2016 | J41: 2017 | K41: 2018 | L41: 2019 | M41: 2020 | N41: 2021 | O41: 2022 | P41: 2023 | Q41: Source Name | R41: Source URL | S41: Comments
A42: Price
A43: Poultry Fat (dollar per metric ton) | D43: 992 | E43: 864 | F43: 793 | G43: 660 | H43: 502 | I43: 546 | J43: 605 | K43: 566 | L43: 564 | M43: 558 | N43: 1038 | O43: 1376 | P43: 1095 | Q43: Render Magazine | R43: https://pubs.rendermagazine.com/archives/2024/2024-04.pdf | S43: Retrieved April 2024
A44: Tallow (dollar per metric ton) | D44: 1180 | E44: 1034 | F44: 966 | G44: 803 | H44: 563 | I44: 746 | J44: 731 | K44: 662 | L44: 748 | M44: 828 | N44: 1444 | O44: 1817 | P44: 1557 | Q44: Render Magazine | R44: https://pubs.rendermagazine.com/archives/2024/2024-04.pdf | S44: Retrieved April 2024
A45: White Grease (dollar per metric ton) | D45: 1020 | E45: 926 | F45: 846 | G45: 711 | H45: 498 | I45: 537 | J45: 549 | K45: 463 | L45: 512 | M45: 534 | N45: 1066 | O45: 1462 | P45: 1174 | Q45: Render Magazine | R45: https://pubs.rendermagazine.com/archives/2024/2024-04.pdf | S45: Retrieved April 2024
A46: Yellow Grease (dollar per metric ton) | D46: 932 | E46: 788 | F46: 727 | G46: 612 | H46: 462 | I46: 505 | J46: 524 | K46: 408 | L46: 466 | M46: 461 | N46: 893 | O46: 1266 | P46: 1027 | Q46: Render Magazine | R46: https://pubs.rendermagazine.com/archives/2024/2024-04.pdf | S46: Retrieved April 2024

Sheet RENEWABLE DIESEL
A1: RENEWABLE DIESEL
A3: PHYSICAL | B3: 2010 | C3: 2011 | D3: 2012 | E3: 2013 | F3: 2014 | G3: 2015 | H3: 2016 | I3: 2017 | J3: 2018 | K3: 2019 | L3: 2020 | M3: 2021 | N3: 2022 | O3: 2023 | P3: Source Name | Q3: Source URL | R3: Comments
A4: Number of Renewable Diesel Plants | M4: 6 | N4: 11 | O4: 17 | P4: EIA | Q4: https://www.eia.gov/biofuels/renewable/capacity/ | R4: Retrieved January 2024
A5: Number of States which have Renewable Diesel Plants in the United States | M5: 5 | N5: 6 | O5: 11 | P5: EIA | Q5: https://www.eia.gov/biofuels/renewable/capacity/ | R5: Retrieved January 2024
A6: Renewable Diesel plant capacities (billion gallons) | M6: 0.791 | N6: 1.75 | O6: 3 | P6: EIA | Q6: https://www.eia.gov/biofuels/renewable/capacity/ | R6: Retrieved January 2024
A8: PRODUCTION | B8: 2010 | C8: 2011 | D8: 2012 | E8: 2013 | F8: 2014 | G8: 2015 | H8: 2016 | I8: 2017 | J8: 2018 | K8: 2019 | L8: 2020 | M8: 2021 | N8: 2022 | O8: 2023 | P8: Source Name | Q8: Source URL | R8: Comments
A9: Total Production of Renewable diesel in the US (million gallons) | B9: 8.776593 | C9: 62.04129 | D9: 52.401102 | E9: 113.28586 | F9: 159.14121 | G9: 176.84762 | H9: 241.48744 | I9: 258.34213 | J9: 305.48445 | K9: 492.00796 | L9: 534 | M9: 861 | N9: 1499 | O9: 2593 | P9: EPA | Q9: https://www.epa.gov/fuels-registration-reporting-and-compliance-help/rins-generated-transactions | R9: Retrieved December 2023
A10: Total Consumption of Renewable diesel in the US (million gallons) | B10: 8.776593 | C10: 62.04129 | D10: 102.67402 | E10: 416.6854 | F10: 487.8927 | G10: 513.14457 | H10: 591.17347 | I10: 602.72382 | J10: 615.33108 | K10: 912.38458 | L10: 966 | M10: 1209 | N10: 1718 | O10: 2868 | P10: EPA | Q10: https://www.epa.gov/fuels-registration-reporting-and-compliance-help/rins-generated-transactions | R10: Retrieved December 2023
A11: Total Volume of Renewable diesel Exported from the US (million gallons) | H11: 0 | I11: 0 | J11: 0 | K11: 0 | L11: 0 | M11: 0 | N11: 0 | O11: 0 | P11: EIA | Q11: https://www.eia.gov/dnav/pet/pet_move_neti_a_EP00_IMN_mbblpd_m.htm | R11: Retrieved December 2023
A12: Total Volume of Renewable diesel Imported into the US (million gallons) | D12: 25.41 | E12: 206.682 | F12: 120.666 | G12: 204.708 | H12: 222.768 | I12: 189.378 | J12: 173.208 | K12: 258.006 | L12: 279.636 | M12: 392.28 | N12: 262.668 | O12: 362.124 | P12: EIA | Q12: https://www.eia.gov/dnav/pet/pet_move_impcus_a2_nus_EPOORDO_im0_mbbl_a.htm | R12: Retrieved December 2023

Sheet RENEWABLE JET FUEL
A1: RENEWABLE JET FUEL
A3: PRODUCTION | B3: 2010 | C3: 2011 | D3: 2012 | E3: 2013 | F3: 2014 | G3: 2015 | H3: 2016 | I3: 2017 | J3: 2018 | K3: 2019 | L3: 2020 | M3: 2021 | N3: 2022 | O3: 2023 | P3: Source Name | Q3: Source URL | R3: Comments
A4: Total production of renewable jet fuel (million gallons) | H4: 1.943717 | I4: 1.711017 | J4: 1.828178 | K4: 2.428702 | L4: 4.608399 | M4: 5.080073 | N4: 7.893137 | O4: 14.016105 | P4: EPA | Q4: https://www.epa.gov/fuels-registration-reporting-and-compliance-help/rins-generated-transactions | R4: Retrieved January 2024
A5: Total consumption of renewable jet fuel (million gallons) | H5: 1.943717 | I5: 1.711017 | J5: 1.828178 | K5: 2.428702 | L5: 4.608399 | M5: 5.080073 | N5: 15.819877 | O5: 26.300097 | P5: EPA | Q5: https://www.epa.gov/fuels-registration-reporting-and-compliance-help/rins-generated-transactions | R5: Retrieved January 2024
A6: Total consumption of jet fuel major US Airlines (million gallons) | H6: 17138 | I6: 17662 | J6: 18325 | K6: 18746 | L6: 11067 | M6: 14617 | N6: 17510 | P6: GAO | Q6: https://www.gao.gov/products/gao-23-105300 | R6: Retrieved January 2024 1L = 0.26172 gallon
A7: Airline off-take agreement (thousand gallons) | E7: 15005 | F7: 395994 | G7: 921009 | H7: 639006 | I7: 39996 | J7: 106 | K7: 255135.12 | L7: 108781.3 | M7: 2412304.6 | N7: 5683241.9 | O7: 2977690.5 | P7: ICAO | Q7: https://www.icao.int/environmental-protection/GFAAF/Pages/Offtake-Agreements.aspx#InplviewHashef347ce3-9fcc-4b72-be6a-207e60680777=ShowInGrid%3DTrue | R7: Retrieved December 2023 1 liter = 0.26172 gallons
A8: Airline off-take agreement | E8: 1 | F8: 2 | G8: 2 | H8: 6 | I8: 2 | J8: 5 | K8: 4 | L8: 5 | M8: 23 | N8: 43 | O8: 28 | P8: ICAO | Q8: https://www.icao.int/environmental-protection/GFAAF/Pages/Offtake-Agreements.aspx#InplviewHashef347ce3-9fcc-4b72-be6a-207e60680777=ShowInGrid%3DTrue | R8: Retrieved January 2024
A9: Number of Eligible Producers | D9: 1 | E9: 2 | F9: 3 | G9: 3 | H9: 3 | I9: 4 | J9: 4 | K9: 4 | L9: 5 | M9: 6 | N9: 6 | O9: 9 | P9: ICAO | Q9: https://www.icao.int/environmental-protection/GFAAF/Pages/Production-Facilities.aspx | R9: Retrieved January 2024
A10: Number of Facilities in Service | D10: 4 | E10: 5 | F10: 6 | G10: 6 | H10: 6 | I10: 7 | J10: 7 | K10: 7 | L10: 10 | M10: 11 | N10: 11 | O10: 14 | P10: ICAO | Q10: https://www.icao.int/environmental-protection/GFAAF/Pages/Production-Facilities.aspx | R10: Retrieved January 2024
A11: Number of Airports with SAF (Ongoing Delivery) | F11: 0 | G11: 0 | H11: 2 | I11: 5 | J11: 9 | K11: 11 | L11: 14 | M11: 46 | N11: 63 | O11: 79 | P11: ICAO | Q11: https://www.icao.int/environmental-protection/GFAAF/Pages/Airports.aspx | R11: Retrieved January 2024
A12: Number of Airports with SAF (Batch Delivery) | F12: 1 | G12: 1 | H12: 3 | I12: 5 | J12: 10 | K12: 15 | L12: 16 | M12: 21 | N12: 31 | O12: 43 | P12: ICAO | Q12: https://www.icao.int/environmental-protection/GFAAF/Pages/Airports.aspx | R12: Retrieved January 2024
A13: Number of States with SAF available at airports | G13: 1 | H13: 2 | I13: 2 | J13: 3 | K13: 3 | L13: 4 | M13: 5 | N13: 6 | O13: 7 | P13: 4AIR | Q13: Where to find Sustainable Aviation Fuel — 4AIR | R13: Retrieved January 2024
A14: Domestic CO2 emissions from aviation sector (Million metric tons) | B14: 288.14 | C14: 296.04 | D14: 301.89 | E14: 311.24 | F14: 321.69 | G14: 338.84 | H14: 356.18 | I14: 380.57 | J14: 395.41 | K14: 403.72 | L14: 279.79 | M14: 321.13 | N14: 347.73 | P14: IEA | Q14: https://www.iea.org/energy-system/transport/aviation#tracking | R14: Retrieved January 2025
A15: Internationa CO2 emissions form aviation sector (Million metric tons) | B15: 465.88 | C15: 479.74 | D15: 481.25 | E15: 490.26 | F15: 505.94 | G15: 534.97 | H15: 559.09 | I15: 595.24 | J15: 622.53 | K15: 632.73 | L15: 302.56 | M15: 343.88 | N15: 436.72 | P15: IEA | Q15: https://www.iea.org/energy-system/transport/aviation#tracking | R15: Retrieved January 2025

Sheet WOOD PELLETS
A1: WOOD PELLETS
A3: PHYSICAL | B3: 2010 | C3: 2011 | D3: 2012 | E3: 2013 | F3: 2014 | G3: 2015 | H3: 2016 | I3: 2017 | J3: 2018 | K3: 2019 | L3: 2020 | M3: 2021 | N3: 2022 | O3: 2023 | P3: Source Name | Q3: Source URL | R3: Comments
A4: Total Operational Capacity of Pellet Mill Facilities (million metric tons) | G4: 9.4225 | H4: 11.158927 | I4: 13.019865 | J4: 12.355042 | K4: 13.0586 | L4: 13.99425 | M4: 13.3658 | N4: 12.8441 | O4: 13.9023 | P4: Biomass Industry Directory | Q4: Biomass Industry Directory, published by BBI International | R4: Retrieved January 2024
A5: Number of WP Plants in the United States | E5: 123 | F5: 122 | G5: 137 | H5: 147 | I5: 148 | J5: 140 | K5: 126 | L5: 124 | M5: 116 | N5: 123 | O5: 118 | P5: Biomass Industry Directory | Q5: Biomass Industry Directory, published by BBI International | R5: Retrieved January 2024
A6: Number of Proposed WP Plants | E6: 11 | F6: 15 | G6: 22 | H6: 18 | I6: 7 | J6: 0 | K6: 3 | L6: 1 | M6: 3 | N6: 3 | O6: 5 | P6: Biomass Industry Directory | Q6: Biomass Industry Directory, published by BBI International | R6: Retrieved January 2024
A7: Number of Existing Plants Under Construction | E7: 7 | F7: 9 | G7: 9 | H7: 11 | I7: 4 | J7: 4 | K7: 2 | L7: 5 | M7: 4 | N7: 4 | O7: 1 | P7: Biomass Industry Directory | Q7: Biomass Industry Directory, published by BBI International | R7: Retrieved January 2024
A8: Number of Existing Plants that Were Put on Standby | H8: 13 | I8: 11 | J8: 6 | K8: 0 | L8: 5 | M8: 1 | N8: 1 | O8: 1 | P8: Biomass Industry Directory | Q8: Biomass Industry Directory, published by BBI International | R8: Retrieved January 2024
A9: Number of States which have an WP Production Facility | E9: 36 | F9: 36 | G9: 36 | H9: 38 | I9: 37 | J9: 40 | K9: 38 | L9: 37 | M9: 36 | N9: 36 | O9: 35 | P9: Biomass Industry Directory | Q9: Biomass Industry Directory, published by BBI International | R9: Retrieved January 2024
A11: PRODUCTION + CONSUMPTION | B11: 2010 | C11: 2011 | D11: 2012 | E11: 2013 | F11: 2014 | G11: 2015 | H11: 2016 | I11: 2017 | J11: 2018 | K11: 2019 | L11: 2020 | M11: 2021 | N11: 2022 | O11: 2023 | P11: Source Name | Q11: Source URL | R11: Comments
A12: Wood pellets Production (million metric tons) | D12: 3.474 | E12: 4.704 | F12: 5.947 | G12: 6.517 | H12: 6.393 | I12: 6.9 | J12: 7.468361 | K12: 8.592713 | L12: 8.412359 | M12: 8.4486 | N12: 9.544 | O12: 9.820703 | P12: FAOSTAT | Q12: http://www.fao.org/faostat/en/#data/FO | R12: Retrieved January 2024
A13: Wood pellets Imports (million metric tons) | D13: 0.086 | E13: 0.152442 | F13: 0.219987 | G13: 0.207 | H13: 0.204847 | I13: 0.211617 | J13: 0.221 | K13: 0.211615 | L13: 0.204958 | M13: 0.195951 | N13: 0.19442 | O13: 0.17687225 | P13: FAOSTAT | Q13: http://www.fao.org/faostat/en/#data/FO | R13: Retrieved January 2024
A14: Wood pellets Exports (million metric tons) | D14: 1.898125 | E14: 2.882517 | F14: 4.005057 | G14: 4.669 | H14: 4.709 | I14: 5.203981 | J14: 6.017 | K14: 6.858462 | L14: 7.25686 | M14: 7.52255 | N14: 8.97716 | O14: 9.54 | P14: FAOSTAT | Q14: http://www.fao.org/faostat/en/#data/FO | R14: Retrieved January 2024
A15: Wood pellets Consumption (million metric tons) | D15: =+D12+D13-D14 -> 1.661875 | E15: =+E12+E13-E14 -> 1.973925 | F15: =+F12+F13-F14 -> 2.16193 | G15: =+G12+G13-G14 -> 2.055 | H15: =+H12+H13-H14 -> 1.888847 | I15: =+I12+I13-I14 -> 1.907636 | J15: =+J12+J13-J14 -> 1.672361 | K15: =+K12+K13-K14 -> 1.945866 | ... O15: =+O12+O13-O14 -> 0.45757525 | P15: Estimation
A16: Electricity Net Generation from Wood (trillion BTUs) | B16: 126.83607 | C16: 127.78123 | D16: 128.97548 | E16: 136.58114 | F16: 144.47001 | G16: 143.06762 | H16: 139.7169 | I16: 140.41639 | J16: 139.9148 | K16: =38543*3412.14/1000000 -> 131.51411 | L16: 123.5843 | M16: 124.41686 | N16: 121.00813 | O16: 107.27427 | P16: EIA | Q16: https://www.eia.gov/totalenergy/data/monthly/pdf/mer.pdf | R16: Retrieved January 2024 1 kwh= 3412.14 BTUs
A17: Industrial Sector | B17: 87.712471 | C17: 91.073429 | D17: 91.189442 | E17: 94.485569 | F17: 92.943281 | G17: 93.212841 | H17: 93.69054 | I17: 93.629122 | J17: 93.983984 | K17: =26433*3412.14/1000000 -> 90.193097 | L17: =24916*3412.14/1000000 -> 85.01688 | M17: =24413*3412.14/1000000 -> 83.300574 | N17: =23287*3412.14/1000000 -> 79.458504 | O17: 74.336882 | P17: EIA | Q17: https://www.eia.gov/totalenergy/data/monthly/pdf/mer.pdf | R17: Retrieved January 2024 1 kwh= 3412.14 BTUs
A18: Electric Power Sector | B18: 39.055354 | C18: 36.622499 | D18: 37.704147 | E18: 41.976146 | F18: 51.274228 | G18: 49.690995 | H18: 45.790919 | I18: 46.545002 | J18: 45.671494 | K18: =12020*3412.14/1000000 -> 41.013923 | L18: 38.253502 | M18: 40.59423 | N18: 40.952504 | O18: 32.568876 | P18: EIA | Q18: https://www.eia.gov/totalenergy/data/monthly/pdf/mer.pdf | R18: Retrieved January 2024 1 kwh= 3412.14 BTUs
A19: Heating from Wood in the US (trillion BTUs) | B19: =+B20-B16 -> 2090.1639 | C19: =+C20-C16 -> 2085.2188 | D19: =+D20-D16 -> 2022.0245 | E19: =+E20-E16 -> 2201.4189 | F19: =+F20-F16 -> 2256.53 | G19: =+G20-G16 -> 2168.9324 | H19: =+H20-H16 -> 2090.2831 | I19: =+I20-I16 -> 2144.5836 | ... O19: =+O20-O16 -> 1810.7257 | P19: Estimation
A20: Energy Consumption from Wood in US (trillion BTUs) | B20: 2217 | C20: 2213 | D20: 2151 | E20: 2338 | F20: 2401 | G20: 2312 | H20: 2230 | I20: 2285 | J20: 2359 | K20: 2237 | L20: 1970 | M20: 1989 | N20: 2012 | O20: 1918 | P20: EIA | Q20: https://www.eia.gov/totalenergy/data/monthly/pdf/mer.pdf | R20: Retrieved April 2024
A21: Residential Sector | B21: 541 | C21: 524 | D21: 438 | E21: 572 | F21: 579 | G21: 513 | H21: 448 | I21: 433 | J21: 525 | K21: 546 | L21: 345 | M21: 344 | N21: 422 | O21: 450 | P21: EIA | Q21: https://www.eia.gov/totalenergy/data/monthly/pdf/mer.pdf | R21: Retrieved April 2024
A22: Commercial Sector | B22: 72 | C22: 69 | D22: 61 | E22: 70 | F22: 76 | G22: 79 | H22: 84 | I22: 84 | J22: 84 | K22: 84 | L22: 83 | M22: 83 | N22: 83 | O22: 82 | P22: EIA | Q22: https://www.eia.gov/totalenergy/data/monthly/pdf/mer.pdf | R22: Retrieved April 2024
A23: Industrial Sector | B23: 1409 | C23: 1438 | D23: 1462 | E23: 1489 | F23: 1495 | G23: 1476 | H23: 1474 | I23: 1539 | J23: 1537 | K23: 1413 | L23: 1356 | M23: 1366 | N23: 1308 | O23: 1224 | P23: EIA | Q23: https://www.eia.gov/totalenergy/data/monthly/pdf/mer.pdf | R23: Retrieved April 2024
A24: Electric Power Sector | B24: 196 | C24: 182 | D24: 190 | E24: 207 | F24: 251 | G24: 244 | H24: 224 | I24: 229 | J24: 221 | K24: 201 | L24: 185 | M24: 199 | N24: 198 | O24: 162 | P24: EIA | Q24: https://www.eia.gov/totalenergy/data/monthly/pdf/mer.pdf | R24: Retrieved April 2024
A25: Wood pellet production worldwide (million metric tons) | B25: 15.7 | C25: 18.3 | D25: 18.053589 | E25: 21.19902 | F25: 25.093777 | G25: 27.381663 | H25: 29.304248 | I25: 33.410286 | J25: 37.627758 | K25: 41.975705 | L25: 42.988148 | M25: 44.971052 | N25: 48.070887 | O25: 49.94409 | P25: Hawkins Wright; REN21; FAO | Q25: [2010-2011] http://task32.ieabioenergy.com/wp-content/uploads/2017/03/03-Fiona_Matthews.pdf [2012-2018] http://www.fao.org/faostat/en/#data/FO | R25: Retrieved April 2024
A26: Average Annual Densified Biomass Capacity (million metric tons) | H26: 10.003977 | I26: 10.867589 | J26: 10.730605 | K26: 10.806215 | L26: 12.010147 | M26: 12.96185 | N26: 13.244444 | O26: 13.26499 | P26: EIA | Q26: http://www.eia.gov/biofuels/biomass/ | R26: Retrieved April 2024
A27: Wood Pellets Exported from US (in million $) | D27: 258.234 | E27: 370.981 | F27: 519.399 | G27: 682.978 | H27: 612.496 | I27: 666.545 | J27: 809.855 | K27: 942.627 | L27: 981.593 | M27: 1059.261 | N27: 1545.409 | O27: 1753.4892 | P27: FAOSTAT | Q27: http://www.fao.org/faostat/en/#data/FO | R27: Retrieved April 2024
A28: Wood Pellets Imported from US (in million $) | D28: 18.348 | E28: 30.262 | F28: 44.906 | G28: 45.782 | H28: 34.745 | I28: 41.134 | J28: 41.139 | K28: 42.323 | L28: 42.118 | M28: 42.997 | N28: 46.788 | O28: 50.057676 | P28: FAOSTAT | Q28: http://www.fao.org/faostat/en/#data/FO | R28: Retrieved April 2024
O29: =+O14/30.18505982 -> 0.31605039
A30: ECONOMICS | B30: 2010 | C30: 2011 | D30: 2012 | E30: 2013 | F30: 2014 | G30: 2015 | H30: 2016 | I30: 2017 | J30: 2018 | K30: 2019 | L30: 2020 | M30: 2021 | N30: 2022 | O30: 2023 | P30: Source Name | Q30: Source URL | R30: Comments
A31: Total Jobs Created in the Wood Pellet Industry | B31: 26549 | C31: 25477 | D31: 25484 | E31: 25085 | F31: 26895 | G31: 23416 | H31: 23596 | I31: 24432 | J31: 25040 | K31: 24738 | L31: 24306 | M31: 25517 | N31: 26939 | O31: 27349 | P31: NAICS | Q31: https://data.bls.gov/cew/apps/data_views/data_views.htm#tab=Tables | R31: Retrieved January 2024

Sheet WASTE TO ENERGY
A1: WASTE TO ENERGY
A3: PHYSICAL | B3: 2010 | C3: 2011 | D3: 2012 | E3: 2013 | F3: 2014 | G3: 2015 | H3: 2016 | I3: 2017 | J3: 2018 | K3: 2019 | L3: 2020 | M3: 2021 | N3: 2022 | O3: 2023 | P3: Source Name | Q3: Source URL | R3: Comments
A4: Number of WTE Plants in the United States | B4: 86 | C4: 85 | D4: 85 | E4: 84 | F4: 84 | G4: 78 | H4: 77 | I4: 76 | J4: 75 | K4: 75 | L4: 64 | M4: 98 | N4: 60 | O4: 61 | P4: EIA | Q4: https://www.eia.gov/electricity/data/eia860m/ | R4: Retrieved February 2024
A5: Number of WTE Plants Proposed in US | B5: 2 | C5: 0 | D5: 2 | E5: 2 | F5: 1 | G5: 0 | H5: 0 | I5: 0 | J5: 0 | K5: 0 | L5: 1 | M5: 2 | N5: 2 | O5: 3 | P5: EIA | Q5: https://www.eia.gov/electricity/data/eia860m/ | R5: Retrieved February 2024
A6: Number of WTE Existing Plants that Were Put on Standby | B6: 2 | C6: 2 | D6: 2 | E6: 2 | F6: 2 | G6: 2 | H6: 1 | I6: 1 | J6: 1 | K6: 0 | L6: 2 | M6: 2 | N6: 0 | O6: 0 | P6: EIA | Q6: https://www.eia.gov/electricity/data/eia860m/ | R6: Retrieved February 2024
A7: Number of WTE Existing Plants that Were Closed-Shut Down | B7: 11 | C7: 10 | D7: 11 | E7: 13 | F7: 8 | G7: 9 | H7: 11 | I7: 11 | J7: 20 | K7: 16 | L7: 11 | M7: 13 | N7: 2 | O7: 0 | P7: EIA | Q7: https://www.eia.gov/electricity/data/eia860m/ | R7: Retrieved February 2024
A8: Number of WTE Fuel Switching Plants in US | B8: 20 | C8: 20 | D8: 16 | E8: 13 | F8: 15 | G8: 15 | H8: 15 | I8: 10 | J8: 16 | K8: 13 | L8: 14 | M8: 13 | N8: 14 | O8: 14 | P8: EIA | Q8: https://www.eia.gov/electricity/data/eia860m/ | R8: Retrieved February 2024
A9: Number of States which have an WTE Fuel Switching Production Facility | B9: 9 | C9: 9 | D9: 7 | E9: 5 | F9: 7 | G9: 7 | H9: 7 | I9: 8 | J9: 6 | K9: 6 | L9: 8 | M9: 8 | N9: 8 | O9: 8 | P9: EIA | Q9: https://www.eia.gov/electricity/data/eia860m/ | R9: Retrieved February 2024
A11: PRODUCTION | B11: 2010 | C11: 2011 | D11: 2012 | E11: 2013 | F11: 2014 | G11: 2015 | H11: 2016 | I11: 2017 | J11: 2018 | K11: 2019 | L11: 2020 | M11: 2021 | N11: 2022 | O11: 2023 | P11: Source Name | Q11: Source URL | R11: Comments
A12: Municipal solid waste generation in the United States (million metric tons) | B12: =+SUM(B13:B15) -> 251.05 | C12: =+SUM(C13:C15) -> 250.5 | D12: =+SUM(D13:D15) -> 251.84 | E12: =+SUM(E13:E15) -> 255.02 | F12: =+SUM(F13:F15) -> 258.95 | G12: =+SUM(G13:G15) -> 262.11 | H12: =+SUM(H13:H15) -> 266.78 | I12: 268.7 | J12: 292.4 | P12: EPA | Q12: [2010-2018]https://www.epa.gov/facts-and-figures-about-materials-waste-and-recycling/advancing-sustainable-materials-management | R12: Retrieved February 2024 1 ton = 0.9072 metric tons
A13: Recycled and composted | B13: =65.26+20.17 -> 85.43 | C13: 87 | D13: 86.89 | E13: 87.56 | F13: 89.57 | G13: =67.56+23.39 -> 90.95 | H13: 93.7 | I13: =67.18+26.99 -> 94.17 | J13: 93.9 | P13: EPA | Q13: [2010-2018]https://www.epa.gov/facts-and-figures-about-materials-waste-and-recycling/advancing-sustainable-materials-management | R13: Retrieved February 2024 1 ton = 0.9072 metric tons
A14: Combusted with Energy recovery | B14: 29.31 | C14: 31.8 | D14: 32.5 | E14: 33.16 | F14: 33.21 | G14: 33.55 | H14: 33.9 | I14: 34.03 | J14: 34.55 | P14: EPA | Q14: [2010-2018]https://www.epa.gov/facts-and-figures-about-materials-waste-and-recycling/advancing-sustainable-materials-management | R14: Retrieved February 2024 1 ton = 0.9072 metric tons
A15: Landfilled | B15: 136.31 | C15: 131.7 | D15: 132.45 | E15: 134.3 | F15: 136.17 | G15: 137.61 | H15: 139.18 | I15: 139.59 | J15: 146.12 | P15: EPA | Q15: [2010-2018]https://www.epa.gov/facts-and-figures-about-materials-waste-and-recycling/advancing-sustainable-materials-management | R15: Retrieved February 2024 1 ton = 0.9072 metric tons
A16: Biogenic Municipal Solid Waste: Consumption for Electricity Generation (million metric tons) | B16: 17.633246 | C16: 15.396998 | D16: 16.968 | E16: 17.007 | F16: 16.706 | G16: 16.631 | H16: 16.994 | I16: 16.348 | J16: 16.783 | K16: 15.559 | L16: 15.516 | M16: 15.223 | N16: 14.589 | O16: 13.86 | P16: EIA | Q16: http://www.eia.gov/electricity/annual/html/epa_05_07_a.html | R16: Retrieved April 2024 1 ton = 0.9072 metric tons
A17: Biogenic Municipal Solid Waste: Consumption for Heating Generation (million metric tons) | B17: 2.0747664 | C17: 1.8180288 | D17: 1.986 | E17: 1.865 | F17: 1.955 | G17: 1.986 | H17: 2.232 | I17: 2.124 | J17: 2.05 | K17: 1.667 | L17: 1.65 | M17: 1.712 | N17: 1.647 | O17: 1.543 | P17: EIA | Q17: http://www.eia.gov/electricity/annual/html/epa_05_07_b.html | R17: Retrieved April 2024 1 ton = 0.9072 metric tons
A18: Biogenic Municipal Solid Waste: Consumption for Energy Generation (million metric tons) | B18: 19.70892 | C18: 17.251315 | D18: 18.954 | E18: 18.871 | F18: 18.661 | G18: 18.617 | H18: 19.226 | I18: 18.473 | J18: 18.833 | K18: 17.225 | L18: 17.166 | M18: 16.934 | N18: 16.236 | O18: 15.403 | P18: EIA | Q18: http://www.eia.gov/electricity/annual/html/epa_05_07_c.html | R18: Retrieved April 2024 1 ton = 0.9072 metric tons
A19: Electric utilities | B19: 0.3646944 | C19: 0.3519936 | D19: 0.418 | E19: 0.456 | F19: 0.444 | G19: 0.452 | H19: 0.464 | I19: 0.422 | J19: 0.467 | K19: 0.297 | L19: 0.28 | M19: 0.252 | N19: 0.274 | O19: 0.283 | P19: EIA | Q19: http://www.eia.gov/electricity/annual/html/epa_05_07_c.html | R19: Retrieved April 2024 1 ton = 0.9072 metric tons
A20: Independent power producers | B20: 15.985771 | C20: 13.940942 | D20: 14.757 | E20: 14.574 | F20: 14.459 | G20: 14.452 | H20: 14.838 | I20: 14.195 | J20: 14.611 | K20: 13.684 | L20: 13.732 | M20: 13.315 | N20: 7.747 | O20: 7.39 | P20: EIA | Q20: http://www.eia.gov/electricity/annual/html/epa_05_07_c.html | R20: Retrieved April 2024 1 ton = 0.9072 metric tons
A21: Commercial sector | B21: 3.2196528 | C21: 2.8150416 | D21: 3.577 | E21: 3.646 | F21: 3.551 | G21: 3.502 | H21: 3.7 | I21: 3.639 | J21: 3.557 | K21: 3.047 | L21: 2.956 | M21: 3.187 | N21: 8.215 | O21: 7.73 | P21: EIA | Q21: http://www.eia.gov/electricity/annual/html/epa_05_07_c.html | R21: Retrieved April 2024 1 ton = 0.9072 metric tons
A22: Industrial Sector | B22: 0.1378944 | C22: 0.1433376 | D22: 0.203 | E22: 0.195 | F22: 0.206 | G22: 0.211 | H22: 0.224 | I22: 0.216 | J22: 0.197 | K22: 0.197 | L22: 0.198 | M22: 0.18 | N22: 0 | O22: 0 | P22: EIA | Q22: http://www.eia.gov/electricity/annual/html/epa_05_07_c.html | R22: Retrieved April 2024 1 ton = 0.9072 metric tons
A23: Biogenic Municipal Solid Waste: Consumption for Electricity Generation (Trillion BTUs) | B23: 144.934 | C23: 135.241 | D23: 135.735 | E23: 135.764 | F23: 134.408 | G23: 133.117 | H23: 135.957 | I23: 130.942 | J23: 134.465 | K23: 115.114 | L23: 114.814 | M23: 113.173 | N23: 108.508 | O23: 103.306 | P23: EIA | Q23: http://www.eia.gov/electricity/annual/html/epa_05_07_d.html | R23: Retrieved February 2024
A24: Biogenic Municipal Solid Waste: Consumption for Heating Generation (Trillion BTUs) | B24: 17.502 | C24: 16.766 | D24: 16.31 | E24: 15.168 | F24: 15.783 | G24: 16.623 | H24: 18.259 | I24: 17.72 | J24: 16.724 | K24: 12.308 | L24: 11.939 | M24: 12.721 | N24: 12.244 | O24: 12.535 | P24: EIA | Q24: http://www.eia.gov/electricity/annual/html/epa_05_07_e.html | R24: Retrieved February 2024
A25: Biogenic Municipal Solid Waste: Consumption for Energy Generation (Trillion BTUs) | B25: 162.436 | D25: 152.045 | E25: 150.932 | F25: 150.191 | G25: 149.74 | H25: 154.216 | I25: 148.662 | J25: 151.188 | K25: 127.422 | L25: 126.752 | M25: 125.894 | N25: 120.753 | O25: 115.841 | P25: EIA | Q25: http://www.eia.gov/electricity/annual/html/epa_05_07_f.html | R25: Retrieved February 2024
A26: Electric utilities | B26: 3.322 | C26: 3.433 | D26: 3.91 | E26: 4.459 | F26: 4.429 | G26: 4.295 | H26: 4.434 | I26: 4.172 | J26: 4.568 | K26: 2.454 | L26: 2.284 | M26: 2.029 | N26: 2.212 | O26: 2.275 | P26: EIA | Q26: http://www.eia.gov/electricity/annual/html/epa_05_07_f.html | R26: Retrieved February 2024
A27: Independent power producers | B27: 130.467 | C27: 121.648 | D27: 117.598 | E27: 115.574 | F27: 115.709 | G27: 114.886 | H27: 17.88 | I27: 112.857 | J27: 116.339 | K27: 101 | L27: 101.362 | M27: 98.516 | N27: 57.217 | O27: 54.557 | P27: EIA | Q27: http://www.eia.gov/electricity/annual/html/epa_05_07_f.html | R27: Retrieved February 2024
A28: Commercial sector | B28: 27.509 | C28: 25.664 | D28: 28.923 | E28: 29.342 | F28: 28.411 | G28: 28.821 | H28: 30.095 | I28: 29.794 | J28: 28.686 | K28: 22.473 | L28: 21.629 | M28: 23.994 | N28: 61.324 | O28: 59.009 | P28: EIA | Q28: http://www.eia.gov/electricity/annual/html/epa_05_07_f.html | R28: Retrieved February 2024
A29: Industrial Sector | B29: 1.138 | C29: 1.262 | D29: 1.614 | E29: 1.557 | F29: 1.643 | G29: 1.739 | H29: 1.806 | I29: 1.839 | J29: 1.596 | K29: 1.495 | L29: 1.478 | M29: 1.355 | N29: 0 | O29: 0 | P29: EIA | Q29: http://www.eia.gov/electricity/annual/html/epa_05_07_f.html | R29: Retrieved February 2024
A31: ECONOMICS | B31: 2010 | C31: 2011 | D31: 2012 | E31: 2013 | F31: 2014 | G31: 2015 | H31: 2016 | I31: 2017 | J31: 2018 | K31: 2019 | L31: 2020 | M31: 2021 | N31: 2022 | O31: 2023 | P31: Source Name | Q31: Source URL | R31: Comments
A32: Revenue from waste electricity generation in the U.S. (million dollars) | C32: 640 | D32: 290 | E32: 550 | F32: 348 | G32: 524 | H32: 227 | I32: 142 | J32: 54 | K32: 57 | L32: 54 | M32: 55 | N32: 55 | P32: AEE | Q32: https://info.aee.net/hubfs/Market%20Report%202019/AEN%202019%20Market%20Report.pdf | R32: Retrieved February 2024
A33: Jobs in WTE Facilities | E33: 5350 | F33: 4753 | H33: 4640 | J33: 4600 | K33: 7000 | P33: ERC | Q33: [domain expired]http://energyrecoverycouncil.org/wp-content/uploads/2019/10/ERC-2018-directory.pdf | R33: Retrieved February 2024
A34: Total jobs (direct, indirect, and induced) created by WTE | E34: =+E33+8557 -> 13907 | F34: 13878 | H34: 13756 | J34: 13601 | P34: ERC | Q34: [domain expired]http://energyrecoverycouncil.org/wp-content/uploads/2019/10/ERC-2018-directory.pdf | R34: Retrieved February 2024
A35: Total Economic output by WTE (million dollars) | E35: 5600 | F35: 5561 | H35: 5576.2 | J35: 5567 | P35: ERC | Q35: [domain expired]http://energyrecoverycouncil.org/wp-content/uploads/2019/10/ERC-2018-directory.pdf | R35: Retrieved February 2024

Sheet BIOGAS
A1: BIOGAS
A3: PHYSICAL | B3: 2010 | C3: 2011 | D3: 2012 | E3: 2013 | F3: 2014 | G3: 2015 | H3: 2016 | I3: 2017 | J3: 2018 | K3: 2019 | L3: 2020 | M3: 2021 | N3: 2022 | O3: 2023 | P3: Source Name | Q3: Source URL | R3: Comments
A4: Number of anaerobic digestion (AD) Plants | B4: 133 | C4: 158 | D4: 183 | E4: 209 | F4: 218 | G4: 225 | H4: 229 | I4: 234 | J4: 245 | K4: 257 | L4: 282 | M4: 341 | N4: 400 | O4: 429 | P4: EPA | Q4: https://www.epa.gov/agstar/livestock-anaerobic-digester-database | R4: Retrieved February 2024
A5: Used for Electricity | B5: 25 | C5: 38 | D5: 50 | E5: 61 | F5: 64 | G5: 65 | H5: 68 | I5: 71 | J5: 75 | K5: 95 | L5: 97 | M5: 101 | N5: 100 | O5: 100 | P5: EPA | Q5: https://www.epa.gov/agstar/livestock-anaerobic-digester-database | R5: Retrieved February 2024
A6: Used for Boiler/Furnace | B6: 14 | C6: 14 | D6: 14 | E6: 14 | F6: 14 | G6: 14 | H6: 14 | I6: 14 | J6: 14 | K6: 11 | L6: 29 | M6: 29 | N6: 15 | O6: 15 | P6: EPA | Q6: https://www.epa.gov/agstar/livestock-anaerobic-digester-database | R6: Retrieved February 2024
A7: Used for "Flare Full Time" | B7: 13 | C7: 13 | D7: 13 | E7: 13 | F7: 13 | G7: 13 | H7: 13 | I7: 13 | J7: 13 | K7: 11 | L7: 10 | M7: 10 | N7: 12 | O7: 12 | P7: EPA | Q7: https://www.epa.gov/agstar/livestock-anaerobic-digester-database | R7: Retrieved February 2024
A8: Used for Cogeneration | B8: 81 | C8: 93 | D8: 106 | E8: 121 | F8: 127 | G8: 133 | H8: 134 | I8: 136 | J8: 143 | K8: 107 | L8: 119 | M8: 119 | N8: 101 | O8: 101 | P8: EPA | Q8: https://www.epa.gov/agstar/livestock-anaerobic-digester-database | R8: Retrieved February 2024
A9: Number of Existing AD Plants Under Construction | B9: 0 | C9: 1 | D9: 4 | E9: 1 | F9: 0 | G9: 0 | H9: 0 | I9: 1 | J9: 3 | K9: 6 | L9: 7 | M9: 15 | N9: 24 | O9: 29 | P9: EPA | Q9: https://www.epa.gov/agstar/livestock-anaerobic-digester-database | R9: Retrieved February 2024
A10: Number of New AD Plants that Went online from livestock | B10: 19 | C10: 25 | D10: 25 | E10: 26 | F10: 9 | G10: 7 | H10: 4 | I10: 5 | J10: 11 | K10: 14 | L10: 18 | M10: 44 | N10: 24 | O10: 1 | P10: EPA | Q10: https://www.epa.gov/agstar/livestock-anaerobic-digester-database | R10: Retrieved February 2024
A11: Number of AD Plants that Shut Down | B11: 3 | C11: 8 | D11: 1 | E11: 3 | F11: 5 | G11: 4 | H11: 9 | I11: 4 | J11: 2 | K11: 3 | L11: 1 | N11: 2 | P11: EPA | Q11: https://www.epa.gov/agstar/livestock-anaerobic-digester-database | R11: Retrieved February 2024
A12: Number of States which have an AD Production Facility | B12: 29 | C12: 34 | D12: 35 | E12: 36 | F12: 36 | G12: 36 | H12: 36 | I12: 36 | J12: 36 | K12: 36 | L12: 35 | M12: 35 | N12: 34 | O12: 35 | P12: EPA | Q12: https://www.epa.gov/agstar/livestock-anaerobic-digester-database | R12: Retrieved February 2024
A13: Number of landfill Plants | B13: 359 | C13: 394 | D13: 425 | E13: 451 | F13: 474 | G13: 483 | H13: 490 | I13: 497 | J13: 514 | K13: 565 | L13: 545 | M13: 549 | N13: 516 | O13: 535 | P13: EPA | Q13: [2010-2019] https://www.epa.gov/lmop/landfill-technical-data [2020-2021] https://www.epa.gov/lmop/landfill-gas-energy-project-data | R13: Retrieved February 2024
A14: Number of States which have a landfill Facility | B14: 46 | C14: 46 | D14: 48 | E14: 48 | F14: 49 | G14: 49 | H14: 49 | I14: 49 | J14: 49 | K14: 49 | L14: 49 | M14: 49 | N14: 49 | O14: 45 | P14: EPA | Q14: [2010-2019] https://www.epa.gov/lmop/landfill-technical-data [2020-2021] https://www.epa.gov/lmop/landfill-gas-energy-project-data | R14: Retrieved February 2024
A16: PRODUCTION | B16: 2010 | C16: 2011 | D16: 2012 | E16: 2013 | F16: 2014 | G16: 2015 | H16: 2016 | I16: 2017 | J16: 2018 | K16: 2019 | L16: 2020 | M16: 2021 | N16: 2022 | O16: 2023 | P16: Source Name | Q16: Source URL | R16: Comments
A17: Biogas potential from landfills (billion cubic feet) | J17: 125.12775 | L17: 344.75903 | M17: 346.13106 | N17: 434.8368 | O17: 435.8735 | P17: EPA | Q17: https://www.epa.gov/lmop/landfill-gas-energy-project-data | R17: Retrieved February 2024
A18: Biogas potential from wastewater (billion cubic feet) | J18: 132 | L18: 147 | O18: 147.08 | P18: American biogas Council | Q18: [2018] https://americanbiogascouncil.org/biogas-market-snapshot/ [2020] https://americanbiogascouncil.org/resources/state-profiles/ | R18: Retrieved February 2024
A19: Biogas potential from animal manure (billion cubic feet) | J19: 1124 | L19: 1157 | O19: 1277.889 | P19: American biogas Council | Q19: [2018] https://americanbiogascouncil.org/biogas-market-snapshot/ [2020] https://americanbiogascouncil.org/resources/state-profiles/ | R19: Retrieved February 2024
A20: Anaerobic digestion: Biogas generated (trillion BTU) | B20: 0.94784545 | C20: 1.3818346 | D20: 1.6778589 | E20: 2.084233 | F20: 2.1646239 | G20: 2.1646239 | H20: 2.1866801 | I20: 2.1870213 | J20: 2.3303905 | K20: 2.3785148 | L20: 2.4109288 | M20: 2.4109288 | N20: 2.4109288 | O20: 2.4109288 | P20: EPA | Q20: https://www.epa.gov/agstar/livestock-anaerobic-digester-database | R20: Retrieved February 2024 1 kwh = 3412 BTUs
A21: Anaerobic digestion: Biogas generated (billion cubic feet) | B21: 5.3880716 | C21: 5.5375621 | D21: 5.9042283 | E21: 7.1320504 | F21: 7.1768724 | G21: 7.8956304 | H21: 7.8956304 | I21: 7.8956304 | J21: 9.7217619 | K21: 10.652238 | L21: 12.763316 | M21: 17.167976 | N21: 18.214614 | O21: 18.251769 | P21: EPA | Q21: https://www.epa.gov/agstar/livestock-anaerobic-digester-database | R21: Retrieved February 2024
A22: Anaerobic digestion: Total Methane Emission Reductions (million metric tons of CO2) | B22: 1.8173376 | C22: 2.3786015 | D22: 3.02899 | E22: 3.5291747 | F22: 3.7230252 | G22: 3.8045922 | H22: 4.0303677 | I22: 4.2102567 | J22: 4.9356798 | K22: 5.7714269 | L22: 7.404395 | M22: 9.7669786 | N22: 10.486236 | O22: 10.504499 | P22: EPA | Q22: https://www.epa.gov/agstar/livestock-anaerobic-digester-database | R22: Retrieved February 2024
A23: Agriculture: total methane emissions (million metric tons of CO2) | B23: 271.1 | C23: 264.86 | D23: 264.39 | E23: 259.24 | F23: 258.46 | G23: 266.56 | H23: 274.03 | I23: 277.5 | J23: 281.21 | K23: 280.37 | L23: 281.02 | M23: 278.23 | N23: 274.3 | P23: EPA | Q23: https://www3.epa.gov/climatechange/ghgemissions/inventoryexplorer/index.html#iallsectors/methane/inventsect/all | R23: Retrieved February 2024
A24: Landfill gas: energy consumption (trillion BTU) | B24: 106.681 | C24: 114.173 | D24: 125.927 | E24: 133.18 | F24: 141.632 | G24: 138.841 | H24: 137.6 | I24: 139.831 | J24: 135.921 | K24: 129.5 | L24: 126.872 | M24: 116.049 | N24: 105.993 | O24: 97.56 | P24: EIA | Q24: https://www.eia.gov/electricity/annual/html/epa_05_06_f.html | R24: Retrieved February 2024
A25: Landfill gas: energy consumption (billion cubic feet) | B25: 219.954 | C25: 235.99 | D25: 259.564 | E25: 272.798 | F25: 287.692 | G25: 284.052 | H25: 277.72 | I25: 282.051 | J25: 273.856 | K25: 261.064 | L25: 256.512 | M25: 235.906 | N25: 216.146 | O25: 197.712 | P25: EIA | Q25: https://www.eia.gov/electricity/annual/html/epa_05_06_c.html | R25: Retrieved February 2024
A26: Landfill gas: Total Methane Emission Reductions (million metric tons of CO2) | B26: 64.16877 | C26: 71.99401 | D26: 80.27265 | E26: 89.39436 | F26: 96.57712 | G26: 99.47028 | H26: 105.34576 | I26: 108.25581 | J26: 115.48526 | K26: 90.05205 | L26: 93.5948 | M26: 94.3788 | N26: 94.8533 | O26: 95.1357 | P26: EPA | Q26: https://www.epa.gov/lmop/landfill-technical-data | R26: Retrieved February 2024
A27: Waste: total methane emissions (million metric tons of CO2) | B27: 163.1 | C27: 153.87 | D27: 155.63 | E27: 151.69 | F27: 151.39 | G27: 150.22 | H27: 146.27 | I27: 147.9 | J27: 150.23 | K27: 152.36 | L27: 147.6 | M27: 145.28 | N27: 143.17 | P27: EPA | Q27: https://www3.epa.gov/climatechange/ghgemissions/inventoryexplorer/index.html#iallsectors/methane/inventsect/all | R27: Retrieved April 2024
A29: ECONOMICS IN THEORY | B29: 2010 | C29: 2011 | D29: 2012 | E29: 2013 | F29: 2014 | G29: 2015 | H29: 2016 | I29: 2107 | J29: 2018 | K29: 2019 | L29: 2020 | M29: 2021 | N29: 2022 | O29: 2023 | P29: Source Name | Q29: Source URL | R29: Comments
A30: In theory, if 11,000 biogas systems made it would generate: | P30: EPA
A31: Short Term Construction Jobs | F31: 275000 | L31: 372870 | P31: EPA | Q31: [2014] https://19january2017snapshot.epa.gov/sites/production/files/2015-12/documents/biogas-roadmap.pdf [2020] https://americanbiogascouncil.org/resources/state-profiles/ | R31: Retrieved February 2024
A32: Permanent Jobs | F32: 18000 | L32: 24826 | P32: EPA | Q32: [2014] https://19january2017snapshot.epa.gov/sites/production/files/2015-12/documents/biogas-roadmap.pdf [2020] https://americanbiogascouncil.org/resources/state-profiles/ | R32: Retrieved February 2024
A33: In theory, if 2,647 dairy operations were installed it would have a market potential of (billion dollars): | F33: 2.9 | P33: EPA | Q33: https://19january2017snapshot.epa.gov/sites/production/files/2015-12/documents/biogas-roadmap.pdf | R33: Retrieved February 2024
A35: Renewable Natural Gas | B35: 2010 | C35: 2011 | D35: 2012 | E35: 2013 | F35: 2014 | G35: 2015 | H35: 2016 | I35: 2017 | J35: 2018 | K35: 2019 | L35: 2020 | M35: 2021 | N35: 2022 | O35: 2023 | P35: Source Name | Q35: Source URL | R35: Comments
A36: Ag RNG projects | B36: 7 | C36: 5 | D36: 6 | E36: 6 | F36: 5 | G36: 6 | H36: 5 | I36: 7 | J36: 14 | K36: 29 | L36: 53 | M36: 97 | N36: 109 | O36: 135 | P36: EPA | Q36: https://www.epa.gov/lmop/renewable-natural-gas | R36: Retriaved May 8 2023
A37: Landfill RNG projects | B37: 30 | C37: 32 | D37: 33 | E37: 38 | F37: 39 | G37: 41 | H37: 41 | I37: 45 | J37: 58 | K37: 63 | L37: 70 | M37: 76 | N37: 82 | O37: 102 | P37: EPA | Q37: https://www.epa.gov/lmop/renewable-natural-gas | R37: Retriaved May 8 2024

Sheet TRADE
A1: 2023 Top Exports | M1: 2022 Top Exports | Y1: 2021 Top Exports
A2: Ethanol | B2: million gallons | D2: Biodiesel | E2: million gallons | G2: Wood Pellets | H2: million metric tons | J2: Poultry Fat | K2: metric tons | M2: Ethanol | N2: million gallons | P2: Biodiesel | Q2: million gallons | S2: Wood Pellets | T2: million metric tons | V2: Poultry Fat | W2: metric tons | Y2: Ethanol | Z2: million gallons | AB2: Biodiesel | AC2: million gallons | AE2: Wood Pellets | AF2: million metric tons | AH2: Poultry Fat | AI2: metric tons
A3: Canada | B3: 625.632 | D3: Canada | E3: 230.664 | G3: United Kingdom | H3: 5.287793 | J3: Canada | K3: 6477 | M3: Canada | N3: 501.815 | P3: Canada | Q3: 190.553 | S3: United Kingdom | T3: 5.287589 | V3: Canada | W3: 5418 | Y3: Canada | Z3: 374.766 | AB3: Canada | AC3: 141.792 | AE3: United Kingdom | AF3: 5.404957 | AH3: Canada | AI3: 5525
A4: United Kingdom | B4: 160.062 | D4: Peru | E4: 26.628 | G4: Netherlands | H4: 1.4244955 | J4: Guatemala | K4: 4957 | M4: Brazil | N4: 60.731 | P4: Netherlands | Q4: 7.265 | S4: Netherlands | T4: 1.756709 | V4: Peru | W4: 4308 | Y4: South Korea | Z4: 150.864 | AB4: Peru | AC4: 27.342 | AE4: Netherlands | AF4: 1.1673211 | AH4: Peru | AI4: 4016
A5: Netherlands | B5: 114.324 | D5: Germany | E5: 0.714 | G5: Japan | H5: 1.3936382 | J5: Mexico | K5: 3048 | M5: India | N5: 72.869 | P5: Peru | Q5: 36.749 | S5: Japan | T5: 0.64670067 | V5: Guatemala | W5: 3600 | Y5: India | Z5: 149.184 | AB5: Netherlands | AC5: 8.358 | AE5: Denmark | AF5: 0.44624637 | AH5: Guatemala | AI5: 3773
A6: Korea | B6: 99.456 | E6: =+E3+E4+E5 -> 258.006 | G6: Denmark | H6: 1.3936382 | J6: Dominican Republic | K6: 1232 | M6: South Korea | N6: 153.845 | P6: Norway | Q6: 1.931 | S6: Denmark | T6: 0.5611442 | V6: Mexico | W6: 1461 | Y6: China | Z6: 100.338 | AB6: Singapore | AC6: 7.098 | AE6: France | AF6: 0.24152277 | AH6: Mexico | AI6: 1718
A7: India | B7: 83.874 | G7: France | H7: 0.32424067 | J7: Indonesia | K7: 1171 | M7: Netherlands | N7: 94.163 | P7: Germany | Q7: 1.133 | S7: Belgium | T7: 0.42933387 | V7: Dominican Republic | W7: 1068 | Y7: Brazil | Z7: 69.552 | AB7: Mexico | AC7: 1.554 | AE7: Belgium | AF7: 0.2212456 | AH7: Chile | AI7: 587
H8: =+H4+H3+H5+H6+H7 -> 9.8238056 | M8: Mexico | N8: 63.293
M9: Singapore | N9: 43.679
M10: United Kingdom | N10: 66.821
A12: Inedible tallow | B12: metric tons | D12: Edible tallow | E12: metric tons | G12: Yellow grease | H12: metric tons | J12: White grease | K12: metric tons | M12: Inedible tallow | N12: metric tons | P12: Edible tallow | Q12: metric tons | S12: Yellow grease | T12: metric tons | V12: White grease | W12: metric tons | Y12: Inedible tallow | Z12: metric tons | AB12: Edible tallow | AC12: metric tons | AE12: Yellow grease | AF12: metric tons | AH12: White grease | AI12: metric tons
A13: Canada | B13: 45420 | D13: Mexico | E13: 43177 | G13: Singapore | H13: 78264 | J13: Mexico | K13: 107 | M13: Canada | N13: 111420 | P13: Mexico | Q13: 64808 | S13: Singapore | T13: 276041 | V13: Canada | W13: 102 | Y13: Mexico | Z13: 97086 | AB13: Mexico | AC13: 108885 | AE13: Singapore | AF13: 501047 | AH13: Ghana | AI13: 77
A14: Mexico | B14: 38946 | D14: Canada | E14: 1504 | G14: Mexico | H14: 62095 | M14: Mexico | N14: 50498 | P14: Canada | Q14: 3228 | S14: United Kingdom | T14: 25971 | V14: Mexico | W14: 26469 | Y14: Canada | Z14: 60869 | AB14: Honduras | AC14: 1675 | AE14: United Kingdom | AF14: 93990 | AH14: Japan | AI14: 15
A15: Singapore | B15: 21950 | D15: China | E15: 1001 | G15: Canada | H15: 24459 | J15: Tallow | K15: metric tons | M15: Singapore | N15: 48587 | S15: *EU27 | T15: 31177 | Y15: Honduras | Z15: 11650 | AB15: Guatemala | AC15: 1500 | AE15: Mexico | AF15: 92240 | AH15: Mexico | AI15: 12
A16: Trinidad and Tabago | B16: 1977 | G16: Ecuador | H16: 4931 | J16: Mexico | K16: =+B14+E13 -> 82123 | M16: Guatemala | N16: 3000 | S16: Mexico | T16: 96212 | Y16: Brazil | Z16: 3000 | AB16: Canada | AC16: 1344 | AE16: *EU27 | AF16: 36942
A17: Honduras | B17: 60 | G17: Dominican Republic | H17: 4370 | J17: Canada | K17: =+E14+B13 -> 46924 | S17: Dominican Republic | T17: 9833 | Y17: Guatemala | Z17: 3800 | AE17: Dominican Republic | AF17: 11309
J18: Singapore | K18: =+B15 -> 21950 | S18: Canada | T18: 25335 | Y18: Morocco | Z18: 7500 | AE18: Canada | AF18: 9417
J19: Trinidad and Tabago | K19: 1977 | S19: *EU27 =the 27 European Union countries after the UK left the EU, So EU28 = 76,665 + 77,345 | Y19: Colombia | Z19: 2400 | AE19: *EU27 =the 27 European Union countries after the UK left the EU, So EU28 = 76,665 + 77,345
J20: China | K20: 1001
A21: 2023 Top Imports | M21: 2022 Top Imports | Y21: 2021 Top Imports
A22: Ethanol | B22: million gallons | D22: Biodiesel | E22: million gallons | G22: Wood Pellets | H22: Thousand metric tons | M22: Ethanol | N22: million gallons | P22: Biodiesel | Q22: million gallons | S22: Wood Pellets | T22: Thousand metric tons | Y22: Ethanol | Z22: million gallons | AB22: Biodiesel | AC22: million gallons | AE22: Wood Pellets | AF22: Thousand metric tons
A23: Brazil | B23: 27.258 | D23: Canada | E23: 140.07 | G23: Canada | H23: 176.51179 | M23: Brazil | N23: 68.795 | P23: Canada | Q23: 123.353 | S23: Canada | T23: 194.09566 | Y23: Brazil | Z23: 60.774 | AB23: Canada | AC23: 129.15 | AE23: Canada | AF23: 28.560177
D24: Germany | E24: 174.72 | G24: Japan | H24: 0.150213 | M24: Canada | N24: 0.293 | P24: Germany | Q24: 76.859 | S24: Japan | T24: 0.10447 | AB24: Germany | AC24: 27.174 | AE24: Viet Nam | AF24: 0.456887
D25: South Korea | E25: 33.054 | G25: Ukraine | H25: 0.062274 | P25: Spain | Q25: 20.579 | S25: China | T25: 0.050596 | AB25: Spain | AC25: 26.88 | AE25: Japan | AF25: 27.003
D26: Italy | E26: 44.73 | G26: China | H26: 0.048161 | P26: South Korea | Q26: 12.515 | S26: Ukraine | T26: 0.037325 | AB26: South Korea | AC26: 23.646 | AE26: Germany | AF26: 1.312694
D27: Spain | E27: 84.462 | G27: Thailand | H27: 0.028172 | P27: Italy | Q27: 12.431 | S27: Malaysia | T27: 0.035948 | AB27: Italy | AC27: 3.36 | AE27: Ukraine | AF27: 0.072214
P28: Belgium | Q28: 4.157
A31: Origin | B31: Destination | C31: Commodity | D31: Value | E31: Units | F31: Variable | G31: %
A32: United States | B32: Canada | C32: Ethanol | D32: 625.632 | E32: million gallons | F32: Export | G32: =+D32/(ETHANOL!$O$22*1000) -> 0.43644887
A33: United States | B33: United Kingdom | C33: Ethanol | D33: 160.062 | E33: million gallons | F33: Export | G33: =+D33/(ETHANOL!$O$22*1000) -> 0.1116613
A34: United States | B34: Netherlands | C34: Ethanol | D34: 114.324 | E34: million gallons | F34: Export | G34: =+D34/(ETHANOL!$O$22*1000) -> 0.079753882
A35: United States | B35: Korea | C35: Ethanol | D35: 99.456 | E35: million gallons | F35: Export | G35: =+D35/(ETHANOL!$O$22*1000) -> 0.069381776
A36: United States | B36: India | C36: Ethanol | D36: 83.874 | E36: million gallons | F36: Export | G36: =+D36/(ETHANOL!$O$22*1000) -> 0.058511573
A37: Brazil | B37: United States | C37: Ethanol | D37: 27 | E37: million gallons | F37: Import | G37: =+D37/(ETHANOL!$O$21*1000) -> 0.99053489
A38: United States | B38: Canada | C38: Biodiesel | D38: 230.664 | E38: million gallons | F38: Export | G38: =D38/$E$6 -> 0.89402572
A39: United States | B39: Peru | C39: Biodiesel | D39: 26.628 | E39: million gallons | F39: Export | G39: =D39/$E$6 -> 0.1032069
A40: United States | B40: Germany | C40: Biodiesel | D40: 0.714 | E40: million gallons | F40: Export | G40: =D40/$E$6 -> 0.0027673775
A41: Canada | B41: United States | C41: Biodiesel | D41: 140.07 | E41: million gallons | F41: Import | G41: =D41/BIODIESEL!$O$13 -> 0.27957079
A42: Germany | B42: United States | C42: Biodiesel | D42: 174.72 | E42: million gallons | F42: Import | G42: =D42/BIODIESEL!$O$13 -> 0.34872999
A43: South Korea | B43: United States | C43: Biodiesel | D43: 33.054 | E43: million gallons | F43: Import | G43: =D43/BIODIESEL!$O$13 -> 0.065973678
A44: Italy | B44: United States | C44: Biodiesel | D44: 44.73 | E44: million gallons | F44: Import | G44: =D44/BIODIESEL!$O$13 -> 0.08927823
A45: Spain | B45: United States | C45: Biodiesel | D45: 84.462 | E45: million gallons | F45: Import | G45: =D45/BIODIESEL!$O$13 -> 0.16858077
A46: United States | B46: United Kingdom | C46: Wood Pellets | D46: 5.287793 | E46: million metric tons | F46: Export | G46: =D46/$H$8 -> 0.53826319
A47: United States | B47: Netherlands | C47: Wood Pellets | D47: 1.4244955 | E47: million metric tons | F47: Export | G47: =D47/$H$8 -> 0.14500445
A48: United States | B48: Japan | C48: Wood Pellets | D48: 1.3936382 | E48: million metric tons | F48: Export | G48: =D48/$H$8 -> 0.14186338
A49: United States | B49: Denmark | C49: Wood Pellets | D49: 1.3936382 | E49: million metric tons | F49: Export | G49: =D49/$H$8 -> 0.14186338
A50: United States | B50: France | C50: Wood Pellets | D50: 0.32424067 | E50: million metric tons | F50: Export | G50: =D50/$H$8 -> 0.033005607
A51: Canada | B51: United States | C51: Wood Pellets | D51: 0.17651179 | E51: million metric tons | F51: Import | G51: =D51/'WOOD PELLETS'!$O$13 -> 0.99796204
A52: Japan | B52: United States | C52: Wood Pellets | D52: 0.000150213 | E52: million metric tons | F52: Import | G52: =D52/'WOOD PELLETS'!$O$13 -> 0.000849274
A53: Ukraine | B53: United States | C53: Wood Pellets | D53: 6.2274e-05 | E53: million metric tons | F53: Import | G53: =D53/'WOOD PELLETS'!$O$13 -> 0.00035208463
A54: China | B54: United States | C54: Wood Pellets | D54: 4.8161e-05 | E54: million metric tons | F54: Import | G54: =D54/'WOOD PELLETS'!$O$13 -> 0.00027229258
A55: Thailand | B55: United States | C55: Wood Pellets | D55: 2.8172e-05 | E55: million metric tons | F55: Import | G55: =D55/'WOOD PELLETS'!$O$13 -> 0.0001592788
A56: United States | B56: Canada | C56: Poultry Fat | D56: 6477 | E56: metric tons | F56: Export | G56: =D56/(FATS!$P$24*1000) -> 0.33734375
A57: United States | B57: Guatemala | C57: Poultry Fat | D57: 4957 | E57: metric tons | F57: Export | G57: =D57/(FATS!$P$24*1000) -> 0.25817708
A58: United States | B58: Mexico | C58: Poultry Fat | D58: 3048 | E58: metric tons | F58: Export | G58: =D58/(FATS!$P$24*1000) -> 0.15875
A59: United States | B59: Dominican Republic | C59: Poultry Fat | D59: 1232 | E59: metric tons | F59: Export | G59: =D59/(FATS!$P$24*1000) -> 0.064166667
A60: United States | B60: Indonesia | C60: Poultry Fat | D60: 1171 | E60: metric tons | F60: Export | G60: =D60/(FATS!$P$24*1000) -> 0.060989583
A61: United States | B61: Canada | C61: Inedible tallow | D61: 45420 | E61: metric tons | F61: Export
A62: United States | B62: Mexico | C62: Inedible tallow | D62: 38946 | E62: metric tons | F62: Export
A63: United States | B63: Singapore | C63: Inedible tallow | D63: 21950 | E63: metric tons | F63: Export
A64: United States | B64: Trinidad and Tabago | C64: Inedible tallow | D64: 1977 | E64: metric tons | F64: Export
A65: United States | B65: Honduras | C65: Inedible tallow | D65: 60 | E65: metric tons | F65: Export
A66: United States | B66: Mexico | C66: Edible tallow | D66: 43177 | E66: metric tons | F66: Export
A67: United States | B67: Canada | C67: Edible tallow | D67: 1504 | E67: metric tons | F67: Export
A68: United States | B68: China | C68: Edible tallow | D68: 1001 | E68: metric tons | F68: Export
A69: United States | B69: Singapore | C69: Yellow grease | D69: 78264 | E69: metric tons | F69: Export | G69: =D69/(FATS!$P$27*1000) -> 0.40677755
A70: United States | B70: Mexico | C70: Yellow grease | D70: 62095 | E70: metric tons | F70: Export | G70: =D70/(FATS!$P$27*1000) -> 0.32273909
A71: United States | B71: Canada | C71: Yellow grease | D71: 24459 | E71: metric tons | F71: Export | G71: =D71/(FATS!$P$27*1000) -> 0.12712578
A72: United States | B72: Ecuador | C72: Yellow grease | D72: 4931 | E72: metric tons | F72: Export | G72: =D72/(FATS!$P$27*1000) -> 0.025628898
A73: United States | B73: Dominican Republic | C73: Yellow grease | D73: 4370 | E73: metric tons | F73: Export | G73: =D73/(FATS!$P$27*1000) -> 0.022713098
A74: United States | B74: Mexico | C74: White grease | D74: 107 | E74: metric tons | F74: Export | G74: =D74/(FATS!$P$26*1000) -> 1
A75: United States | B75: Mexico | C75: Tallow | D75: 82123 | E75: metric tons | F75: Export | G75: =D75/(FATS!$P$25*1000) -> 0.53292018
A76: United States | B76: Canada | C76: Tallow | D76: 46924 | E76: metric tons | F76: Export | G76: =D76/(FATS!$P$25*1000) -> 0.30450357
A77: United States | B77: Singapore | C77: Tallow | D77: 21950 | E77: metric tons | F77: Export | G77: =D77/(FATS!$P$25*1000) -> 0.14243997
A78: United States | B78: Trinidad and Tabago | C78: Tallow | D78: 1977 | E78: metric tons | F78: Export | G78: =D78/(FATS!$P$25*1000) -> 0.012829332
A79: United States | B79: China | C79: Tallow | D79: 1001 | E79: metric tons | F79: Export | G79: =D79/(FATS!$P$25*1000) -> 0.006495782

Sheet BIOPRODUCTS
A1: BIOPRODUCTS SUMMARY
A3: USDA BIOPREFFERED PROGRAM | B3: 2008 | C3: 2009 | D3: 2010 | E3: 2011 | F3: 2012 | G3: 2013 | H3: 2014 | I3: 2015 | J3: 2016 | K3: 2017 | L3: 2018 | M3: 2019 | N3: 2020 | O3: 2021 | P3: 2022 | Q3: 2023 | R3: Source Name | S3: Source URL | T3: Comments
A4: USDA BioPreferred product certifications | K4: 1297 | L4: 1550 | M4: 2216 | N4: =M4+658 -> 2874 | O4: =N4+1357 -> 4231 | P4: 8424 | Q4: 9092 | R4: USDA | S4: https://www.biopreferred.gov/BioPreferred/faces/catalog/Catalog.xhtml | T4: Retrieved April 2024
A5: Baby and Kids | K5: 53 | L5: 46 | M5: 58 | N5: 52 | P5: 238 | Q5: =35+18+42+10+12+17+27+41+9+9+6+51 -> 277 | R5: USDA | S5: https://www.biopreferred.gov/BioPreferred/faces/catalog/Catalog.xhtml | T5: Retrieved April 2024
A6: Construction | K6: 57 | L6: 106 | M6: 116 | N6: 74 | P6: 562 | Q6: =67+79+28+107+31+41+107+279+9 -> 748 | R6: USDA | S6: https://www.biopreferred.gov/BioPreferred/faces/catalog/Catalog.xhtml | T6: Retrieved April 2024
A7: Custodial Services | K7: 148 | L7: 176 | M7: 341 | N7: 212 | P7: 821 | Q7: 927 | R7: USDA | S7: https://www.biopreferred.gov/BioPreferred/faces/catalog/Catalog.xhtml | T7: Retrieved April 2024
A8: Films and Packaging | K8: 85 | L8: 106 | M8: 60 | N8: 95 | P8: 378 | Q8: =120+19+219+22+33 -> 413 | R8: USDA | S8: https://www.biopreferred.gov/BioPreferred/faces/catalog/Catalog.xhtml | T8: Retrieved April 2024
A9: Food Services/Cafeteria | K9: 68 | L9: 88 | M9: 138 | N9: 351 | P9: 601 | Q9: =10+42+84+361+185 -> 682 | R9: USDA | S9: https://www.biopreferred.gov/BioPreferred/faces/catalog/Catalog.xhtml | T9: Retrieved April 2024
A10: Grounds Maintenance | K10: 110 | L10: 72 | M10: 82 | N10: 48 | P10: 414 | Q10: =23+3+28+6+107+29+85+38+26+2+27+64+48 -> 486 | R10: USDA | S10: https://www.biopreferred.gov/BioPreferred/faces/catalog/Catalog.xhtml | T10: Retrieved April 2024
A11: Household Supplies | K11: 218 | L11: 207 | M11: 404 | N11: 375 | P11: 1130 | Q11: =15+65+7+17+29+42+258+67+83+21+167+498 -> 1269 | R11: USDA | S11: https://www.biopreferred.gov/BioPreferred/faces/catalog/Catalog.xhtml | T11: Retrieved April 2024
A12: Intermediates | K12: 157 | L12: 373 | M12: 345 | N12: 330 | P12: 2074 | Q12: =5+30+613+159+662+214+190+72+263+345+429+15+233 -> 3230 | R12: USDA | S12: https://www.biopreferred.gov/BioPreferred/faces/catalog/Catalog.xhtml | T12: Retrieved April 2024
A13: Miscellaneous | K13: 63 | L13: 43 | M13: 114 | N13: 84 | P13: 223 | Q13: =126+3+27+30+21+3+2+51 -> 263 | R13: USDA | S13: https://www.biopreferred.gov/BioPreferred/faces/catalog/Catalog.xhtml | T13: Retrieved April 2024
A14: Office Supplies | K14: 9 | L14: 21 | M14: 16 | N14: 20 | P14: 103 | Q14: =4+7+5+2+81+1+13+1 -> 114 | R14: USDA | S14: https://www.biopreferred.gov/BioPreferred/faces/catalog/Catalog.xhtml | T14: Retrieved April 2024
A15: Operations and Maintenance | K15: 164 | L15: 121 | M15: 113 | N15: 62 | P15: 783 | Q15: =90+34+3+50+8+8+36+2+38+48+55+58+4+22+252+22+74+3+39+6+54+3+17+2 -> 928 | R15: USDA | S15: https://www.biopreferred.gov/BioPreferred/faces/catalog/Catalog.xhtml | T15: Retrieved April 2024
A16: Personal Care and Toiletries | K16: 160 | L16: 186 | M16: 423 | N16: 209 | P16: 1041 | Q16: =1035+7 -> 1042 | R16: USDA | S16: https://www.biopreferred.gov/BioPreferred/faces/catalog/Catalog.xhtml | T16: Retrieved April 2024
A17: Safety Equipment | K17: 1 | L17: 0 | M17: 0 | N17: 0 | P17: 20 | Q17: =1+10+20 -> 31 | R17: USDA | S17: https://www.biopreferred.gov/BioPreferred/faces/catalog/Catalog.xhtml | T17: Retrieved April 2024
A18: Vehicles and Equipment Maintenance | K18: 4 | L18: 5 | M18: 6 | N18: 2 | P18: 36 | Q18: =1+12+6+17+22+1 -> 59 | R18: USDA | S18: https://www.biopreferred.gov/BioPreferred/faces/catalog/Catalog.xhtml | T18: Retrieved April 2024

Sheet BIOPLASTICS
A1: PLASTICS
A3: US/GLOBAL PLASTICS | B3: 2008 | C3: 2009 | D3: 2010 | E3: 2011 | F3: 2012 | G3: 2013 | H3: 2014 | I3: 2015 | J3: 2016 | K3: 2017 | L3: 2018 | M3: 2019 | N3: 2020 | O3: 2021 | P3: 2022 | Q3: 2023 | S3: Source Name | T3: Source URL | U3: Comments
A4: U.S. Plastic and Rubber Products Value Added (billion dollars) | B4: 56 | C4: 60.4 | D4: 61.8 | E4: 62.9 | F4: 67.5 | G4: 69 | H4: 67.1 | I4: 78.3 | J4: 79.8 | K4: 77.2 | L4: 80.8 | M4: 84.8 | N4: 80.2 | O4: 79.1 | P4: 90.4 | Q4: 93.65 | S4: Bureau of Economic Analysis | T4: https://apps.bea.gov/iTable/?reqid=19&step=2&isuri=1&categories=survey&_gl=1*1r7rqrk*_ga*MTM3MDkyNjc3LjE3MDg2OTk4NjU.*_ga_J4698JNNFT*MTcwODk1ODU4NC4yLjEuMTcwODk2MDEzMy42MC4wLjA. | U4: Retrieved April 2024
A5: Value Added of Manufacturing US Plastic and Rubber Products as Percentage of GDP (%) | B5: 0.4 | C5: 0.4 | D5: 0.4 | E5: 0.4 | F5: 0.4 | G5: 0.4 | H5: 0.4 | I5: 0.4 | J5: 0.4 | K5: 0.4 | L5: 0.4 | M5: 0.4 | N5: 0.4 | O5: 0.325 | P5: 0.35 | Q5: 0.325 | S5: Bureau of Economic Analysis | T5: https://www.bea.gov/iTable/iTable.cfm?ReqID=51&step=1#reqid=51&step=51&isuri=1&5114=a&5102=5 | U5: Retrieved April 2024
A6: Gross Output of US Plastic and Rubber Products (billion dollars) | B6: 198.9 | C6: 167.8 | D6: 186.6 | E6: 201 | F6: 216.5 | G6: 224.5 | H6: 231.2 | I6: 233.541 | J6: 230.789 | K6: 236.375 | L6: 250.674 | M6: 245.614 | N6: 237.937 | O6: 236.175 | P6: 227.775 | Q6: 298.625 | S6: Bureau of Economic Analysis | T6: https://www.bea.gov/iTable/iTable.cfm?ReqID=51&step=1#reqid=51&step=51&isuri=1&5114=a&5102=5 | U6: Retrieved April 2024
A7: Compensation of Employees, Value Added of Plastics and Rubber Products (billion dollars) | B7: 40 | C7: 34.5 | D7: 36.1 | E7: 37.729 | F7: 39 | G7: 40 | H7: 42.1 | I7: 43.6 | J7: 44.9 | K7: 47.2 | L7: 49.309 | M7: 50.633 | N7: 50.572 | O7: 54.512 | P7: 58.826 | S7: Bureau of Economic Analysis | T7: https://apps.bea.gov/iTable/iTable.cfm?reqid=19&step=2&isuri=1&1921=survey# | U7: Retrieved April 2024
A8: Taxes on Production and Imports, Less Subsides of US Plastics and Rubber Products (billion dollars) | B8: 1.7 | C8: 1.4 | D8: 1.4 | E8: 1.8 | F8: 1.5 | G8: 1.9 | H8: 1.8 | I8: 1.8 | J8: 1.7 | K8: 2 | L8: 2.2 | M8: 2.4 | N8: -0.4 | O8: 1.2 | P8: 2.4 | S8: Bureau of Economic Analysis | T8: https://www.bea.gov/iTable/iTable.cfm?ReqID=51&step=1#reqid=51&step=51&isuri=1&5114=a&5102=5 | U8: Retrieved April 2024
A9: Gross Operating Surplus of Plastics and Rubber Product Products (billion dollars) | B9: 14.4 | C9: 24.5 | D9: 24.2 | E9: 23.4 | F9: 26.9 | G9: 27.1 | H9: 23.2 | I9: 32.9 | J9: 33.1 | K9: 28.1 | L9: 29.3 | M9: 31.7 | N9: 30.1 | O9: 23.5 | P9: 29.2 | S9: Bureau of Economic Analysis | T9: https://www.bea.gov/iTable/iTable.cfm?ReqID=51&step=1#reqid=51&step=51&isuri=1&5114=a&5102=5 | U9: Retrieved April 2024
A10: Full and Part Time Employees (thousands) | B10: 727 | C10: 627 | D10: 624 | E10: 634 | F10: 646 | G10: 658 | H10: 674 | I10: 688 | J10: 702 | K10: 715 | L10: 730 | M10: 731 | N10: 693 | O10: 722 | P10: 748 | S10: Bureau of Economic Analysis | T10: https://apps.bea.gov/iTable/iTable.cfm?reqid=19&step=2&isuri=1&1921=survey | U10: Retrieved April 2024
A11: Global Plastic Production (million metric tons) | B11: 245 | C11: 250 | D11: 265 | E11: 279 | F11: 288 | G11: 299 | H11: 311 | I11: 322 | J11: 335 | K11: 348 | L11: 365.5 | M11: 374.8 | N11: 380.4 | O11: 394 | P11: 400.3 | S11: Plastics Europe | T11: https://plasticseurope.org/resources/market-data/ | U11: Retrieved April 2024
A13: GLOBAL BIOPLASTIC | B13: 2008 | C13: 2009 | D13: 2010 | E13: 2011 | F13: 2012 | G13: 2013 | H13: 2014 | I13: 2015 | J13: 2016 | K13: 2017 | L13: 2018 | M13: 2019 | N13: 2020 | O13: 2021 | P13: 2022 | Q13: 2023 | S13: Source Name | T13: Source URL | U13: Comments
A14: Global production capacity of biodegradable bioplastics (million metric tons) | B14: 0.178 | C14: 0.295 | D14: 0.342 | E14: 0.486 | F14: 0.571 | G14: 0.591 | H14: 0.663 | I14: 0.459 | J14: 0.862 | K14: 0.88 | L14: 1.077 | M14: 1.174 | N14: 1.239 | O14: 1.05 | P14: 1.142 | Q14: 1.13578 | S14: European Plastics Institute for bioplastics and biocomposites Nova Institute for Ecology and Innovation | T14: [2008-2009] http://www.sustainableplant.com/2011/05/bioplastic-production-to-exceed-one-million-tonnes-in-2011/ [2010-2011] http://biomassmagazine.com/articles/9845/bioplastic-market-expected-to-increase-significantly-through-2017 [2012-2018] http://www.bio-based.eu/market_study/media/files/15-05-13_Bio-based_Polymers_and_Building_Blocks_in_the_World-nova_Booklet.pdf | U14: Retrieved April 2024
A15: Global production capacity of non-biodegradable bioplastics (million metric tons) | B15: 0.006 | C15: 0.023 | D15: 0.674 | E15: 0.675 | F15: 0.921 | G15: 0.99 | H15: 1.034 | I15: 1.177 | J15: 1.177 | K15: 1.174 | L15: 0.934 | M15: 0.941 | N15: 0.848 | O15: 0.742 | P15: 1.075 | Q15: 1.04422 | S15: European Plastics Institute for bioplastics and biocomposites Nova Institute for Ecology and Innovation | T15: [2008-2009] http://www.sustainableplant.com/2011/05/bioplastic-production-to-exceed-one-million-tonnes-in-2011/ [2010-2011] http://biomassmagazine.com/articles/9845/bioplastic-market-expected-to-increase-significantly-through-2017 [2012-2018] http://www.bio-based.eu/market_study/media/files/15-05-13_Bio-based_Polymers_and_Building_Blocks_in_the_World-nova_Booklet.pdf | U15: Retrieved April 2024
A16: Global production capacities of biodegradable and non-biodegradable bioplastics (million metric tons) | B16: =+B15+B14 -> 0.184 | C16: =+C15+C14 -> 0.318 | D16: =+D15+D14 -> 1.016 | E16: =+E15+E14 -> 1.161 | F16: =+F15+F14 -> 1.492 | G16: =+G15+G14 -> 1.581 | H16: =+H15+H14 -> 1.697 | I16: =+I15+I14 -> 1.636 | ... Q16: =+Q15+Q14 -> 2.18 | S16: European Plastics Institute for bioplastics and biocomposites Nova Institute for Ecology and Innovation | T16: [2008-2009] http://www.sustainableplant.com/2011/05/bioplastic-production-to-exceed-one-million-tonnes-in-2011/ [2010-2011] http://biomassmagazine.com/articles/9845/bioplastic-market-expected-to-increase-significantly-through-2017 [2012-2018] http://www.bio-based.eu/market_study/media/files/15-05-13_Bio-based_Polymers_and_Building_Blocks_in_the_World-nova_Booklet.pdf | U16: Retrieved April 2024
A17: Packaging | K17: 58 | L17: 57.742471 | M17: 53 | N17: 47.287373 | O17: 64.636872 | P17: 48.274775 | Q17: 42.844 | S17: European Plastics Institute for bioplastics and biocomposites Nova Institute for Ecology and Innovation | T17: [2013/2018] http://www.bio-based.eu/market_study/media/files/15-05-13_Bio-based_Polymers_and_Building_Blocks_in_the_World-nova_Booklet.pdf [2014] https://www.kunststoffe.de/en/news/overview/artikel/global-bioplastics-production-capacities-continue-to-grow-1253170.html [2016] https://www.ifbb-hannover.de/de/facts-and-statistics.html [2017] http://docs.european-bioplastics.org/publications/EUBP_Facts_and_figures.pdf | U17: Retrieved April 2024
A18: Textiles | K18: 11 | L18: 11.335072 | M18: 11 | N18: 11.419095 | O18: 13.575419 | P18: 14.815315 | Q18: 20.715596 | S18: European Plastics Institute for bioplastics and biocomposites Nova Institute for Ecology and Innovation | T18: [2013/2018] http://www.bio-based.eu/market_study/media/files/15-05-13_Bio-based_Polymers_and_Building_Blocks_in_the_World-nova_Booklet.pdf [2014] https://www.kunststoffe.de/en/news/overview/artikel/global-bioplastics-production-capacities-continue-to-grow-1253170.html [2016] https://www.ifbb-hannover.de/de/facts-and-statistics.html [2017] http://docs.european-bioplastics.org/publications/EUBP_Facts_and_figures.pdf | U18: Retrieved April 2024
A19: Consumer Goods | K19: 7 | L19: 6.8057861 | M19: 8 | N19: 12.248282 | O19: 15.055866 | P19: 14.072073 | Q19: 13.366975 | S19: European Plastics Institute for bioplastics and biocomposites Nova Institute for Ecology and Innovation | T19: [2013/2018] http://www.bio-based.eu/market_study/media/files/15-05-13_Bio-based_Polymers_and_Building_Blocks_in_the_World-nova_Booklet.pdf [2014] https://www.kunststoffe.de/en/news/overview/artikel/global-bioplastics-production-capacities-continue-to-grow-1253170.html [2016] https://www.ifbb-hannover.de/de/facts-and-statistics.html [2017] http://docs.european-bioplastics.org/publications/EUBP_Facts_and_figures.pdf | U19: Retrieved April 2024
A20: Agriculture & Horticulture | K20: 5 | L20: 5.6675362 | M20: 8 | N20: 7.7469794 | O20: 11.899441 | P20: 4.3873874 | Q20: 4.5366972 | S20: European Plastics Institute for bioplastics and biocomposites Nova Institute for Ecology and Innovation | T20: [2013/2018] http://www.bio-based.eu/market_study/media/files/15-05-13_Bio-based_Polymers_and_Building_Blocks_in_the_World-nova_Booklet.pdf [2014] https://www.kunststoffe.de/en/news/overview/artikel/global-bioplastics-production-capacities-continue-to-grow-1253170.html [2016] https://www.ifbb-hannover.de/de/facts-and-statistics.html [2017] http://docs.european-bioplastics.org/publications/EUBP_Facts_and_figures.pdf | U20: Retrieved April 2024
A21: Automotive & Transport | K21: 7 | L21: 7.3511975 | M21: 7 | N21: 5.7332386 | O21: 6.5921788 | P21: 7.1621622 | Q21: 9.7285321 | S21: European Plastics Institute for bioplastics and biocomposites Nova Institute for Ecology and Innovation | T21: [2013/2018] http://www.bio-based.eu/market_study/media/files/15-05-13_Bio-based_Polymers_and_Building_Blocks_in_the_World-nova_Booklet.pdf [2014] https://www.kunststoffe.de/en/news/overview/artikel/global-bioplastics-production-capacities-continue-to-grow-1253170.html [2016] https://www.ifbb-hannover.de/de/facts-and-statistics.html [2017] http://docs.european-bioplastics.org/publications/EUBP_Facts_and_figures.pdf | U21: Retrieved April 2024
A22: Building & Construction | K22: 4 | L22: 3.6281717 | M22: 4 | N22: 3.5299692 | O22: 4.301676 | P22: 0.94144144 | Q22: 0.63761468 | S22: European Plastics Institute for bioplastics and biocomposites Nova Institute for Ecology and Innovation | T22: [2013/2018] http://www.bio-based.eu/market_study/media/files/15-05-13_Bio-based_Polymers_and_Building_Blocks_in_the_World-nova_Booklet.pdf [2014] https://www.kunststoffe.de/en/news/overview/artikel/global-bioplastics-production-capacities-continue-to-grow-1253170.html [2016] https://www.ifbb-hannover.de/de/facts-and-statistics.html [2017] http://docs.european-bioplastics.org/publications/EUBP_Facts_and_figures.pdf | U22: Retrieved April 2024
A23: Electronics | K23: 2 | L23: 1.6125207 | M23: 2 | N23: 3 | O23: 3.5195531 | P23: 2.5990991 | Q23: 3.5366972 | S23: European Plastics Institute for bioplastics and biocomposites Nova Institute for Ecology and Innovation | T23: [2013/2018] http://www.bio-based.eu/market_study/media/files/15-05-13_Bio-based_Polymers_and_Building_Blocks_in_the_World-nova_Booklet.pdf [2014] https://www.kunststoffe.de/en/news/overview/artikel/global-bioplastics-production-capacities-continue-to-grow-1253170.html [2016] https://www.ifbb-hannover.de/de/facts-and-statistics.html [2017] http://docs.european-bioplastics.org/publications/EUBP_Facts_and_figures.pdf | U23: Retrieved April 2024
A24: Others | K24: 6 | L24: 5.8572445 | M24: 7 | N24: 5 | O24: 10.083799 | P24: 6.0045045 | Q24: 3.40366 | S24: European Plastics Institute for bioplastics and biocomposites Nova Institute for Ecology and Innovation | T24: [2013/2018] http://www.bio-based.eu/market_study/media/files/15-05-13_Bio-based_Polymers_and_Building_Blocks_in_the_World-nova_Booklet.pdf [2014] https://www.kunststoffe.de/en/news/overview/artikel/global-bioplastics-production-capacities-continue-to-grow-1253170.html [2016] https://www.ifbb-hannover.de/de/facts-and-statistics.html [2017] http://docs.european-bioplastics.org/publications/EUBP_Facts_and_figures.pdf | U24: Retrieved April 2024
A25: Percentage of Bioplastic in Total Global Plastic Consumption | B25: =+B16/B11*100 -> 0.075102041 | C25: =+C16/C11*100 -> 0.1272 | D25: =+D16/D11*100 -> 0.38339623 | E25: =+E16/E11*100 -> 0.41612903 | F25: =+F16/F11*100 -> 0.51805556 | G25: =+G16/G11*100 -> 0.52876254 | H25: =+H16/H11*100 -> 0.54565916 | I25: =+I16/I11*100 -> 0.50807453 | ... P25: =+P16/P11*100 -> 0.55383462 | S25: Calculation
A26: Land Used for Bioplastics (million ha) | G26: 0.554 | H26: 0.683 | I26: 0.749 | J26: 0.751 | K26: 0.898 | L26: 0.81 | M26: 0.79 | S26: Institute for bioplastics and biocomposites | T26: https://docs.european-bioplastics.org/publications/EUBP_Facts_and_figures.pdf | U26: Retrieved April 2021
A27: Land Used for Bioplastics/Total Amount of Arable Land (%) | G27: 0.039571429 | H27: 0.048785714 | I27: 0.0535 | J27: 0.053642857 | K27: 0.064142857 | L27: 0.057857143 | M27: 0.02 | S27: Institute for bioplastics and biocomposites | T27: https://docs.european-bioplastics.org/publications/EUBP_Facts_and_figures.pdf | U27: Retrieved April 2021
A29: GLOBAL BIO-BASED STRUCTURAL POLYMERS | B29: 2008 | C29: 2009 | D29: 2010 | E29: 2011 | F29: 2012 | G29: 2013 | H29: 2014 | I29: 2015 | J29: 2016 | K29: 2017 | L29: 2018 | M29: 2019 | N29: 2020 | O29: 2021 | P29: 2022 | Q29: 2023 | S29: Source Name | T29: Source URL | U29: Comments
A30: Total Production Capacity | H30: 1.7 | K30: 2.05 | L30: 2.01 | M30: 2.11 | N30: =N16 -> 2.087 | O30: =O16 -> 1.792 | P30: =P16 -> 2.217 | Q30: 2.18 | S30: Nova Institute for Ecology and Innovation | T30: https://www.european-bioplastics.org/market/# | U30: Retrieved April 2024
A31: Starch Blends (%) | H31: 10 | K31: 18.8 | L31: 18.2 | M31: 21.3 | N31: 18.7 | O31: 16.4 | P31: 17.9 | Q31: 10.6 | R31: Biodegradable | S31: Nova Institute for Ecology and Innovation | T31: https://www.european-bioplastics.org/market/# | U31: Retrieved April 2024
A32: Polylactic Acid (PLA) (%) | H32: 12.2 | K32: 10.3 | L32: 10.3 | M32: 13.9 | N32: 18.7 | O32: 18.9 | P32: 20.7 | Q32: 31 | R32: Biodegradable | S32: Nova Institute for Ecology and Innovation | T32: https://www.european-bioplastics.org/market/# | U32: Retrieved April 2024
A33: Poly (butylene adipate-co-terephthalate) (PBAT) (%) | H33: 13 | K33: 5 | L33: 7.2 | M33: 13.4 | N33: 13.5 | O33: 19.2 | P33: 4.5 | Q33: 4.6 | R33: Biodegradable | S33: Nova Institute for Ecology and Innovation | T33: https://www.european-bioplastics.org/market/# | U33: Retrieved April 2024
A34: Polyethylene (PE) (%) | H34: 11.8 | K34: 9.7 | L34: 9.5 | M34: 11.8 | N34: 10.5 | O34: 9.5 | P34: 14.8 | Q34: 12.3 | R34: Biobased | S34: Nova Institute for Ecology and Innovation | T34: https://www.european-bioplastics.org/market/# | U34: Retrieved April 2024
A35: Polyamides (PA) (%) | H35: 5.5 | K35: 11.9 | L35: 11.6 | M35: 11.6 | N35: 11.9 | O35: 9.1 | P35: 11.1 | Q35: 18.3 | R35: Biobased | S35: Nova Institute for Ecology and Innovation | T35: https://www.european-bioplastics.org/market/# | U35: Retrieved April 2024
A36: Polyethylene Terephthalate (PET) (%) | H36: 35.4 | K36: 26.3 | L36: 26.6 | M36: 9.8 | N36: 7.8 | O36: 6.2 | P36: 4.2 | Q36: 2.2 | R36: Biobased | S36: Nova Institute for Ecology and Innovation | T36: https://www.european-bioplastics.org/market/# | U36: Retrieved April 2024
A37: Polytrimethylene Terephthalate (PTT) (%) | H37: 7.1 | L37: 9.2 | M37: 9.2 | N37: 9.2 | O37: 8.1 | P37: 13.3 | Q37: 13.5 | R37: Biobased | S37: Nova Institute for Ecology and Innovation | T37: https://www.european-bioplastics.org/market/# | U37: Retrieved April 2024
A38: Polybutylene Succinate (PBS) (%) | H38: 1.6 | K38: 4.9 | L38: 4.6 | M38: 4.3 | N38: 4.1 | O38: 3.5 | P38: 0.9 | Q38: 0.9 | R38: Biodegradable | S38: Nova Institute for Ecology and Innovation | T38: https://www.european-bioplastics.org/market/# | U38: Retrieved April 2024
A39: Other (%) | H39: 1.4 | K39: 10.7 | L39: 1.4 | M39: 2.6 | N39: 2.5 | O39: 1 | P39: 1.1 | Q39: 1.1 | R39: Biobased | S39: Nova Institute for Ecology and Innovation | T39: https://www.european-bioplastics.org/market/# | U39: Retrieved April 2024
A40: Polyhydroxyalkanoates (PHA) (%) | H40: 2 | K40: 2.4 | L40: 1.4 | M40: 1.2 | N40: 1.7 | O40: 1.8 | P40: 3.9 | Q40: 4.8 | R40: Biodegradable | S40: Nova Institute for Ecology and Innovation | T40: https://www.european-bioplastics.org/market/# | U40: Retrieved April 2024
A41: Polyproprylene (PP) (%) | H41: 0 | K41: 0 | L41: 0 | M41: 0.9 | N41: 1.4 | O41: 1.9 | P41: 3.9 | Q41: 0.5 | R41: Biobased | S41: Nova Institute for Ecology and Innovation | T41: https://www.european-bioplastics.org/market/# | U41: Retrieved April 2024
Q42: =SUM(Q31:Q41) -> 99.8

Sheet ENZYMES
A1: ENZYMES
A3: GLOBAL | B3: 2008 | C3: 2009 | D3: 2010 | E3: 2011 | F3: 2012 | G3: 2013 | H3: 2014 | I3: 2015 | J3: 2016 | K3: 2017 | L3: 2018 | M3: 2019 | N3: 2020 | O3: 2021 | P3: 2022 | Q3: 2023 | R3: Source Name | S3: Source URL | T3: Comments
A4: Global Industrial Enzyme Market (billion dollars) By market: | B4: 2.93 | C4: 3.16 | D4: 3.63 | E4: 4.03 | F4: 4.49 | G4: 4.77 | H4: 4.6 | I4: 4.9 | J4: 5 | K4: 5.2541 | L4: 5.5 | M4: 5.6 | N4: 5.93 | O4: 6.4 | R4: BBC Research | S4: https://www.bccresearch.com/market-research/biotechnology/global-markets-for-enzymes-in-industrial-applications.html | T4: Retrieved April 2021
A5: * Food (billion dollars) | E5: 1.2048 | F5: 1.3472 | G5: 1.3472 | J5: 1.5 | K5: 1.9259 | R5: BBC Research | S5: “Global Markets for Enzymes in Industrial Applications.” BCC Research (September 2018) | T5: Retrieved June 2020
A6: * Feed (billion dollars) | E6: 1.0029 | F6: 1.1002 | G6: 1.2149 | J6: 1.2 | K6: 0.5962 | R6: BBC Research | S6: “Global Markets for Enzymes in Industrial Applications.” BCC Research (September 2018) | T6: Retrieved June 2020
A7: * Technical (billion dollars) | E7: 0.9684 | F7: 1.1052 | G7: 1.1518 | J7: 1.2 | K7: 1.2983 | R7: BBC Research | S7: “Global Markets for Enzymes in Industrial Applications.” BCC Research (September 2018) | T7: Retrieved June 2020
A8: * Biofuel (billion dollars) | K8: 0.7193 | O8: 1.3 | R8: BBC Research | S8: “Global Markets for Enzymes in Industrial Applications.” BCC Research (September 2018) | T8: Retrieved June 2020
A9: * Other (billion dollars) | K9: 0.7144 | R9: BBC Research | S9: “Global Markets for Enzymes in Industrial Applications.” BCC Research (September 2018) | T9: Retrieved June 2020
A10: * Detergent (billion dollars) | E10: 0.8319 | F10: 0.9669 | G10: 1.0535 | J10: 1.1 | R10: BBC Research | S10: “Global Markets for Enzymes in Industrial Applications.” BCC Research (September 2018) | T10: Retrieved June 2020

Sheet APPAREL AND TEXTILES
A1: APPAREL AND TEXTILES
A3: US TEXTILE MILLS AND TEXTILE PRODUCT MILLS (NAICS) | B3: 2008 | C3: 2009 | D3: 2010 | E3: 2011 | F3: 2012 | G3: 2013 | H3: 2014 | I3: 2015 | J3: 2016 | K3: 2017 | L3: 2018 | M3: 2019 | N3: 2020 | O3: 2021 | P3: 2022 | Q3: 2023 | R3: Source Name | S3: Source URL | T3: Comments
A4: U.S. Textile Mills and Textile Product Mills Value Added (billion dollars) | B4: 17.8 | C4: 15.1 | D4: 15.6 | E4: 15.1 | F4: 16 | G4: 16.8 | H4: 17.8 | I4: 17.9 | J4: 18.6 | K4: 17.7 | L4: 16.7 | M4: 16.8 | N4: 15.3 | O4: 16.525 | P4: 17.425 | Q4: 17.275 | R4: Bureau of Economic Analysis | S4: https://apps.bea.gov/iTable/?reqid=150&step=2&isuri=1&categories=gdpxind&_gl=1*14rxqpt*_ga*MTM3MDkyNjc3LjE3MDg2OTk4NjU.*_ga_J4698JNNFT*MTcwODk1ODU4NC4yLjEuMTcwODk2MjUwMS42MC4wLjA.#eyJhcHBpZCI6MTUwLCJzdGVwcyI6WzEsMiwzXSwiZGF0YSI6W1siY2F0ZWdvcmllcyIsIkdkcHhJbmQiXSxbIlRhYmxlX0xpc3QiLCIxNSJdXX0= | T4: Accessed April 2024
A5: Value Added of Manufacturing US Textile Mills and Textile Product Mills as a Percentage of GDP (%) | B5: 0.1 | C5: 0.1 | D5: 0.1 | E5: 0.1 | F5: 0.1 | G5: 0.1 | H5: 0.1 | I5: 0.1 | J5: 0.1 | K5: 0.1 | L5: 0.1 | M5: 0.1 | N5: 0.1 | O5: 0.1 | P5: 0.1 | Q5: 0.1 | R5: Bureau of Economic Analysis | S5: https://apps.bea.gov/iTable/?reqid=150&step=2&isuri=1&categories=gdpxind&_gl=1*14rxqpt*_ga*MTM3MDkyNjc3LjE3MDg2OTk4NjU.*_ga_J4698JNNFT*MTcwODk1ODU4NC4yLjEuMTcwODk2MjUwMS42MC4wLjA.#eyJhcHBpZCI6MTUwLCJzdGVwcyI6WzEsMiwzXSwiZGF0YSI6W1siY2F0ZWdvcmllcyIsIkdkcHhJbmQiXSxbIlRhYmxlX0xpc3QiLCIxNSJdXX0= | T5: Accessed April 2024
A6: Gross Output of US Textile Mills and Textile Product Mills (billion dollars) | B6: 56.5 | C6: 46.3 | D6: 49.8 | E6: 52.9 | F6: 51.7 | G6: 54 | H6: 55.8 | I6: 53.5 | J6: 52.3 | K6: 50.2 | L6: 50.6 | M6: 50.3 | N6: 47.5 | O6: 50.775 | P6: 52.5 | Q6: 49.675 | R6: Bureau of Economic Analysis | S6: https://apps.bea.gov/iTable/?reqid=150&step=2&isuri=1&categories=gdpxind&_gl=1*14rxqpt*_ga*MTM3MDkyNjc3LjE3MDg2OTk4NjU.*_ga_J4698JNNFT*MTcwODk1ODU4NC4yLjEuMTcwODk2MjUwMS42MC4wLjA.#eyJhcHBpZCI6MTUwLCJzdGVwcyI6WzEsMiwzXSwiZGF0YSI6W1siY2F0ZWdvcmllcyIsIkdkcHhJbmQiXSxbIlRhYmxlX0xpc3QiLCIxNSJdXX0= | T6: Accessed April 2024
A7: Compensation of Employees, Value Added of Textile Mills & Textile Product Mills (billion dollars) | B7: 13.5 | C7: 10.9 | D7: 10.9 | E7: 11 | F7: 11.2 | G7: 11.5 | H7: 12.1 | I7: 12 | J7: 12 | K7: 12.3 | L7: 12.5 | M7: 12.4 | N7: 11.5 | O7: 12.3 | P7: 13 | R7: Bureau of Economic Analysis | S7: https://apps.bea.gov/iTable/?reqid=150&step=2&isuri=1&categories=gdpxind&_gl=1*14rxqpt*_ga*MTM3MDkyNjc3LjE3MDg2OTk4NjU.*_ga_J4698JNNFT*MTcwODk1ODU4NC4yLjEuMTcwODk2MjUwMS42MC4wLjA.#eyJhcHBpZCI6MTUwLCJzdGVwcyI6WzEsMiwzXSwiZGF0YSI6W1siY2F0ZWdvcmllcyIsIkdkcHhJbmQiXSxbIlRhYmxlX0xpc3QiLCIxNSJdXX0= | T7: Accessed April 2024
A8: Taxes of Production and Imports, Less Subsides of US Textile Mills & Textile Product Mills (billion dollars) | B8: 0.7 | C8: 0.7 | D8: 0.6 | E8: 0.6 | F8: 0.6 | G8: 0.6 | H8: 0.6 | I8: 0.6 | J8: 0.6 | K8: 0.6 | L8: 0.6 | M8: 0.6 | N8: -0.4 | O8: 0.2 | P8: 0.7 | R8: Bureau of Economic Analysis | S8: https://apps.bea.gov/iTable/?reqid=150&step=2&isuri=1&categories=gdpxind&_gl=1*14rxqpt*_ga*MTM3MDkyNjc3LjE3MDg2OTk4NjU.*_ga_J4698JNNFT*MTcwODk1ODU4NC4yLjEuMTcwODk2MjUwMS42MC4wLjA.#eyJhcHBpZCI6MTUwLCJzdGVwcyI6WzEsMiwzXSwiZGF0YSI6W1siY2F0ZWdvcmllcyIsIkdkcHhJbmQiXSxbIlRhYmxlX0xpc3QiLCIxNSJdXX0= | T8: Accessed April 2024
A9: Gross Operating Surplus of Textile Mills & Textile Product Mills Products (billion dollars) | B9: 3.7 | C9: 3.6 | D9: 4 | E9: 3.5 | F9: 4.2 | G9: 4.7 | H9: 5.2 | I9: 5.4 | J9: 6 | K9: 4.4 | L9: 3.4 | M9: 3.7 | N9: 4.7 | O9: 4 | P9: 3.7 | R9: Bureau of Economic Analysis | S9: https://apps.bea.gov/iTable/?reqid=150&step=2&isuri=1&categories=gdpxind&_gl=1*14rxqpt*_ga*MTM3MDkyNjc3LjE3MDg2OTk4NjU.*_ga_J4698JNNFT*MTcwODk1ODU4NC4yLjEuMTcwODk2MjUwMS42MC4wLjA.#eyJhcHBpZCI6MTUwLCJzdGVwcyI6WzEsMiwzXSwiZGF0YSI6W1siY2F0ZWdvcmllcyIsIkdkcHhJbmQiXSxbIlRhYmxlX0xpc3QiLCIxNSJdXX0= | T9: Accessed April 2024
A10: Full and Part Time Employees (thousands) | B10: 303 | C10: 251 | D10: 240 | E10: 240 | F10: 236 | G10: 233 | H10: 235 | I10: 234 | J10: 230 | K10: 229 | L10: 228 | M10: 221 | N10: 199 | O10: 202 | P10: 203 | R10: Bureau of Economic Analysis | S10: https://apps.bea.gov/iTable/?reqid=150&step=2&isuri=1&categories=gdpxind&_gl=1*14rxqpt*_ga*MTM3MDkyNjc3LjE3MDg2OTk4NjU.*_ga_J4698JNNFT*MTcwODk1ODU4NC4yLjEuMTcwODk2MjUwMS42MC4wLjA.#eyJhcHBpZCI6MTUwLCJzdGVwcyI6WzEsMiwzXSwiZGF0YSI6W1siY2F0ZWdvcmllcyIsIkdkcHhJbmQiXSxbIlRhYmxlX0xpc3QiLCIxNSJdXX0= | T10: Accessed April 2024
A12: US APPAREL AND LEATHER AND ALLIED PRODUCTS (NAICS) | B12: 2008 | C12: 2009 | D12: 2010 | E12: 2011 | F12: 2012 | G12: 2013 | H12: 2014 | I12: 2015 | J12: 2016 | K12: 2017 | L12: 2018 | M12: 2019 | N12: 2020 | O12: 2021 | P12: 2022 | Q12: 2023 | R12: Source Name | S12: Source URL | T12: Comments
A13: Apparel and Leather and Allied Products Value Added (billion dollars) | B13: 11.6 | C13: 9.9 | D13: 10.4 | E13: 10.1 | F13: 10 | G13: 10.2 | H13: 9.9 | I13: 9.7 | J13: 9.6 | K13: 9.4 | L13: 9.3 | M13: 9.3 | N13: 9.8 | O13: 10 | P13: 10.375 | Q13: 10.7 | R13: Bureau of Economic Analysis | S13: https://apps.bea.gov/iTable/?reqid=150&step=2&isuri=1&categories=gdpxind&_gl=1*14rxqpt*_ga*MTM3MDkyNjc3LjE3MDg2OTk4NjU.*_ga_J4698JNNFT*MTcwODk1ODU4NC4yLjEuMTcwODk2MjUwMS42MC4wLjA.#eyJhcHBpZCI6MTUwLCJzdGVwcyI6WzEsMiwzXSwiZGF0YSI6W1siY2F0ZWdvcmllcyIsIkdkcHhJbmQiXSxbIlRhYmxlX0xpc3QiLCIxNSJdXX0= | T13: Accessed April 2024
A14: Valued Added of Manufacturing US Apparel and Leather and Allied Products as a Percentage of GDP (%) | B14: 0.1 | C14: 0.1 | D14: 0.1 | E14: 0.1 | F14: 0.1 | G14: 0.1 | H14: 0.1 | I14: 0.1 | J14: 0.1 | K14: 0 | L14: 0 | M14: 0 | N14: 0.2 | O14: 0.3 | P14: 0 | Q14: 0 | R14: Bureau of Economic Analysis | S14: https://apps.bea.gov/iTable/?reqid=150&step=2&isuri=1&categories=gdpxind&_gl=1*14rxqpt*_ga*MTM3MDkyNjc3LjE3MDg2OTk4NjU.*_ga_J4698JNNFT*MTcwODk1ODU4NC4yLjEuMTcwODk2MjUwMS42MC4wLjA.#eyJhcHBpZCI6MTUwLCJzdGVwcyI6WzEsMiwzXSwiZGF0YSI6W1siY2F0ZWdvcmllcyIsIkdkcHhJbmQiXSxbIlRhYmxlX0xpc3QiLCIxNSJdXX0= | T14: Accessed April 2024
A15: Gross Output of US Apparel and Leather and Allied Products (billion dollars) | B15: 26.7 | C15: 24.4 | D15: 23.3 | E15: 24.9 | F15: 19.2 | G15: 19.6 | H15: 19.1 | I15: 18.6 | J15: 19 | K15: 17.9 | L15: 17.4 | M15: 17.2 | N15: 17.8 | O15: 18.35 | P15: 19.675 | Q15: 19.6 | R15: Bureau of Economic Analysis | S15: https://apps.bea.gov/iTable/?reqid=150&step=2&isuri=1&categories=gdpxind&_gl=1*14rxqpt*_ga*MTM3MDkyNjc3LjE3MDg2OTk4NjU.*_ga_J4698JNNFT*MTcwODk1ODU4NC4yLjEuMTcwODk2MjUwMS42MC4wLjA.#eyJhcHBpZCI6MTUwLCJzdGVwcyI6WzEsMiwzXSwiZGF0YSI6W1siY2F0ZWdvcmllcyIsIkdkcHhJbmQiXSxbIlRhYmxlX0xpc3QiLCIxNSJdXX0= | T15: Accessed April 2024
A16: Compensation of Employees, Value Added of Apparel and Leather and Allied Products (billion dollars) | B16: 10.5 | C16: 8.6 | D16: 8.4 | E16: 8.1 | F16: 8.2 | G16: 8.2 | H16: 8.4 | I16: 8.2 | J16: 8.1 | K16: 7.9 | L16: 7.8 | M16: 7.7 | N16: 6.7 | O16: 7.3 | P16: 8.1 | R16: Bureau of Economic Analysis | S16: https://apps.bea.gov/iTable/?reqid=150&step=2&isuri=1&categories=gdpxind&_gl=1*14rxqpt*_ga*MTM3MDkyNjc3LjE3MDg2OTk4NjU.*_ga_J4698JNNFT*MTcwODk1ODU4NC4yLjEuMTcwODk2MjUwMS42MC4wLjA.#eyJhcHBpZCI6MTUwLCJzdGVwcyI6WzEsMiwzXSwiZGF0YSI6W1siY2F0ZWdvcmllcyIsIkdkcHhJbmQiXSxbIlRhYmxlX0xpc3QiLCIxNSJdXX0= | T16: Accessed April 2024
A17: Taxes of Production and Imports, Less Subsides of US Apparel and Leather and Allied Products (billion dollars) | B17: 0.3 | C17: 0.3 | D17: 0.3 | E17: 0.3 | F17: 0.3 | G17: 0.3 | H17: 0.3 | I17: 0.3 | J17: 0.3 | K17: 0.3 | L17: 0.3 | M17: 0.3 | N17: -0.7 | O17: -0.6 | P17: 0.4 | R17: Bureau of Economic Analysis | S17: https://apps.bea.gov/iTable/?reqid=150&step=2&isuri=1&categories=gdpxind&_gl=1*14rxqpt*_ga*MTM3MDkyNjc3LjE3MDg2OTk4NjU.*_ga_J4698JNNFT*MTcwODk1ODU4NC4yLjEuMTcwODk2MjUwMS42MC4wLjA.#eyJhcHBpZCI6MTUwLCJzdGVwcyI6WzEsMiwzXSwiZGF0YSI6W1siY2F0ZWdvcmllcyIsIkdkcHhJbmQiXSxbIlRhYmxlX0xpc3QiLCIxNSJdXX0= | T17: Accessed April 2024
A18: Gross Operating Surplus of Apparel and Leather and Allied Products Products (billion dollars) | B18: 0.8 | C18: 1 | D18: 1.7 | E18: 1.7 | F18: 1.6 | G18: 1.7 | H18: 1.3 | I18: 1.2 | J18: 1.3 | K18: 1.3 | L18: 1.3 | M18: 1.7 | N18: 3.5 | O18: 3.3 | P18: 1.9 | R18: Bureau of Economic Analysis | S18: https://apps.bea.gov/iTable/?reqid=150&step=2&isuri=1&categories=gdpxind&_gl=1*14rxqpt*_ga*MTM3MDkyNjc3LjE3MDg2OTk4NjU.*_ga_J4698JNNFT*MTcwODk1ODU4NC4yLjEuMTcwODk2MjUwMS42MC4wLjA.#eyJhcHBpZCI6MTUwLCJzdGVwcyI6WzEsMiwzXSwiZGF0YSI6W1siY2F0ZWdvcmllcyIsIkdkcHhJbmQiXSxbIlRhYmxlX0xpc3QiLCIxNSJdXX0= | T18: Accessed April 2024
A19: Full and Part Time Employees (thousands) | B19: 233 | C19: 198 | D19: 187 | E19: 181 | F19: 178 | G19: 174 | H19: 170 | I19: 166 | J19: 159 | K19: 149 | L19: 142 | M19: 137 | N19: 114 | O19: 117 | P19: 119 | R19: Bureau of Economic Analysis | S19: https://apps.bea.gov/iTable/?reqid=150&step=2&isuri=1&categories=gdpxind&_gl=1*14rxqpt*_ga*MTM3MDkyNjc3LjE3MDg2OTk4NjU.*_ga_J4698JNNFT*MTcwODk1ODU4NC4yLjEuMTcwODk2MjUwMS42MC4wLjA.#eyJhcHBpZCI6MTUwLCJzdGVwcyI6WzEsMiwzXSwiZGF0YSI6W1siY2F0ZWdvcmllcyIsIkdkcHhJbmQiXSxbIlRhYmxlX0xpc3QiLCIxNSJdXX0= | T19: Accessed April 2024
A21: TRADE | B21: 2008 | C21: 2009 | D21: 2010 | E21: 2011 | F21: 2012 | G21: 2013 | H21: 2014 | I21: 2015 | J21: 2016 | K21: 2017 | L21: 2018 | M21: 2019 | N21: 2020 | O21: 2021 | P21: 2022 | Q21: 2023 | R21: Source Name | S21: Source URL | T21: Comments
A22: Value of the U.S. apparel exports worldwide (billion dollars) | C22: 4.02 | D22: 4.497 | E22: 5.01 | F22: 5.165 | G22: 5.439 | H22: 5.695 | I22: 5.697 | J22: 5.302 | K22: 5.315 | L22: 5.658 | M22: 5.561 | N22: 4.347 | O22: 5.449 | P22: 6.493 | Q22: 6.574 | R22: ITA | S22: https://www.trade.gov/data-visualization/tradestats-express-us-trade-product | T22: Accessed August 2024
A23: Value of the U.S. apparel imports worldwide (billion dollars) | C23: 66.884703 | D23: 75.644307 | E23: 82.247087 | F23: 81.259191 | G23: 84.386293 | H23: 86.60965 | I23: 89.89304 | J23: 84.738049 | K23: 84.343617 | L23: 87.43622 | M23: 88.035916 | N23: 71.807796 | O23: 86.403237 | P23: 103.9599 | Q23: 81.606597 | R23: ITA | S23: https://www.trade.gov/data-visualization/tradestats-express-us-trade-product | T23: Accessed August 2024
A24: Value of the U.S. textiles exports worldwide (billion dollars) | C24: 6.6854863 | D24: 8.1604995 | E24: 9.465875 | F24: 9.310538 | G24: 9.6473534 | H24: 10.024618 | I24: 9.7622466 | J24: 9.1155358 | K24: 9.3394037 | L24: 9.5646385 | M24: 9.2583285 | N24: 7.5391898 | O24: 8.8510388 | P24: 9.4361329 | Q24: 8.4388061 | R24: ITA | S24: https://www.trade.gov/data-visualization/tradestats-express-us-trade-product | T24: Accessed August 2024
A25: Value of the U.S. textiles imports worldwide (billion dollars) | C25: 5.2920875 | D25: 6.5358656 | E25: 7.330905 | F25: 7.7750181 | G25: 8.0410699 | H25: 8.4601825 | I25: 8.6507927 | J25: 8.2525303 | K25: 8.1829452 | L25: 8.7653571 | M25: 8.2144911 | N25: 8.2874789 | O25: 9.8263712 | P25: 10.257758 | Q25: 8.7231181 | R25: ITA | S25: https://www.trade.gov/data-visualization/tradestats-express-us-trade-product | T25: Accessed August 2024

Sheet FOREST PRODUCTS
A1: FOREST PRODUCTS
A3: US WOOD PRODUCTS (NAICS) | B3: 2008 | C3: 2009 | D3: 2010 | E3: 2011 | F3: 2012 | G3: 2013 | H3: 2014 | I3: 2015 | J3: 2016 | K3: 2017 | L3: 2018 | M3: 2019 | N3: 2020 | O3: 2021 | P3: 2022 | Q3: 2023 | R3: Source Name | S3: Source URL | T3: Comments
A4: U.S. Wood Products Real Value Added (billion dollars) | B4: 25.6 | C4: 21.2 | D4: 23.3 | E4: 23.6 | F4: 25.8 | G4: 30.5 | H4: 30.9 | I4: 32.5 | J4: 35.3 | K4: 37.5 | L4: 40.4 | M4: 41.2 | N4: 42.2 | O4: 35.8 | P4: 34.25 | Q4: 36.875 | R4: Bureau of Economic Analysis | S4: https://apps.bea.gov/iTable/?reqid=19&step=2&isuri=1&categories=survey&_gl=1*1r7rqrk*_ga*MTM3MDkyNjc3LjE3MDg2OTk4NjU.*_ga_J4698JNNFT*MTcwODk1ODU4NC4yLjEuMTcwODk2MDEzMy42MC4wLjA. | T4: Retrieved April 2024
A5: Value Added of Manufacturing US Wood Products as Percentage of GDP (%) | B5: 0.2 | C5: 0.1 | D5: 0.2 | E5: 0.2 | F5: 0.2 | G5: 0.2 | H5: 0.2 | I5: 0.2 | J5: 0.2 | K5: 0.2 | L5: 0.2 | M5: 0.2 | N5: 0.2 | O5: 0.25 | P5: 0.2 | Q5: 0.2 | R5: Bureau of Economic Analysis | S5: https://apps.bea.gov/iTable/?reqid=150&step=2&isuri=1&categories=gdpxind&_gl=1*14rxqpt*_ga*MTM3MDkyNjc3LjE3MDg2OTk4NjU.*_ga_J4698JNNFT*MTcwODk1ODU4NC4yLjEuMTcwODk2MjUwMS42MC4wLjA.#eyJhcHBpZCI6MTUwLCJzdGVwcyI6WzEsMiwzXSwiZGF0YSI6W1siY2F0ZWdvcmllcyIsIkdkcHhJbmQiXSxbIlRhYmxlX0xpc3QiLCIxNSJdXX0= | T5: Retrieved April 2024
A6: Gross Output of US Wood Products (billion dollars) | B6: 89.1 | C6: 65.9 | D6: 71.9 | E6: 73 | F6: 80.8 | G6: 90.6 | H6: 97.6 | I6: 101 | J6: 105.3 | K6: 112 | L6: 120 | M6: 117.6 | N6: 113 | O6: 163.15 | P6: 174.1 | Q6: 171.325 | R6: Bureau of Economic Analysis | S6: https://apps.bea.gov/iTable/?reqid=19&step=2&isuri=1&categories=survey&_gl=1*1r7rqrk*_ga*MTM3MDkyNjc3LjE3MDg2OTk4NjU.*_ga_J4698JNNFT*MTcwODk1ODU4NC4yLjEuMTcwODk2MDEzMy42MC4wLjA. | T6: Retrieved April 2024
A7: Compensation of Employees, Value Added of Wood Products (billion dollars) | B7: 21.2 | C7: 16.3 | D7: 15.9 | E7: 16.3 | F7: 16.7 | G7: 17.7 | H7: 19.4 | I7: 20.4 | J7: 21.1 | K7: 22.2 | L7: 23.537 | M7: 24.642 | N7: 25.438 | O7: 28.122 | P7: 31.358 | R7: Bureau of Economic Analysis | S7: [Table 6.2D] https://apps.bea.gov/iTable/?reqid=19&step=2&isuri=1&categories=survey&_gl=1*1r7rqrk*_ga*MTM3MDkyNjc3LjE3MDg2OTk4NjU.*_ga_J4698JNNFT*MTcwODk1ODU4NC4yLjEuMTcwODk2MDEzMy42MC4wLjA. | T7: Retrieved April 2024
A8: Taxes of Production and Imports, Less Subsides of US Wood Products (billion dollars) | B8: 0.7 | C8: 0.7 | D8: 0.7 | E8: 0.7 | F8: 0.7 | G8: 0.7 | H8: 0.7 | I8: 0.7 | J8: 0.7 | K8: 0.8 | L8: 0.8 | M8: 0.9 | N8: -1 | O8: 0.1 | P8: 1 | R8: Bureau of Economic Analysis | S8: https://apps.bea.gov/iTable/?reqid=150&step=2&isuri=1&categories=gdpxind&_gl=1*14rxqpt*_ga*MTM3MDkyNjc3LjE3MDg2OTk4NjU.*_ga_J4698JNNFT*MTcwODk1ODU4NC4yLjEuMTcwODk2MjUwMS42MC4wLjA.#eyJhcHBpZCI6MTUwLCJzdGVwcyI6WzEsMl0sImRhdGEiOltbImNhdGVnb3JpZXMiLCJDb21wQnlJbmQiXV19 | T8: Retrieved April 2024
A9: Gross Operating Surplus of Wood Products (billion dollars) | B9: 3.7 | C9: 4.2 | D9: 6.8 | E9: 6.7 | F9: 8.4 | G9: 12.1 | H9: 10.9 | I9: 11.4 | J9: 13.5 | K9: 12.7 | L9: 12.6 | M9: 11.3 | N9: 18.5 | O9: 31.9 | P9: 29.7 | R9: Bureau of Economic Analysis | S9: https://apps.bea.gov/iTable/?reqid=150&step=2&isuri=1&categories=gdpxind&_gl=1*14rxqpt*_ga*MTM3MDkyNjc3LjE3MDg2OTk4NjU.*_ga_J4698JNNFT*MTcwODk1ODU4NC4yLjEuMTcwODk2MjUwMS42MC4wLjA.#eyJhcHBpZCI6MTUwLCJzdGVwcyI6WzEsMl0sImRhdGEiOltbImNhdGVnb3JpZXMiLCJDb21wQnlJbmQiXV19 | T9: Retrieved April 2024
A10: Full and Part Time Employees (thousands) | B10: 456 | C10: 362 | D10: 342 | E10: 338 | F10: 341 | G10: 355 | H10: 371 | I10: 381 | J10: 391 | K10: 398 | L10: 406 | M10: 407 | N10: 396 | O10: 410 | P10: 428 | R10: Bureau of Economic Analysis | S10: [6.4D] https://apps.bea.gov/iTable/?reqid=19&step=2&isuri=1&categories=survey&_gl=1*1r7rqrk*_ga*MTM3MDkyNjc3LjE3MDg2OTk4NjU.*_ga_J4698JNNFT*MTcwODk1ODU4NC4yLjEuMTcwODk2MDEzMy42MC4wLjA. | T10: Retrieved April 2024
A12: US PAPER PRODUCTS (NAICS) | B12: 2008 | C12: 2009 | D12: 2010 | E12: 2011 | F12: 2012 | G12: 2013 | H12: 2014 | I12: 2015 | J12: 2016 | K12: 2017 | L12: 2018 | M12: 2019 | N12: 2020 | O12: 2021 | P12: 2022 | Q12: 2023 | R12: Source Name | S12: Source URL | T12: Comments
A13: U.S. Paper Products Value Added (billion dollars) | B13: 51.4 | C13: 59.3 | D13: 56.3 | E13: 53.7 | F13: 53 | G13: 56.3 | H13: 56.7 | I13: 59.7 | J13: 58.4 | K13: 55.2 | L13: 59.9 | M13: 61.2 | N13: 58 | O13: 64.375 | P13: 61.2 | Q13: 56.25 | R13: Bureau of Economic Analysis | S13: https://apps.bea.gov/iTable/?reqid=19&step=2&isuri=1&categories=survey&_gl=1*1r7rqrk*_ga*MTM3MDkyNjc3LjE3MDg2OTk4NjU.*_ga_J4698JNNFT*MTcwODk1ODU4NC4yLjEuMTcwODk2MDEzMy42MC4wLjA. | T13: Retrieved April 2024
A14: Value Added of Manufacturing US Paper Products as Percentage of GDP (%) | B14: 0.3 | C14: 0.4 | D14: 0.4 | E14: 0.3 | F14: 0.3 | G14: 0.3 | H14: 0.3 | I14: 0.3 | J14: 0.3 | K14: 0.3 | L14: 0.3 | M14: 0.3 | N14: 0.3 | O14: 0.3 | P14: 0.3 | Q14: 0.275 | R14: Bureau of Economic Analysis | S14: https://apps.bea.gov/iTable/?reqid=150&step=2&isuri=1&categories=gdpxind&_gl=1*14rxqpt*_ga*MTM3MDkyNjc3LjE3MDg2OTk4NjU.*_ga_J4698JNNFT*MTcwODk1ODU4NC4yLjEuMTcwODk2MjUwMS42MC4wLjA.#eyJhcHBpZCI6MTUwLCJzdGVwcyI6WzEsMiwzXSwiZGF0YSI6W1siY2F0ZWdvcmllcyIsIkdkcHhJbmQiXSxbIlRhYmxlX0xpc3QiLCIxNSJdXX0= | T14: Retrieved April 2024
A15: Gross Output of US Paper Products (billion dollars) | B15: 177.4 | C15: 160.5 | D15: 169.4 | E15: 175.6 | F15: 179 | G15: 183.8 | H15: 184.6 | I15: 182.9 | J15: 178.9 | K15: 180.8 | L15: 187.6 | M15: 189.3 | N15: 188.2 | O15: 196.35 | P15: 203.75 | Q15: 206.45 | R15: Bureau of Economic Analysis | S15: https://apps.bea.gov/iTable/?reqid=19&step=2&isuri=1&categories=survey&_gl=1*1r7rqrk*_ga*MTM3MDkyNjc3LjE3MDg2OTk4NjU.*_ga_J4698JNNFT*MTcwODk1ODU4NC4yLjEuMTcwODk2MDEzMy42MC4wLjA. | T15: Retrieved April 2024
A16: Compensation of Employees, Value Added of Paper Products (billion dollars) | B16: 31.2 | C16: 28.5 | D16: 28.9 | E16: 29.2 | F16: 29.1 | G16: 29.4 | H16: 29.8 | I16: 30.2 | J16: 30 | K16: 30.4 | L16: 31.315 | M16: 32.455 | N16: 32.02 | O16: 32.493 | P16: 34.83 | R16: Bureau of Economic Analysis | S16: [6.2D] https://apps.bea.gov/iTable/?reqid=19&step=2&isuri=1&categories=survey&_gl=1*1r7rqrk*_ga*MTM3MDkyNjc3LjE3MDg2OTk4NjU.*_ga_J4698JNNFT*MTcwODk1ODU4NC4yLjEuMTcwODk2MDEzMy42MC4wLjA. | T16: Retrieved April 2024
A17: Taxes of Production and Imports, Less Subsides of US Paper Products (billion dollars) | B17: 1.8 | C17: 1.9 | D17: 1.8 | E17: 1.8 | F17: 1.8 | G17: 1.8 | H17: 1.7 | I17: 1.7 | J17: 1.8 | K17: 1.8 | L17: 1.9 | M17: 2 | N17: 1 | O17: 1.8 | P17: 2.2 | R17: Bureau of Economic Analysis | S17: https://apps.bea.gov/iTable/?reqid=150&step=2&isuri=1&categories=gdpxind&_gl=1*14rxqpt*_ga*MTM3MDkyNjc3LjE3MDg2OTk4NjU.*_ga_J4698JNNFT*MTcwODk1ODU4NC4yLjEuMTcwODk2MjUwMS42MC4wLjA.#eyJhcHBpZCI6MTUwLCJzdGVwcyI6WzEsMl0sImRhdGEiOltbImNhdGVnb3JpZXMiLCJDb21wQnlJbmQiXV19 | T17: Retrieved April 2024
A18: Gross Operating Surplus of Paper Products (billion dollars) | B18: 18.3 | C18: 28.9 | D18: 25.6 | E18: 22.7 | F18: 22.1 | G18: 25.2 | H18: 25.3 | I18: 27.8 | J18: 26.6 | K18: 23 | L18: 27.3 | M18: 27.7 | N18: 31.9 | O18: 30.3 | P18: 32.1 | R18: Bureau of Economic Analysis | S18: https://apps.bea.gov/iTable/?reqid=150&step=2&isuri=1&categories=gdpxind&_gl=1*14rxqpt*_ga*MTM3MDkyNjc3LjE3MDg2OTk4NjU.*_ga_J4698JNNFT*MTcwODk1ODU4NC4yLjEuMTcwODk2MjUwMS42MC4wLjA.#eyJhcHBpZCI6MTUwLCJzdGVwcyI6WzEsMl0sImRhdGEiOltbImNhdGVnb3JpZXMiLCJDb21wQnlJbmQiXV19 | T18: Retrieved April 2024
A19: Full and Part Time Employees (thousands) | B19: 442 | C19: 406 | D19: 394 | E19: 388 | F19: 380 | G19: 377 | H19: 373 | I19: 372 | J19: 370 | K19: 368 | L19: 367 | M19: 373 | N19: 355 | O19: 354 | P19: 367 | R19: Bureau of Economic Analysis | S19: [6.4D] https://apps.bea.gov/iTable/?reqid=19&step=2&isuri=1&categories=survey&_gl=1*1r7rqrk*_ga*MTM3MDkyNjc3LjE3MDg2OTk4NjU.*_ga_J4698JNNFT*MTcwODk1ODU4NC4yLjEuMTcwODk2MDEzMy42MC4wLjA. | T19: Retrieved April 2024
A21: Forest Products | B21: 2008 | C21: 2009 | D21: 2010 | E21: 2011 | F21: 2012 | G21: 2013 | H21: 2014 | I21: 2015 | J21: 2016 | K21: 2017 | L21: 2018 | M21: 2019 | N21: 2020 | O21: 2021 | P21: 2022 | Q21: 2023 | R21: Source Name | S21: Source URL | T21: Comments
A22: Wood fuel (million m3) | B22: 43.613844 | C22: 40.436676 | D22: 40.436676 | E22: 40.436676 | F22: 40.436 | G22: 41.880843 | H22: 41.880843 | I22: 44.345 | J22: 62.156 | K22: 64.37 | L22: 71.608562 | M22: 71.426931 | N22: 60.52536 | O22: 71.11054 | P22: 72.369 | Q22: 66.026 | R22: FAOSTAT | S22: http://www.fao.org/faostat/en/#data/FO | T22: Retrieved February 2025
A23: Wood residues ( million m3) | B23: 15.409 | C23: 9.706 | D23: 11.757 | E23: 11.654 | F23: 12.328 | G23: 13.198 | H23: 13.8 | I23: 13.8 | J23: 13.8 | K23: 14.275 | L23: 14.818026 | M23: 15.288915 | N23: 13.241628 | O23: 16.27606 | P23: 9.515616 | Q23: 9.659327 | R23: FAOSTAT | S23: http://www.fao.org/faostat/en/#data/FO | T23: Retrieved February 2025
A24: Roundwood (million m3) | B24: 380.50884 | C24: 332.52768 | D24: 376.57168 | E24: 395.14068 | F24: 387.512 | G24: 396.81784 | H24: 398.69275 | I24: 399.02341 | J24: 436.632 | K24: 436.69138 | L24: 464.11815 | M24: 459.12888 | N24: 430 | O24: 453.446 | P24: 456.32969 | Q24: 412.29133 | R24: FAOSTAT | S24: http://www.fao.org/faostat/en/#data/FO | T24: Retrieved February 2025
A25: Sawnwood (million m3) | B25: 72.86928 | C25: 54.276 | D25: 60.0134 | E25: 63.1738 | F25: 67.474 | G25: 71.115 | H25: 75.8333 | I25: 76.362 | J25: 78.165 | K25: 80.374 | L25: 81.9976 | M25: 82.4717 | N25: 79.133603 | O25: 80.705 | P25: 81.637 | Q25: 77.872 | R25: FAOSTAT | S25: http://www.fao.org/faostat/en/#data/FO | T25: Retrieved February 2025
A26: Wood-based panels (million m3) | B26: 35.17645 | C26: 33.965789 | D26: 32.19228 | E26: 31.649823 | F26: 31.059 | G26: 33.06239 | H26: 35.05954 | I26: 35.258505 | J26: 35.95673 | K26: 36.20091 | L26: 34.244962 | M26: 34.353377 | N26: 33.110844 | O26: 34.651024 | P26: 33.322828 | Q26: 31.394901 | R26: FAOSTAT | S26: http://www.fao.org/faostat/en/#data/FO | T26: Retrieved February 2025
A27: Wood fuel (million tonnes) | B27: =+B22*1.38 -> 60.187105 | C27: =+C22*1.38 -> 55.802613 | D27: =+D22*1.38 -> 55.802613 | E27: =+E22*1.38 -> 55.802613 | F27: =+F22*1.38 -> 55.80168 | G27: =+G22*1.38 -> 57.795563 | H27: =+H22*1.38 -> 57.795563 | I27: =+I22*1.38 -> 61.1961 | ... Q27: =+Q22*1.38 -> 91.11588 | R27: Calculation | T27: Retrieved February 2025
A28: Wood residues ( mililon tonnes) | B28: =+B23*1.48 -> 22.80532 | C28: =+C23*1.48 -> 14.36488 | D28: =+D23*1.48 -> 17.40036 | E28: =+E23*1.48 -> 17.24792 | F28: =+F23*1.48 -> 18.24544 | G28: =+G23*1.48 -> 19.53304 | H28: =+H23*1.48 -> 20.424 | I28: =+I23*1.48 -> 20.424 | ... Q28: =+Q23*1.48 -> 14.295804 | R28: Calculation | T28: Retrieved February 2025
A29: Roundwood (million tonnes) | B29: =+B24*1.43 -> 544.12765 | C29: =+C24*1.43 -> 475.51458 | D29: =+D24*1.43 -> 538.4975 | E29: =+E24*1.43 -> 565.05117 | F29: =+F24*1.43 -> 554.14216 | G29: =+G24*1.43 -> 567.44952 | H29: =+H24*1.43 -> 570.13063 | I29: =+I24*1.43 -> 570.60348 | ... Q29: =+Q24*1.43 -> 589.5766 | R29: Calculation | T29: Retrieved February 2025
A30: Sawnwood (million tonnes) | B30: =+B25*1.82 -> 132.62209 | C30: =+C25*1.82 -> 98.78232 | D30: =+D25*1.82 -> 109.22439 | E30: =+E25*1.82 -> 114.97632 | F30: =+F25*1.82 -> 122.80268 | G30: =+G25*1.82 -> 129.4293 | H30: =+H25*1.82 -> 138.01661 | I30: =+I25*1.82 -> 138.97884 | ... Q30: =+Q25*1.82 -> 141.72704 | R30: Calculation | T30: Retrieved February 2025
A31: Wood-based panels (million tonnes) | B31: =+B26*1.3 -> 45.729385 | C31: =+C26*1.3 -> 44.155526 | D31: =+D26*1.3 -> 41.849964 | E31: =+E26*1.3 -> 41.14477 | F31: =+F26*1.3 -> 40.3767 | G31: =+G26*1.3 -> 42.981107 | H31: =+H26*1.3 -> 45.577402 | I31: =+I26*1.3 -> 45.836056 | ... Q31: =+Q26*1.3 -> 40.813371 | R31: Calculation | T31: Retrieved February 2025
A32: Wood pulp (million tonnes) | B32: 52.898853 | C32: 49.045972 | D32: 50.905939 | E32: 51.114622 | F32: 50.20053 | G32: 49.0551 | H32: 50.10664 | I32: 49.36821 | J32: 49.53443 | K32: 49.247516 | L32: 53.233456 | M32: 52.061998 | N32: 51 | O32: 49.718 | P32: 49.017673 | Q32: 47.981531 | R32: FAOSTAT | S32: http://www.fao.org/faostat/en/#data/FO | T32: Retrieved February 2025
A33: Paper and paperboard (million tonnes) | B33: 80.178382 | C33: 71.355455 | D33: 75.772845 | E33: 76.430822 | F33: 74.492 | G33: 71.732298 | H33: 73.093 | I33: 72.397 | J33: 71.902239 | K33: 72.044539 | L33: 70.891067 | M33: 68.15681 | N33: 66 | O33: 67 | P33: 65.507164 | Q33: 60.674376 | R33: FAOSTAT | S33: http://www.fao.org/faostat/en/#data/FO | T33: Retrieved February 2025
A34: Wood pellets (million tonnes) | F34: 3.474 | G34: 4.704 | H34: 5.947 | I34: 6.517 | J34: 6.393 | K34: 6.9 | L34: 7.468361 | M34: 8.592713 | N34: 8.412359 | O34: 8.4486 | P34: 9.544 | Q34: 9.820703 | R34: FAOSTAT | S34: http://www.fao.org/faostat/en/#data/FO | T34: Retrieved February 2025
A35: Forest products Imports (billion dollars) | B35: 24.327525 | C35: 17.122792 | D35: 19.542151 | E35: 19.527676 | F35: 20.752316 | G35: 22.952586 | H35: 24.61398 | I35: 23.685321 | J35: 24.078761 | K35: 24.938866 | L35: 26.90665 | M35: 23.306733 | N35: 24.606244 | O35: 36.694449 | P35: 39.159768 | Q35: 27.151341 | R35: FAOSTAT | S35: http://www.fao.org/faostat/en/#data/FO | T35: Retrieved February 2025
A36: Forest products Exports (billion dollars) | B36: 21.274008 | C36: 19.14826 | D36: 22.923905 | E36: 25.250957 | F36: 25.605682 | G36: 26.595675 | H36: 27.234076 | I36: 25.149516 | J36: 24.636383 | K36: 27.08495 | L36: 28.2969 | M36: 24.441916 | N36: 22.364104 | O36: 27.051831 | P36: 29.972067 | Q36: 25.010582 | R36: FAOSTAT | S36: http://www.fao.org/faostat/en/#data/FO | T36: Retrieved February 2025

Sheet FUNDING
A1: FUNDING
A3: NIFA | B3: 2010 | C3: 2011 | D3: 2012 | E3: 2013 | F3: 2014 | G3: 2015 | H3: 2016 | I3: 2017 | J3: 2018 | K3: 2019 | L3: 2020 | M3: 2021 | N3: 2022 | O3: 2023 | P3: Source Name | Q3: Source URL | R3: Comments
A4: Keyword
A5: Ethanol | B5: 269 | C5: 143 | D5: 147 | E5: 150 | F5: 165 | G5: 151 | H5: 107 | I5: 132 | J5: 133 | K5: 141 | L5: 104 | M5: 118 | N5: 42 | O5: 48 | P5: USDA | Q5: https://portal.nifa.usda.gov/enterprise-search/project_details | R5: Retrieved February 2025
A6: Biodiesel | B6: 99 | C6: 52 | D6: 50 | E6: 45 | F6: 49 | G6: 23 | H6: 16 | I6: 21 | J6: 23 | K6: 29 | L6: 11 | M6: 6 | N6: 3 | O6: 6 | P6: USDA | Q6: https://portal.nifa.usda.gov/enterprise-search/project_details | R6: Retrieved February 2025
A7: Renewable diesel | B7: 2 | C7: 1 | D7: 2 | E7: 0 | F7: 1 | G7: 0 | H7: 0 | I7: 2 | J7: 0 | K7: 3 | L7: 0 | M7: 4 | N7: 2 | O7: 0 | P7: USDA | Q7: https://portal.nifa.usda.gov/enterprise-search/project_details | R7: Retrieved February 2025
A8: Renewable Jet fuel | B8: 1 | C8: 14 | D8: 22 | E8: 14 | F8: 18 | G8: 17 | H8: 16 | I8: 21 | J8: 14 | K8: 14 | L8: 11 | M8: 5 | N8: 6 | O8: 5 | P8: USDA | Q8: https://portal.nifa.usda.gov/enterprise-search/project_details | R8: Retrieved February 2025
A9: Recycled greases | B9: 0 | C9: 1 | D9: 1 | E9: 0 | F9: 1 | G9: 0 | H9: 0 | I9: 0 | J9: 0 | K9: 0 | L9: 0 | M9: 0 | N9: 0 | O9: 0 | P9: USDA | Q9: https://portal.nifa.usda.gov/enterprise-search/project_details | R9: Retrieved February 2025
A10: Animal Fats | B10: 1 | C10: 3 | D10: 4 | E10: 4 | F10: 3 | G10: 0 | H10: 3 | I10: 0 | J10: 0 | K10: 3 | L10: 0 | M10: 0 | N10: 0 | O10: 0 | P10: USDA | Q10: https://portal.nifa.usda.gov/enterprise-search/project_details | R10: Retrieved February 2025
A11: Wood pellets | B11: 7 | C11: 4 | D11: 5 | E11: 6 | F11: 4 | G11: 2 | H11: 4 | I11: 6 | J11: 5 | K11: 3 | L11: 4 | M11: 0 | N11: 0 | O11: 0 | P11: USDA | Q11: https://portal.nifa.usda.gov/enterprise-search/project_details | R11: Retrieved February 2025
A12: Waste to energy | B12: 5 | C12: 3 | D12: 4 | E12: 3 | F12: 4 | G12: 2 | H12: 1 | I12: 3 | J12: 2 | K12: 4 | L12: 3 | M12: 3 | N12: 1 | O12: 1 | P12: USDA | Q12: https://portal.nifa.usda.gov/enterprise-search/project_details | R12: Retrieved February 2025
A13: Biogas | B13: 27 | C13: 23 | D13: 15 | E13: 16 | F13: 23 | G13: 13 | H13: 19 | I13: 16 | J13: 12 | K13: 20 | L13: 15 | M13: 9 | N13: 9 | O13: 12 | P13: USDA | Q13: https://portal.nifa.usda.gov/enterprise-search/project_details | R13: Retrieved February 2025
A14: Bioproducts | B14: 68 | C14: 54 | D14: 36 | E14: 37 | F14: 53 | G14: 33 | H14: 32 | I14: 42 | J14: 37 | K14: 42 | L14: 27 | M14: 18 | N14: 15 | O14: 22 | P14: USDA | Q14: https://portal.nifa.usda.gov/enterprise-search/project_details | R14: Retrieved February 2025
A15: Bioplastics | B15: 11 | C15: 5 | D15: 7 | E15: 5 | F15: 6 | G15: 3 | H15: 8 | I15: 5 | J15: 8 | K15: 10 | L15: 4 | M15: 5 | N15: 8 | O15: 8 | P15: USDA | Q15: https://portal.nifa.usda.gov/enterprise-search/project_details | R15: Retrieved February 2025
A16: Biochemicals | B16: 14 | C16: 16 | D16: 10 | E16: 10 | F16: 13 | G16: 5 | H16: 6 | I16: 6 | J16: 11 | K16: 8 | L16: 4 | M16: 6 | N16: 2 | O16: 3 | P16: USDA | Q16: https://portal.nifa.usda.gov/enterprise-search/project_details | R16: Retrieved February 2025
... A18: NSF | B18: 2010 | C18: 2011 | D18: 2012 | E18: 2013 | F18: 2014 | G18: 2015 | H18: 2016 | I18: 2017 | J18: 2018 | K18: 2019 | L18: 2020 | M18: 2021 | N18: 2022 | O18: 2023 | P18: Source Name | Q18: Source URL | R18: Comments
A19: Keyword
A20: Ethanol | B20: 34 | C20: 22 | D20: 37 | E20: 26 | F20: 26 | G20: 24 | H20: 23 | I20: 16 | J20: 14 | K20: 14 | L20: 15 | M20: 16 | N20: 6 | O20: 14 | P20: NSF | Q20: https://www.nsf.gov/awardsearch/advancedSearch.jsp | R20: Retrieved February 2025
A21: Biodiesel | B21: 24 | C21: 19 | D21: 14 | E21: 11 | F21: 9 | G21: 13 | H21: 10 | I21: 2 | J21: 3 | K21: 3 | L21: 3 | M21: 4 | N21: 3 | O21: 3 | P21: NSF | Q21: https://www.nsf.gov/awardsearch/advancedSearch.jsp | R21: Retrieved February 2025
A22: Renewable diesel | B22: 1 | C22: 1 | D22: 0 | E22: 1 | F22: 1 | G22: 0 | H22: 0 | I22: 0 | J22: 0 | K22: 0 | L22: 0 | M22: 0 | N22: 1 | O22: 0 | P22: NSF | Q22: https://www.nsf.gov/awardsearch/advancedSearch.jsp | R22: Retrieved February 2025
A23: Renewable Jet fuel | B23: 0 | C23: 0 | D23: 0 | E23: 0 | F23: 0 | G23: 0 | H23: 0 | I23: 0 | J23: 0 | K23: 0 | L23: 0 | M23: 0 | N23: 0 | O23: 2 | P23: NSF | Q23: https://www.nsf.gov/awardsearch/advancedSearch.jsp | R23: Retrieved February 2025
A24: Recycled greases | B24: 0 | C24: 0 | D24: 0 | E24: 0 | F24: 0 | G24: 0 | H24: 0 | I24: 0 | J24: 0 | K24: 0 | L24: 0 | M24: 0 | N24: 0 | O24: 0 | P24: NSF | Q24: https://www.nsf.gov/awardsearch/advancedSearch.jsp | R24: Retrieved February 2025
A25: Animal Fats | B25: 1 | C25: 0 | D25: 0 | E25: 0 | F25: 1 | G25: 0 | H25: 1 | I25: 0 | J25: 0 | K25: 0 | L25: 2 | M25: 0 | N25: 0 | O25: 0 | P25: NSF | Q25: https://www.nsf.gov/awardsearch/advancedSearch.jsp | R25: Retrieved February 2025
A26: Wood pellets | B26: 0 | C26: 1 | D26: 0 | E26: 0 | F26: 0 | G26: 0 | H26: 2 | I26: 0 | J26: 1 | K26: 0 | L26: 0 | M26: 0 | N26: 0 | O26: 0 | P26: NSF | Q26: https://www.nsf.gov/awardsearch/advancedSearch.jsp | R26: Retrieved February 2025
A27: Waste to energy | B27: 1 | C27: 0 | D27: 0 | E27: 1 | F27: 0 | G27: 0 | H27: 3 | I27: 0 | J27: 3 | K27: 3 | L27: 0 | M27: 0 | N27: 3 | O27: 1 | P27: NSF | Q27: https://www.nsf.gov/awardsearch/advancedSearch.jsp | R27: Retrieved February 2025
A28: Biogas | B28: 7 | C28: 4 | D28: 8 | E28: 7 | F28: 8 | G28: 1 | H28: 5 | I28: 4 | J28: 1 | K28: 5 | L28: 5 | M28: 6 | N28: 8 | O28: 8 | P28: NSF | Q28: https://www.nsf.gov/awardsearch/advancedSearch.jsp | R28: Retrieved February 2025
A29: Bioproducts | B29: 1 | C29: 6 | D29: 8 | E29: 4 | F29: 2 | G29: 10 | H29: 6 | I29: 3 | J29: 4 | K29: 6 | L29: 5 | M29: 7 | N29: 7 | O29: 9 | P29: NSF | Q29: https://www.nsf.gov/awardsearch/advancedSearch.jsp | R29: Retrieved February 2025
A30: Bioplastics | B30: 6 | C30: 1 | D30: 3 | E30: 13 | F30: 10 | G30: 4 | H30: 5 | I30: 6 | J30: 7 | K30: 4 | L30: 5 | M30: 10 | N30: 6 | O30: 11 | P30: NSF | Q30: https://www.nsf.gov/awardsearch/advancedSearch.jsp | R30: Retrieved February 2025
A31: Biochemicals | B31: 2 | C31: 6 | D31: 4 | E31: 8 | F31: 4 | G31: 7 | H31: 4 | I31: 4 | J31: 8 | K31: 1 | L31: 2 | M31: 5 | N31: 2 | O31: 6 | P31: NSF | Q31: https://www.nsf.gov/awardsearch/advancedSearch.jsp | R31: Retrieved February 2025
... A33: NIFA+NSF | B33: 2010 | C33: 2011 | D33: 2012 | E33: 2013 | F33: 2014 | G33: 2015 | H33: 2016 | I33: 2017 | J33: 2018 | K33: 2019 | L33: 2020 | M33: 2021 | N33: 2022 | O33: 2023 | P33: Source Name | Q33: Source URL | R33: Comments
A34: Keyword
A35: Ethanol | B35: =+B5+B20 -> 303 | C35: =+C5+C20 -> 165 | D35: =+D5+D20 -> 184 | E35: =+E5+E20 -> 176 | F35: =+F5+F20 -> 191 | G35: =+G5+G20 -> 175 | H35: =+H5+H20 -> 130 | I35: =+I5+I20 -> 148 | ... O35: =+O5+O20 -> 62 | P35: NSF | Q35: https://www.nsf.gov/awardsearch/advancedSearch.jsp | R35: Retrieved February 2025
A36: Biodiesel | B36: =+B6+B21 -> 123 | C36: =+C6+C21 -> 71 | D36: =+D6+D21 -> 64 | E36: =+E6+E21 -> 56 | F36: =+F6+F21 -> 58 | G36: =+G6+G21 -> 36 | H36: =+H6+H21 -> 26 | I36: =+I6+I21 -> 23 | ... O36: =+O6+O21 -> 9 | P36: NSF | Q36: https://www.nsf.gov/awardsearch/advancedSearch.jsp | R36: Retrieved February 2025
A37: Renewable diesel | B37: =+B7+B22 -> 3 | C37: =+C7+C22 -> 2 | D37: =+D7+D22 -> 2 | E37: =+E7+E22 -> 1 | F37: =+F7+F22 -> 2 | G37: =+G7+G22 -> 0 | H37: =+H7+H22 -> 0 | I37: =+I7+I22 -> 2 | ... O37: =+O7+O22 -> 0 | P37: NSF | Q37: https://www.nsf.gov/awardsearch/advancedSearch.jsp | R37: Retrieved February 2025
A38: Renewable Jet fuel | B38: =+B8+B23 -> 1 | C38: =+C8+C23 -> 14 | D38: =+D8+D23 -> 22 | E38: =+E8+E23 -> 14 | F38: =+F8+F23 -> 18 | G38: =+G8+G23 -> 17 | H38: =+H8+H23 -> 16 | I38: =+I8+I23 -> 21 | ... O38: =+O8+O23 -> 7 | P38: NSF | Q38: https://www.nsf.gov/awardsearch/advancedSearch.jsp | R38: Retrieved February 2025
A39: Recycled greases | B39: =+B9+B24 -> 0 | C39: =+C9+C24 -> 1 | D39: =+D9+D24 -> 1 | E39: =+E9+E24 -> 0 | F39: =+F9+F24 -> 1 | G39: =+G9+G24 -> 0 | H39: =+H9+H24 -> 0 | I39: =+I9+I24 -> 0 | ... O39: =+O9+O24 -> 0 | P39: NSF | Q39: https://www.nsf.gov/awardsearch/advancedSearch.jsp | R39: Retrieved February 2025
A40: Animal Fats | B40: =+B10+B25 -> 2 | C40: =+C10+C25 -> 3 | D40: =+D10+D25 -> 4 | E40: =+E10+E25 -> 4 | F40: =+F10+F25 -> 4 | G40: =+G10+G25 -> 0 | H40: =+H10+H25 -> 4 | I40: =+I10+I25 -> 0 | ... O40: =+O10+O25 -> 0 | P40: NSF | Q40: https://www.nsf.gov/awardsearch/advancedSearch.jsp | R40: Retrieved February 2025
A41: Wood pellets | B41: =+B11+B26 -> 7 | C41: =+C11+C26 -> 5 | D41: =+D11+D26 -> 5 | E41: =+E11+E26 -> 6 | F41: =+F11+F26 -> 4 | G41: =+G11+G26 -> 2 | H41: =+H11+H26 -> 6 | I41: =+I11+I26 -> 6 | ... O41: =+O11+O26 -> 0 | P41: NSF | Q41: https://www.nsf.gov/awardsearch/advancedSearch.jsp | R41: Retrieved February 2025
A42: Waste to energy | B42: =+B12+B27 -> 6 | C42: =+C12+C27 -> 3 | D42: =+D12+D27 -> 4 | E42: =+E12+E27 -> 4 | F42: =+F12+F27 -> 4 | G42: =+G12+G27 -> 2 | H42: =+H12+H27 -> 4 | I42: =+I12+I27 -> 3 | ... O42: =+O12+O27 -> 2 | P42: NSF | Q42: https://www.nsf.gov/awardsearch/advancedSearch.jsp | R42: Retrieved February 2025
A43: Biogas | B43: =+B13+B28 -> 34 | C43: =+C13+C28 -> 27 | D43: =+D13+D28 -> 23 | E43: =+E13+E28 -> 23 | F43: =+F13+F28 -> 31 | G43: =+G13+G28 -> 14 | H43: =+H13+H28 -> 24 | I43: =+I13+I28 -> 20 | ... O43: =+O13+O28 -> 20 | P43: NSF | Q43: https://www.nsf.gov/awardsearch/advancedSearch.jsp | R43: Retrieved February 2025
A44: Bioproducts | B44: =+B14+B29 -> 69 | C44: =+C14+C29 -> 60 | D44: =+D14+D29 -> 44 | E44: =+E14+E29 -> 41 | F44: =+F14+F29 -> 55 | G44: =+G14+G29 -> 43 | H44: =+H14+H29 -> 38 | I44: =+I14+I29 -> 45 | ... O44: =+O14+O29 -> 31 | P44: NSF | Q44: https://www.nsf.gov/awardsearch/advancedSearch.jsp | R44: Retrieved February 2025
A45: Bioplastics | B45: =+B15+B30 -> 17 | C45: =+C15+C30 -> 6 | D45: =+D15+D30 -> 10 | E45: =+E15+E30 -> 18 | F45: =+F15+F30 -> 16 | G45: =+G15+G30 -> 7 | H45: =+H15+H30 -> 13 | I45: =+I15+I30 -> 11 | ... O45: =+O15+O30 -> 19 | P45: NSF | Q45: https://www.nsf.gov/awardsearch/advancedSearch.jsp | R45: Retrieved February 2025
A46: Biochemicals | B46: =+B16+B31 -> 16 | C46: =+C16+C31 -> 22 | D46: =+D16+D31 -> 14 | E46: =+E16+E31 -> 18 | F46: =+F16+F31 -> 17 | G46: =+G16+G31 -> 12 | H46: =+H16+H31 -> 10 | I46: =+I16+I31 -> 10 | ... O46: =+O16+O31 -> 9 | P46: NSF | Q46: https://www.nsf.gov/awardsearch/advancedSearch.jsp | R46: Retrieved February 2025
A47: Biofuels | B47: =+B17+B32 -> 387 | C47: =+C17+C32 -> 327 | D47: =+D17+D32 -> 267 | E47: =+E17+E32 -> 233 | F47: =+F17+F32 -> 233 | G47: =+G17+G32 -> 185 | H47: =+H17+H32 -> 144 | I47: =+I17+I32 -> 136 | ... O47: =+O17+O32 -> 42 | P47: NSF | Q47: https://www.nsf.gov/awardsearch/advancedSearch.jsp | R47: Retrieved February 2025
A48: Traditional biofuel | B48: =B35+B36+B41+B42+B43 -> 473 | C48: =C35+C36+C41+C42+C43 -> 271 | D48: =D35+D36+D41+D42+D43 -> 280 | E48: =E35+E36+E41+E42+E43 -> 265 | F48: =F35+F36+F41+F42+F43 -> 288 | G48: =G35+G36+G41+G42+G43 -> 229 | H48: =H35+H36+H41+H42+H43 -> 190 | I48: =I35+I36+I41+I42+I43 -> 200 | ... O48: =O35+O36+O41+O42+O43 -> 93
A49: Emergent biofuel | B49: =B37+B38+B39+B40 -> 6 | C49: =C37+C38+C39+C40 -> 20 | D49: =D37+D38+D39+D40 -> 29 | E49: =E37+E38+E39+E40 -> 19 | F49: =F37+F38+F39+F40 -> 25 | G49: =G37+G38+G39+G40 -> 17 | H49: =H37+H38+H39+H40 -> 20 | I49: =I37+I38+I39+I40 -> 23 | ... O49: =O37+O38+O39+O40 -> 7
A50: Bioproducts | B50: =B44+B45+B46 -> 102 | C50: =C44+C45+C46 -> 88 | D50: =D44+D45+D46 -> 68 | E50: =E44+E45+E46 -> 77 | F50: =F44+F45+F46 -> 88 | G50: =G44+G45+G46 -> 62 | H50: =H44+H45+H46 -> 61 | I50: =I44+I45+I46 -> 66 | ... O50: =O44+O45+O46 -> 59
A52: Amount awarded 2023 NIFA | B52: Ethanol | C52: Biodiesel | D52: Renewable diesel | E52: Sustainable aviation fuel | F52: Recycled greases | G52: Animal Fats | H52: Wood pellets | I52: Waste to energy | J52: Biogas | K52: Bioproducts | L52: Bioplastics | M52: Biochemicals | N52: Biofuels | P52: Source Name | Q52: Source URL | R52: Comments
A53: 0-250K | B53: 17 | C53: 2 | D53: 0 | E53: 2 | F53: 0 | G53: 0 | H53: 0 | I53: 0 | J53: 4 | K53: 3 | L53: 2 | M53: 0 | N53: 6 | P53: USDA | Q53: https://portal.nifa.usda.gov/enterprise-search/project_details | R53: Retrieved February 2025
A54: 250K-500K | B54: 13 | C54: 1 | D54: 0 | E54: 0 | F54: 0 | G54: 0 | H54: 0 | I54: 0 | J54: 2 | K54: 3 | L54: 2 | M54: 2 | N54: 3 | P54: USDA | Q54: https://portal.nifa.usda.gov/enterprise-search/project_details | R54: Retrieved February 2025
A55: 500K-1M | B55: 15 | C55: 2 | D55: 0 | E55: 2 | F55: 0 | G55: 0 | H55: 0 | I55: 1 | J55: 4 | K55: 12 | L55: 3 | M55: 1 | N55: 7 | P55: USDA | Q55: https://portal.nifa.usda.gov/enterprise-search/project_details | R55: Retrieved February 2025
A56: >1M | B56: 3 | C56: 1 | D56: 0 | E56: 1 | F56: 0 | G56: 0 | H56: 0 | I56: 0 | J56: 2 | K56: 4 | L56: 1 | M56: 0 | N56: 1 | P56: USDA | Q56: https://portal.nifa.usda.gov/enterprise-search/project_details | R56: Retrieved February 2025
A57: Amount awarded 2023 NSF | B57: Ethanol | C57: Biodiesel | D57: Renewable diesel | E57: Sustainable aviation fuel | F57: Recycled greases | G57: Animal Fats | H57: Wood pellets | I57: Waste to energy | J57: Biogas | K57: Bioproducts | L57: Bioplastics | M57: Biochemicals | N57: Biofuels | P57: Source Name | Q57: Source URL | R57: Comments
A58: <50K | B58: 0 | C58: 0 | D58: 0 | E58: 0 | F58: 0 | G58: 0 | H58: 0 | I58: 0 | J58: 0 | K58: 2 | L58: 0 | M58: 0 | N58: 4 | P58: NSF | Q58: https://portal.nifa.usda.gov/enterprise-search/project_details | R58: Retrieved February 2025
A59: 50K-100K | B59: 0 | C59: 0 | D59: 0 | E59: 0 | F59: 0 | G59: 0 | H59: 0 | I59: 0 | J59: 0 | K59: 1 | L59: 0 | M59: 1 | N59: 2 | P59: NSF | Q59: https://portal.nifa.usda.gov/enterprise-search/project_details | R59: Retrieved February 2025
A60: 100K-500K | B60: 12 | C60: 3 | D60: 0 | E60: 1 | F60: 0 | G60: 0 | H60: 0 | I60: 0 | J60: 5 | K60: 0 | L60: 5 | M60: 1 | N60: 11 | P60: NSF | Q60: https://portal.nifa.usda.gov/enterprise-search/project_details | R60: Retrieved February 2025
A61: 500K-1M | B61: 2 | C61: 0 | D61: 0 | E61: 1 | F61: 0 | G61: 0 | H61: 0 | I61: 0 | J61: 2 | K61: 5 | L61: 3 | M61: 2 | N61: 5 | P61: NSF | Q61: https://portal.nifa.usda.gov/enterprise-search/project_details | R61: Retrieved February 2025
A62: >1M | B62: 0 | C62: 0 | D62: 0 | E62: 0 | F62: 0 | G62: 0 | H62: 0 | I62: 1 | J62: 1 | K62: 1 | L62: 3 | M62: 2 | N62: 3 | P62: NSF | Q62: https://portal.nifa.usda.gov/enterprise-search/project_details | R62: Retrieved February 2025

Sheet CSC
A1: State | B1: Number of projects | C1: Major Commodities | D1: CSC Practices | E1: Federal Funding | F1: B$ | G1: Dairy and livestock | H1: Row and energy crops | I1: Fruits, vegetables and specialty crops | J1: Forests and agroforestry
A2: California | B2: =(SUM(G2:J2)) -> 37 | C2: 53 | D2: 155 | E2: 1100 | F2: =E2/1000 -> 1.1 | G2: 11.583333 | H2: 9.4166667 | I2: 10.083333 | J2: 5.9166667 | L2: Total unding for all projects that potentially impact this area, commodities, practices, and projects as filtered.
A3: Missouri | B3: =(SUM(G3:J3)) -> 37 | C3: 44 | D3: 129 | E3: 1280 | F3: =E3/1000 -> 1.28 | G3: 12.5 | H3: 14.5 | I3: 6 | J3: 4 | L3: https://publicdashboards.dl.usda.gov/t/FPAC_PUB/views/PartnershipsForClimate-SmartCommodities/Overview?%3Aembed=y&%3AisGuestRedirectFromVizportal=y&%3Atoolbar=top
A4: New York | B4: =(SUM(G4:J4)) -> 32 | C4: 55 | D4: 128 | E4: 1060 | F4: =E4/1000 -> 1.06 | G4: 14.166667 | H4: 6 | I4: 3.8333333 | J4: 8
A5: Texas | B5: =(SUM(G5:J5)) -> 32 | C5: 41 | D5: 141 | E5: 1110 | F5: =E5/1000 -> 1.11 | G5: 13.666667 | H5: 12.166667 | I5: 3.1666667 | J5: 3
A6: Virginia | B6: =(SUM(G6:J6)) -> 32 | C6: 55 | D6: 88 | E6: 947.37 | F6: =E6/1000 -> 0.94737 | G6: 12.166667 | H6: 7.6666667 | I6: 5.6666667 | J6: 6.5
A7: Iowa | B7: =(SUM(G7:J7)) -> 31 | C7: 46 | D7: 114 | E7: 1110 | F7: =E7/1000 -> 1.11 | G7: 11.583333 | H7: 12.083333 | I7: 4.4166667 | J7: 2.9166667
A8: Minnesota | B8: =(SUM(G8:J8)) -> 31 | C8: 49 | D8: 126 | E8: 1210 | F8: =E8/1000 -> 1.21 | G8: 12.333333 | H8: 11.333333 | I8: 2.6666667 | J8: 4.6666667
A9: Pennsylvania | B9: =(SUM(G9:J9)) -> 31 | C9: 49 | D9: 96 | E9: 917.96 | F9: =E9/1000 -> 0.91796 | G9: 13.166667 | H9: 6 | I9: 4.8333333 | J9: 7
A10: Mississippi | B10: =(SUM(G10:J10)) -> 30 | C10: 48 | D10: 129 | E10: 948.02 | F10: =E10/1000 -> 0.94802 | G10: 10.25 | H10: 10.416667 | I10: 6.75 | J10: 2.5833333
A11: Oklahoma | B11: =(SUM(G11:J11)) -> 30 | C11: 46 | D11: 120 | E11: 989.9 | F11: =E11/1000 -> 0.9899 | G11: 12.583333 | H11: 7.5833333 | I11: 5.4166667 | J11: 4.4166667
A12: North Carolina | B12: =(SUM(G12:J12)) -> 30 | C12: 49 | D12: 112 | E12: 1020 | F12: =E12/1000 -> 1.02 | G12: 11.583333 | H12: 6.75 | I12: 5.0833333 | J12: 6.5833333
A13: Wisconsin | B13: =(SUM(G13:J13)) -> 29 | C13: 47 | D13: 118 | E13: 1090 | F13: =E13/1000 -> 1.09 | G13: 11.333333 | H13: 9.8333333 | I13: 3.6666667 | J13: 4.1666667
A14: Georgia | B14: =(SUM(G14:J14)) -> 29 | C14: 46 | D14: 114 | E14: 925.2 | F14: =E14/1000 -> 0.9252 | G14: 9.1666667 | H14: 6.8333333 | I14: 8.8333333 | J14: 4.1666667
A15: Indiana | B15: =(SUM(G15:J15)) -> 29 | C15: 42 | D15: 114 | E15: 1040 | F15: =E15/1000 -> 1.04 | G15: 11.916667 | H15: 9.4166667 | I15: 3.4166667 | J15: 4.25
... A51: Alaska | B51: =(SUM(G51:J51)) -> 5 | C51: 17 | D51: 86 | E51: 179.36 | F51: =E51/1000 -> 0.17936 | G51: 2.5833333 | H51: 1.0833333 | I51: 0.58333333 | J51: 0.75
A54: United States | B54: =(SUM(G54:J54)) -> 133 | C54: 102 | D54: 198 | E54: 3.05 | F54: B | G54: 38.666667 | H54: 34.666667 | I54: 39.166667 | J54: 20.5
B57: 2012 | C57: 2013 | D57: 2014 | E57: 2015 | F57: 2016 | G57: 2017 | H57: 2018 | I57: 2019 | J57: 2020 | K57: 2021 | L57: 2022 | M57: 2023
A58: Global bioenergy jobs (million jobs) | B58: 2.4 | C58: 2.5 | D58: 2.99 | E58: 2.88 | F58: 2.74 | G58: 3.05 | H58: 3.18 | I58: 3.58 | J58: 3.52 | K58: 3.44 | L58: 3.58 | M58: 3.88
A59: US bioenergy jobs (million jobs) | B59: =0.152+0.217 -> 0.369 | C59: =0.152+0.236 -> 0.388 | D59: =0.282+0.152 -> 0.434 | E59: =0.277+0.152 -> 0.429 | F59: =0.2837+0.0797+0.007 -> 0.3704 | G59: =0.299+0.087 -> 0.386 | H59: =0.311+0.079+0.007 -> 0.397 | I59: =0.297+0.057 -> 0.354 | J59: =0.271+0.0445 -> 0.3155 | K59: =0.3226+0.0463 -> 0.3689 | L59: =0.36+0.047 -> 0.407 | M59: =0.342+0.0474 -> 0.3894
