Workbook

Sheet NEtZero
A1: 2023 companies with targets | B1: Net-Zero targets | C1: Other mitigation targets | D1: No target | E1: TOTAL | F1: Source | G1: URL | H1: Retrieve Date
A2: European Union | B2: 0.71 | C2: 0.22 | D2: 0.07 | E2: 466 | F2: Net Zero Tracker | G2: https://ca1-nzt.edcdn.com/Reports/Net_Zero_Stocktake_2023.pdf?v=1696255114/ | H2: 45383
A3: United States | B3: 0.46 | C3: 0.28 | D3: 0.27 | E3: 626 | F3: Net Zero Tracker | G3: https://ca1-nzt.edcdn.com/Reports/Net_Zero_Stocktake_2023.pdf?v=1696255114/ | H3: 45383
A4: China | B4: 0.2 | C4: 0.1 | D4: 0.7 | E4: 282 | F4: Net Zero Tracker | G4: https://ca1-nzt.edcdn.com/Reports/Net_Zero_Stocktake_2023.pdf?v=1696255114/ | H4: 45383
A5: RoW | B5: 0.68 | C5: 0.15 | D5: 0.17 | E5: 702 | F5: Net Zero Tracker | G5: https://ca1-nzt.edcdn.com/Reports/Net_Zero_Stocktake_2023.pdf?v=1696255114/ | H5: 45383
A6: World | B6: 0.68 | C6: 0.15 | D6: 0.17 | E6: 2076 | F6: Net Zero Tracker | G6: https://ca1-nzt.edcdn.com/Reports/Net_Zero_Stocktake_2023.pdf?v=1696255114/ | H6: 45383
A8: Total Emissions share (%) 2023 | B8: Total Emissions share (%) | F8: Source | G8: URL | H8: Retrieve Date
A9: Other countries with similar net zero announcements | B9: 0.33094 | F9: Climate Action Tracker | G9: https://climateactiontracker.org/global/cat-net-zero-target-evaluations/ | H9: 45383
A10: European Union (EU27) | B10: 0.07495 | F10: Climate Action Tracker | G10: https://climateactiontracker.org/global/cat-net-zero-target-evaluations/ | H10: 45383
A11: China | B11: 0.2795 | F11: Climate Action Tracker | G11: https://climateactiontracker.org/global/cat-net-zero-target-evaluations/ | H11: 45383
A12: United States | B12: 0.13623 | F12: Climate Action Tracker | G12: https://climateactiontracker.org/global/cat-net-zero-target-evaluations/ | H12: 45383
A13: India | B13: 0.06729 | F13: Climate Action Tracker | G13: https://climateactiontracker.org/global/cat-net-zero-target-evaluations/ | H13: 45383
A14: Countries with no net zero target | B14: 0.11109 | F14: Climate Action Tracker | G14: https://climateactiontracker.org/global/cat-net-zero-target-evaluations/ | H14: 45383

Sheet NetZeroStates
A1: last_updated | B1: id_code | C1: name | D1: end_target_status | E1: end_target | F1: end_target_year | H1: status_date | I1: interim_target | J1: interim_target_percentage_reduction | K1: interim_target_baseline_year | L1: interim_target_year | M1: end_target_text | N1: interim_target_text | O1: target_notes | P1: source_url | Q1: gasses_coverage | R1: territorial_emissions | S1: consumption_emissions | T1: historical_emissions | U1: coverage_notes | V1: has_plan | W1: plan_options | X1: reporting_mechanism | Y1: equity | Z1: accountability | AA1: governance_notes | AB1: carbon_credit_offsets | AC1: removals_targets | AD1: cdr | AE1: sinks_and_credits_notes | AF1: population | AG1: ghg | AH1: inventory_year | AI1: gdp_real | AJ1: interim_target_other | AK1: carbon_credit_conditions | AL1: max_emission_offset | AM1: conditions_other | AN1: end_target_percentage_reduction | AO1: end_target_baseline_year | AP1: end_target_other
A2: 2024-03-13 10:44:21 | B2: REG-0003 | C2: Louisiana | D2: In law | E2: Net zero | F2: 2050 | H2: 2020 | I2: Emissions reduction target | J2: 26 | K2: 2005 | L2: 2025 | M2: by 2050 reduce greenhouse gas emissions to net zero | N2: by 2025, reduce net greenhouse gas emissions by 26-28% of 2005 levels by 2030, reduce net greenhouse gas emissions by 40-50% of 2005 levels | O2: https://gov.louisiana.gov/page/climate-initiatives-task-force | P2: https://gov.louisiana.gov/assets/docs/CCI-Task-force/CAP/Climate_Action_Plan_FINAL_3.pdf | Q2: Carbon dioxide and other GHGs | R2: Yes | S2: No | T2: No | U2: https://gov.louisiana.gov/assets/docs/CCI-Task-force/CAP/Climate_Action_Plan_FINAL_3.pdf, pg. 3 The GHG emissions reduction goals (Figure 1) are derived in part from the declaration by the Intergovernmental Panel on Climate Change (IPCC) that “global net human-caused emissions of carbon dioxide [CO2]...would need to fall by about 45 percent from 2010 levels by 2030, reaching ‘net zero’ around 2050.”1 These goals also align with the U.S.' Nationally Determined Contributions (NDCs) which represent its commitment in the Paris Climate Agreement to limit global warming to 1.5°C,2 and are calibrated to 2005 to correspond to Louisiana‘s 2010 Greenhouse Gas Inventory (GHG Inventory). Additionally, Governor Edwards’ goals put Louisiana in line with commitments made by dozens of other states as well as businesses operating in multiple sectors internationally, nationally, and within Louisiana. These businesses span a variety of industrial sectors including energy producers, public utilities, chemical manufacturers, technology firms, and finance. https://gov.louisiana.gov/assets/docs/CCI-Task-force/CAP/Climate_Action_Plan_FINAL_3.pdf, pg. 11 in Louisiana, the industrial sector contributes an overwhelming 66% of overall state emissions. Though Louisiana’s GHG emissions are most concentrated in the industrial sector, transportation and power generation emissions across the state are also significant. The transportation sector is responsible for 19% of CO2e emissions, and the electric power sector makes up 13% of Louisiana’s CO2e emissions. | V2: Yes | W2: Measures for all emission scopes that are covered by the target|Information on the emission reductions expected from these measures within a certain time period|Information on the extent to which measures will be applied (e.g. if switching to EVs, what share of the fleet; if installing an own solar PV installation, what is the installed capacity)|Schedule for regular review of measures | X2: Annual reporting | Y2: Yes | Z2: Not Specified | AA2: 2023 Annual Report: https://drive.google.com/uc?id=1qzBtt2Dt0QF4PHWqEQi49UNWF0HHIgSn&export=download EQUITY https://gov.louisiana.gov/assets/docs/CCI-Task-force/CAP/Climate_Action_Plan_FINAL_3.pdf, pg 36 "In Louisiana and around the world, climate change and GHG emissions disproportionately impact low-income, Black, and Indigenous communities. These communities are the least responsible for emissions but bear the highest costs in health and environmental degradation. In addition to their own inherent value as people of the state of Louisiana and the price they have paid through past inequities, these communities hold tremendous knowledge of the state’s lands, waters, wildlife, and environment and are needed leaders in the implementation of GHG-reducing actions. Representation and process integration are the foundation for equitable opportunity and outcomes. From the start of the Climate Action Plan development process, the Task Force and supporting members were chosen with this reality in mind, and open discussion of equity considerations were fostered during public meetings. In addition, an equity advisory group was formed to specifically consider the potential outcomes of policy proposals for advancing or negating progress toward a more equitable society. The equity advisory group developed a definition of climate equity and evaluated the potential impact of climate actions on the three equity-centered fundamental objectives aimed at reducing disparities, addressing historic and structural inequities, and increasing participation for Black, low- income, historically marginalized, and Indigenous peoples across Louisiana." STRATEGY 17. Build a more inclusive and resilient economy for all Louisiana residents https://gov.louisiana.gov/assets/docs/CCI-Task-force/CAP/Climate_Action_Plan_FINAL_3.pdf, pg 97 Deliberate action is necessary to ensure that all Louisianans have equitable access to future economic opportunities and that any disruptions to the economy associated with the energy transition do not fall disproportionately on any one community. By prioritizing the success of those who have historically been excluded from the benefits of prior economic transitions and those who are most directly affected by the energy transition, the shift to a low-carbon economy can more broadly, inclusively, and equitably provide benefits throughout the state. | AB2: Not Specified | AC2: No | AD2: Yes (nature-based and CCS-based removals) | AE2: "Louisiana's forested areas 'are a considerable carbon sink' with wetlands -- assessed for the first time in this inventory -- also supporting carbon sequestration... Louisiana’s land-based carbon sequestration has increased since 2012, contributing to an annual reduction of 35 MMT CO2e, which is comparable to the entire power generation sector." https://gov.louisiana.gov/assets/docs/CCI-Task-force/CAP/Climate_Action_Plan_FINAL_3.pdf, pg 38 ACTION 14.2 Support the expansion of urban tree canopy and green spaces https://gov.louisiana.gov/assets/docs/CCI-Task-force/CAP/Climate_Action_Plan_FINAL_3.pdf, pg 89 Activities that reforest public areas in urban environments, increase urban green spaces (e.g., parks, gardens, farms), and provide landscape-based stormwater management through green infrastructure can sequester carbon while also reducing heat island effect, reducing localized flooding, and increasing access to open space. Further co-benefits are reduced energy consumption and ongoing energy use due to a reduced heat island effect. This action proposes the state government, through LDAF, serve as convenor of parish and municipal governments to develop and promote a coherent, statewide approach that supports tree planting programs and maintenance in urban areas, particularly in historically underserved communities. In addition to this statewide approach, this action should empower locals to survey existing tree canopies in urban areas, with progress tracked and reported annually. Near-term deployment of a statewide approach and local surveys of existing canopies should inform longer-term urban transportation projects. Specific focus should be on increasing tree canopy and open space access in low-income, urban areas in both regional and local plans (e.g., State Watershed Plan, Hazard Mitigation Plan, Comprehensive Plans). ACTION 15.1 Optimize the carbon sequestration potential of Louisiana’s coastal wetlands through implementation of Coastal Master Plan projects https://gov.louisiana.gov/assets/docs/CCI-Task-force/CAP/Climate_Action_Plan_FINAL_3.pdf, pg 90 Implementation of Louisiana’s Coastal Master Plan* includes coastal restoration actions to reduce land loss with a focus on risk reduction to support coastal communities. This action proposes that the Coastal Protection and Restoration Authority (CPRA) incorporate climate mitigation goals and measures (e.g., carbon sequestration potential of wetlands) into future iterations of the Coastal Master Plan as well as into project design and prioritization. Carbon sequestration potential should further make the case for investment in Louisiana’s coastal program and unlock additional resources for project implementation. (Associated Submitted Action Proposals: 77) ACTION 16.7 Encourage sustainable forest management and greater use of Louisiana forest products for construction https://gov.louisiana.gov/assets/docs/CCI-Task-force/CAP/Climate_Action_Plan_FINAL_3.pdf, pg 95 Markets for wood products create incentives for landowners to plant more trees and better manage forests, resulting in more carbon sequestered. Educating landowners on and establishing sustainable forestry practices maximizes carbon sequestration of forested lands, encourages participation in carbon markets, and enhances early succession benefits and realized co-benefits to ecosystems and species. Further, implementation of a Buy Clean Louisiana policy (Action 6.1) will encourage and require manufacturers and end users to purchase sustainably forested products in construction and consumer products, increasing the amount of carbon stored by trees. This action proposes LDAF’s Forestry Protection Program and the Louisiana Forestry Association (LFA) partner to educate major foresters on the sustainable management of forests and the necessary steps to engage in existing carbon markets. ACTION 26.2 Solicit a study to more comprehensively understand potential impacts of CCUS technology and infrastructure on communities, ecosystems, and cultural resources to inform siting and permitting deployment https://gov.louisiana.gov/assets/docs/CCI-Task-force/CAP/Climate_Action_Plan_FINAL_3.pdf, pg 110 With Louisiana’s extensive geologic storage potential and federal incentives for near-term investment, Louisiana is seeing significant interest and investment in the deployment of CCUS to address industrial GHG emissions. Members of the Task Force and the public have raised concerns related to the capture process at facilities, transport through pipelines, and geologic storage underground. To address these concerns, this action recommends the state, through leadership of DNR, and its research institutions synthesize existing research on CCUS and disseminate information and materials for public education. The state and its research institutions should also fund a comprehensive understanding of CCUS impacts, including but not limited to siting impacts on cultural characteristics of neighboring populations, air quality impacts on nearby communities, increased energy intensity for different industry processes, pipeline safety implications, environmental and resilience impact of pipeline buildout, potential incidents of geologic storage, and long-term risks and costs. (Associated Submitted Action Proposals: N/A) | AF2: 4649000
A3: 2024-03-19 14:22:41 | B3: REG-0004 | C3: Nevada | D3: In policy document | E3: Net zero | F3: 2050 | H3: 2021 | I3: Emissions reduction target | J3: 28 | K3: 2005 | L3: 2025 | M3: long-term reductions of greenhouse gas emissions to zero or near-zero by the year 2050 | N3: statewide reduction of net greenhouse gas emissions of 28 percent by the year 2025, as compared to the level of greenhouse gas emissions in this State in 2005 statewide reduction in net greenhouse gas emissions of 45 percent by the year 2030, as compared to the level of greenhouse gas emissions in this State in 2005 However, under current policies and based on the best available science, Nevada is currently on a path to reduce economy-wide GHG emissions 24% by 2025 (4% short of the 28% goal) and 26% by 2030 (19% short of the 45% goal), thus missing the emissions-reduction goals. (GHG inventory, p.12) | O3: The targets themselves do not appear to be in law (referring to policies "that could achieve reductions"), but the submission of the annual report is Law SB254: https://www.leg.state.nv.us/App/NELIS/REL/80th2019/Bill/6431/Text GHG inventory 2021: https://ndep.nv.gov/uploads/air-pollutants-docs/ghg_report_2021.pdf | P3: https://climateaction.nv.gov/wp-content/uploads/2021/01/NVClimateStrategy_011921.pdf | Q3: Carbon dioxide and other GHGs | R3: Yes | S3: Not Specified | T3: No | U3: "statewide inventory of greenhouse gas emissions" | V3: Yes | W3: Measures for all emission scopes that are covered by the target|Information on the emission reductions expected from these measures within a certain time period|Information on the extent to which measures will be applied (e.g. if switching to EVs, what share of the fleet; if installing an own solar PV installation, what is the installed capacity) | X3: Annual reporting | Y3: Yes | Z3: Not Specified | AA3: Annual reporting: " requiring the State Department of Conservation and Natural Resources to issue an annual report concerning greenhouse gas emissions in this State"; "equires the report to provide policies, identified by an entity or entities designated by the Governor, that could achieve reductions in greenhouse gas emissions and a qualitative assessment of whether such policies support long-term reductions of greenhouse gas emissions in this State to zero or near-zero by the year 2050" Reporting here: https://ndep.nv.gov/air/air-pollutants/greenhouse-gas-emissions Public plan: Nevada's 2020 State Climate Strategy has catalog of policies it plans to implement across different sectors, and each policy is assessed on 4 metrics: (1.) GHG Emissions reduction potential; (2.) Climate justice considerations; (3.) Budgetary and economic implications; (4.) Implementation feasibility (Climate Strategy, p.52) Equity: One of the key metrics per proposed climate policy is climate justice, which is defined as: Have communities of color, low-income households, and tribal partners (i.e., Indigenous communities) been directly engaged and consulted about the challenges and opportunities associated with the policy? Will the policy avoid any negative impacts to vulnerable communities, provide the opportunity for a net benefit, and/or reconcile broader social justice issues? (Climate Strategy, p.53) GHG inventory (2021) suggests need to establish a state climate structure centred on equity, environmental justice, and economic recovery (p. 50). In Kleinmann report (2023): "While much of the strategic modeling of CCS and CDR deployment has focused on techno–economic impact categories, these types of analyses can overlook the cumulative social and environmental impacts of these approaches. Many of the strategies identified in this study could place increasing stress on marginalized populations." (p. 7, https://kleinmanenergy.upenn.edu/wp-content/uploads/2022/04/KCEP-Digest-Net-Zero-Nevada_withthanks.pdf) | AB3: Not Specified | AC3: No | AD3: Yes (nature-based removals e.g. Forestation, soil carbon enhancement) | AE3: NATURE BASED REMOVALS ARE ADDRESSED but no explicit details are provided on the extent of these nature-based removal schemes and by how much they will reduce emissions by. In https://climateaction.nv.gov/wp-content/uploads/2021/01/NVClimateStrategy_011921.pdf there is reference to: Promote land management practices that increase carbon sequestration by natural lands that are typical and/or native to Nevada. Expand speci | AF3: 3080000 | AG3: 36200000 | AH3: 2017
A4: 2023-05-12 06:50:54 | B4: REG-0005 | C4: Colorado | D4: In law | E4: Net zero | F4: 2050 | H4: 2023 | I4: Emissions reduction target | J4: 26 | K4: 2005 | L4: 2025 | M4: (2) It is further declared that: (g) (I) Accordingly, Colorado shall strive to increase renewable energy generation and eliminate statewide greenhouse gas pollution by the middle of the twenty-first century and have goals of achieving, at a minimum: ... (F) A ONE HUNDRED percent reduction in statewide greenhouse gas pollution by 2050. | N4: (A) A twenty-six percent reduction in statewide greenhouse gas pollution by 2025; (B) A fifty percent reduction in statewide greenhouse gas pollution by 2030; (C) A SIXTY- FIVE PERCENT REDUCTION IN STATEWIDE GREENHOUSE GAS POLLUTION BY 2035; (D) A SEVENTY - FIVE PERCENT REDUCTION IN STATEWIDE GREENHOUSE GAS POLLUTION BY 2040; (E) A NINETY PERCENT REDUCTION IN STATEWIDE GREENHOUSE GAS POLLUTION BY 2045; and ... (II) The reductions identified in this subsection (2)(g) are measured relative to 2005 statewide greenhouse gas pollution levels. | O4: 2019 law: https://leg.colorado.gov/bills/hb19-1261 Full 2023 bill: https://leg.colorado.gov/sites/default/files/documents/2023A/bills/2023a_016_enr.pdf https://www.edf.org/media/colorado-legislature-passes-bill-strengthening-states-climate-targets | P4: https://leg.colorado.gov/bills/sb23-016 | Q4: Carbon dioxide and other GHGs | R4: Not Specified | S4: Not Specified | T4: No | U4: Methane also included in target (e.g., " "Recovered methane protocol" means a documented set of procedures and requirements established by the air quality control commission to quantify ongoing greenhouse gas emission reductions or greenhouse gas removal enhancements achieved by a recovered methane project and to calculate the project baseline.") | V4: Yes | W4: Information on the extent to which measures will be applied (e.g. if switching to EVs, what share of the fleet; if installing an own solar PV installation, what is the installed capacity)|Information on the emission reductions expected from these measures within a certain time period|Schedule for regular review of measures | X4: No reporting mechanism | Y4: No | Z4: Not Specified | AA4: Equity p14 of Reduction Roadmap: https://energyoffice.colorado.gov/climate-energy/ghg-pollution-reduction-roadmap Revision over time: e) (II) Consistent with section 25-7-102 (2)(g), the commission shall timely promulgate implementing rules and regulations. The implementing rules may take into account other relevant laws and rules, as well as voluntary actions taken by local communities and the private sector, to enhance efficiency and cost-effectiveness, and shall be revised as necessary over time to ensure timely progress toward the 2025, 2030, 2035, 2040, 2045, and 2050 goals. | AB4: Not Specified | AC4: No | AD4: Yes (unspecified) | AE4: ""Recovered methane protocol" means a documented set of procedures and requirements established by the air quality control commission to quantify ongoing greenhouse gas emission reductions or greenhouse gas removal enhancements achieved by a recovered methane project and to calculate the project baseline." "1) The Colorado energy office shall ... (XIII) SUPPORT POLLUTION REDUCTION THROUGH CARBON CAPTURE AND SEQUESTRATION AND OTHER FORMS OF CARBON MANAGEMENT" | AF4: 5759000 | AG4: 89300000 | AH4: 2018 | AI4: 392986000000
A5: 2024-03-12 16:37:59 | B5: REG-0009 | C5: California | D5: In law | E5: Net zero | F5: 2045 | H5: 2020 | I5: Emissions reduction target | J5: 48 | K5: 1990 | L5: 2030 | M5: "achieve carbon neutrality as soon as possible, and no later than 2045, and achieve and maintain net negative emissions thereafter" | N5: 2030: 40% below 1990 levels 2050: 80% below 1990 levels - Scoping plan furthered the interim target: "That includes a 48% reduction of greenhouse gasses by 2030, surpassing the statutory mandate to reduce emissions 40% below 1990 levels in 2030;" (source: https://www.gov.ca.gov/2022/11/16/california-releases-worlds-first-plan-to-achieve-net-zero-carbon-pollution/) | O5: B-55-18 is an executive order, so carries the force of law https://ww2.arb.ca.gov/sites/default/files/2020-08/e3_cn_draft_report_aug2020.pdf https://leginfo.legislature.ca.gov/faces/billTextClient.xhtml?bill_id=201520160SB32 | P5: https://www.ca.gov/archive/gov39/wp-content/uploads/2018/09/9.10.18-Executive-Order.pdf | Q5: Not Specified | R5: Not Specified | S5: Not Specified | T5: No | U5: California's fourth climate change assessment covers Temperature, Water, Wildfire, Sea Level, Communities and Governance (California's Fourth Climate Change Assessment) | V5: Yes | W5: Measures for all emission scopes that are covered by the target|Information on the emission reductions expected from these measures within a certain time period|Schedule for regular review of measures|Information on the extent to which measures will be applied (e.g. if switching to EVs, what share of the fleet; if installing an own solar PV installation, what is the installed capacity) | X5: Annual reporting | Y5: Yes | Z5: Not Specified | AA5: "shall seek to improve air quality and support the health and economic resiliency of urban and rural communities, particularly low-income and disadvantaged communities" and "shall be implemented in a manner that supports climate adaptation and biodiversity" Plans -https://ww2.arb.ca.gov/our-work/programs/ab-32-climate-change-scoping-plan; https://ww2.arb.ca.gov/sites/default/files/2020-08/e3_cn_draft_report_aug2020.pdf | AB5: Not Specified | AC5: No | AD5: Not Specified | AE5: "shall include sequestration targets in the Natural and Working Lands Climate Change Implementation Plan" | AF5: 39510000 | AG5: 425280804 | AH5: 2018 | AI5: 3132800000000
A6: 2024-03-12 14:17:24 | B6: REG-0010 | C6: Hawaii | D6: In law | E6: Climate neutral | F6: 2045 | H6: 2024 | I6: Emissions reduction target | J6: 50 | K6: 2005 | L6: 2030 | M6: "pledge to be carbon-neutral by 2045" - https://governor.hawaii.gov/newsroom/latest-news/governors-office-news-release-governor-david-ige-signs-bills-to-set-carbon-neutral-goal-and-combat-climate-change/ | N6: "Hawaiʻi again reaffirmed this comitment with Act 238 (Session Laws of Hawaii, or SLH 2022) which codified in Hawai‘i Revised Statutes (HRS) §225P-5, requires Hawai‘i to reduce GHG emissions by at least 50 percent below 2005 levels by 2030 and 100% by 2045, in line with the United States’ Paris Agreement commitments and Nationally Determined Contribution." (https://climate.hawaii.gov/wp-content/uploads/2024/03/Hawaii-PCAP-FINAL-March-1-2024-1-3.pdf, page 2) | O6: commitment to have a one hundred per cent renewable energy portfolio by 2045 | P6: https://climate.hawaii.gov/wp-content/uploads/2024/03/Hawaii-PCAP-FINAL-March-1-2024-1-3.pdf | Q6: Carbon dioxide and other GHGs | R6: Yes | S6: Not Specified | T6: No | U6: Gases included are CO2, SF6, N2O, CH4, HFCs, PFCs | V6: Yes | W6: Measures for all emission scopes that are covered by the target|Information on the emission reductions expected from these measures within a certain time period|Information on the extent to which measures will be applied (e.g. if switching to EVs, what share of the fleet; if installing an own solar PV installation, what is the installed capacity) | X6: Annual reporting | Y6: Yes | Z6: Not Specified | AA6: Reports - https://climate.hawaii.gov/hi-mitigation/mitigation-reports/ "Beginning with the regular session of 2024, submit an annual report of its findings and recommendations, including any proposed legislation, to the legislature and the climate change mitigation and adaptation commission no later than twenty days prior to the convening of each regular session" - https://www.capitol.hawaii.gov/session2018/bills/HB2182_CD1_.htm Plan and measures detailed on page 25-28 of https://climate.hawaii.gov/wp-content/uploads/2024/03/Hawaii-PCAP-FINAL-March-1-2024-1-3.pdf "Equity is at the center of Hawai‘i’s response to climate change" and "To build climate equity, it is essential to center the voices and strengths of historically underserved communities and acknowledge the institutions and policies that are responsible for these disparities. Recognizing this, CCMAC puts equity at the center of its mission statement, to quickly “promote ambitious climate-neutral culturally responsive strategies for climate change mitigation and adaptation in a manner that is clean, equitable and resilient.”" (https://climate.hawaii.gov/wp-content/uploads/2024/03/Hawaii-PCAP-FINAL-March-1-2024-1-3.pdf, page 2) | AB6: Not Specified | AC6: No | AD6: Yes (nature-based removals e.g. Forestation, soil carbon enhancement) | AE6: "In Act 33, Session Laws of Hawaii 2017, the State established the carbon farming task force to gain a more thorough understanding of how agricultural land management practices can sequester carbon, provide greenhouse gas benefits, and decrease marine sedimentation" aim to "create a carbon offset program" "3.Increase long term carbon sequestration and ecosystem resilience by planting 2,800 food trees, 1,100 native trees, and 17,000 native understory species on 110 acres over a five-year period." (https://climate.hawaii.gov/wp-content/uploads/2024/03/Hawaii-PCAP-FINAL-March-1-2024-1-3.pdf, page 23) | AF6: 1416000 | AG6: 19580000 | AH6: 2016 | AI6: 97281700000
A7: 2023-01-04 15:14:33 | B7: REG-0011 | C7: Maine | D7: In law | E7: Carbon neutral(ity) | F7: 2045 | H7: 2020 | I7: Emissions reduction target | J7: 45 | K7: 1990 | L7: 2030 | M7: shall strive to achieve a carbon neutral economy no later than 2045 | N7: 2030: gross annual greenhouse gas emissions at least 45% below 1990 2040: gross annual greenhouse gas emissions must, at a minimum, be on an annual trajectory sufficient to achieve the 2050 annual emissions (80%) renewable energy mandate of 80 percent renewable energy by 2030 and a goal of 100 percent by 2050 | O7: https://legislature.maine.gov/legis/bills/bills_129th/billtexts/SP055002.asp | P7: https://www.maine.gov/governor/mills/sites/maine.gov.governor.mills/files/inline-files/Executive%20Order%209-23-2019_0.pdf | Q7: Not Specified | R7: Not Specified | S7: Not Specified | T7: No | V7: Yes | W7: Schedule for regular review of measures|Information on the extent to which measures will be applied (e.g. if switching to EVs, what share of the fleet; if installing an own solar PV installation, what is the installed capacity) | X7: Less than annual reporting | Y7: Yes | Z7: Yes | AA7: Maine Climate Council "update that plan every four years" and "responsible for Maine's Climate Action Plan" Plan from 2020: http://climatecouncil.maine.gov/future/sites/maine.gov.future/files/inline-files/MaineWontWait_December2020_printable_12.1.20.pdf https://www.maine.gov/dep/sustainability/climate/mitigation-actions.html - progress reports are bienniel (Dec 2022 report here: https://www.maine.gov/future/sites/maine.gov.future/files/inline-files/MWWProgressReport_December2022_digital.pdf) goal of 100,000 heat pumps before 2025 goal of weatherizing 17,500 homes by 2025 127 communities are now participating in the Community Resilience Partnership, a new program to encourage cities, towns, and Tribal governments to identify climate and resilience priorities and start or expand their local climate planning and actions | AB7: Not Specified | AC7: No | AD7: Not Specified | AE7: "Develop New Incentives to Increase Carbon Storage" - http://climatecouncil.maine.gov/future/sites/maine.gov.future/files/inline-files/MaineWontWait_December2020_printable_12.1.20.pdf "a comprehensive Maine carbon-cycle analysis is needed for the state to understand and track its progress towards carbon neutrality and allow for accurate potential future participation in carbon-offset markets" - not currently a participant in offsetting | AF7: 1344000 | AG7: 15000000 | AH7: 2018 | AI7: 67717000000
A8: 2024-03-19 17:19:16 | B8: REG-0012 | C8: Massachusetts | D8: In law | E8: Net zero | F8: 2050 | H8: 2020 | I8: Emissions reduction target | J8: 33 | K8: 1990 | L8: 2025 | M8: https://www.mass.gov/doc/clean-energy-and-climate-plan-for-2025-and-2030/download 'A statewide limit of net zero emissions means that in 2050, total GHG emissions emitted by all sources in Massachusetts must be equal to or less than the total amount of carbon sequestered within Massachusetts or through actions directly attributable to Massachusetts' | N8: "As part of a letter issued contemporaneously with the Clean Energy and Climate Plan for 2025 and 2030 (2025/2030 CECP), the Secretary of the Executive Office of Energy and Environmental Affairs has determined that the Commonwealth’s economy-wide emissions limit will be a 33% reduction from 1990 level in 2025, and a 50% reduction in 2030." [p12] | O8: Previous target 25% reduction on 1990 levels for 2020. Massachusetts’ approach to achieving its emissions limits and sublimits is based on three basic principles: (1) electrify non-electric energy uses, (2) decarbonize the electric grid, and (3) reduce energy costs and the costs of transition by increasing the efficiency of transportation and energy systems. | P8: https://malegislature.gov/Bills/191/H4912 | Q8: Carbon dioxide and other GHGs | R8: Not Specified | S8: Not Specified | T8: No | U8: https://www.mass.gov/news/baker-polito-administration-issues-letter-establishing-net-zero-emissions-target https://www.mass.gov/doc/ma-2050-decarbonization-roadmap/download direct and indrect emissions mentioned, but not explicitly clear what the target includes. The 2021 climate law includes setting sector-specific GHG emissions limits, including in residential heating and cooling, commercial and industrial heating and cooling, transportation, electrical power, natural gas distribution and service and industrial processes. GHG emissions associated with agriculture, solid waste decomposition in landfills, and wastewater disposal are not represented in the sector specific sublimit. | V8: Yes | W8: Measures for all emission scopes that are covered by the target|Information on the emission reductions expected from these measures within a certain time period|Schedule for regular review of measures|Information on the extent to which measures will be applied (e.g. if switching to EVs, what share of the fleet; if installing an own solar PV installation, what is the installed capacity) | X8: Annual reporting | Y8: Yes | Z8: Not Specified | AA8: Reports - https://www.mass.gov/info-details/ma-decarbonization-roadmap#final-reports- "Achieving Net Zero Affordably for All" - https://www.mass.gov/doc/ma-2050-decarbonization-roadmap/download "The decarbonization policies and approaches contained in this 2025/2030 CECP will have substantial impacts on Massachusetts residents and the economy. To estimate these impacts, BW Research Partnership and Industrial Economics, Incorporated (the research team) worked with EEA to model the employment, macroeconomic, and equity impacts of the decarbonization pathway" [p119] | AB8: Not Specified | AC8: No | AD8: Yes (unspecified) | AE8: Natural and working lands’ ability to sequester emissions will be a critical component of achieving net zero GHG emissions in Massachusetts. For the first time, this 2025/2030 CECP provides an analysis of the emissions from, and the carbon sequestration by, Massachusetts’ NWL; outlines policies to support the conservation, climate smart management, and restoration of NWL; and identifies additional ongoing and existing actions the Commonwealth is pursuing to achieve net zero emissions by 2050. "Achieving net zero in 2050 will require real, verified annual sequestration of as much as 14.2 MMTCO2e by resources in, or attributable to, the Commonwealth. EEA’s current assessment is that NWL in Massachusetts are not likely to be capable of sequestering carbon dioxide at this rate in 2050 without seriously compromising other ecosystem services and land uses. Thus, it will be necessary to develop regionally consistent sequestration measurement, accounting, and market frameworks that will allow Massachusetts to purchase additional, least-cost sequestration services from other states in the region to allow the Commonwealth to achieve net zero GHG emissions in 2050." [p117] | AF8: 6893000 | AG8: 63000000 | AH8: 2018 | AI8: 596593000000
A9: 2024-03-12 14:00:31 | B9: REG-0013 | C9: Michigan | D9: In law | E9: Carbon neutral(ity) | F9: 2050 | H9: 2020 | I9: Emissions reduction target | J9: 28 | K9: 2005 | L9: 2025 | M9: "economy-wide carbon neutrality no later than 2050, and to maintain net negative greenhouse gas emissions thereafter" | N9: Reduce GHG emissions 28% below 2005 levels by 2025 Reduce GHG emissions 52% below 2005 levels by 2030 | O9: https://www.michigan.gov/whitmer/0,9309,7-387-90499_90704-540278--,00.html https://www.michigan.gov/egle/-/media/Project/Websites/egle/Documents/Offices/OCE/MI-Healthy-Climate-Plan.pdf?rev=d13f4adc2b1d45909bd708cafccbfffa | P9: https://www.michigan.gov/whitmer/news/state-orders-and-directives/2020/09/23/executive-directive-2020-10.pdf | Q9: Not Specified | R9: Yes | S9: Not Specified | T9: No | U9: Not specified- reference is only to GHG | V9: Yes | W9: Information on the extent to which measures will be applied (e.g. if switching to EVs, what share of the fleet; if installing an own solar PV installation, what is the installed capacity) | X9: Annual reporting | Y9: Yes | Z9: Not Specified | AA9: Quite a detailed plan on Energy productions, transportation, businesses and homes, environmental justice, leadership and innovation. | AB9: Not Specified | AC9: No | AD9: Not Specified | AF9: 9987000 | AG9: 162100000 | AH9: 2018 | AI9: 536888000000
A10: 2024-03-19 15:14:18 | B10: REG-0014 | C10: Montana | D10: In policy document | E10: GHG neutral(ity) | F10: 2050 | H10: 2020 | I10: Other | L10: 2035 | M10: "goal of net greenhouse gas neutrality economy-wide at a date to be determined by the Council." Executive Order 8-2019, p. 3, http://formergovernors.mt.gov/bullock/docs/2019EOs/EO-08-2019_Creating%20Climate%20Solutions%20Council.pdf 2020 montana climate solutions plan, p.4, https://deq.mt.gov/files/deqadmin/climate/2020-09-09_montanaclimatesolutions_final.pdf | N10: "interim goal of net ghg neutrality for average annual electric loads in the state by no later than 2035" Executive Order 8-2019, p. 3, http://formergovernors.mt.gov/bullock/docs/2019EOs/EO-08-2019_Creating%20Climate%20Solutions%20Council.pdf 2020 montana climate solutions plan, p.4, https://deq.mt.gov/files/deqadmin/climate/2020-09-09_montanaclimatesolutions_final.pdf | O10: This record gives updates from March 2024 - Montana's Priority Climate Action Plan: This plan differs from past climate planning because it is directly tied to federal funding made available to implement the projects states identify. This is an opportunity for Montana-made, market-driven solutions focused on innovation that will also reduce emissions. Nothing in this plan is intended to be implemented through new policies, regulations, or requirements, and projects that propose to use regulation to cut emissions are not covered by this plan. From the start, DEQ (Department of Environmental Quality) established an expectation that the measures included in Montana’s plan would be non-regulatory, incentive-based actions that focus on innovation and do not expand government. However, priority measures include Healthy Resilient Forests, Sustainable Schools, Innovative Agricultural Practices & Working Lands, Clean, Reliable Transportation, Industrial & Power Sector Innovation, High Performance Homes & Businesses, Waste Reduction or Diversion These suggested measures are accompanied by quantifications of how much emissions reduction each could achieve E.g. within the forests section, Expand Forest Management & Wildfire Mitigation is calculated to have the capacity to reduce GHG emissions by 0.22 MMT CO2e by 2030 or 1.09 MMT by 2050 | P10: https://deq.mt.gov/files/About/CPRG/Montana%20Pollution%20Reduction%20Plan.pdf | Q10: Carbon dioxide and other GHGs | R10: No | S10: Not Specified | T10: No | U10: "net greenhouse gas neutrality economy-wide" (pg 3) http://formergovernors.mt.gov/bullock/docs/2019EOs/EO-08-2019_Creating%20Climate%20Solutions%20Council.pdf | V10: Yes | W10: Measures for all emission scopes that are covered by the target|Information on the emission reductions expected from these measures within a certain time period | X10: Less than annual reporting | Y10: Yes | Z10: Not Specified | AA10: https://deq.mt.gov/about/Climate-Resilience: Plan: Under the Climate Pollution Reductions Grant , DEQ is beginning the process of developing a Montana Climate Action Plan. The planning grant has three deliverables: Priority Climate Action Plan (PCAP) due March 1, 2024 (this has been submitted: https://deq.mt.gov/files/About/CPRG/Montana%20Pollution%20Reduction%20Plan.pdf) Comprehensive Climate Action Plan (CCAP) due summer 2025 Status Report due summer 2027 Equity: In the Priority Climate Action Plan (PCAP), with reference to restoring forests: This measure would deliver substantial benefits to low-income and disadvantaged communities, aligning with Justice. This strategic focus addresses the heightened risks these communities face due to climate change and their limited resources to adapt or recover from such impacts. In addition, the measure would help protect public health by reducing wildfire smoke, a significant source of air pollution. The plan also has a section entitled 'LOW-INCOME AND DISADVANTAGED COMMUNITY BENEFITS ANALYSIS' | AB10: Not Specified | AC10: No | AD10: Yes (nature-based and CCS-based removals) | AE10: March 2024 Priority Climate Action Plan focuses on nature-based removals (reforestation, aovided forest conversion, fire management, soil carbon sequestration). Not much mention of CCS, however a section on Innovation in the Beef & Cattle Industry mentions 'tools to improve efficiency and reduce the environmental impacts of the beef supply chain through capture and reuse of methane gas' - 'If the emissions of 50,000 cows are reduced by 50 percent through methane capture and/or feed advancements,2 that results in 2,495 metric tons of methane reduced every five years' "b) Reducing emissions from traditional electricity generation sources while maintaining competitive advantages in electricity production, generation, and exports such as; 1. Continuing to advance the demonstration and deployment of carbon capture, storage, and utilization in support of negative emissions technologies;" (pg 3) http://formergovernors.mt.gov/bullock/docs/2019EOs/EO-08 2019_Creating%20Climate%20Solutions%20Council.pdf Lots of discussion of carbon capture in Montana Climate Solutions Plan: "Even as Montana diversifies its energy portfolio, fossil fuels are expected to meet a portion of energy demand. The deployment of carbon capture and storage (CCS) technology can accelerate efforts to reduce emissions from power plants and industrial processes, and support other needs such as renewable fuel production central to meeting the net-neutral goal." (pg 52) https://deq.mt.gov/files/DEQAdmin/Climate/2020-09-09_MontanaClimateSolutions_Final.pdf Nature based solutions "3. Northern Plains Precision Agricultural and Soil Carbon Innovation. A Northern Plains precision agriculture and soil carbon innovation cluster would build on and expand research capacity at MSU Northern and MSU. Agriculture is an important sector in Montana’s economy and culture and is a key sector with opportunities to reduce emissions from operations, sequester carbon in soils, and meet regional and global market demands" (pg 64) https://deq.mt.gov/files/DEQAdmin/Climate/2020-09-09_MontanaClimateSolutions_Final.pdf | AF10: 1069000 | AG10: 30700000 | AH10: 2018 | AI10: 52935000000 | AJ10: "interim goal of net ghg neutrality for average annual electric loads in the state by no later than 2035 and the goal of net green house gas neutrality economy-wide at a date to be determined by the concil" executive order 8-2019, p. 3, http://formergovernors.mt.gov/bullock/docs/2019eos/eo-08-2019_creating%20climate%20solutions%20council.pdf 2020 montana climate solutions plan, p.4, https://deq.mt.gov/files/deqadmin/climate/2020-09-09_montanaclimatesolutions_final.pdf
A11: 2024-03-12 14:23:48 | B11: REG-0015 | C11: New York State | D11: In law | E11: Net zero | F11: 2050 | H11: 2019 | I11: Emissions reduction target | J11: 40 | K11: 1990 | L11: 2030 | M11: "Net-Zero emissions statewide by 2050" "adopt measures to put the state on a path to reduce statewide greenhouse gas emissions by eighty-five percent by two thousand fifty and net zero emissions in all sectors of the economy" | N11: 2030: 40% below 1990 levels by 2030 2050: no less than 85% below 1990 levels | O11: "minimum of 70 percent of statewide electric generation be secured by renewable energy systems by 2030 and zero emissions from the statewide electrical demand system in 2040" "the community air monitoring program required by section 2 of the act shall take effect on October 1, 2022" More updated version of the bill at: https://climate.ny.gov/resources/scoping-plan/ | P11: https://www.nysenate.gov/legislation/bills/2019/s6599 | Q11: Carbon dioxide and other GHGs | R11: Yes | S11: No | T11: No | U11: "statewide greenhouse gas emissions means the total annual emissions of greenhouse gases produced within the state from anthropogenic sources and greenhouse gases produced outside of the state that are associated with the generation of electricity imported into the state and the extraction and transmission of fossil fuels imported into the state" | V11: Yes | W11: Measures for all emission scopes that are covered by the target|Information on the emission reductions expected from these measures within a certain time period|Information on the extent to which measures will be applied (e.g. if switching to EVs, what share of the fleet; if installing an own solar PV installation, what is the installed capacity) | X11: Less than annual reporting | Y11: Yes | Z11: Not Specified | AA11: Plan and measures detailed page 12-22 in Executive Summary of https://climate.ny.gov/resources/scoping-plan/ Equity - "provisions to address potential impacts on disadvantaged communities"; "THE COUNCIL SHALL CONVENE A JUST TRANSITION WORKING GROUP "This Scoping Plan prioritizes Disadvantaged Communities and the creation of good, family-sustaining, union jobs accessible to all New Yorkers." (https://climate.ny.gov/resources/scoping-plan/ page 3) "Every four years, DEC will publish a report on the implementation of GHG emission reduction measures, in consultation with the Council and CJWG." (https://climate.ny.gov/resources/scoping-plan/ Executive Summary page 23) | AB11: Yes | AC11: No | AD11: Not Specified | AE11: Offsetting: "the use of such mechanism shall account for not greater than fifteen percent of statewide greenhouse gas emissions estimated as a percentage of nineteen ninety emissions pursuant to section 75-0105 of this article, provided that the use of this mechanism must offset a quantity greater than or equal to the greenhouse gases emitted" "the offset of greenhouse gas emissions shall not result in disadvantaged communities having to bear a disproportionate burden of environmental impacts" | AF11: 19677151 | AG11: 205610000 | AH11: 2016 | AI11: 1772260000000 | AK11: Must be high environmental integrity|Avoid social harm|Maximum percentage of emissions that can be offset|Other conditions | AL11: 15 | AM11: "real, additional, verifiable, enforceable, and permanent" "sufficiently demonstrate that compliance with the greenhouse gas emissions limits is not technologically feasible, and that the source has reduced emissions to the maximum extent practicable" "sources in the electric generation sector shall not be eligible to participate in such mechanism." other prohibited projects: waste-to-energy projects (inc incineration and pyrolysis), biofuels for energy/transport, research projects and studies/assessments without commitment to implement "discernable benefit to the environment rather than to the source" "located in the same county, and within twenty-five linear miles, of the source of emissions, to the extent practicable"
A12: 2023-01-04 15:24:36 | B12: REG-0016 | C12: Washington State | D12: In law | E12: Net zero | F12: 2050 | H12: 2020 | I12: Emissions reduction target | J12: 45 | K12: 1990 | L12: 2030 | M12: "net zero greenhouse gas emissions by 2050" | N12: 2030: 45% below 2005 2040: 70% below 2005 2050: 95% below 2005 & achieve net zero GHG emissions | O12: https://apps.leg.wa.gov/rcw/default.aspx?cite=70A.45.020 | P12: https://ecology.wa.gov/Air-Climate/Climate-change/Greenhouse-gases | Q12: Carbon dioxide and other GHGs | R12: Yes | S12: Not Specified | T12: No | U12: "overall emissions of greenhouse gases in the state" | V12: Yes | W12: Measures for all emission scopes that are covered by the target | X12: Less than annual reporting | Y12: Yes | Z12: Not Specified | AA12: "By December 31st of each even-numbered year beginning in 2010, the department and the department of commerce shall report to the governor and the appropriate committees of the senate and house of representatives the total emissions of greenhouse gases for the preceding two years" - https://apps.leg.wa.gov/rcw/default.aspx?cite=70A.45.020 Equity: limits to be met in a way that (a) Reduces the burdens and creates benefits for vulnerable populations and highly impacted communities with long-term and short-term outcomes for public health, economic well-being, local environments, and community resiliency that benefits all Washington residents; (b) Supports the current skilled and trained construction workforce, retains and creates other high quality employment opportunities, and generates broad, widely shared economic benefits for the state and Washington residents; and (c) Maintains Washington's manufacturing economy and avoids leakage of emissions to other jurisdictions Proposed actions are details in this report https://apps.ecology.wa.gov/publications/SummaryPages/1201004.html (particularly in appendices) | AB12: Yes | AC12: No | AD12: Yes (nature-based removals e.g. Forestation, soil carbon enhancement) | AE12: "all pathways to one and one-half degrees Celsius rely on some amount of negative emissions through carbon sequestration. It is therefore the intent of the legislature to strengthen Washington's statutory greenhouse gas emission limits to reflect current science and to align with the limits that other jurisdictions are setting to combat climate change and to encourage voluntary actions that increase carbon sequestration on natural and working lands and storage in the related products from those lands." - https://apps.leg.wa.gov/rcw/default.aspx?cite=70A.45.020 https://ecology.wa.gov/Air-Climate/Climate-change/Greenhouse-gases/Reducing-greenhouse-gases/Climate-Commitment-Act "A portion of a facility’s compliance obligation can come from credits generated by projects that prevent greenhouse gas emissions, called offset projects. Covered entities can meet up to 5% of their obligations with offsets through 2026, and 4% from 2027 to 2030" | AF12: 7740745 | AG12: 78800000 | AH12: 2018 | AI12: 612996000000 | AK12: Maximum percentage of emissions that can be offset | AL12: 5
A13: 2023-03-21 14:42:25 | B13: REG-0074 | C13: Alabama | E13: No target | I13: No target | O13: Alabama is only 1 of 8 States to not have a Statewide Comprehensive Energy Plan (https://www.naseo.org/stateenergyplans) Alabama is considered as a part of the Southeast region along with (Georgia, Mississippi, North Carolina, South Carolina, and Tennessee). With some initial investigation about net zero target. //efaidnbmnnnibpcajpcglclefindmkaj/https://irp-cdn.multiscreensite.com/be6d1d56/files/uploaded/SDSN_Southeast%20Report_FINAL.pdf | Q13: Not Specified | AF13: 4908620 | AI13: 228143000000
A14: 2024-03-12 14:53:14 | B14: REG-0075 | C14: Alaska | E14: No target | I14: No target | O14: Bill Walker ordered the creation of a Climate Action for Alaska Leadership Team in 2017 (https://gov.alaska.gov/admin-orders/administrative-order-no-289/). They published a plan (https://web.archive.org/web/20181130010258/http://climatechange.gov.alaska.gov/wp-content/uploads/sites/11/2018/09/Ak_Climate_Action_Plan_brochure_final_web.pdf) in 2018 for reductions, but were disbanded by Michael Dunleavy in 2019 (https://gov.alaska.gov/admin-orders/administrative-order-no-309/) | Q14: Not Specified | AF14: 731545 | AI14: 54386000000
A15: 2024-03-12 15:04:17 | B15: REG-0076 | C15: Arizona | E15: No target | I15: No target | O15: In 2006, the then Governor signed Executive Order 2006-13 " to reduce GHG emissions in Arizona to its 2000 emissions level by 2020 and to 50 percent below its 2000 emissions level by 2040" https://apps.azsos.gov/public_services/register/2006/37/governor.pdf In 2010, this was effectively nullified by the signing of a bill prohibiting state regulation of GHGs without permission of the state legislature by the new Governor (https://www.azleg.gov/legtext/49leg/2r/bills/hb2442h.pdf) Arizona Corporation Commissions regulates utilities: https://www.azcc.gov/news/2021/05/26/may-26-2021-special-open-meeting-highlights "Arizona’s regulated utilities [should be] 100% carbon-free energy by 2070" with "50% reduction by 2032, a 65% reduction by 2040, an 80% reduction by 2050, and a 95% reduction by 2060." https://www.azcc.gov/news/2022/01/27/january-contingency-open-meeting-highlights "Commissioners voted 3-2 at their January Contingency Open Meeting to not move forward with a package of energy rules that, if adopted, would have required electric utilities to achieve 100% zero-carbon emissions energy by 2070." | Q15: Not Specified | AF15: 7279000 | AG15: 87000000 | AH15: 2016 | AI15: 370119000000
A16: 2023-09-09 08:00:57 | B16: REG-0077 | C16: Arkansas | E16: No target | I16: No target | O16: No state-wide target in place. Although the report from the Governor's Commission on Global Warming (published in 2008) includes recommended emission reduction goals (written on the second page of the report, which can be accessed here: https://web.archive.org/web/20230618211959/https://uccrnna.org/wp-content/uploads/2017/06/Arkansas_2008_Governors-Commission-On-Global-Warming.pdf) it was only a report, and there doesn’t appear to be any legal instruments that are putting any state-wide emissions reduction target into effect. Arkansas’ lack of an emissions reduction target is also reflected on these websites: - https://climate-xchange.org/dashboard/map/arkansas/ - https://www.c2es.org/document/greenhouse-gas-emissions-targets/ - https://spotforcleanenergy.org/state/arkansas/emissions-standard/ | Q16: Not Specified | AF16: 3018000 | AI16: 130954000000
A17: 2024-03-12 16:52:16 | B17: REG-0078 | C17: Connecticut | D17: In law | E17: Emissions reduction target | F17: 2050 | H17: 2008 | I17: Emissions reduction target | J17: 45 | K17: 2001 | L17: 2030 | M17: By 2050, overall state emissions will be 80% below the level emitted in 2001 Governor's Bill No. 10 - Connecticut General Assembly, p.10, https://www.cga.ct.gov/2022/TOB/S/PDF/2022SB-00010-R00-SB.PDF | N17: The state shall reduce the level of emissions of greenhouse gas: (1) Not later than January 1, 2020, to a level at least 10% below the level emitted in 1990; (2) Not later than January 1, 2030, to a level at least 45% below the level emitted in 2001; (3) Not later than January 1, 2040, to a level of 0% from electricity supplied to electric customers in the state; and (4) Not later than January 1, 2050, to a level at least 80% below the level emitted in 2001 Governor's Bill No. 10 - Connecticut General Assembly, p.10, https://www.cga.ct.gov/2022/TOB/S/PDF/2022SB-00010-R00-SB.PDF | O17: "Economy-wide reduction target of 45% below 2001 levels by 2030...ensures Connecticut is on a downward trajectory from today's GHG emissions to the 80% reduction the Global Warming Solutions Act requires by 2050" (Building a Low Carbon future for Connecticut Report, p.11) | P17: https://www.cga.ct.gov/2022/TOB/S/PDF/2022SB-00010-R00-SB.PDF | Q17: Not Specified | R17: Not Specified | S17: No | T17: No | U17: The target covers the electric sector (focusing on a transition to green energy by 84% in 2050), transportation sector (increase in light-duty ZEV penetration rate to at least 20% by 2030), building sector (transition to 26% renewable thermal technologies by 2050) and non-energy GHG emissions (e..g.g., agricultural, industrial and waste sectors) (Building a Low Carbon future for Connecticut Report) | V17: Yes | W17: Information on the emission reductions expected from these measures within a certain time period|Information on the extent to which measures will be applied (e.g. if switching to EVs, what share of the fleet; if installing an own solar PV installation, what is the installed capacity)|Measures for all emission scopes that are covered by the target | X17: Less than annual reporting | Y17: Yes | Z17: Not Specified | AA17: In relation to equity, there is the aim to be involved in “prioritizing, integrating and advancing equitable distribution of the costs and benefits of climate change mitigation planning policies, specifically addressing disproportionate impacts of such strategies on environmental justice communities,” 2021 GC3 Phase 1 Report: https://portal.ct.gov/-/media/DEEP/climatechange/GC3/GC3_Phase1_Report_Jan2021.pdf Climate Action Timeline for Connecticut: https://portal.ct.gov/DEEP/Climate-Change/Climate-Action-Timeline-for-Connecticut | AB17: Not Specified | AC17: No | AD17: Yes (nature-based removals e.g. Forestation, soil carbon enhancement) | AE17: Aims to increase the mitigation of GHG in Connecticut's forests through several means: a. Evaluate feasibility of a goal of permanent protection of at least 50% of core forests greater than 250 acres by 2040 and identify resources that would be needed to achieve that goal. b. Consider actions to increase statewide forest cover from 59% to over 60% by 2040. 2021 GC3 Phase 1 Report: https://portal.ct.gov/-/media/DEEP/climatechange/GC3/GC3_Phase1_Report_Jan2021.pdf | AF17: 3565000 | AG17: 40603041 | AH17: 2017 | AI17: 287822000000 | AN17: 80 | AO17: 2001
A18: 2023-03-21 15:03:49 | B18: REG-0079 | C18: Delaware | D18: In policy document | E18: Emissions reduction target | F18: 2025 | H18: 2021 | I18: No target | M18: "In 2017, Governor John Carney committed Delaware to reducing greenhouse gas emissions by 26% to 28% from 2005 levels by 2025. Delaware’s Climate Action Plan provides information on our state’s emissions reduction progress and lays out strategies for meeting or exceeding our goal." (pg 12) https://documents.dnrec.delaware.gov/energy/Documents/Climate/Plan/Delaware-Climate-Action-Plan-2021.pdf | P18: https://documents.dnrec.delaware.gov/energy/Documents/Climate/Plan/Delaware-Climate-Action-Plan-2021.pdf | Q18: Carbon dioxide and other GHGs | R18: Not Specified | S18: Not Specified | T18: No | U18: "Delaware’s goal for 2025 is to reduce annual emissions to approximately 16,500,000 MT CO2e, a reduction of 28% (and a difference of about 6,300,000 MT CO2e) compared to 2005. What is MT CO2e? This is called the carbon dioxide equivalent (CO2e), and it allows us to use a single measure to calculate all greenhouse gas emissions: metric tons of carbon dioxide equivalent (MT CO2e)." (pg 51) https://documents.dnrec.delaware.gov/energy/Documents/Climate/Plan/Delaware-Climate-Action-Plan-2021.pdf | V18: Yes | W18: Information on the extent to which measures will be applied (e.g. if switching to EVs, what share of the fleet; if installing an own solar PV installation, what is the installed capacity)|Measures for all emission scopes that are covered by the target|Information on the emission reductions expected from these measures within a certain time period | X18: No reporting mechanism | Y18: Yes | Z18: Not Specified | AA18: "Collaborations and partnerships with communities can help build equity into climate action. Early and continued engagement is essential, as residents can speak first-hand to community-specific climatic and economic impacts." (pg 19) "It is also important to gain an understanding of how climate action, such as transitioning to low-carbon energy, could impact existing jobs or alter job opportunities. Knowledge of potential job gains and losses resulting from climate action can help guide where state resources are most needed to ensure that certain populations are not left behind." (pg 83) https://documents.dnrec.delaware.gov/energy/Documents/Climate/Plan/Delaware-Climate-Action-Plan-2021.pdf | AB18: Not Specified | AC18: No | AD18: Yes (nature-based removals e.g. Forestation, soil carbon enhancement) | AE18: "Delaware’s forests, croplands, wetlands and urban greenspaces can play an important role in responding to climate change. The plants and soils in these “natural and working lands” have the ability to absorb (or sequester) carbon dioxide from the atmosphere. This provides a cost-effective, temporary or long-term carbon storage solution. Capitalizing on natural carbon storage can help offset a portion of emissions released by human activities. Strategies Delaware can implement: - Support best management practices on agricultural lands that provide greenhouse gas emissions co-benefits - Support conservation and restoration of forest lands - Support local communities’ enhancement of urban greenspaces - Improve methods for measuring and tracking carbon sequestration" (pg 16) https://documents.dnrec.delaware.gov/energy/Documents/Climate/Plan/Delaware-Climate-Action-Plan-2021.pdf | AF18: 973764 | AG18: 12600000 | AH18: 2018 | AI18: 77082000000 | AN18: 28 | AO18: 2005
A19: 2024-03-12 16:16:01 | B19: REG-0080 | C19: Florida | D19: In law | E19: Emissions reduction target | F19: 2050 | H19: 2007 | I19: Other | L19: 2025 | M19: " by 2050, reduce greenhouse gas emissions by 80% of 1990 levels" | N19: "by 2025, reduce greenhouse gas emissions to 1990 levels" | O19: https://flsenate.gov/Session/Bill/2020/178 "Prohibiting state-financed constructors from commencing construction of certain structures in coastal areas after a specified date without first taking certain steps regarding a sea level impact projection study" https://www.fsec.ucf.edu/en/media/enews/2007/pdf/07-128-actionteam.pdf creation of Action Team (subsequent report: https://www.fdacs.gov/ezs3download/download/89011/2560887/Media/Files/Energy-Files/Florida%20Energy%20and%20Climate%20Plan.pdf) | P19: https://www.fsec.ucf.edu/en/media/enews/2007/pdf/07-127-emissions.pdf | Q19: Carbon dioxide and other GHGs | R19: Not Specified | S19: Not Specified | T19: No | U19: Report covers infrastructure, transport, energy-water nexus, education and workforce development, R&D, electric industry, agriculture and efficiency and renewable energy. (Florida Energy and Climate Plan Powering Change, iii) | V19: Yes | W19: Information on the extent to which measures will be applied (e.g. if switching to EVs, what share of the fleet; if installing an own solar PV installation, what is the installed capacity)|Information on the emission reductions expected from these measures within a certain time period | X19: No reporting mechanism | Y19: No | Z19: Not Specified | AA19: https://www.fdacs.gov/ezs3download/download/89011/2560887/Media/Files/Energy-Files/Florida%20Energy%20and%20Climate%20Plan.pdf | AB19: Not Specified | AC19: No | AD19: Not Specified | AE19: Sinks and Credits are not a key part of this report (Florida Energy and Climate Plan Powering Change) | AF19: 21480000 | AG19: 230100000 | AH19: 2016 | AI19: 1106500000000 | AJ19: reduce greenhouse gas emissions to 1990 levels | AN19: 80 | AO19: 1990
A20: 2023-10-27 16:33:55 | B20: REG-0081 | C20: Idaho | E20: No target | I20: No target | O20: Idaho has no climate change policies in place as seen in https://www.americashealthrankings.org/explore/measures/climate_policy/ID | Q20: Not Specified | AF20: 1787000 | AI20: 83666000000
A21: 2023-10-26 11:41:05 | B21: REG-0082 | C21: Illinois | D21: In law | E21: Net zero | F21: 2050 | H21: 2019 | I21: Emissions reduction target | J21: 26 | K21: 2005 | L21: 2030 | M21: The U.S. Climate Alliance (including Illinois) is a bipartisan coalition of governors securing America’s net-zero future by advancing state-led, high-impact climate action. Alliance members are working to achieve the Paris Agreement’s goal of keeping temperature increases below 1.5 degrees Celsius through four key commitments: 1. Reducing Emissions - "Reducing collective net greenhouse gas (GHG) emissions at least 26-28% by 2025 and 50-52% by 2030, both below 2005 levels, and collectively achieving overall net-zero GHG emissions as soon as practicable, and no later than 2050." 2. Accelerating Action - "Accelerating new and existing policies to reduce climate pollution, build resilience to the impacts of climate change, and promote clean energy deployment at the state and federal levels." 3. Centering Equity - "Centering equity, environmental justice, and a just economic transition in their efforts to achieve their climate goals and create high-quality jobs." 4. Tracking Progress - "Tracking and reporting progress to the global community in appropriate settings, including when the world convenes to take stock of the Paris Agreement." https://usclimatealliance.org/about/ | N21: Reducing collective net GHG emissions at least 26-28 percent by 2025 and 50-52 percent by 2030 (below 2005 levels) | O21: 2023 Update: SPRINGFIELD, IL – Gov. JB Pritzker signed legislation protecting Illinois-based clean energy projects from a growing number of local bans. HB4412 prevents counties from enacting preemptive local ordinances that outright ban local wind and solar projects, hindering the state’s new climate goals set forth in the Climate and Equitable Jobs Act (CEJA). The bill passed during the Illinois General Assembly’s lame duck legislative session, and Gov. Pritzker signed it into law on Friday, Jan. 27, 2023. - https://ilenviro.org/gov-pritzker-signs-legislation-protecting-clean-energy-projects/ Climate and Equitable Jobs Act - https://www2.illinois.gov/IISNews/23893-Climate_and_Equitable_Jobs_Act.pdf 2022 Update: The Illinois Department of Natural Resources (IDNR) has developed a Climate Action Plan (CAP) with the goal of achieving net-zero greenhouse gas emissions by 2050. The CAP outlines strategies for reducing emissions from operations, buildings, and transportation, and increasing the use of renewable energy production sources. The CAP was facilitated by the Illinois Smart Energy Design Assistance Center (SEDAC) and developed with the participation of over 70 IDNR staff over the past year. The CAP will guide the agency’s path to reducing its climate footprint while increasing the resilience of natural resources in its care. The CAP outlines the steps to address climate change across the agency and in partnership with communities. - https://dnr.illinois.gov/content/dam/soi/en/web/dnr/outreach/cap/cap-documents/cap-executive-summary.pdf EO 2019-06: Illinois joined US Climate Alliance (http://www.usclimatealliance.org) - https://www.illinois.gov/government/executive-orders/executive-order.executive-order-number-6.2019.html State of Illinois to move toward 100% clean energy by 2050; path to 40% renewable energy by 2030 and 50% by 2040 - https://www.illinois.gov/news/press-release.23893.html | P21: https://static1.squarespace.com/static/5a4cfbfe18b27d4da21c9361/t/5d8e52300ba3362bcd5df005/1569608241528/USCA_2019+State+Factsheet-IL_20190924.pdf | Q21: Carbon dioxide and other GHGs | R21: Not Specified | S21: Not Specified | T21: No | U21: Reach Net Zero Greenhouse Gas Emissions by 2050. IDNR emits an estimated 38,700 MTCO2e annually, equivalent to emissions from 8,600 gasoline-powered passenger vehicles driven for one year. IDNR emissions come from building energy use (72%), internal transportation and fuels for site operations (20%), solid waste (7%), and water/wastewater (1%). IDNR’s goal is to reduce emissions as much as possible through conservation and energy efficiency. Remaining emissions will be offset with renewable energy generation to reach Net Zero emissions by 2050. - https://dnr.illinois.gov/outreach/climate-action-plan.html | V21: Yes | W21: Information on the emission reductions expected from these measures within a certain time period | X21: No reporting mechanism | Y21: Yes | Z21: Not Specified | AA21: Equity: IDNR should prioritize equity and inclusion in its climate action efforts by engaging and empowering underserved communities that have been disproportionately impacted by climate change and by promoting diversity, equity, accessibility, and inclusion within the organization. - https://dnr.illinois.gov/content/dam/soi/en/web/dnr/outreach/cap/cap-documents/cap-executive-summary.pdf https://www2.illinois.gov/IISNews/23893-Climate_and_Equitable_Jobs_Act.pdf | AB21: Not Specified | AC21: No | AD21: Yes (nature-based removals e.g. Forestation, soil carbon enhancement) | AE21: Unavoidable emissions from visitor transportation can be offset by biological carbon sequestration initiatives: native plantings, habitat restoration, prairie recovery, and floodplain management. - https://dnr.illinois.gov/content/dam/soi/en/web/dnr/outreach/cap/cap-documents/cap-executive-summary.pdf | AF21: 12670000 | AG21: 210200000 | AH21: 2018 | AI21: 885583000000
A22: 2023-12-21 16:45:46 | B22: REG-0083 | C22: Indiana | E22: No target | I22: No target | Q22: Not Specified | AF22: 6732000 | AI22: 379684000000
A23: 2023-11-02 10:58:32 | B23: REG-0084 | C23: Iowa | E23: No target | I23: No target | Q23: Not Specified | AF23: 3155000 | AI23: 194658000000
A24: 2023-12-16 17:00:13 | B24: REG-0085 | C24: Kansas | E24: No target | I24: No target | R24: Not Specified | S24: Not Specified | T24: No | V24: No | X24: No reporting mechanism | Y24: No | Z24: Not Specified | AB24: Not Specified | AC24: No | AD24: Not Specified | AF24: 2913000 | AI24: 176493000000
A25: 2023-12-21 16:52:01 | B25: REG-0086 | C25: Kentucky | E25: No target | I25: No target | Q25: Not Specified | AF25: 4468000 | AI25: 215399000000
A26: 2024-03-12 15:48:34 | B26: REG-0087 | C26: Maryland | D26: In law | E26: Net zero | F26: 2045 | H26: 2023 | I26: Emissions reduction target | J26: 60 | K26: 2006 | L26: 2031 | M26: "Attain a net-zero economy by 2045" (June 2023 Maryland's Climate Pathway Report, p.20) | N26: "60% reduction of GHG emissions by 2031 relative to 2006 levels" (June 2023 Maryland's Climate Pathway Report, p.20) | O26: "Climate Solutions Now Act of 2022" sets more ambitious targets than the 2016 "Greenhouse Gas Emissions Reduction Act – Reauthorization" and codifies into law the target of reaching net-zero by 2045 Maryland plans to meet these targets "with additional reductions including 3.6 MMTCO2e from transportation, 2.3 MMTCO2e from electricity generation and 1.6 MMTCO2e from buildings" | P26: https://mde.maryland.gov/programs/air/ClimateChange/Documents/MARYLANDS%20PATHWAY%20REPORT%20AND%202031%20GHG%20PLAN/Maryland%27s%20Climate%20Pathway%20Report.pdf | Q26: Carbon dioxide and other GHGs | R26: Yes | S26: Not Specified | T26: Yes | U26: "GHG emission results are calibrated to the 2020 Maryland GHG inventory the last available year of historical data" (June 2023 Maryland's Climate Pathway Report, p.31) | V26: Yes | W26: Measures for all emission scopes that are covered by the target|Information on the emission reductions expected from these measures within a certain time period|Information on the extent to which measures will be applied (e.g. if switching to EVs, what share of the fleet; if installing an own solar PV installation, what is the installed capacity) | X26: Annual reporting | Y26: Yes | Z26: Not Specified | AA26: "Once the final version of Maryland's climate plan has been adopted, further collaboration and engagement within and across sectors can help support and deliver the needed action...This report identifies key areas for continued work to deepen the understanding of important sectors and strategies for meeting the state's climate goals". (June 2023 Maryland's Climate Pathway Report, p.99) - Although the report recognises that further work will be needed, it does not set out formal deadlines to ensure accountability. "State agencies, many of which have a prominent role in the implementation of the policies and initiatives in this plan, are required to report annually on the status of programs that support the state’s GHG reduction efforts or address climate change to the Maryland Commission on Climate Change." (https://mde.maryland.gov/programs/air/ClimateChange/Maryland%20Climate%20Reduction%20Plan/Maryland%27s%20Climate%20Pollution%20Reduction%20Plan%20-%20Final%20-%20Dec%2028%202023.pdf, page 95) - "These annual reports must include program descriptions and objectives; implementation milestones and whether or not they have been met; enhancement opportunities; funding; challenges; estimated GHG reductions by program for the prior calendar year; and any other information that the agency considers relevant" | AB26: No | AC26: No | AD26: Yes (nature-based removals e.g. Forestation, soil carbon enhancement) | AE26: Most of the plan focuses on emissions reduction for particular sectors rather than looking at ways in which carbon could be stored or captured from the atmosphere. "Net emissions sinks (carbon sequestration pathways) in this sector include the carbon flux in forested and treed landscapes; carbon stored in harvested wood products, wood in landfills, and landfilled yard trimmings and food scraps; carbon flux in agricultural soils; and carbon flux in coastal (tidal) wetlands and submerged aquatic vegetation. This sector is not included in Maryland’s gross emissions accounting and is instead factored into Maryland’s net emissions calculation for 2045." (https://mde.maryland.gov/programs/air/ClimateChange/Maryland%20Climate%20Reduction%20Plan/Maryland%27s%20Climate%20Pollution%20Reduction%20Plan%20-%20Final%20-%20Dec%2028%202023.pdf, page 60) "Expanding statewide adoption of agricultural conservation practices and scaling forest conservation and restoration beyond current levels offers an opportunity to increase carbon removal from the atmosphere" (https://mde.maryland.gov/programs/air/ClimateChange/Maryland%20Climate%20Reduction%20Plan/Maryland%27s%20Climate%20Pollution%20Reduction%20Plan%20-%20Final%20-%20Dec%2028%202023.pdf, page 64) | AF26: 6046000 | AG26: 59400000 | AH26: 2018 | AI26: 426747000000
A27: 2023-05-23 14:54:46 | B27: REG-0088 | C27: Minnesota | D27: In law | E27: Emissions reduction target | F27: 2050 | H27: 2007 | I27: Emissions reduction target | J27: 30 | K27: 2005 | L27: 2025 | M27: In 2007, Governor Tim Pawlenty signed the Next Generation Energy Act (NGEA), which outlined a series of goals for reducing carbon emissions and supporting energy efficiency and clean, renewable energy in Minnesota. The NGEA, which had bipartisan support in the state legislature, set statutory goals to reduce GHG emissions in the state by 30% by 2025 (from 2005 levels) and by 80% by 2050. But Minnesota did not meet its 2015 goal of 15% reduction, and is not on track to meet the 2025 goal. | O27: https://mn.gov/commerce/news/?id=17-563384 Bill signed in 2023 for "100% carbon-free electricity by 2040" | P27: https://climate.state.mn.us/ | Q27: Carbon dioxide and other GHGs | R27: Yes | S27: No | T27: No | U27: ""Greenhouse gases" include carbon dioxide, methane, nitrous oxide, hydrofluorocarbons, perfluorocarbons, and sulfur hexafluoride or any other chemical that is determined by the Pollution Control Agency to contribute comparably to global climate change and that is emitted by anthropogenic sources." - https://www.revisor.mn.gov/bills/text.php?number=HF436&type=ce&version=1&session=ls85&session_year=2007&session_number=0 | V27: Yes | W27: Measures for all emission scopes that are covered by the target|Information on the emission reductions expected from these measures within a certain time period|Information on the extent to which measures will be applied (e.g. if switching to EVs, what share of the fleet; if installing an own solar PV installation, what is the installed capacity)|Schedule for regular review of measures | X27: Annual reporting | Y27: No | Z27: No | AA27: https://mn.gov/governor/assets/2019_12_2_EO_19-37_Climate_tcm1055-412094.pdf | AB27: No | AC27: No | AD27: Yes (nature-based removals e.g. Forestation, soil carbon enhancement) | AF27: 5640000 | AG27: 92600000 | AH27: 2018 | AI27: 383777000000 | AN27: 80 | AO27: 2005
A28: 2023-12-21 16:48:32 | B28: REG-0089 | C28: Mississippi | E28: No target | I28: No target | P28: https://climate-xchange.org/dashboard/map/mississippi/ | Q28: Not Specified | AF28: 2976000 | AI28: 115971000000
A29: 2023-12-09 13:10:15 | B29: REG-0090 | C29: Missouri | E29: No target | I29: No target | Q29: Not Specified | AF29: 6137000 | AI29: 328401000000
A30: 2023-12-21 16:50:24 | B30: REG-0091 | C30: Nebraska | E30: No target | I30: No target | Q30: Not Specified | AF30: 1934000 | AI30: 130012000000
A31: 2023-09-23 18:07:42 | B31: REG-0092 | C31: New Hampshire | D31: In policy document | E31: Emissions reduction target | F31: 2050 | I31: Emissions reduction target | J31: 20 | K31: 1990 | L31: 2025 | M31: "The Task Force recommends that New Hampshire strive to achieve a long-term reduction in greenhouse gas emissions of 80 percent below 1990 levels by 2050." | N31: "Based on the greenhouse gas emission reductions projected for the recommended actions, the Task Force has chosen a mid-term goal of reducing greenhouse gas emissions 20 percent below 1990 levels by 2025." | P31: https://www.des.nh.gov/sites/g/files/ehbemt341/files/documents/r-ard-09-1.pdf | Q31: Not Specified | V31: No | Z31: No | AB31: Yes | AD31: Not Specified | AE31: New Hampshire is part of RGGI | AF31: 1360000 | AG31: 13800000 | AH31: 2016 | AI31: 87634000000 | AK31: Maximum percentage of emissions that can be offset | AN31: 80 | AO31: 1990
A32: 2024-02-21 10:26:31 | B32: REG-0093 | C32: New Jersey | D32: In law | E32: Emissions reduction target | F32: 2050 | H32: 2021 | I32: Emissions reduction target | J32: 50 | K32: 2006 | L32: 2030 | M32: "Under this law, the Department of Environmental Protection (DEP) is responsible for assessing the state’s greenhouse gas emissions and, in collaboration with other state agencies, presenting recommendations for reducing emissions by 20% below 2006 levels by 2020 and 80% by 2050—known as the 80x50 goal." (as of 2020 in Version 1.0 of the New Jersey 80x50 report) | N32: https://dep.nj.gov/ghg/ghg-emissions-goals/: "In 2021, Governor Murphy signed Executive Order 274, this order established an interim greenhouse gas reduction target of 50 percent below 2006 levels (approximately 60.6 MMTCO2e) by 2030." | O32: As of October 2020, New Jersey has already reduced emissions by 20% below 2006 levels. https://dep.nj.gov/ghg/ghg-emissions-goals/: The Global Warming Response Act (GWRA) (P.L. 2007 c.112; P.L. 2019 c.197) established two greenhouse gas reduction goals for New Jersey: 1) Reduce statewide greenhouse gas emissions to 1990 levels (approximately 111.5 MMTCO2e) by the year 2020, and, 2) Reduce statewide greenhouse gas emissions 80% below the 2006 level (approximately 24.2 MMTCO2e) by the year 2050. | P32: https://dep.nj.gov/wp-content/uploads/climatechange/nj-gwra-80x50-report-2020.pdf | Q32: Carbon dioxide and other GHGs | R32: Yes | S32: No | T32: No | U32: Gases covered: CO2, black carbon, methane, halogenated gases (HFCs) | V32: Yes | W32: Measures for all emission scopes that are covered by the target|Information on the emission reductions expected from these measures within a certain time period|Information on the extent to which measures will be applied (e.g. if switching to EVs, what share of the fleet; if installing an own solar PV installation, what is the installed capacity) | X32: Less than annual reporting | Y32: No | Z32: Not Specified | AB32: Not Specified | AC32: No | AD32: Yes (nature-based removals e.g. Forestation, soil carbon enhancement) | AE32: "Natural carbon sinks are an important component of New Jersey’s GHG inventory and management system...New Jersey’s land sector sequestered the equivalent of 8.1 MMT CO2e (8% of New Jersey’s net emissions) in 2018... Collectively, DEP projects that strategies to conserve and protect the state’s natural carbon sinks could increase carbon sequestration up to 33% to 10.8 MMT CO2e by 2050." | AF32: 8882190 | AG32: 108100000 | AH32: 2018 | AI32: 634784000000 | AN32: 80 | AO32: 2006
A33: 2024-02-25 20:41:36 | B33: REG-0094 | C33: New Mexico | D33: In law | E33: Emissions reduction target | F33: 2030 | H33: 2019 | I33: No target | M33: The State of New Mexico will support the 2015 Paris Agreement Goals by joining the U.S. Climate Alliance. New Mexico's objective is to achieve a statewide reduction in greenhouse gas emissions of at least 45% by 2030 as compared to 2005 levels. | O33: Still working towards this target in latest Climate Strategy Report (2021): https://www.climateaction.nm.gov/wp-content/uploads/sites/39/2023/07/NMClimateChange_2021_final.pdf | P33: https://www.governor.state.nm.us/wp-content/uploads/2019/01/EO_2019-003.pdf | Q33: Carbon dioxide and other GHGs | R33: Yes | S33: No | T33: No | V33: Yes | X33: Less than annual reporting | Y33: Yes | Z33: Not Specified | AA33: Between 2019-2021, an annual Climate Strategy Report was published; this no longer appears to be the case. | AB33: Not Specified | AC33: No | AD33: Yes (nature-based and CCS-based removals) | AE33: 2021 Climate Strategy Report discusses purchasing credits from generators of low-carbon-intensity fuels or businesses that reduce emissions from the transportation sector* 2019 Climate Strategy Report discusses reforestation projects** *https://www.climateaction.nm.gov/wp-content/uploads/sites/39/2023/07/NMClimateChange_2021_final.pdf **https://www.climateaction.nm.gov/wp-content/uploads/sites/39/2023/07/NMClimateChange_2019.pdf | AF33: 2096829 | AG33: 45400000 | AH33: 2018 | AI33: 105143000000 | AN33: 45 | AO33: 2005
A34: 2024-02-29 04:15:25 | B34: REG-0095 | C34: North Carolina | D34: Pledge | E34: Net zero | F34: 2050 | H34: 2022 | I34: Emissions reduction target | J34: 50 | K34: 2005 | L34: 2030 | M34: In EXECUTIVE ORDER NO. 246: NORTH CAROLINA'S TRANSFORMATION TO A CLEAN, EQUITABLE ECONOMY (ordered January 7, 2022): "...achieve net-zero emissions as soon as possible, no later than 2050," | N34: "Reduce statewide GHG emissions to at least 50 percent below 2005 levels by 2030," | O34: "Governor Roy Cooper today issued Executive Order No. 246 affirming North Carolina’s commitment to a clean energy economy and directing next steps in the state’s plan to achieve net-zero greenhouse gas emissions and create economic opportunities for North Carolinians across the state, especially in underserved communities." (https://governor.nc.gov/news/press-releases/2022/01/07/governor-cooper-signs-executive-order-detailing-next-steps-path-clean-energy-and-equitable-economy) Updates North Carolina’s economy-wide carbon reduction emissions goals to align with climate science, reduce pollution, create good jobs and protect communities. Increases the statewide goal to a 50% reduction from 2005 levels by 2030 and net-zero greenhouse gas emissions as soon as possible, no later than 2050. Directs the Governor’s administration to update a statewide greenhouse gas inventory to measure current levels of greenhouse gas emissions, as well as analyze potential pathways for achieving net-zero greenhouse gas emissions by 2050. Calls for an increase in registered zero-emission vehicles (ZEVs) to at least 1,250,000 by 2030 and for 50% of sales of new vehicles in North Carolina to be zero-emission by 2030. It also directs the North Carolina Department of Transportation to develop a North Carolina Clean Transportation Plan for decarbonizing the transportation sector through reductions in vehicle miles traveled, an increase in zero-emission cars, trucks, and buses, and other strategies. | P34: https://governor.nc.gov/executive-order-no-246/open | Q34: Not Specified | R34: Yes | S34: No | T34: No | V34: No | X34: Less than annual reporting | Y34: No | Z34: No | AB34: Not Specified | AC34: No | AD34: Not Specified | AF34: 104888084 | AG34: 119300000 | AH34: 2018 | AI34: 591601000000
A35: 2023-12-16 17:06:16 | B35: REG-0096 | C35: North Dakota | D35: Proposed | E35: Carbon neutral(ity) | F35: 2030 | H35: 2021 | I35: No target | M35: "We can reach carbon neutrality in the state of North Dakota by 2030 without a single mandate, without any additional regulation"; "challenge to make North Dakota a carbon-neutral state by 2030" | P35: https://climate-xchange.org/dashboard/map/north-dakota/ | Q35: Not Specified | R35: Not Specified | S35: Not Specified | T35: No | V35: No | X35: No reporting mechanism | Z35: No | AB35: Not Specified | AC35: No | AD35: Yes (CCS-based removals e.g. BECCS, DACCS) | AE35: https://www.governor.nd.gov/news/updated-waudio-burgum-addresses-williston-basin-petroleum-conference-issues-carbon-neutral There are bills to support CCSU efforts | AF35: 762062 | AI35: 57181000000
A36: 2023-06-21 12:46:01 | B36: REG-0097 | C36: Ohio | E36: No target | I36: No target | Q36: Not Specified | AF36: 11689100 | AI36: 695362000000
A37: 2023-07-20 22:04:10 | B37: REG-0098 | C37: Oklahoma | E37: Other | H37: 2021 | I37: No target | O37: Oklahoma plans to remain a top 5 producer of clean renewable energy, partner with new technologies to maximise solar power. Oklahoma pioneered the 'Water for 2060' Act, this aims to consume no more freshwater than was consumed in 2010. Oklahoma achieved its goals of expanding CNG fueling and EV charging infrastructure as outlined in the 2011 First Energy Plan. After reaching a high of 125 stations in 2016, CNG has settled at 120 fueling stations. Oklahoma is home to 258 EV Charging locations, which they predict to rise through the ChargeOK program. | P37: https://ee.ok.gov/wp-content/uploads/2021/09/FUL-FEP_Final-Draft6-1.pdf | Q37: Not Specified | R37: Not Specified | S37: No | T37: No | U37: 'Our Vision is to protect and enhance the natural beauty of the State of Oklahoma. This vision will ensure that the land, air, water and wildlife of our beautiful and ecologically diverse State remain accessible for generations to come. Oklahoma will continue to harness our vast natural resources to allow our economy to thrive while delivering a pristine environment for our citizens. We will pursue regulatory policies that ensure a prosperous Oklahoma without sacrificing environmental protection. Our support for the Environmental, Health, and Safety Audit Privilege Act shows our commitment to this dual purpose. Oklahoma’s Water for 2060 Plan, our partnership with U.S. EPA under the National Water Reuse Action Plan, and our dedication to improve the efficiency of water systems around the state, all show our commitment to remain responsible stewards of our water resources. Our commitment to expand our electric vehicle infrastructure and capitalize on clean burning fuels for our vehicles demonstrates our continued effort to improve our air quality.' | V37: Yes | X37: Less than annual reporting | Y37: No | Z37: Not Specified | AA37: Report states it has been over a decade since Oklahoma last published an Energy plan. 'The Oklahoma 2021 Energy Plan is meant to highlight Oklahoma’s incredible energy story and set a roadmap for the future.' Plan does not specify numeric goals and states that 'Oklahoma tries to avoid picking winners and losers. We achieved our status as energy leaders and energy pioneers by following the trends of consumers and investors while following demand.' | AB37: Not Specified | AC37: No | AD37: No | AE37: No mention of sinks/credits. | AF37: 3956971 | AI37: 202036000000 | AP37: oklahoma’s plans to 'continue of a lower carbon trajectory' but no specific carbon reduction plans in place as of the 2021 state energy & environment plan. oklahoma describes their environmental plan as follows 'you will notice that this plan does not set specific numeric goals for one particular fuel source versus another and oklahoma tries to avoid picking winners and losers. we achieved our status as energy leaders and energy pioneers by following the trends of consumers and investors while following demand. unnecessary regulation and mandates serves only to penalize the consumer by making all forms of energy more expensive while not following demand. one of our main objectives is to ready our state to take on whatever new challenges arise and to lead in whatever’s next in energy that fits our diverse natural resources and human capital.'
A38: 2023-12-16 13:22:58 | B38: REG-0099 | C38: Oregon | D38: In law | E38: Emissions reduction target | F38: 2050 | H38: 2020 | I38: Emissions reduction target | J38: 45 | K38: 1990 | L38: 2035 | M38: Executive Order No. 20-04, Page Five 2. GHG Emissions Reduction Goals. Consistent with the Minimum GHG reduction goals set forth in ORS 468A.205(1)(c), this Executive Order establishes science-based GHG emissions reduction goals, and calls for the State of Oregon to reduce its GHG emissions (1) at least 45 percent below 1990 emisisons levels by 2035; and (20 at least 80 percent below 1990 emissions levels by 2050. https://www.oregon.gov/gov/eo/eo_20-04.pdf | N38: Executive Order No. 20-04, Page Five 2. GHG Emissions Reduction Goals. Consistent with the Minimum GHG reduction goals set forth in ORS 468A.205(1)(c), this Executive Order establishes science-based GHG emissions reduction goals, and calls for the State of Oregon to reduce its GHG emissions (1) at least 45 percent below 1990 emisisons levels by 2035; and (20 at least 80 percent below 1990 emissions levels by 2050. https://www.oregon.gov/gov/eo/eo_20-04.pdf | O38: https://www.oregon.gov/gov/Pages/carbonpolicy_climatechange.aspx https://www.oregon.gov/energy/energy-oregon/Pages/Climate-Change-Energy.aspx https://www.oregonencyclopedia.org/articles/climate-change-in-oregon/ 2021 Bill "Requires retail electricity providers to reduce greenhouse gas emissions associated with electricity sold to Oregon consumers to 80 percent below baseline emissions levels by 2030, 90 percent below baseline emissions levels by 2035 and 100 percent below baseline emissions levels by 2040." - https://olis.oregonlegislature.gov/liz/2021R1/Measures/Overview/HB2021 Oregon made significant progress in 2021 by passing a clean electricity standard requiring utilities to eliminate electricity-related GHG emissions by 2040, adopting the Clean Trucks Rule to accelerate zero-emissions truck sales, and approving a new emissions cap for covered natural gas and transportation fuels under the Climate Protection Program (CPP). If implemented, these historic policies could significantly cut Oregon’s emissions by 2050. Oregon’s clean electricity standard will reduce power sector emissions 100% by 2040 through 2050, compared to just a 36% reduction by 2050 without it, cutting state-wide GHG emissions more than 11 MMT annually by 2040. The state’s average temperatures have increased by 2.2ºF (1.2ºC) since 1895, and scientists predict they will increase by another 5ºF (2.8ºC) by 2050 and 8.2ºF (4.6ºC) by 2080. | P38: https://www.oregon.gov/gov/eo/eo_20-04.pdf | Q38: Carbon dioxide and other GHGs | R38: Not Specified | S38: Not Specified | T38: No | V38: Yes | W38: Schedule for regular review of measures | X38: Less than annual reporting | Y38: No | Z38: Not Specified | AA38: The Oregon Global Warming Commission (OGWC) is directed by statute to produce a biennial report to the Governor and Legislature on Oregon’s progress toward meeting the state’s GHG emission reduction goals. High-level plan from OGWC is the Oregon Climate Action Roadmap to 2030 (https://static1.squarespace.com/static/59c554e0f09ca40655ea6eb0/t/64275befc3f5d82a60b981b2/1680301043241/2023-Climate-Action-Roadmap.pdf). Details of plan's methods are in the Transformational Integrated Greenhouse Gas Emissions Reduction Project Report (https://static1.squarespace.com/static/59c554e0f09ca40655ea6eb0/t/64275c449499a72eb55aa206/1680301133140/2023-TIGHGER-Project-Report.pdf). Appears to only cover Scope 1: "Calculated GHG reduction amounts from each action are only the direct emission reductions (scope one emissions) and not the secondary or tertiary emission reductions. Only the GHG emissions reductions from direct energy use reduction or avoided emissions caused by an action were calculated." Programs and projects related to targets are led by various state entities, summarized at https://olis.oregonlegislature.gov/liz/2023R1/Downloads/CommitteeMeetingDocument/261893. | AB38: Not Specified | AC38: No | AD38: Not Specified | AE38: "consideration of adoption of state goals for carbon sequestration and storage by Oregon's natural and working landscapes' | AF38: 4217737 | AG38: 64561358 | AH38: 2017 | AI38: 253623000000 | AN38: 80 | AO38: 1990
A39: 2023-06-20 13:57:02 | B39: REG-0100 | C39: Pennsylvania | D39: In policy document | E39: Emissions reduction target | F39: 2050 | I39: Emissions reduction target | J39: 26 | K39: 2005 | L39: 2025 | M39: "Governor Tom Wolf issued an Executive Order in 2019 that established a Pennsylvania climate goal of ... an 80% reduction by 2050, from 2005 levels." Sources: - https://www.youtube.com/watch?v=0o815pMSB9E - https://www.dep.pa.gov/Citizens/climate/Pages/PA-Climate-Action-Plan.aspx - https://www.sierraclub.org/pennsylvania/blog/2022/02/overview-pennsylvanias-2021-climate-action-plan | N39: "Governor Tom Wolf issued an Executive Order in 2019 that established a Pennsylvania climate goal of a 26% reduction in GHG emissions statewide by 2025 ...from 2005 levels." Sources: - https://www.youtube.com/watch?v=0o815pMSB9E - https://www.dep.pa.gov/Citizens/climate/Pages/PA-Climate-Action-Plan.aspx - https://www.sierraclub.org/pennsylvania/blog/2022/02/overview-pennsylvanias-2021-climate-action-plan | P39: https://files.dep.state.pa.us/Energy/Office%20of%20Energy%20and%20Technology/OETDPortalFiles/Climate%20Change%20Advisory%20Committee/2021/6-22-21/FINAL_DRAFT_PA_CAP_2021_June_16_2021.pdf | Q39: Carbon dioxide and other GHGs | R39: Yes | S39: Not Specified | T39: No | U39: - “[g]ases that trap heat in the atmosphere, contributing to global warming and climate change. Common GHGs include carbon dioxide (CO2), methane (CH4), nitrous oxide (N20), and fluorinated gases”. (p. 162) Source: https://www.dep.pa.gov/Citizens/climate/Pages/PA-Climate-Action-Plan.aspx - "If all states achieved such targets, and other nations met comparable goals, climate science analysis suggests that global temperature rise could be kept below the 2-degree Celsius threshold. Accordingly, the GHG reduction targets used in this Plan are: 26 percent reduction of net GHG emissions by 2025, from 2005 levels, 80 percent reduction of net GHG emissions by 2050, from 2005 levels" Source: https://www.c2es.org/wp-content/uploads/2020/06/PA_2019_Action_Plan.pdf | V39: Yes | W39: Measures for all emission scopes that are covered by the target|Information on the emission reductions expected from these measures within a certain time period|Information on the extent to which measures will be applied (e.g. if switching to EVs, what share of the fleet; if installing an own solar PV installation, what is the installed capacity) | X39: Less than annual reporting | Y39: Yes | Z39: No | AA39: - "The Pennsylvania Climate Change Act of 2008 (Act 70) requires the Department of Environmental Protection (DEP) to compile an annual greenhouse gas (GHG) inventory for Pennsylvania’s GHG emissions, to develop a voluntary GHG registry, and to develop a climate action plan (CAP) and impacts assessment (IA) and update them every three years." - "Equity was considered and integrated into the evaluation and prioritization of the GHG reduction strategies. Strategy-specific considerations related to equity are included in the implementation recommendations below." - Example of equity consideration in Pennsylvania Climate Action Plan 2021: "Be cost-effective on a cost per MTCO2e reduced basis when considered together as a cohesive approach to reducing GHG emissions in the Commonwealth. Additionally, most strategies result in co-benefits such as improved air and water quality, improved health outcomes, increased energy security, and improved equity and environmental justice outcomes." Source: https://files.dep.state.pa.us/Energy/Office%20of%20Energy%20and%20Technology/OETDPortalFiles/Climate%20Change%20Advisory%20Committee/2021/6-2221/FINAL_DRAFT_PA_CAP_2021_June_16_2021.pdf | AB39: Yes | AC39: No | AD39: Yes (nature-based and CCS-based removals) | AE39: "The strategies outlined above will rely on existing and future technologies. Leveraging technologies will allow the Commonwealth to more effectively implement the proposed GHG reduction strategies, typically by optimizing performance, reducing overall implementation costs, and/or by reducing GHG emissions at a greater level than possible through alternative technologies or in the absence of technology. Many of these technologies will also be key elements of increasing the resilience and reliability of Pennsylvania’s energy systems. Seven key enabling technologies were identified, including: • Incentivizing grid-level battery storage; • Power-to-gas and blue and green hydrogen; • Carbon capture, utilization, and storage (CCUS); • Direct Air Capture (DAC); • Peak energy load and balancing strategies; • Carbon offsets; and • Disruptive digital technologies" Source: https://files.dep.state.pa.us/Energy/Office%20of%20Energy%20and%20Technology/OETDPortalFiles/Climate%20Change%20Advisory%20Committee/2021/6-22-21/FINAL_DRAFT_PA_CAP_2021_June_16_2021.pdf | AF39: 12801989 | AG39: 221300000 | AH39: 2018 | AI39: 808738000000 | AK39: Must be high environmental integrity|Other conditions | AM39: "Carbon offsets must meet the following requirements: • Be verified as legitimate (i.e., a trusted third-party verifies that the offset action will truly reduce emissions) • Be “additional” (i.e., the activity would not have taken place without the purchase of the offset) • Be real and permanent (i.e., an acre of trees was actually planted and will not be cut down right after the offset is issued)" Source: https://files.dep.state.pa.us/Energy/Office%20of%20Energy%20and%20Technology/OETDPortalFiles/Climate%20Change%20Advisory%20Committee/2021/6-2221/FINAL_DRAFT_PA_CAP_2021_June_16_2021.pdf | AN39: 80 | AO39: 2005
A40: 2023-09-12 16:22:19 | B40: REG-0101 | C40: Rhode Island | D40: In law | E40: Net zero | F40: 2050 | H40: 2021 | I40: Emissions reduction target | J40: 45 | K40: 1990 | L40: 2030 | M40: § 42-6.2-9. Statewide greenhouse gas emission reduction mandate. Mandatory targets for emissions reduction: It is hereby established that the state shall reduce its statewide greenhouse gas emissions to the targets set forth in § 42-6.2-2(a)(2)(i), as those targets may from time to time be revised, and that achieving those targets shall be mandatory under the provisions of this chapter. The targets at the time of the enactment of this act [April 10, 2021] are that greenhouse gas emissions shall be ten percent (10%) below 1990 levels by 2020, shall be forty-five percent (45%) below 1990 levels by 2030; eighty percent (80%) below 1990 levels by 2040, and shall be net-zero emissions by 2050. (http://webserver.rilin.state.ri.us/Statutes/TITLE42/42-6.2/42-6.2-9.htm) | N40: § 42-6.2-9. Statewide greenhouse gas emission reduction mandate. Mandatory targets for emissions reduction: It is hereby established that the state shall reduce its statewide greenhouse gas emissions to the targets set forth in § 42-6.2-2(a)(2)(i), as those targets may from time to time be revised, and that achieving those targets shall be mandatory under the provisions of this chapter. The targets at the time of the enactment of this act [April 10, 2021] are that greenhouse gas emissions shall be ten percent (10%) below 1990 levels by 2020, shall be forty-five percent (45%) below 1990 levels by 2030; eighty percent (80%) below 1990 levels by 2040, and shall be net-zero emissions by 2050. (http://webserver.rilin.state.ri.us/Statutes/TITLE42/42-6.2/42-6.2-9.htm) | O40: 2021 Act on Climate mandates 45% reduction below 1990 levels by 2030, 80% below 1990 levels by 2040, and net-zero emissions by 2050. (https://climatechange.ri.gov/act-climate) | P40: http://webserver.rilin.state.ri.us/Statutes/TITLE42/42-6.2/INDEX.HTM | Q40: Carbon dioxide and other GHGs | R40: Yes | S40: Not Specified | T40: No | U40: CO2 and other GHGs are specified in the 2022 Climate Update (https://climatechange.ri.gov/act-climate/2025-climate-update; 2022 Climate Update pdf; pg 14). | V40: Yes | W40: Schedule for regular review of measures | X40: Less than annual reporting | Y40: Yes | Z40: Yes | AA40: A comprehensive climate strategy will be developed by 2025, to be updated every five years thereafter. The 2022 Climate Update report refined the 1990 baseline measures and provided recommendations for priority actions by sector. High-level modeling of some recommended actions showed that the 2030 mandate will not be met. "[I]t is projected that Rhode Island is not fully on track to meet the Act on Climate’s 2030 reduction mandate of 45% by 0.5 MMTCO2e. To put this in perspective, the emissions in 2030 are projected by the EPS to be 7.39 MMTCO2e, as compared to the 1990 baseline of 12.48 MMTCO2e...More refined modeling and development of specific strategies to increase that confidence will be the crux of the 2025 Climate Strategy." (https://climatechange.ri.gov/act-climate/2025-climate-update; 2022 Climate Update pdf; pgs 9, 60) References to equity are in § 42-6.2-2 (2) (http://webserver.rilin.state.ri.us/Statutes/TITLE42/42-6.2/42-6.2-2.htm) and the 2022 Update, Priority Actions to Address Climate Justice (pg 88). Enforcement (§ 42-6.2-10; http://webserver.rilin.state.ri.us/Statutes/TITLE42/42-6.2/42-6.2-10.htm) allows the state Attorney General or state residents/entities to bring a civil suit after 2026 for not meeting targets. | AB40: Not Specified | AC40: No | AD40: Yes (nature-based removals e.g. Forestation, soil carbon enhancement) | AE40: Per 2022 Update (https://climatechange.ri.gov/act-climate/2025-climate-update; 2022 Climate Update pdf), Rhode Island’s revised GHG methodology for the 2019 inventory included emissions sinks. Accounting for 2019 (baseline) included -7.2% of gross GHG emissions (-0.78 MMTCO2e) offset by Land Use, Land Use Change, and Forestry (pg 22). "As we progress toward 2050, we will continue to refine methods of accounting for emissions reductions due to land use, land use change, and forestry." (pg. 16) The 2022 Update addresses the use of offsets for baseline accounting in the electric sector (pgs 25-27), but future methodology is not specified. | AF40: 1059361 | AG40: 11200000 | AH40: 2018 | AI40: 61884000000
A41: 2023-11-19 16:07:46 | B41: REG-0102 | C41: South Carolina | E41: Other | I41: No target | O41: there are two source URLs: https://columbiabusinessreport.com/news/innovation/84178/ https://www.sustainsouthcarolina.org/roadmap-to-sustain-sc | P41: https://www.sustainsouthcarolina.org/roadmap-to-sustain-sc | Q41: Not Specified | U41: no target specified. | V41: No | AE41: no public plan published. | AF41: 5148714 | AI41: 247544000000 | AP41: there are 7 key areas that sustain sc had identified as part of their roadmap to work on to improve south carolina's rankings of sustainable states in the u.s. : 1) partnerships for economic prosperity and quality of life: sustain sc will advance a future of strong cross-sector collaboration among commerce and conservation partners to attract new, sustainable industries, enhance the existing industry in south carolina, and protect our quality of life. 2) the three-legged stool - affordable, reliable, and sustainable energy: through multi-stakeholder engagement with the private and public sector and conservation ngos, sustain sc supports cross-sector energy engagement to retain and attract industry in our state. 3) stem2030 workforce accelerator: sustain sc is modernizing the stem initiative to ensure all learners have the knowledge and skills to promote sustainable development, enhance scientific research, upgrade technology capabilities, and encourage sustainable innovation throughout every workforce sector. 4) capitalizing on the sustainable revolution: in an effort to establish south carolina as the center point of sustainable economic development, sustain sc is forging alliances between industry and conservation organizations to transition from traditional 20th-century economic practices to 21st-century industries that provide well-paying jobs and implement innovative, sustainable methods in production, supply chain management, and distribution. between 2022 and 2023, companies announced more than $9.7 billion in ev investments across south carolina. 5) the circular economy - south carolina’s new economic opportunity: reducing, reusing, repairing, and repurposing materials for production and consumption in south carolina not only lowers emissions and protects our natural resources, it creates innovative solutions, reduces costs, increases profits, and saves consumers money. industries in sc are engaged in the circular economy, re-envisioning our waste as an economic engine for our future. 6) a resilient state: sustain sc land and water action platform: after five consecutive years of flooding and storms, south carolina’s office of resilience (scor) has created a plan to protect our state’s natural resources and buffer our communities from increased threats through nature-based solutions. sustain sc is collaborating with scor, as well as businesses and organizations in the industry and conservation sectors to leverage state dollars with private and federal dollar investments to protect south carolina's most critical natural resources. 7) meeting goals at the local level: approximately 80% of industries in south carolina are actively assessing and tracking their sustainability efforts. sustain sc is collaborating with both industry and conservation partners to establish standardized metrics and approaches for measuring sustainability at the state level.
A42: 2023-09-23 12:56:57 | B42: REG-0103 | C42: South Dakota | E42: No target | I42: No target | O42: The state passed over an opportunity to draft a GHG emission reduction plan. It could have availed the grants under Inflation Reduction Act, but failed to do so. https://listen.sdpb.org/politics/2023-04-03/state-skips-out-on-3-million-to-craft-emissions-reduction-plan | Q42: Not Specified | AF42: 884659 | AI42: 54941000000
A43: 2023-09-20 09:04:54 | B43: REG-0104 | C43: Tennessee | E43: No target | I43: No target | Q43: Not Specified | AF43: 6829174 | AI43: 376582000000
A44: 2023-02-22 13:29:03 | B44: REG-0105 | C44: Texas | E44: No target | I44: No target | Q44: Not Specified | AF44: 28995881 | AI44: 1843800000000
A45: 2024-03-19 14:14:40 | B45: REG-0106 | C45: Utah | D45: Proposed | E45: Emissions reduction target | F45: 2050 | H45: 2020 | I45: Emissions reduction target | J45: 25 | K45: 2005 | L45: 2025 | M45: Reduce CO2 emissions statewide ... 80% [below 2005 levels] by 2050. | N45: Reduce CO2 emissions statewide 25% below 2005 levels by 2025, 50% by 2030 | O45: "At the request of the Utah Legislature, the Kem C. Gardner Policy Institute ... prepared this Utah Roadmap to assist with legislative policy" - NB have NOT since been adopted by resolution or statute as suggested. See 'roadmap' here - https://gardner.utah.edu/wp-content/uploads/TheUtahRoadmap-Feb2020.pdf?x71849 | P45: https://gardner.utah.edu/utahroadmap/ | Q45: Carbon dioxide only | R45: Not Specified | S45: Not Specified | T45: No | U45: Reduce criteria pollutant air emissions below 2017 levels by 50% by 2050. Reduce CO2 emissions statewide 25% below 2005 levels by 2025, 50% by 2030, and 80% by 2050. | V45: No | X45: No reporting mechanism | Y45: Yes | Z45: No | AA45: Equity: Provide transition assistance to impacted rural communities. Prioritize rural economic development in energy dependent areas, Provide training/scholarships, Invest in placemaking, Invest in housing, Capitalize on opportunity zones | AB45: Not Specified | AC45: No | AD45: Not Specified | AE45: Roadmap only mentions market-based approaches such as "neutral/border adjusted carbon pricing, cap and trade". Also mentions more funding for reforestation. | AF45: 3205958 | AI45: 192519000000 | AN45: 80 | AO45: 2005
A46: 2022-02-05 12:28:53 | B46: REG-0107 | C46: Vermont | D46: In law | E46: Emissions reduction target | F46: 2050 | H46: 2020 | I46: Emissions reduction target | J46: 26 | K46: 2005 | L46: 2025 | M46: In 2020, the Vermont Legislature passed the Global Warming Solutions Act (Act 153 as Enacted), which created legally binding emission reduction targets. The Act was created in response to concerns around Vermont’s changing climate and the magnitude of what must be done to reduce greenhouse gas emissions and prepare for the impacts of climate change on Vermont’s landscape. The Act requires Vermont to reduce greenhouse gas pollution to 26% below 2005 levels by 2025. Emissions would need to be 40% below 1990 levels by 2030 and 80% below by 2050. In addition to the emission reductions required by the statute, the law also directs the Council to consider opportunities for conservation through long-term carbon sequestration and identify actions Vermont communities can take to better prepare for more extreme weather. | N46: In 2020, the Vermont Legislature passed the Global Warming Solutions Act (Act 153 as Enacted), which created legally binding emission reduction targets. The Act was created in response to concerns around Vermont’s changing climate and the magnitude of what must be done to reduce greenhouse gas emissions and prepare for the impacts of climate change on Vermont’s landscape. The Act requires Vermont to reduce greenhouse gas pollution to 26% below 2005 levels by 2025. Emissions would need to be 40% below 1990 levels by 2030 and 80% below by 2050. In addition to the emission reductions required by the statute, the law also directs the Council to consider opportunities for conservation through long-term carbon sequestration and identify actions Vermont communities can take to better prepare for more extreme weather. | O46: In 2020, the Vermont Legislature passed the Global Warming Solutions Act (Act 153 as Enacted), which created legally binding emission reduction targets. The Act was created in response to concerns around Vermont’s changing climate and the magnitude of what must be done to reduce greenhouse gas emissions and prepare for the impacts of climate change on Vermont’s landscape. The Act requires Vermont to reduce greenhouse gas pollution to 26% below 2005 levels by 2025. Emissions would need to be 40% below 1990 levels by 2030 and 80% below by 2050. In addition to the emission reductions required by the statute, the law also directs the Council to consider opportunities for conservation through long-term carbon sequestration and identify actions Vermont communities can take to better prepare for more extreme weather. | P46: http://climatechange.ri.gov/state-actions/governor-climate-priorities.php | Q46: Carbon dioxide and other GHGs | R46: Yes | S46: Yes | T46: No | U46: The calculations in https://dec.vermont.gov/sites/dec/files/aqc/climate-change/documents/_Vermont_Greenhouse_Gas_Emissions_Inventory_Update_1990-2017_Final.pdf appear to cover all sectors. this is the basis of their targets. "The Global Warming Solutions Act includes a requirement that Vermont achieve net zero emissions by 2050 but does not outline which sectors should be included and how to quantify fluxes" Vermont has calculated its GHG emissions and Carbon Removal from agriculture, forestry, and other land uses (AFOLU) in the GHG Emissions Inventory and the Carbon Budget resp. but has not decided what is included in its targets | V46: Yes | W46: Schedule for regular review of measures|Information on the extent to which measures will be applied (e.g. if switching to EVs, what share of the fleet; if installing an own solar PV installation, what is the installed capacity)|Measures for all emission scopes that are covered by the target | X46: Less than annual reporting | Y46: Yes | Z46: No | AA46: SHORT SUMMARY OF PLAN: https://climatechange.vermont.gov/sites/climatecouncilsandbox/files/2021-12/VT%20CAP%20Summary_Final_0.pdf FULL PLAN: https://climatechange.vermont.gov/sites/climatecouncilsandbox/files/2021-12/Initial%20Climate%20Action%20Plan%20-%20Final%20-%2012-1-21.pdf Measures start at page 80, with timelines given for each, and numerical targets given some of the time. REPORTING 2009-2017: https://dec.vermont.gov/sites/dec/files/aqc/climate-change/documents/_Vermont_Greenhouse_Gas_Emissions_Inventory_Update_1990-2017_Final.pdf SCHEDULE FOR REVIEW: "Adoption of the Vermont Climate Action Plan by December 1, 2021, to be updated at least every 4 years, " COMMITMENT TO REPORTING:"Identification of accurate means to measure the state’s GHG emissions and progress towards meeting the reduction requirements" EQUITY: "Support economic sectors and regions of the state that face the greatest barriers to emissions reductions, especially rural and economically distressed regions and industries" equity is mentioned in the details of all the actions | AB46: Not Specified | AC46: No | AD46: Not Specified | AE46: As above, Vermont hasn't decided whether to include natural carbon sinks will be included in its targets | AF46: 623989 | AG46: 5900000 | AH46: 2018 | AI46: 34013000000 | AN46: 80 | AO46: 1990
A47: 2023-08-23 13:44:15 | B47: REG-0108 | C47: Virginia | D47: Proposed | E47: Net zero | F47: 2045 | I47: Other | L47: 2030 | M47: Establishing greenhouse gas emissions reduction goals across Virginia's economy sufficient to reach net-zero emissions by 2045, including the electric power, transportation, industrial, agricultural, building, and infrastructure sectors Source: https://lis.virginia.gov/cgi-bin/legp604.exe?201+ful+CHAP1191 | N47: Developing energy resources necessary to produce 30 percent of Virginia's electricity from renewable energy sources by 2030. Source: https://lis.virginia.gov/cgi-bin/legp604.exe?201+ful+CHAP1191 | P47: https://lis.virginia.gov/cgi-bin/legp604.exe?201+ful+CHAP1191 | Q47: Carbon dioxide only | R47: Not Specified | S47: Not Specified | T47: No | U47: Virginia aims to decarbonise energy sources whilst ensuring this energy is reliable Source: https://lis.virginia.gov/cgi-bin/legp604.exe?201+ful+CHAP1191 | V47: Yes | W47: Measures for all emission scopes that are covered by the target|Information on the extent to which measures will be applied (e.g. if switching to EVs, what share of the fleet; if installing an own solar PV installation, what is the installed capacity)|Schedule for regular review of measures | X47: Less than annual reporting | Y47: Yes | Z47: Not Specified | AA47: There will be interim updates on the Plan by using numerous scoring systems to measure solar and wind power and measuring the impact on disadvantaged communities. | AC47: No | AD47: Not Specified | AF47: 8535519 | AI47: 556905000000 | AJ47: virginia intends to improve the welfare and health of their citizens through enabling widespread renewable, cost-efficient energy sources which will also lead to new jobs and generate revenue. by prioritising investments in disadvantaged communities, virgina aims to mitigate the negative impacts of climate change and develop carbon-free energy resources which will in turn decarbonise the power supply of the commonwealth and include the production of 30% renewable energy sources by 2030.
A48: 2023-12-21 16:54:26 | B48: REG-0109 | C48: West Virginia | E48: No target | I48: No target | Q48: Not Specified | AF48: 1792147 | AI48: 78864000000
A49: 2023-06-20 14:56:03 | B49: REG-0110 | C49: Wisconsin | D49: In policy document | E49: Emissions reduction target | F49: 2025 | H49: 2020 | I49: No target | M49: "This commitment was first demonstrated in Governor Evers' February 2019 announcement... that he would joining the U.S. Climate Alliance, a bipartisan coalition of 25 governors committed to implementing policies that advance the goals of the Paris Agreement: to reduce GHG emissions to 26-28 percent below 2005 levels by 2025' | O49: The emissions reduction percentage is between 26-28% below 2005 levels. | P49: https://climatechange.wi.gov/Documents/Final%20Report/GovernorsTaskForceonClimateChangeReport-LowRes.pdf | Q49: Carbon dioxide and other GHGs | R49: Not Specified | S49: Not Specified | T49: No | U49: -"Ensure the State of Wisconsin is fulfilling the carbon reduction goals of the 2015 Paris Climate Accord." Source: https://evers.wi.gov/Documents/EO%20038%20Clean%20Energy.pdf -"To reduce GHG emissions to 26–28 percent below 2005 levels by 2025." Source: https://climatechange.wi.gov/Documents/Final%20Report/GovernorsTaskForceonClimateChangeReport-LowRes.pdf | V49: Yes | X49: No reporting mechanism | Y49: Yes | Z49: Not Specified | AA49: -The 2020 Governor's Task Force on Climate Change Report outline climate solutions across 9 sectors including climate justice & equity, energy, transportation and eduction. Source: https://climatechange.wi.gov/Documents/Final%20Report/GovernorsTaskForceonClimateChangeReport-LowRes.pdf -Additionally, there is an updated 2023 sectoral plan focusing on how to establish carbon neutral clean energy by 2050. Source: https://osce.wi.gov/PublishingImages/Pages/Forms/EditForm/Clean%20Energy%20Plan%202023%20Progress%20Report.pdf | AB49: Yes | AC49: No | AD49: Yes (nature-based removals e.g. Forestation, soil carbon enhancement) | AE49: - The 2020 Governor's Task Force on Climate Change Report will launch carbon pricing pilots, conducting "internal carbon price research and implementation through UW System Institutions" - "Wisconsin can request plans from utilities that identify how they can cost-effectively close coal plants early. Wisconsin could also consider mechanisms that would allow utilities to cost-effectively address the remaining non-depreciated “book value” of their coal facilities, so these facilities can be closed as soon as feasible, including: Seeking carbon credits from the California or voluntary carbon markets" - Example of relying on nature-based removals to offset GHG emissions; "In addition, producing thermal energy from sustainably produced biomass that is currently generated by propane or heating oil can offset fossil-fuel use and reduce GHG emissions." Source: https://climatechange.wi.gov/Documents/Final%20Report/GovernorsTaskForceonClimateChangeReport-LowRes.pdf | AF49: 5822434 | AI49: 349416000000 | AK49: No conditions specified | AN49: 26 | AO49: 2005
A50: 2023-12-21 16:52:58 | B50: REG-0111 | C50: Wyoming | E50: No target | I50: No target | O50: Governor has spoken of "ambitious goal of net negative C02 emissions", but without disruption to fossil fuel industry or mentioning a date https://governor.wyo.gov/media/news-releases/2021-news-releases/terrapower-wyoming-governor-and-pacificorp-announce-efforts-to-advance-nuc | P50: https://governor.wyo.gov/media/news-releases/2021-news-releases/governor-gordon-celebrates-states-resilience-lays-out-vision-to-address-w | Q50: Not Specified | AF50: 578759 | AI50: 40420000000
A51: 2024-03-21 18:38:43 | B51: REG-0790 | C51: Georgia | E51: No target | I51: No target | O51: The State of Georgia does not have an emission reduction target. The Georgia Environmental Protection Division (EPD) has published the "Peach State Voluntary Emission Reduction Plan" (https://www.epa.gov/system/files/documents/2024-03/georgia_psverp.pdf; dated March 8, 2024). The plan states that "[b]ecause the measures included in this plan are voluntary in nature, no additional regulatory authority is required to enable their implementation." The Georgia EPD plans to publish the "Comprehensive Peach State Voluntary Emission Reduction Plan" by June 1, 2025, which will include voluntary GHG reduction targets (see Section 8.2 Comprehensive Peach State Voluntary Emission Reduction Plan). | P51: https://www.epa.gov/system/files/documents/2024-03/georgia_psverp.pdf | R51: No | S51: Not Specified | T51: No | V51: No | X51: No reporting mechanism | Y51: No | Z51: Not Specified | AB51: Not Specified | AC51: No | AD51: Not Specified | AF51: 10912876
A54: Source | B54: Net Zero Tracker
A55: URL | B55: https://zerotracker.net/#data-explorer
A56: Retrieve Date | B56: 45383

Sheet Ethanol
A1: Ethanol Production | B1: 2010 | C1: 2011 | D1: 2012 | E1: 2013 | F1: 2014 | G1: 2015 | H1: 2016 | I1: 2017 | J1: 2018 | K1: 2019 | L1: 2020 | M1: 2021 | N1: 2022 | O1: 2023 | P1: 2024 | Q1: 2025 | R1: 2026 | S1: 2027 | T1: 2028 | U1: 2029 | V1: 2030 | W1: 2031 | X1: 2032 | Y1: Source | Z1: URL | AA1: Retrieve Date
A2: US Production (million gallons) | B2: 13616.38 | C2: 14334.214 | D2: 13685.601 | E2: 13698.018 | F2: 14730.779 | G2: 15199.736 | H2: 15728.402 | I2: 16257.332 | J2: 16480.053 | K2: 16202.114 | L2: 14404.491 | M2: 15493.527 | N2: 15790.439 | O2: 15851.332 | P2: 15882.182 | Q2: 15883.754 | R2: 15928.328 | S2: 15952.843 | T2: 15987.886 | U2: 16018.711 | V2: 16055.678 | W2: 16097.139 | X2: 16138.703 | Y2: OECD-FAO Agricultural Outlook | Z2: https://www.oecd-ilibrary.org/agriculture-and-food/data/oecd-agriculture-statistics/oecd-fao-agricultural-outlook-edition-2023_3f870a2b-en | AA2: 45352
A3: Brazil Production (million gallons) | B3: 7388.4227 | C3: 5982.3804 | D3: 6182.5654 | E3: 7219.2523 | F3: 7453.0066 | G3: 7847.2629 | H3: 7366.2166 | I3: 7290.1982 | J3: 8765.9709 | K3: 9287.6988 | L3: 8613.8705 | M3: 7874.959 | N3: 8309.2312 | O3: 8908.9247 | P3: 9211.1202 | Q3: 9403.0859 | R3: 9655.2048 | S3: 9882.502 | T3: 10145.078 | U3: 10369.509 | V3: 10592.515 | W3: 10800.956 | X3: 11012.288 | Y3: OECD-FAO Agricultural Outlook | Z3: https://www.oecd-ilibrary.org/agriculture-and-food/data/oecd-agriculture-statistics/oecd-fao-agricultural-outlook-edition-2023_3f870a2b-en | AA3: 45352
A4: EU Production (million gallons) | B4: 1277.6222 | C4: 1519.3527 | D4: 1390.7266 | E4: 1452.2801 | F4: 1617.21 | G4: 1553.8917 | H4: 1504.4122 | I4: 1574.8296 | J4: 1566.2906 | K4: 1596.8111 | L4: 1654.1268 | M4: 1884.5231 | N4: 1705.1598 | O4: 1732.8058 | P4: 1750.5892 | Q4: 1767.8045 | R4: 1788.9194 | S4: 1808.288 | T4: 1828.5125 | U4: 1848.391 | V4: 1868.4914 | W4: 1889.1598 | X4: 1909.9762 | Y4: OECD-FAO Agricultural Outlook | Z4: https://www.oecd-ilibrary.org/agriculture-and-food/data/oecd-agriculture-statistics/oecd-fao-agricultural-outlook-edition-2023_3f870a2b-en | AA4: 45352
A5: Canada Production (million gallons) | B5: 375.16513 | C5: 480.84544 | D5: 484.80845 | E5: 494.05548 | F5: 494.05548 | G5: 498.01849 | H5: 500.6605 | I5: 501.98151 | J5: 501.98151 | K5: 557.46367 | L5: 500.6605 | M5: 505.94452 | N5: 521.12285 | O5: 534.2642 | P5: 544.73976 | Q5: 554.53104 | R5: 565.83091 | S5: 576.54425 | T5: 587.88639 | U5: 599.3897 | V5: 611.38177 | W5: 623.85469 | X5: 636.61823 | Y5: OECD-FAO Agricultural Outlook | Z5: https://www.oecd-ilibrary.org/agriculture-and-food/data/oecd-agriculture-statistics/oecd-fao-agricultural-outlook-edition-2023_3f870a2b-en | AA5: 45352
A6: China Production (million gallons) | B6: 2182.2985 | C6: 2203.4346 | D6: 2166.4465 | E6: 2408.1902 | F6: 2589.1678 | G6: 2553.5007 | H6: 2457.0674 | I6: 2457.0674 | J6: 2515.1915 | K6: 2589.1678 | L6: 2430.6473 | M6: 2708.0581 | N6: 2681.5086 | O6: 2684.4333 | P6: 2707.2365 | Q6: 2745.395 | R6: 2781.7305 | S6: 2807.1968 | T6: 2839.218 | U6: 2866.2193 | V6: 2896.7345 | W6: 2925.0753 | X6: 2954.1162 | Y6: OECD-FAO Agricultural Outlook | Z6: https://www.oecd-ilibrary.org/agriculture-and-food/data/oecd-agriculture-statistics/oecd-fao-agricultural-outlook-edition-2023_3f870a2b-en | AA6: 45352
A7: Indonesia Production (million gallons) | B7: 54.927345 | C7: 55.878468 | D7: 56.380449 | E7: 55.059445 | F7: 51.228534 | G7: 55.297226 | H7: 54.610304 | I7: 52.153236 | J7: 50.224571 | K7: 50.14531 | L7: 46.78996 | M7: 47.186262 | N7: 47.608983 | O7: 48.570674 | P7: 49.638045 | Q7: 50.72391 | R7: 51.812417 | S7: 52.908851 | T7: 53.978864 | U7: 55.025099 | V7: 56.047556 | W7: 57.048877 | X7: 58.029062 | Y7: OECD-FAO Agricultural Outlook | Z7: https://www.oecd-ilibrary.org/agriculture-and-food/data/oecd-agriculture-statistics/oecd-fao-agricultural-outlook-edition-2023_3f870a2b-en | AA7: 45352
A8: UK Production (million gallons) | B8: 174.37252 | C8: 153.23646 | D8: 129.45839 | E8: 140.02642 | F8: 243.06473 | G8: 192.86658 | H8: 236.46235 | I8: 272.12682 | J8: 245.70674 | K8: 125.49802 | L8: 158.52048 | M8: 163.80449 | N8: 198.15059 | O8: 206.93263 | P8: 213.88375 | Q8: 214.16909 | R8: 210.49934 | S8: 205.13871 | T8: 208.41215 | U8: 210.7424 | V8: 212.39102 | W8: 213.19683 | X8: 217.05945 | Y8: OECD-FAO Agricultural Outlook | Z8: https://www.oecd-ilibrary.org/agriculture-and-food/data/oecd-agriculture-statistics/oecd-fao-agricultural-outlook-edition-2023_3f870a2b-en | AA8: 45352
A9: RoW Production (million gallons) | B9: =+B10-SUM(B2:B8) -> 2275.3633 | C9: =+C10-SUM(C2:C8) -> 2412.5073 | D9: =+D10-SUM(D2:D8) -> 2522.9089 | E9: =+E10-SUM(E2:E8) -> 2731.0277 | F9: =+F10-SUM(F2:F8) -> 2971.033 | G9: =+G10-SUM(G2:G8) -> 3046.7081 | H9: =+H10-SUM(H2:H8) -> 3290.4201 | I9: =+I10-SUM(I2:I8) -> 3265.3131 | ... X9: =+X10-SUM(X2:X8) -> 6950.0766 | Y9: OECD-FAO Agricultural Outlook | Z9: https://www.oecd-ilibrary.org/agriculture-and-food/data/oecd-agriculture-statistics/oecd-fao-agricultural-outlook-edition-2023_3f870a2b-en | AA9: 45352
A10: World Production (million gallons) | B10: 27344.552 | C10: 27141.849 | D10: 26618.896 | E10: 28197.91 | F10: 30149.546 | G10: 30947.281 | H10: 31138.251 | I10: 31671.001 | J10: 33785.102 | K10: 34242.674 | L10: 31519.445 | M10: 32843.564 | N10: 34185.971 | O10: 35270.151 | P10: 36003.477 | Q10: 36524.243 | R10: 37093.736 | S10: 37570.938 | T10: 38091.654 | U10: 38550.129 | V10: 39006.314 | W10: 39441.728 | X10: 39876.867 | Y10: OECD-FAO Agricultural Outlook | Z10: https://www.oecd-ilibrary.org/agriculture-and-food/data/oecd-agriculture-statistics/oecd-fao-agricultural-outlook-edition-2023_3f870a2b-en | AA10: 45352
A11: US Consumption (million gallons) | B11: 13236.343 | C11: 13624.225 | D11: 13517.049 | E11: 13768.431 | F11: 14111.59 | G11: 14450.145 | H11: 14900.18 | I11: 14995.517 | J11: 15098.005 | K11: 15116.037 | L11: 13338.299 | M11: 14467.376 | N11: 14565.247 | O11: 14614.801 | P11: 14514.602 | Q11: 14469.731 | R11: 14486.497 | S11: 14484.753 | T11: 14492.145 | U11: 14489.107 | V11: 14487.974 | W11: 14481.229 | X11: 14474.713 | Y11: OECD-FAO Agricultural Outlook | Z11: https://www.oecd-ilibrary.org/agriculture-and-food/data/oecd-agriculture-statistics/oecd-fao-agricultural-outlook-edition-2023_3f870a2b-en | AA11: 45352
A12: Brazil Consumption (million gallons) | B12: 6651.9736 | C12: 5905.8071 | D12: 5352.6341 | E12: 6353.0145 | F12: 7074.0238 | G12: 8268.5337 | H12: 7582.8269 | I12: 7427.2312 | J12: 8544.1744 | K12: 9339.1308 | L12: 8018.5258 | M12: 7550.1797 | N12: 7854.9273 | O12: 8438.5971 | P12: 8783.1783 | Q12: 9040.9326 | R12: 9285.7966 | S12: 9505.2074 | T12: 9741.675 | U12: 9962.2114 | V12: 10186.692 | W12: 10402.626 | X12: 10621.052 | Y12: OECD-FAO Agricultural Outlook | Z12: https://www.oecd-ilibrary.org/agriculture-and-food/data/oecd-agriculture-statistics/oecd-fao-agricultural-outlook-edition-2023_3f870a2b-en | AA12: 45352
A13: EU Consumption (million gallons) | B13: 1360.0106 | C13: 1493.8838 | D13: 1489.1466 | E13: 1498.9723 | F13: 1695.5746 | G13: 1553.0304 | H13: 1542.1849 | I13: 1594.6209 | J13: 1724.148 | K13: 1784.4306 | L13: 1811.2523 | M13: 1925.5429 | N13: 1810.3593 | O13: 1843.7754 | P13: 1864.6605 | Q13: 1881.7305 | R13: 1906.1559 | S13: 1931.4822 | T13: 1952.2114 | U13: 1967.6196 | V13: 1971.1466 | W13: 1975.0489 | X13: 1975.0832 | Y13: OECD-FAO Agricultural Outlook | Z13: https://www.oecd-ilibrary.org/agriculture-and-food/data/oecd-agriculture-statistics/oecd-fao-agricultural-outlook-edition-2023_3f870a2b-en | AA13: 45352
A14: Canada Consumption (million gallons) | B14: 0 | C14: 0 | D14: 703.30251 | E14: 798.15059 | F14: 838.04491 | G14: 859.70938 | H14: 858.91678 | I14: 872.39102 | J14: 867.29194 | K14: 896.45971 | L14: 814.49934 | M14: 848.214 | N14: 934.80581 | O14: 1000.4069 | P14: 1062.0317 | Q14: 1119.5429 | R14: 1174.4174 | S14: 1226.2404 | T14: 1279.5324 | U14: 1330.9696 | V14: 1382.7794 | W14: 1435.8151 | X14: 1491.2893 | Y14: OECD-FAO Agricultural Outlook | Z14: https://www.oecd-ilibrary.org/agriculture-and-food/data/oecd-agriculture-statistics/oecd-fao-agricultural-outlook-edition-2023_3f870a2b-en | AA14: 45352
A15: China Consumption (million gallons) | B15: 2140.0264 | C15: 2179.5746 | D15: 2179.7358 | E15: 2375.1651 | F15: 2575.9577 | G15: 2668.428 | H15: 2668.428 | I15: 2509.9075 | J15: 2694.8481 | K15: 2668.428 | L15: 2404.2272 | M15: 2826.9485 | N15: 2715.6697 | O15: 2756.6394 | P15: 2784.2351 | Q15: 2827.1387 | R15: 2864.3725 | S15: 2892.8613 | T15: 2926.4544 | U15: 2955.6063 | V15: 2986.8877 | W15: 3015.7807 | X15: 3045.3871 | Y15: OECD-FAO Agricultural Outlook | Z15: https://www.oecd-ilibrary.org/agriculture-and-food/data/oecd-agriculture-statistics/oecd-fao-agricultural-outlook-edition-2023_3f870a2b-en | AA15: 45352
A16: Indonesia Consumption (million gallons) | B16: 41.743725 | C16: 38.309115 | D16: 41.215324 | E16: 30.647292 | F16: 28.269485 | G16: 41.479524 | H16: 36.459709 | I16: 36.459709 | J16: 33.817701 | K16: 31.968296 | L16: 41.743725 | M16: 39.89432 | N16: 38.573316 | O16: 39.640687 | P16: 40.708058 | Q16: 41.793923 | R16: 42.882431 | S16: 43.978864 | T16: 45.048877 | U16: 46.095112 | V16: 47.117569 | W16: 48.11889 | X16: 49.099075 | Y16: OECD-FAO Agricultural Outlook | Z16: https://www.oecd-ilibrary.org/agriculture-and-food/data/oecd-agriculture-statistics/oecd-fao-agricultural-outlook-edition-2023_3f870a2b-en | AA16: 45352
A17: UK Consumption (million gallons) | B17: 272.27741 | C17: 277.88111 | D17: 296.96169 | E17: 303.56671 | F17: 288.50727 | G17: 284.01849 | H17: 273.18362 | I17: 256.75033 | J17: 286.7107 | K17: 285.87583 | L17: 246.76618 | M17: 296.43329 | N17: 392.33818 | O17: 340.95905 | P17: 349.99207 | Q17: 352.21136 | R17: 350.33289 | S17: 346.88771 | T17: 352.07398 | U17: 356.30911 | V17: 359.82563 | W17: 362.48613 | X17: 364.41215 | Y17: OECD-FAO Agricultural Outlook | Z17: https://www.oecd-ilibrary.org/agriculture-and-food/data/oecd-agriculture-statistics/oecd-fao-agricultural-outlook-edition-2023_3f870a2b-en | AA17: 45352
A18: RoW Consumption (million gallons) | B18: =+B19-SUM(B11:B17) -> 2534.8639 | C18: =+C19-SUM(C11:C17) -> 2672.5099 | D18: =+D19-SUM(D11:D17) -> 2747.3765 | E18: =+E19-SUM(E11:E17) -> 2983.6539 | F18: =+F19-SUM(F11:F17) -> 3296.6209 | G18: =+G19-SUM(G11:G17) -> 3558.9273 | H18: =+H19-SUM(H11:H17) -> 3885.4927 | I18: =+I19-SUM(I11:I17) -> 3975.2312 | ... X18: =+X19-SUM(X11:X17) -> 7868.679 | Y18: OECD-FAO Agricultural Outlook | Z18: https://www.oecd-ilibrary.org/agriculture-and-food/data/oecd-agriculture-statistics/oecd-fao-agricultural-outlook-edition-2023_3f870a2b-en | AA18: 45352
A19: World Consumption (million gallons) | B19: 26237.239 | C19: 26192.19 | D19: 26327.421 | E19: 28111.601 | F19: 29908.589 | G19: 31684.272 | H19: 31747.672 | I19: 31668.108 | J19: 33600.402 | K19: 34715.997 | L19: 31442.47 | M19: 32990.719 | N19: 34127.535 | O19: 35276.209 | P19: 35988.528 | Q19: 36573.041 | R19: 37150.84 | S19: 37642.1 | T19: 38156.063 | U19: 38614.362 | V19: 39057.561 | W19: 39476.531 | X19: 39889.715 | Y19: OECD-FAO Agricultural Outlook | Z19: https://www.oecd-ilibrary.org/agriculture-and-food/data/oecd-agriculture-statistics/oecd-fao-agricultural-outlook-edition-2023_3f870a2b-en | AA19: 45352
A20: Ethanol Trade | B20: 2010 | C20: 2011 | D20: 2012 | E20: 2013 | F20: 2014 | G20: 2015 | H20: 2016 | I20: 2017 | J20: 2018 | K20: 2019 | L20: 2020 | M20: 2021 | N20: 2022 | O20: 2023 | P20: 2024 | Q20: 2025 | R20: 2026 | S20: 2027 | T20: 2028 | U20: 2029 | V20: 2030 | W20: 2031 | X20: 2032 | Y20: Source | Z20: URL | AA20: Retrieve Date
A21: US Imports (million gallons) | B21: 124.54954 | C21: 292.12417 | D21: 650.23514 | E21: 520.6605 | F21: 235.8679 | G21: 282.01057 | H21: 214.79524 | I21: 270.95905 | J21: 272.14531 | K21: 339.77543 | L21: 322.81374 | M21: 134.83223 | N21: 151.01982 | O21: 136.43857 | P21: 138.45707 | Q21: 137.46367 | R21: 133.85997 | S21: 131.97886 | T21: 130.22721 | U21: 127.92867 | V21: 125.04359 | W21: 121.98151 | X21: 119.14663 | Y21: OECD-FAO Agricultural Outlook | Z21: https://www.oecd-ilibrary.org/agriculture-and-food/data/oecd-agriculture-statistics/oecd-fao-agricultural-outlook-edition-2023_3f870a2b-en | AA21: 45352
A22: Brazil Imports (million gallons) | B22: 20.174373 | C22: 303.85997 | D22: 144.14795 | E22: 34.797886 | F22: 119.41876 | G22: 135.49538 | H22: 220.51255 | I22: 482.33554 | J22: 469.04359 | K22: 385.09908 | L22: 266.79789 | M22: 114.20343 | N22: 67.812417 | O22: 61.896962 | P22: 68.60502 | Q22: 73.402906 | R22: 74.850727 | S22: 72.784676 | T22: 70.412153 | U22: 69.582563 | V22: 70.290621 | W22: 71.569353 | X22: 72.549538 | Y22: OECD-FAO Agricultural Outlook | Z22: https://www.oecd-ilibrary.org/agriculture-and-food/data/oecd-agriculture-statistics/oecd-fao-agricultural-outlook-edition-2023_3f870a2b-en | AA22: 45352
A23: EU Imports (million gallons) | B23: 150.13738 | C23: 205.36856 | D23: 186.35667 | E23: 239.65918 | F23: 208.79524 | G23: 190.43065 | H23: 210.06605 | I23: 203.35007 | J23: 164.04756 | K23: 254.86658 | L23: 348.56011 | M23: 253.51387 | N23: 399.13078 | O23: 259.6539 | P23: 247.46367 | Q23: 204.33554 | R23: 205.11493 | S23: 206.73712 | T23: 209.03303 | U23: 210.65522 | V23: 212.09775 | W23: 213.43197 | X23: 214.78468 | Y23: OECD-FAO Agricultural Outlook | Z23: https://www.oecd-ilibrary.org/agriculture-and-food/data/oecd-agriculture-statistics/oecd-fao-agricultural-outlook-edition-2023_3f870a2b-en | AA23: 45352
A24: Canada Imports (million gallons) | B24: 155.35007 | C24: 266.3144 | D24: 287.18626 | E24: 313.07794 | F24: 354.02906 | G24: 372.25892 | H24: 370.14531 | I24: 383.09115 | J24: 369.72259 | K24: 338.20343 | L24: 341.40026 | M24: 366.04756 | N24: 437.46103 | O24: 489.26552 | P24: 542.01321 | Q24: 588.87186 | R24: 632.4148 | S24: 673.29987 | T24: 715.52708 | U24: 755.37384 | V24: 795.107 | W24: 835.70938 | X24: 878.50991 | Y24: OECD-FAO Agricultural Outlook | Z24: https://www.oecd-ilibrary.org/agriculture-and-food/data/oecd-agriculture-statistics/oecd-fao-agricultural-outlook-edition-2023_3f870a2b-en | AA24: 45352
A25: China Imports (million gallons) | B25: 0.95640687 | C25: 1.321004 | D25: 3.9630119 | E25: 0 | F25: 7.0541612 | G25: 181.50594 | H25: 235.13871 | I25: 6.6050198 | J25: 273.44782 | K25: 27.476882 | L25: 18.150594 | M25: 220.42272 | N25: 1.321004 | O25: 98.422721 | P25: 103.42668 | Q25: 107.05945 | R25: 107.64333 | S25: 110.66843 | T25: 112.17173 | U25: 113.89168 | V25: 114.70542 | W25: 115.18362 | X25: 115.82563 | Y25: OECD-FAO Agricultural Outlook | Z25: https://www.oecd-ilibrary.org/agriculture-and-food/data/oecd-agriculture-statistics/oecd-fao-agricultural-outlook-edition-2023_3f870a2b-en | AA25: 45352
A26: Indonesia Imports (million gallons) | B26: 0.079260238 | C26: 0.18494055 | D26: 0.81902246 | E26: 0.1321004 | F26: 0.26420079 | G26: 0.10568032 | H26: 0.58124174 | I26: 1.2681638 | J26: 25.284016 | K26: 0.21136063 | L26: 7.5033025 | M26: 14.187583 | N26: 8.9299868 | O26: 8.9299868 | P26: 8.9299868 | Q26: 8.9299868 | R26: 8.9299868 | S26: 8.9299868 | T26: 8.9299868 | U26: 8.9299868 | V26: 8.9299868 | W26: 8.9299868 | X26: 8.9299868 | Y26: OECD-FAO Agricultural Outlook | Z26: https://www.oecd-ilibrary.org/agriculture-and-food/data/oecd-agriculture-statistics/oecd-fao-agricultural-outlook-edition-2023_3f870a2b-en | AA26: 45352
A27: UK Imports (million gallons) | B27: 142.15852 | C27: 163.89168 | D27: 200.25099 | E27: 210.72919 | F27: 117.32365 | G27: 170.06077 | H27: 146.11889 | I27: 148.58388 | J27: 152.47556 | K27: 211.35271 | L27: 124.45971 | M27: 175.4214 | N27: 273.44782 | O27: 176.20872 | P27: 178.69485 | Q27: 180.38045 | R27: 182.1638 | S27: 184.01057 | T27: 185.99207 | U27: 187.8679 | V27: 189.71466 | W27: 191.58256 | X27: 189.67503 | Y27: OECD-FAO Agricultural Outlook | Z27: https://www.oecd-ilibrary.org/agriculture-and-food/data/oecd-agriculture-statistics/oecd-fao-agricultural-outlook-edition-2023_3f870a2b-en | AA27: 45352
A28: RoW Imports (million gallons) | B28: =+B29-SUM(B21:B27) -> 767.23118 | C28: =+C29-SUM(C21:C27) -> 757.50594 | D28: =+D29-SUM(D21:D27) -> 843.89168 | E28: =+E29-SUM(E21:E27) -> 891.17041 | F28: =+F29-SUM(F21:F27) -> 904.06605 | G28: =+G29-SUM(G21:G27) -> 1005.0938 | H28: =+H29-SUM(H21:H27) -> 1124.3567 | I28: =+I29-SUM(I21:I27) -> 1247.8283 | ... X28: =+X29-SUM(X21:X27) -> 1534.8507 | Y28: OECD-FAO Agricultural Outlook | Z28: https://www.oecd-ilibrary.org/agriculture-and-food/data/oecd-agriculture-statistics/oecd-fao-agricultural-outlook-edition-2023_3f870a2b-en | AA28: 45352
A29: World Imports (million gallons) | B29: 1360.6367 | C29: 1990.5707 | D29: 2316.8507 | E29: 2210.2272 | F29: 1946.819 | G29: 2336.9617 | H29: 2521.7147 | I29: 2744.0211 | J29: 3021.1598 | K29: 2944.5178 | L29: 3051.181 | M29: 2707.897 | N29: 2874.7081 | O29: 2771.469 | P29: 2836.214 | Q29: 2841.1625 | R29: 2881.6222 | S29: 2923.889 | T29: 2969.5403 | U29: 3011.2602 | V29: 3051.8626 | W29: 3093.6513 | X29: 3134.2721 | Y29: OECD-FAO Agricultural Outlook | Z29: https://www.oecd-ilibrary.org/agriculture-and-food/data/oecd-agriculture-statistics/oecd-fao-agricultural-outlook-edition-2023_3f870a2b-en | AA29: 45352
A30: US Exports (million gallons) | B30: 395.75958 | C30: 1193.2655 | D30: 731.60106 | E30: 616.69749 | F30: 839.20476 | G30: 910.06869 | H30: 1161.1546 | I30: 1387.6011 | J30: 1675.1176 | K30: 1446.7741 | L30: 1312.4861 | M30: 1236.2378 | N30: 1398.8851 | O30: 1383.0066 | P30: 1487.3501 | Q30: 1549.5482 | R30: 1572.8217 | S30: 1601.4875 | T30: 1621.4584 | U30: 1655.0066 | V30: 1691.6063 | W30: 1735.9841 | X30: 1779.5482 | Y30: OECD-FAO Agricultural Outlook | Z30: https://www.oecd-ilibrary.org/agriculture-and-food/data/oecd-agriculture-statistics/oecd-fao-agricultural-outlook-edition-2023_3f870a2b-en | AA30: 45352
A31: Brazil Exports (million gallons) | B31: 551.01717 | C31: 518.87979 | D31: 807.21004 | E31: 770.56011 | F31: 369.32629 | G31: 493.321 | H31: 472.65522 | I31: 364.63672 | J31: 446.2959 | K31: 512.78203 | L31: 711.94716 | M31: 514.72655 | N31: 497.91546 | O31: 533.08851 | P31: 493.87847 | Q31: 435.31572 | R31: 443.15984 | S31: 448.56803 | T31: 471.72787 | U31: 475.93395 | V31: 475.98679 | W31: 469.55086 | X31: 462.77939 | Y31: OECD-FAO Agricultural Outlook | Z31: https://www.oecd-ilibrary.org/agriculture-and-food/data/oecd-agriculture-statistics/oecd-fao-agricultural-outlook-edition-2023_3f870a2b-en | AA31: 45352
A32: EU Exports (million gallons) | B32: 93.252312 | C32: 98.64465 | D32: 106.24042 | E32: 152.35931 | F32: 143.87318 | G32: 179.40291 | H32: 183.03303 | I32: 195.46103 | J32: 197.80713 | K32: 192.69749 | L32: 158.80053 | M32: 146.17173 | N32: 114.60766 | O32: 141.71731 | P32: 141.38705 | Q32: 140.96697 | R32: 148.51255 | S32: 153.87318 | T32: 156.12946 | U32: 158.70277 | V32: 161.36592 | W32: 164.08454 | X32: 166.80053 | Y32: OECD-FAO Agricultural Outlook | Z32: https://www.oecd-ilibrary.org/agriculture-and-food/data/oecd-agriculture-statistics/oecd-fao-agricultural-outlook-edition-2023_3f870a2b-en | AA32: 45352
A33: Canada Exports (million gallons) | B33: 24.834875 | C33: 20.343461 | D33: 14.266843 | E33: 15.323646 | F33: 16.64465 | G33: 17.965654 | H33: 20.07926 | I33: 23.24967 | J33: 23.778071 | K33: 23.778071 | L33: 23.778071 | M33: 23.778071 | N33: 23.778071 | O33: 23.89432 | P33: 23.822985 | Q33: 23.815059 | R33: 23.820343 | S33: 23.809775 | T33: 23.799207 | U33: 23.793923 | V33: 23.796565 | W33: 23.799207 | X33: 23.801849 | Y33: OECD-FAO Agricultural Outlook | Z33: https://www.oecd-ilibrary.org/agriculture-and-food/data/oecd-agriculture-statistics/oecd-fao-agricultural-outlook-edition-2023_3f870a2b-en | AA33: 45352
A34: China Exports (million gallons) | B34: 41.22325 | C34: 11.450462 | D34: 11.889036 | E34: 10.568032 | F34: 8.7186262 | G34: 6.6050198 | H34: 8.9035667 | I34: 35.138705 | J34: 20.951123 | K34: 5.5482166 | L34: 96.988111 | M34: 6.1294584 | N34: 3.9577279 | O34: 26.528402 | P34: 25.992074 | Q34: 25.365918 | R34: 25.017173 | S34: 25.128137 | T34: 24.866579 | U34: 24.504624 | V34: 24.583884 | W34: 24.496697 | X34: 24.528402 | Y34: OECD-FAO Agricultural Outlook | Z34: https://www.oecd-ilibrary.org/agriculture-and-food/data/oecd-agriculture-statistics/oecd-fao-agricultural-outlook-edition-2023_3f870a2b-en | AA34: 45352
A35: Indonesia Exports (million gallons) | B35: 13.21004 | C35: 17.701453 | D35: 15.957728 | E35: 24.649934 | F35: 23.32893 | G35: 14.055482 | H35: 18.705416 | I35: 16.882431 | J35: 41.743725 | K35: 18.335535 | L35: 12.443857 | M35: 21.532365 | N35: 17.859974 | O35: 17.859974 | P35: 17.859974 | Q35: 17.859974 | R35: 17.859974 | S35: 17.859974 | T35: 17.859974 | U35: 17.859974 | V35: 17.859974 | W35: 17.859974 | X35: 17.859974 | Y35: OECD-FAO Agricultural Outlook | Z35: https://www.oecd-ilibrary.org/agriculture-and-food/data/oecd-agriculture-statistics/oecd-fao-agricultural-outlook-edition-2023_3f870a2b-en | AA35: 45352
A36: UK Exports (million gallons) | B36: 38.435931 | C36: 38.853369 | D36: 50.77675 | E36: 32.171731 | F36: 89.442536 | G36: 79.453104 | H36: 106.89828 | I36: 152.28798 | J36: 108.58653 | K36: 50.634082 | L36: 46.861295 | M36: 40.235139 | N36: 42.272127 | O36: 42.417437 | P36: 42.309115 | Q36: 42.324967 | R36: 42.327609 | S36: 42.322325 | T36: 42.303831 | U36: 42.301189 | V36: 42.306473 | W36: 42.309115 | X36: 42.311757 | Y36: OECD-FAO Agricultural Outlook | Z36: https://www.oecd-ilibrary.org/agriculture-and-food/data/oecd-agriculture-statistics/oecd-fao-agricultural-outlook-edition-2023_3f870a2b-en | AA36: 45352
A37: RoW Exports (million gallons) | B37: =+B38-SUM(B30:B36) -> 445.84148 | C37: =+C38-SUM(C30:C36) -> 459.28402 | D37: =+D38-SUM(D30:D36) -> 585.27609 | E37: =+E38-SUM(E30:E36) -> 588.95641 | F37: =+F38-SUM(F30:F36) -> 543.13606 | G37: =+G38-SUM(G30:G36) -> 440.57067 | H37: =+H38-SUM(H30:H36) -> 479.59049 | I37: =+I38-SUM(I30:I36) -> 487.98415 | ... X37: =+X38-SUM(X30:X36) -> 616.64201 | Y37: OECD-FAO Agricultural Outlook | Z37: https://www.oecd-ilibrary.org/agriculture-and-food/data/oecd-agriculture-statistics/oecd-fao-agricultural-outlook-edition-2023_3f870a2b-en | AA37: 45352
A38: World Exports (million gallons) | B38: 1603.5746 | C38: 2358.4227 | D38: 2323.218 | E38: 2211.2867 | F38: 2033.675 | G38: 2141.4425 | H38: 2451.0198 | I38: 2663.2417 | J38: 3044.6764 | K38: 2798.8137 | L38: 2871.5456 | M38: 2511.2814 | N38: 2691.7992 | O38: 2771.469 | P38: 2836.214 | Q38: 2841.1625 | R38: 2881.6222 | S38: 2923.889 | T38: 2969.5403 | U38: 3011.2602 | V38: 3051.8626 | W38: 3093.6513 | X38: 3134.2721 | Y38: OECD-FAO Agricultural Outlook | Z38: https://www.oecd-ilibrary.org/agriculture-and-food/data/oecd-agriculture-statistics/oecd-fao-agricultural-outlook-edition-2023_3f870a2b-en | AA38: 45352

Sheet Biodiesel
A1: Ethanol Production | B1: 2010 | C1: 2011 | D1: 2012 | E1: 2013 | F1: 2014 | G1: 2015 | H1: 2016 | I1: 2017 | J1: 2018 | K1: 2019 | L1: 2020 | M1: 2021 | N1: 2022 | O1: 2023 | P1: 2024 | Q1: 2025 | R1: 2026 | S1: 2027 | T1: 2028 | U1: 2029 | V1: 2030 | W1: 2031 | X1: 2032 | Y1: Source | Z1: URL | AA1: Retrieve Date
A2: US Production (million gallons) | B2: 343.01982 | C2: 1022.1427 | D2: 1036.8269 | E2: 1459.4003 | F2: 1419.5826 | G2: 1389.6328 | H2: 1781.2048 | I2: 1824.111 | J2: 2127.4055 | K2: 2159.9128 | L2: 2286.8375 | M2: 2360.4861 | N2: 3137.6486 | O2: 3234.9458 | P2: 3565.0647 | Q2: 3689.5931 | R2: 3787.7305 | S2: 3893.1546 | T2: 3968.2985 | U2: 4034.465 | V2: 4125.3395 | W2: 4195.9736 | X2: 4273.6724 | Y2: OECD-FAO Agricultural Outlook | Z2: https://www.oecd-ilibrary.org/agriculture-and-food/data/oecd-agriculture-statistics/oecd-fao-agricultural-outlook-edition-2023_3f870a2b-en | AA2: 45352
A3: Brazil Production (million gallons) | B3: 630.38309 | C3: 706.20872 | D3: 739.76222 | E3: 775.42933 | F3: 906.20872 | G3: 1062.0872 | H3: 1004.2272 | I3: 1133.6856 | J3: 1426.6843 | K3: 1558.5786 | L3: 1698.8058 | M3: 1786.9696 | N3: 1746.7688 | O3: 1861.1889 | P3: 1882.4756 | Q3: 1892.9115 | R3: 1910.5443 | S3: 1933.8917 | T3: 1976.4412 | U3: 2017.1598 | V3: 2059.7913 | W3: 2101.8177 | X3: 2144.9221 | Y3: OECD-FAO Agricultural Outlook | Z3: https://www.oecd-ilibrary.org/agriculture-and-food/data/oecd-agriculture-statistics/oecd-fao-agricultural-outlook-edition-2023_3f870a2b-en | AA3: 45352
A4: EU Production (million gallons) | B4: 2885.3791 | C4: 2831.0225 | D4: 3102.3303 | E4: 3261.963 | F4: 3632.9432 | G4: 3606.1004 | H4: 3479.7834 | I4: 3866.6764 | J4: 4017.9234 | K4: 4193.358 | L4: 4450.7847 | M4: 4166.0819 | N4: 5072.1744 | O4: 4542.6552 | P4: 4569.7305 | Q4: 4539.0383 | R4: 4563.284 | S4: 4586.6288 | T4: 4594.4861 | U4: 4588.8507 | V4: 4555.0938 | W4: 4546.8507 | X4: 4578.0449 | Y4: OECD-FAO Agricultural Outlook | Z4: https://www.oecd-ilibrary.org/agriculture-and-food/data/oecd-agriculture-statistics/oecd-fao-agricultural-outlook-edition-2023_3f870a2b-en | AA4: 45352
A5: Canada Production (million gallons) | B5: 30.383091 | C5: 31.704095 | D5: 26.420079 | E5: 81.109643 | F5: 71.334214 | G5: 76.089828 | H5: 71.334214 | I5: 71.334214 | J5: 79.260238 | K5: 99.075297 | L5: 97.675033 | M5: 103.36592 | N5: 106.56803 | O5: 113.31308 | P5: 121.5033 | Q5: 129.01189 | R5: 135.98415 | S5: 141.26024 | T5: 149.28137 | U5: 157.19683 | V5: 165.12021 | W5: 173.02774 | X5: 180.95905 | Y5: OECD-FAO Agricultural Outlook | Z5: https://www.oecd-ilibrary.org/agriculture-and-food/data/oecd-agriculture-statistics/oecd-fao-agricultural-outlook-edition-2023_3f870a2b-en | AA5: 45352
A6: China Production (million gallons) | B6: 150.06605 | C6: 194.98018 | D6: 244.91413 | E6: 285.07266 | F6: 299.3395 | G6: 207.92602 | H6: 240.15852 | I6: 275.56143 | J6: 220.34346 | K6: 248.08454 | L6: 384.41215 | M6: 484.80845 | N6: 642.00793 | O6: 616.61559 | P6: 589.69353 | Q6: 554.18494 | R6: 520.79789 | S6: 489.16248 | T6: 488.13474 | U6: 499.84676 | V6: 503.93131 | W6: 505.0568 | X6: 512.50198 | Y6: OECD-FAO Agricultural Outlook | Z6: https://www.oecd-ilibrary.org/agriculture-and-food/data/oecd-agriculture-statistics/oecd-fao-agricultural-outlook-edition-2023_3f870a2b-en | AA6: 45352
A7: Indonesia Production (million gallons) | B7: 207.66182 | C7: 475.29723 | D7: 601.5852 | E7: 789.96037 | F7: 901.98151 | G7: 317.83355 | H7: 920.47556 | I7: 728.92999 | J7: 1458.9168 | K7: 2024.8349 | L7: 2236.4597 | M7: 2507.0013 | N7: 2721.2682 | O7: 2843.4875 | P7: 2906.6262 | Q7: 2955.0964 | R7: 2994.7926 | S7: 3021.8018 | T7: 3078.6209 | U7: 3126.2853 | V7: 3174.1823 | W7: 3222.7213 | X7: 3272.2166 | Y7: OECD-FAO Agricultural Outlook | Z7: https://www.oecd-ilibrary.org/agriculture-and-food/data/oecd-agriculture-statistics/oecd-fao-agricultural-outlook-edition-2023_3f870a2b-en | AA7: 45352
A8: UK Production (million gallons) | B8: 41.188904 | C8: 47.450462 | D8: 66.076618 | E8: 70.805812 | F8: 37.859974 | G8: 39.418758 | H8: 90.805812 | I8: 102.88507 | J8: 129.45575 | K8: 148.51519 | L8: 158.52048 | M8: 160.10568 | N8: 161.70674 | O8: 163.32365 | P8: 162.07662 | Q8: 164.76882 | R8: 167.45046 | S8: 172.06605 | T8: 175.93923 | U8: 180.90885 | V8: 185.65125 | W8: 191.05152 | X8: 196.44386 | Y8: OECD-FAO Agricultural Outlook | Z8: https://www.oecd-ilibrary.org/agriculture-and-food/data/oecd-agriculture-statistics/oecd-fao-agricultural-outlook-edition-2023_3f870a2b-en | AA8: 45352
A9: RoW Production (million gallons) | B9: =+B10-SUM(B2:B8) -> 1047.2655 | C9: =+C10-SUM(C2:C8) -> 1276.074 | D9: =+D10-SUM(D2:D8) -> 1560.6737 | E9: =+E10-SUM(E2:E8) -> 1684.8613 | F9: =+F10-SUM(F2:F8) -> 1883.4716 | G9: =+G10-SUM(G2:G8) -> 1781.8811 | H9: =+H10-SUM(H2:H8) -> 1954.251 | I9: =+I10-SUM(I2:I8) -> 2129.498 | ... X9: =+X10-SUM(X2:X8) -> 2517.0832 | Y9: OECD-FAO Agricultural Outlook | Z9: https://www.oecd-ilibrary.org/agriculture-and-food/data/oecd-agriculture-statistics/oecd-fao-agricultural-outlook-edition-2023_3f870a2b-en | AA9: 45352
A10: World Production (million gallons) | B10: 5335.3474 | C10: 6584.8798 | D10: 7378.5892 | E10: 8408.6024 | F10: 9152.7213 | G10: 8480.9696 | H10: 9542.2404 | I10: 10132.682 | J10: 11558.14 | K10: 12701.49 | L10: 13205.95 | M10: 13631.641 | N10: 15635.968 | O10: 15479.741 | P10: 16013.937 | Q10: 16222.51 | R10: 16438.898 | S10: 16620.79 | T10: 16844.18 | U10: 17043.313 | V10: 17233.392 | W10: 17426.801 | X10: 17675.844 | Y10: OECD-FAO Agricultural Outlook | Z10: https://www.oecd-ilibrary.org/agriculture-and-food/data/oecd-agriculture-statistics/oecd-fao-agricultural-outlook-edition-2023_3f870a2b-en | AA10: 45352
A11: US Consumption (million gallons) | B11: 270.08983 | C11: 940.51255 | D11: 964.48613 | E11: 1689.7966 | F11: 1676.9273 | G11: 1828.9273 | H11: 2439.2338 | I11: 2347.2074 | J11: 2227.5509 | K11: 2418.531 | L11: 2549.5376 | M11: 2957.7279 | N11: 3354.0291 | O11: 3540.3567 | P11: 3838.4042 | Q11: 3931.1334 | R11: 4000.6394 | S11: 4076.9168 | T11: 4149.963 | U11: 4227.0674 | V11: 4320.3884 | W11: 4389.897 | X11: 4466.5654 | Y11: OECD-FAO Agricultural Outlook | Z11: https://www.oecd-ilibrary.org/agriculture-and-food/data/oecd-agriculture-statistics/oecd-fao-agricultural-outlook-edition-2023_3f870a2b-en | AA11: 45352
A12: Brazil Consumption (million gallons) | B12: 650.46235 | C12: 690.35667 | D12: 738.44122 | E12: 773.57992 | F12: 900.9247 | G12: 1057.86 | H12: 1003.963 | I12: 1128.6658 | J12: 1420.7133 | K12: 1554.9379 | L12: 1695.2919 | M12: 1800.148 | N12: 1736.4069 | O12: 1857.2787 | P12: 1878.5416 | Q12: 1888.5918 | R12: 1906.1083 | S12: 1929.1863 | T12: 1971.5746 | U12: 2012.1321 | V12: 2054.605 | W12: 2096.4491 | X12: 2139.3791 | Y12: OECD-FAO Agricultural Outlook | Z12: https://www.oecd-ilibrary.org/agriculture-and-food/data/oecd-agriculture-statistics/oecd-fao-agricultural-outlook-edition-2023_3f870a2b-en | AA12: 45352
A13: EU Consumption (million gallons) | B13: 3377.535 | C13: 3353.8309 | D13: 3684.7186 | E13: 3433.3844 | F13: 3582.5416 | G13: 3598.2087 | H13: 3784.4174 | I13: 4223.4478 | J13: 4605.6248 | K13: 4919.6935 | L13: 5019.2761 | M13: 5127.2232 | N13: 5237.4901 | O13: 5216.1427 | P13: 5234.6631 | Q13: 5200.8454 | R13: 5217.2946 | S13: 5235.5218 | T13: 5235.712 | U13: 5221.5509 | V13: 5179.4267 | W13: 5162.2246 | X13: 5191.3342 | Y13: OECD-FAO Agricultural Outlook | Z13: https://www.oecd-ilibrary.org/agriculture-and-food/data/oecd-agriculture-statistics/oecd-fao-agricultural-outlook-edition-2023_3f870a2b-en | AA13: 45352
A14: Canada Consumption (million gallons) | B14: 29.326288 | C14: 42.272127 | D14: 29.85469 | E14: 72.655218 | F14: 61.558785 | G14: 95.376486 | H14: 93.791281 | I14: 95.112285 | J14: 98.546896 | K14: 125.02774 | L14: 117.16248 | M14: 118.01057 | N14: 118.51519 | O14: 130.64465 | P14: 144.25363 | Q14: 157.07001 | R14: 169.38177 | S14: 179.97886 | T14: 193.3395 | U14: 206.67635 | V14: 220.03963 | W14: 233.40555 | X14: 246.78732 | Y14: OECD-FAO Agricultural Outlook | Z14: https://www.oecd-ilibrary.org/agriculture-and-food/data/oecd-agriculture-statistics/oecd-fao-agricultural-outlook-edition-2023_3f870a2b-en | AA14: 45352
A15: China Consumption (million gallons) | B15: 150.06605 | C15: 194.98018 | D15: 257.85997 | E15: 521.53236 | F15: 559.57728 | G15: 209.51123 | H15: 222.19287 | I15: 229.06209 | J15: 351.38705 | K15: 301.1889 | L15: 137.91281 | M15: 149.00925 | N15: 158.52048 | O15: 161.51651 | P15: 164.85337 | Q15: 167.63012 | R15: 170.96433 | S15: 174.15588 | T15: 177.59577 | U15: 181.2893 | V15: 184.92734 | W15: 188.63672 | X15: 192.38309 | Y15: OECD-FAO Agricultural Outlook | Z15: https://www.oecd-ilibrary.org/agriculture-and-food/data/oecd-agriculture-statistics/oecd-fao-agricultural-outlook-edition-2023_3f870a2b-en | AA15: 45352
A16: Indonesia Consumption (million gallons) | B16: 58.916777 | C16: 94.848085 | D16: 176.75033 | E16: 277.41083 | F16: 488.77147 | G16: 227.21268 | H16: 795.24439 | I16: 678.99604 | J16: 990.75297 | K16: 1688.2431 | L16: 2227.2127 | M16: 2457.0674 | N16: 2668.428 | O16: 2786.3382 | P16: 2851.3263 | Q16: 2895.3712 | R16: 2933.2021 | S16: 2958.2299 | T16: 3013.823 | U16: 3058.6367 | V16: 3104.2087 | W16: 3150.5575 | X16: 3197.6988 | Y16: OECD-FAO Agricultural Outlook | Z16: https://www.oecd-ilibrary.org/agriculture-and-food/data/oecd-agriculture-statistics/oecd-fao-agricultural-outlook-edition-2023_3f870a2b-en | AA16: 45352
A17: UK Consumption (million gallons) | B17: 150.5786 | C17: 92.177015 | D17: 100.77939 | E17: 118.66579 | F17: 110.94848 | G17: 81.886394 | H17: 147.85205 | I17: 162.0502 | J17: 285.90489 | K17: 425.33421 | L17: 465.17041 | M17: 279.79392 | N17: 392.24042 | O17: 310.19815 | P17: 307.82827 | Q17: 312.94584 | R17: 318.03963 | S17: 326.80581 | T17: 334.1638 | U17: 343.60106 | V17: 352.60766 | W17: 362.86129 | X17: 373.10436 | Y17: OECD-FAO Agricultural Outlook | Z17: https://www.oecd-ilibrary.org/agriculture-and-food/data/oecd-agriculture-statistics/oecd-fao-agricultural-outlook-edition-2023_3f870a2b-en | AA17: 45352
A18: RoW Consumption (million gallons) | B18: =+B19-SUM(B11:B17) -> 665.9498 | C18: =+C19-SUM(C11:C17) -> 803.60634 | D18: =+D19-SUM(D11:D17) -> 1009.712 | E18: =+E19-SUM(E11:E17) -> 1119.7596 | F18: =+F19-SUM(F11:F17) -> 1300.0053 | G18: =+G19-SUM(G11:G17) -> 1357.2444 | H18: =+H19-SUM(H11:H17) -> 1323.3289 | I18: =+I19-SUM(I11:I17) -> 1469.004 | ... X18: =+X19-SUM(X11:X17) -> 1878.0528 | Y18: OECD-FAO Agricultural Outlook | Z18: https://www.oecd-ilibrary.org/agriculture-and-food/data/oecd-agriculture-statistics/oecd-fao-agricultural-outlook-edition-2023_3f870a2b-en | AA18: 45352
A19: World Consumption (million gallons) | B19: 5352.9247 | C19: 6212.5839 | D19: 6962.6024 | E19: 8006.7847 | F19: 8681.255 | G19: 8456.2272 | H19: 9810.0238 | I19: 10333.546 | J19: 11461.432 | K19: 13125.794 | L19: 13656.753 | M19: 14347.863 | N19: 15105.96 | O19: 15491.16 | P19: 16025.16 | Q19: 16233.538 | R19: 16449.733 | S19: 16631.435 | T19: 16854.634 | U19: 17053.583 | V19: 17243.477 | W19: 17436.441 | X19: 17685.305 | Y19: OECD-FAO Agricultural Outlook | Z19: https://www.oecd-ilibrary.org/agriculture-and-food/data/oecd-agriculture-statistics/oecd-fao-agricultural-outlook-edition-2023_3f870a2b-en | AA19: 45352
A20: Ethanol Trade | B20: 2010 | C20: 2011 | D20: 2012 | E20: 2013 | F20: 2014 | G20: 2015 | H20: 2016 | I20: 2017 | J20: 2018 | K20: 2019 | L20: 2020 | M20: 2021 | N20: 2022 | O20: 2023 | P20: 2024 | Q20: 2025 | R20: 2026 | S20: 2027 | T20: 2028 | U20: 2029 | V20: 2030 | W20: 2031 | X20: 2032 | Y20: Source | Z20: URL | AA20: Retrieve Date
A21: US Imports (million gallons) | B21: 51.056803 | C21: 50.5786 | D21: 50.861295 | E21: 496.46499 | F21: 312.32761 | G21: 584.15324 | H21: 881.14663 | I21: 582.74505 | J21: 258.6103 | K21: 320.98811 | L21: 458.69749 | M21: 817.26816 | N21: 543.72523 | O21: 539.86526 | P21: 516.38309 | Q21: 492.37252 | R21: 471.48745 | S21: 449.98943 | T21: 455.81242 | U21: 474.75561 | V21: 485.19419 | W21: 492.0819 | X21: 499.03038 | Y21: OECD-FAO Agricultural Outlook | Z21: https://www.oecd-ilibrary.org/agriculture-and-food/data/oecd-agriculture-statistics/oecd-fao-agricultural-outlook-edition-2023_3f870a2b-en | AA21: 45352
A22: Brazil Imports (million gallons) | B22: 2.3778071 | C22: 4.7556143 | D22: 0 | E22: 0 | F22: 0 | G22: 0 | H22: 0 | I22: 0 | J22: 0 | K22: 0 | L22: 0 | M22: 0 | N22: 0 | O22: 0 | P22: 0 | Q22: 0 | R22: 0 | S22: 0 | T22: 0 | U22: 0 | V22: 0 | W22: 0 | X22: 0 | Y22: OECD-FAO Agricultural Outlook | Z22: https://www.oecd-ilibrary.org/agriculture-and-food/data/oecd-agriculture-statistics/oecd-fao-agricultural-outlook-edition-2023_3f870a2b-en | AA22: 45352
A23: EU Imports (million gallons) | B23: 555.83355 | C23: 783.73052 | D23: 803.09379 | E23: 420.67635 | F23: 265.43197 | G23: 268.83223 | H23: 318.21136 | I23: 511.65918 | J23: 1169.7622 | K23: 1219.4373 | L23: 1045.3078 | M23: 953.45575 | N23: 994.4967 | O23: 851.13606 | P23: 849.9498 | Q23: 853.96037 | R23: 853.94716 | S23: 856.61559 | T23: 857.22589 | U23: 857.33157 | V23: 857.85997 | W23: 858.14267 | X23: 858.75561 | Y23: OECD-FAO Agricultural Outlook | Z23: https://www.oecd-ilibrary.org/agriculture-and-food/data/oecd-agriculture-statistics/oecd-fao-agricultural-outlook-edition-2023_3f870a2b-en | AA23: 45352
A24: Canada Imports (million gallons) | B24: 30.383091 | C24: 31.704095 | D24: 26.420079 | E24: 36.988111 | F24: 76.61823 | G24: 89.828269 | H24: 126.55218 | I24: 135.00661 | J24: 99.603699 | K24: 98.607662 | L24: 97.622193 | M24: 96.64465 | N24: 95.677675 | O24: 104.58653 | P24: 113.51915 | Q24: 122.36724 | R24: 131.23646 | S24: 140.09247 | T24: 148.96169 | U24: 157.89432 | V24: 166.8428 | W24: 175.80713 | X24: 184.76354 | Y24: OECD-FAO Agricultural Outlook | Z24: https://www.oecd-ilibrary.org/agriculture-and-food/data/oecd-agriculture-statistics/oecd-fao-agricultural-outlook-edition-2023_3f870a2b-en | AA24: 45352
A25: China Imports (million gallons) | B25: 0 | C25: 0 | D25: 12.945839 | E25: 236.45971 | F25: 271.59841 | G25: 8.7186262 | H25: 2.1136063 | I25: 4.7556143 | J25: 225.36328 | K25: 251.78336 | L25: 26.948481 | M25: 53.896962 | N25: 77.939234 | O25: 76.058124 | P25: 76.649934 | Q25: 71.561427 | R25: 71.371202 | S25: 69.558785 | T25: 68.922061 | U25: 69.542933 | V25: 69.2893 | W25: 69.764861 | X25: 69.952444 | Y25: OECD-FAO Agricultural Outlook | Z25: https://www.oecd-ilibrary.org/agriculture-and-food/data/oecd-agriculture-statistics/oecd-fao-agricultural-outlook-edition-2023_3f870a2b-en | AA25: 45352
A26: Indonesia Imports (million gallons) | B26: 0 | C26: 0 | D26: 0 | E26: 0 | F26: 0 | G26: 0 | H26: 0 | I26: 0 | J26: 0 | K26: 0 | L26: 0 | M26: 0 | N26: 0 | O26: 0 | P26: 0 | Q26: 0 | R26: 0 | S26: 0 | T26: 0 | U26: 0 | V26: 0 | W26: 0 | X26: 0 | Y26: OECD-FAO Agricultural Outlook | Z26: https://www.oecd-ilibrary.org/agriculture-and-food/data/oecd-agriculture-statistics/oecd-fao-agricultural-outlook-edition-2023_3f870a2b-en | AA26: 45352
A27: UK Imports (million gallons) | B27: 115.49273 | C27: 53.180978 | D27: 38.216645 | E27: 54.042272 | F27: 82.044914 | G27: 48.229855 | H27: 68.134742 | I27: 68.142668 | J27: 178.11889 | K27: 296.9432 | L27: 321.8996 | M27: 230.11625 | N27: 330.99339 | O27: 196 | P27: 195.61427 | Q27: 198.78732 | R27: 201.95773 | S27: 206.87979 | T27: 211.14663 | U27: 216.40687 | V27: 221.47688 | W27: 227.41612 | X27: 233.09379 | Y27: OECD-FAO Agricultural Outlook | Z27: https://www.oecd-ilibrary.org/agriculture-and-food/data/oecd-agriculture-statistics/oecd-fao-agricultural-outlook-edition-2023_3f870a2b-en | AA27: 45352
A28: RoW Imports (million gallons) | B28: =+B29-SUM(B21:B27) -> 45.215324 | C28: =+C29-SUM(C21:C27) -> 53.669749 | D28: =+D29-SUM(D21:D27) -> 112.4148 | E28: =+E29-SUM(E21:E27) -> 143.43461 | F28: =+F29-SUM(F21:F27) -> 221.39234 | G28: =+G29-SUM(G21:G27) -> 174.0317 | H28: =+H29-SUM(H21:H27) -> 170.3646 | I28: =+I29-SUM(I21:I27) -> 176.02642 | ... X28: =+X29-SUM(X21:X27) -> 74.113606 | Y28: OECD-FAO Agricultural Outlook | Z28: https://www.oecd-ilibrary.org/agriculture-and-food/data/oecd-agriculture-statistics/oecd-fao-agricultural-outlook-edition-2023_3f870a2b-en | AA28: 45352
A29: World Imports (million gallons) | B29: 800.35931 | C29: 977.61955 | D29: 1043.9524 | E29: 1388.0661 | F29: 1229.4135 | G29: 1173.7939 | H29: 1566.5231 | I29: 1478.3355 | J29: 2053.3316 | K29: 2351.1149 | L29: 2059.1361 | M29: 2273.6565 | N29: 2124.6684 | O29: 1846.0634 | P29: 1828.0951 | Q29: 1813.7807 | R29: 1803.1731 | S29: 1795.7992 | T29: 1815.0172 | U29: 1849.1731 | V29: 1874.1929 | W29: 1897.0304 | X29: 1919.7094 | Y29: OECD-FAO Agricultural Outlook | Z29: https://www.oecd-ilibrary.org/agriculture-and-food/data/oecd-agriculture-statistics/oecd-fao-agricultural-outlook-edition-2023_3f870a2b-en | AA29: 45352
A30: US Exports (million gallons) | B30: 125.62483 | C30: 76.232497 | D30: 124.05284 | E30: 189.39762 | F30: 83.503303 | G30: 110.72127 | H30: 120.02114 | I30: 149.11229 | J30: 167.35271 | K30: 189.40819 | L30: 196.25363 | M30: 220.02642 | N30: 327.34478 | O30: 234.45178 | P30: 243.04624 | Q30: 250.83223 | R30: 258.5786 | S30: 266.22721 | T30: 274.14795 | U30: 282.15324 | V30: 290.14531 | W30: 298.15852 | X30: 306.13738 | Y30: OECD-FAO Agricultural Outlook | Z30: https://www.oecd-ilibrary.org/agriculture-and-food/data/oecd-agriculture-statistics/oecd-fao-agricultural-outlook-edition-2023_3f870a2b-en | AA30: 45352
A31: Brazil Exports (million gallons) | B31: 2.1136063 | C31: 1.5852048 | D31: 0 | E31: 10.303831 | F31: 10.568032 | G31: 3.1704095 | H31: 0 | I31: 2.6420079 | J31: 2.8005284 | K31: 3.3764861 | L31: 3.2496697 | M31: 3.7331572 | N31: 3.7569353 | O31: 3.9128137 | P31: 3.9313078 | Q31: 4.319683 | R31: 4.4359313 | S31: 4.7027741 | T31: 4.8639366 | U31: 5.0277411 | V31: 5.1889036 | W31: 5.3659181 | X31: 5.5429326 | Y31: OECD-FAO Agricultural Outlook | Z31: https://www.oecd-ilibrary.org/agriculture-and-food/data/oecd-agriculture-statistics/oecd-fao-agricultural-outlook-edition-2023_3f870a2b-en | AA31: 45352
A32: EU Exports (million gallons) | B32: 186.08454 | C32: 168.01057 | D32: 110.87186 | E32: 238.71334 | F32: 241.07266 | G32: 207.66975 | H32: 233.99207 | I32: 248.98811 | J32: 380.04227 | K32: 565.04624 | L32: 486.85337 | M32: 270.25627 | N32: 182.78203 | O32: 189.71466 | P32: 196.90092 | Q32: 203.85997 | R32: 211.46631 | S32: 219.08058 | T32: 227.1889 | U32: 235.65125 | V32: 244.38309 | W32: 253.46367 | X32: 256 | Y32: OECD-FAO Agricultural Outlook | Z32: https://www.oecd-ilibrary.org/agriculture-and-food/data/oecd-agriculture-statistics/oecd-fao-agricultural-outlook-edition-2023_3f870a2b-en | AA32: 45352
A33: Canada Exports (million gallons) | B33: 29.062087 | C33: 21.136063 | D33: 26.948481 | E33: 41.215324 | F33: 86.393659 | G33: 70.541612 | H33: 105.68032 | I33: 110.96433 | J33: 78.996037 | K33: 72.655218 | L33: 78.1321 | M33: 82 | N33: 83.733157 | O33: 87.254954 | P33: 90.768824 | Q33: 94.309115 | R33: 97.838838 | S33: 101.37384 | T33: 104.90357 | U33: 108.41744 | V33: 111.92338 | W33: 115.42933 | X33: 118.93527 | Y33: OECD-FAO Agricultural Outlook | Z33: https://www.oecd-ilibrary.org/agriculture-and-food/data/oecd-agriculture-statistics/oecd-fao-agricultural-outlook-edition-2023_3f870a2b-en | AA33: 45352
A34: China Exports (million gallons) | B34: 0 | C34: 0 | D34: 0 | E34: 0 | F34: 11.360634 | G34: 7.1334214 | H34: 20.07926 | I34: 51.254954 | J34: 94.319683 | K34: 198.679 | L34: 273.44782 | M34: 389.69617 | N34: 561.42668 | O34: 531.15456 | P34: 501.48745 | Q34: 458.11625 | R34: 421.20211 | S34: 384.56539 | T34: 379.46367 | U34: 388.1004 | V34: 388.2959 | W34: 386.18494 | X34: 390.07133 | Y34: OECD-FAO Agricultural Outlook | Z34: https://www.oecd-ilibrary.org/agriculture-and-food/data/oecd-agriculture-statistics/oecd-fao-agricultural-outlook-edition-2023_3f870a2b-en | AA34: 45352
A35: Indonesia Exports (million gallons) | B35: 148.74505 | C35: 380.44914 | D35: 425.36328 | E35: 512.54954 | F35: 414.79524 | G35: 90.620872 | H35: 125.75958 | I35: 49.405548 | J35: 467.6354 | K35: 335.53501 | L35: 10.303831 | M35: 50.990753 | N35: 52.840159 | O35: 57.149273 | P35: 55.30251 | Q35: 59.727873 | R35: 61.590489 | S35: 63.571995 | T35: 64.797886 | U35: 67.651255 | V35: 69.97358 | W35: 72.163804 | X35: 74.517834 | Y35: OECD-FAO Agricultural Outlook | Z35: https://www.oecd-ilibrary.org/agriculture-and-food/data/oecd-agriculture-statistics/oecd-fao-agricultural-outlook-edition-2023_3f870a2b-en | AA35: 45352
A36: UK Exports (million gallons) | B36: 6.1030383 | C36: 8.4544254 | D36: 3.5138705 | E36: 6.1822985 | F36: 8.9564069 | G36: 5.7622193 | H36: 11.088507 | I36: 8.9801849 | J36: 21.669749 | K36: 20.124174 | L36: 15.247028 | M36: 110.42801 | N36: 100.45971 | O36: 49.125495 | P36: 49.862616 | Q36: 50.610304 | R36: 51.371202 | S36: 52.140026 | T36: 52.922061 | U36: 53.717305 | V36: 54.523118 | W36: 55.339498 | X36: 56.171731 | Y36: OECD-FAO Agricultural Outlook | Z36: https://www.oecd-ilibrary.org/agriculture-and-food/data/oecd-agriculture-statistics/oecd-fao-agricultural-outlook-edition-2023_3f870a2b-en | AA36: 45352
A37: RoW Exports (million gallons) | B37: =+B38-SUM(B30:B36) -> 441.06473 | C37: =+C38-SUM(C30:C36) -> 526.13738 | D37: =+D38-SUM(D30:D36) -> 654.1321 | E37: =+E38-SUM(E30:E36) -> 718.57596 | F37: =+F38-SUM(F30:F36) -> 800.10832 | G37: =+G38-SUM(G30:G36) -> 594.4465 | H37: =+H38-SUM(H30:H36) -> 804.19287 | I37: =+I38-SUM(I30:I36) -> 822.51519 | ... X37: =+X38-SUM(X30:X36) -> 712.33289 | Y37: OECD-FAO Agricultural Outlook | Z37: https://www.oecd-ilibrary.org/agriculture-and-food/data/oecd-agriculture-statistics/oecd-fao-agricultural-outlook-edition-2023_3f870a2b-en | AA37: 45352
A38: World Exports (million gallons) | B38: 938.79789 | C38: 1182.0053 | D38: 1344.8824 | E38: 1716.9379 | F38: 1656.7583 | G38: 1090.0661 | H38: 1420.8137 | I38: 1443.8626 | J38: 1956.3831 | K38: 2125.2655 | L38: 1618.8904 | M38: 1844.0925 | N38: 2006.9564 | O38: 1846.0634 | P38: 1828.0951 | Q38: 1813.7807 | R38: 1803.1731 | S38: 1795.7992 | T38: 1815.0172 | U38: 1849.1731 | V38: 1874.1929 | W38: 1897.0304 | X38: 1919.7094 | Y38: OECD-FAO Agricultural Outlook | Z38: https://www.oecd-ilibrary.org/agriculture-and-food/data/oecd-agriculture-statistics/oecd-fao-agricultural-outlook-edition-2023_3f870a2b-en | AA38: 45352

Sheet Biofuels
A1: Biofuels Production (million gallons) | B1: 2010 | C1: 2011 | D1: 2012 | E1: 2013 | F1: 2014 | G1: 2015 | H1: 2016 | I1: 2017 | J1: 2018 | K1: 2019 | L1: 2020 | M1: 2021 | N1: 2022 | O1: 2023 | P1: 2024 | Q1: 2025 | R1: 2026 | S1: 2027 | T1: 2028 | U1: 2029 | V1: 2030 | W1: 2031 | X1: 2032 | AA1: Source | AB1: URL | AC1: Retrieve Date
A2: United States | B2: =+Ethanol!B2+Biodiesel!B2 -> 13959.4 | C2: =+Ethanol!C2+Biodiesel!C2 -> 15356.357 | D2: =+Ethanol!D2+Biodiesel!D2 -> 14722.428 | E2: =+Ethanol!E2+Biodiesel!E2 -> 15157.419 | F2: =+Ethanol!F2+Biodiesel!F2 -> 16150.362 | G2: =+Ethanol!G2+Biodiesel!G2 -> 16589.369 | H2: =+Ethanol!H2+Biodiesel!H2 -> 17509.606 | I2: =+Ethanol!I2+Biodiesel!I2 -> 18081.443 | ... X2: =+Ethanol!X2+Biodiesel!X2 -> 20412.375 | Y2: =+(X2-O2)/X2*100 -> 6.4965382 | Z2: =+X2-O2 -> 1326.0978 | AA2: OECD-FAO Agricultural Outlook | AB2: https://www.oecd-ilibrary.org/agriculture-and-food/data/oecd-agriculture-statistics/oecd-fao-agricultural-outlook-edition-2023_3f870a2b-en | AC2: 45352
A3: Brazil | B3: =+Ethanol!B3+Biodiesel!B3 -> 8018.8058 | C3: =+Ethanol!C3+Biodiesel!C3 -> 6688.5892 | D3: =+Ethanol!D3+Biodiesel!D3 -> 6922.3276 | E3: =+Ethanol!E3+Biodiesel!E3 -> 7994.6816 | F3: =+Ethanol!F3+Biodiesel!F3 -> 8359.2153 | G3: =+Ethanol!G3+Biodiesel!G3 -> 8909.3501 | H3: =+Ethanol!H3+Biodiesel!H3 -> 8370.4439 | I3: =+Ethanol!I3+Biodiesel!I3 -> 8423.8838 | ... X3: =+Ethanol!X3+Biodiesel!X3 -> 13157.21 | Y3: =+(X3-O3)/X3*100 -> 18.142877 | Z3: =+X3-O3 -> 2387.0964 | AA3: OECD-FAO Agricultural Outlook | AB3: https://www.oecd-ilibrary.org/agriculture-and-food/data/oecd-agriculture-statistics/oecd-fao-agricultural-outlook-edition-2023_3f870a2b-en | AC3: 45352
A4: European Union | B4: =+Ethanol!B4+Biodiesel!B4 -> 4163.0013 | C4: =+Ethanol!C4+Biodiesel!C4 -> 4350.3752 | D4: =+Ethanol!D4+Biodiesel!D4 -> 4493.0568 | E4: =+Ethanol!E4+Biodiesel!E4 -> 4714.2431 | F4: =+Ethanol!F4+Biodiesel!F4 -> 5250.1532 | G4: =+Ethanol!G4+Biodiesel!G4 -> 5159.9921 | H4: =+Ethanol!H4+Biodiesel!H4 -> 4984.1955 | I4: =+Ethanol!I4+Biodiesel!I4 -> 5441.5059 | ... X4: =+Ethanol!X4+Biodiesel!X4 -> 6488.0211 | Y4: =+(X4-O4)/X4*100 -> 3.2761932 | Z4: =+X4-O4 -> 212.56011 | AA4: OECD-FAO Agricultural Outlook | AB4: https://www.oecd-ilibrary.org/agriculture-and-food/data/oecd-agriculture-statistics/oecd-fao-agricultural-outlook-edition-2023_3f870a2b-en | AC4: 45352
A5: Canada | B5: =+Ethanol!B5+Biodiesel!B5 -> 405.54822 | C5: =+Ethanol!C5+Biodiesel!C5 -> 512.54954 | D5: =+Ethanol!D5+Biodiesel!D5 -> 511.22853 | E5: =+Ethanol!E5+Biodiesel!E5 -> 575.16513 | F5: =+Ethanol!F5+Biodiesel!F5 -> 565.3897 | G5: =+Ethanol!G5+Biodiesel!G5 -> 574.10832 | H5: =+Ethanol!H5+Biodiesel!H5 -> 571.99472 | I5: =+Ethanol!I5+Biodiesel!I5 -> 573.31572 | ... X5: =+Ethanol!X5+Biodiesel!X5 -> 817.57728 | Y5: =+(X5-O5)/X5*100 -> 20.793141 | Z5: =+X5-O5 -> 170 | AA5: OECD-FAO Agricultural Outlook | AB5: https://www.oecd-ilibrary.org/agriculture-and-food/data/oecd-agriculture-statistics/oecd-fao-agricultural-outlook-edition-2023_3f870a2b-en | AC5: 45352
A6: China | B6: =+Ethanol!B6+Biodiesel!B6 -> 2332.3646 | C6: =+Ethanol!C6+Biodiesel!C6 -> 2398.4148 | D6: =+Ethanol!D6+Biodiesel!D6 -> 2411.3606 | E6: =+Ethanol!E6+Biodiesel!E6 -> 2693.2629 | F6: =+Ethanol!F6+Biodiesel!F6 -> 2888.5073 | G6: =+Ethanol!G6+Biodiesel!G6 -> 2761.4267 | H6: =+Ethanol!H6+Biodiesel!H6 -> 2697.2259 | I6: =+Ethanol!I6+Biodiesel!I6 -> 2732.6288 | ... X6: =+Ethanol!X6+Biodiesel!X6 -> 3466.6182 | Y6: =+(X6-O6)/X6*100 -> 4.7761058 | Z6: =+X6-O6 -> 165.56935 | AA6: OECD-FAO Agricultural Outlook | AB6: https://www.oecd-ilibrary.org/agriculture-and-food/data/oecd-agriculture-statistics/oecd-fao-agricultural-outlook-edition-2023_3f870a2b-en | AC6: 45352
A7: Indonesia | B7: =+Ethanol!B7+Biodiesel!B7 -> 262.58917 | C7: =+Ethanol!C7+Biodiesel!C7 -> 531.17569 | D7: =+Ethanol!D7+Biodiesel!D7 -> 657.96565 | E7: =+Ethanol!E7+Biodiesel!E7 -> 845.01982 | F7: =+Ethanol!F7+Biodiesel!F7 -> 953.21004 | G7: =+Ethanol!G7+Biodiesel!G7 -> 373.13078 | H7: =+Ethanol!H7+Biodiesel!H7 -> 975.08587 | I7: =+Ethanol!I7+Biodiesel!I7 -> 781.08322 | ... X7: =+Ethanol!X7+Biodiesel!X7 -> 3330.2457 | Y7: =+(X7-O7)/X7*100 -> 13.157815 | Z7: =+X7-O7 -> 438.18758 | AA7: OECD-FAO Agricultural Outlook | AB7: https://www.oecd-ilibrary.org/agriculture-and-food/data/oecd-agriculture-statistics/oecd-fao-agricultural-outlook-edition-2023_3f870a2b-en | AC7: 45352
A8: UK | B8: =+Ethanol!B8+Biodiesel!B8 -> 215.56143 | C8: =+Ethanol!C8+Biodiesel!C8 -> 200.68692 | D8: =+Ethanol!D8+Biodiesel!D8 -> 195.53501 | E8: =+Ethanol!E8+Biodiesel!E8 -> 210.83223 | F8: =+Ethanol!F8+Biodiesel!F8 -> 280.9247 | G8: =+Ethanol!G8+Biodiesel!G8 -> 232.28534 | H8: =+Ethanol!H8+Biodiesel!H8 -> 327.26816 | I8: =+Ethanol!I8+Biodiesel!I8 -> 375.01189 | ... X8: =+Ethanol!X8+Biodiesel!X8 -> 413.5033 | Y8: =+(X8-O8)/X8*100 -> 10.45869 | Z8: =+X8-O8 -> 43.247028 | AA8: OECD-FAO Agricultural Outlook | AB8: https://www.oecd-ilibrary.org/agriculture-and-food/data/oecd-agriculture-statistics/oecd-fao-agricultural-outlook-edition-2023_3f870a2b-en | AC8: 45352
A9: RoW | B9: =+Ethanol!B9+Biodiesel!B9 -> 3322.6288 | C9: =+Ethanol!C9+Biodiesel!C9 -> 3688.5812 | D9: =+Ethanol!D9+Biodiesel!D9 -> 4083.5826 | E9: =+Ethanol!E9+Biodiesel!E9 -> 4415.889 | F9: =+Ethanol!F9+Biodiesel!F9 -> 4854.5046 | G9: =+Ethanol!G9+Biodiesel!G9 -> 4828.5892 | H9: =+Ethanol!H9+Biodiesel!H9 -> 5244.6711 | I9: =+Ethanol!I9+Biodiesel!I9 -> 5394.8111 | ... X9: =+Ethanol!X9+Biodiesel!X9 -> 9467.1598 | Y9: =+(X9-O9)/X9*100 -> 21.760072 | Z9: =+X9-O9 -> 2060.0608 | AA9: OECD-FAO Agricultural Outlook | AB9: https://www.oecd-ilibrary.org/agriculture-and-food/data/oecd-agriculture-statistics/oecd-fao-agricultural-outlook-edition-2023_3f870a2b-en | AC9: 45352
A10: World | B10: =+Ethanol!B10+Biodiesel!B10 -> 32679.9 | C10: =+Ethanol!C10+Biodiesel!C10 -> 33726.729 | D10: =+Ethanol!D10+Biodiesel!D10 -> 33997.485 | E10: =+Ethanol!E10+Biodiesel!E10 -> 36606.513 | F10: =+Ethanol!F10+Biodiesel!F10 -> 39302.267 | G10: =+Ethanol!G10+Biodiesel!G10 -> 39428.251 | H10: =+Ethanol!H10+Biodiesel!H10 -> 40680.491 | I10: =+Ethanol!I10+Biodiesel!I10 -> 41803.683 | ... X10: =+Ethanol!X10+Biodiesel!X10 -> 57552.711 | Y10: =+(X10-O10)/X10*100 -> 11.820154 | Z10: =+X10-O10 -> 6802.819 | AA10: OECD-FAO Agricultural Outlook | AB10: https://www.oecd-ilibrary.org/agriculture-and-food/data/oecd-agriculture-statistics/oecd-fao-agricultural-outlook-edition-2023_3f870a2b-en | AC10: 45352
A11: Biofuels Consumption (million gallons) | B11: 2010 | C11: 2011 | D11: 2012 | E11: 2013 | F11: 2014 | G11: 2015 | H11: 2016 | I11: 2017 | J11: 2018 | K11: 2019 | L11: 2020 | M11: 2021 | N11: 2022 | O11: 2023 | P11: 2024 | Q11: 2025 | R11: 2026 | S11: 2027 | T11: 2028 | U11: 2029 | V11: 2030 | W11: 2031 | X11: 2032 | AA11: Source | AB11: URL | AC11: Retrieve Date
A12: United States | B12: =+Ethanol!B11+Biodiesel!B11 -> 13506.433 | C12: =+Ethanol!C11+Biodiesel!C11 -> 14564.737 | D12: =+Ethanol!D11+Biodiesel!D11 -> 14481.535 | E12: =+Ethanol!E11+Biodiesel!E11 -> 15458.227 | F12: =+Ethanol!F11+Biodiesel!F11 -> 15788.518 | G12: =+Ethanol!G11+Biodiesel!G11 -> 16279.073 | H12: =+Ethanol!H11+Biodiesel!H11 -> 17339.413 | I12: =+Ethanol!I11+Biodiesel!I11 -> 17342.724 | ... X12: =+Ethanol!X11+Biodiesel!X11 -> 18941.279 | Y12: =+(X12-O12)/X12*100 -> 4.1503087 | Z12: =+X12-O12 -> 786.12153 | AA12: OECD-FAO Agricultural Outlook | AB12: https://www.oecd-ilibrary.org/agriculture-and-food/data/oecd-agriculture-statistics/oecd-fao-agricultural-outlook-edition-2023_3f870a2b-en | AC12: 45352
A13: Brazil | B13: =+Ethanol!B12+Biodiesel!B12 -> 7302.4359 | C13: =+Ethanol!C12+Biodiesel!C12 -> 6596.1638 | D13: =+Ethanol!D12+Biodiesel!D12 -> 6091.0753 | E13: =+Ethanol!E12+Biodiesel!E12 -> 7126.5945 | F13: =+Ethanol!F12+Biodiesel!F12 -> 7974.9485 | G13: =+Ethanol!G12+Biodiesel!G12 -> 9326.3937 | H13: =+Ethanol!H12+Biodiesel!H12 -> 8586.79 | I13: =+Ethanol!I12+Biodiesel!I12 -> 8555.897 | ... X13: =+Ethanol!X12+Biodiesel!X12 -> 12760.431 | Y13: =+(X13-O13)/X13*100 -> 19.314041 | Z13: =+X13-O13 -> 2464.5548 | AA13: OECD-FAO Agricultural Outlook | AB13: https://www.oecd-ilibrary.org/agriculture-and-food/data/oecd-agriculture-statistics/oecd-fao-agricultural-outlook-edition-2023_3f870a2b-en | AC13: 45352
A14: European Union | B14: =+Ethanol!B13+Biodiesel!B13 -> 4737.5456 | C14: =+Ethanol!C13+Biodiesel!C13 -> 4847.7147 | D14: =+Ethanol!D13+Biodiesel!D13 -> 5173.8653 | E14: =+Ethanol!E13+Biodiesel!E13 -> 4932.3567 | F14: =+Ethanol!F13+Biodiesel!F13 -> 5278.1162 | G14: =+Ethanol!G13+Biodiesel!G13 -> 5151.2391 | H14: =+Ethanol!H13+Biodiesel!H13 -> 5326.6024 | I14: =+Ethanol!I13+Biodiesel!I13 -> 5818.0687 | ... X14: =+Ethanol!X13+Biodiesel!X13 -> 7166.4174 | Y14: =+(X14-O14)/X14*100 -> 1.486089 | Z14: =+X14-O14 -> 106.49934 | AA14: OECD-FAO Agricultural Outlook | AB14: https://www.oecd-ilibrary.org/agriculture-and-food/data/oecd-agriculture-statistics/oecd-fao-agricultural-outlook-edition-2023_3f870a2b-en | AC14: 45352
A15: Canada | B15: =+Ethanol!B14+Biodiesel!B14 -> 29.326288 | C15: =+Ethanol!C14+Biodiesel!C14 -> 42.272127 | D15: =+Ethanol!D14+Biodiesel!D14 -> 733.1572 | E15: =+Ethanol!E14+Biodiesel!E14 -> 870.80581 | F15: =+Ethanol!F14+Biodiesel!F14 -> 899.6037 | G15: =+Ethanol!G14+Biodiesel!G14 -> 955.08587 | H15: =+Ethanol!H14+Biodiesel!H14 -> 952.70806 | I15: =+Ethanol!I14+Biodiesel!I14 -> 967.5033 | ... X15: =+Ethanol!X14+Biodiesel!X14 -> 1738.0766 | Y15: =+(X15-O15)/X15*100 -> 34.925106 | Z15: =+X15-O15 -> 607.0251 | AA15: OECD-FAO Agricultural Outlook | AB15: https://www.oecd-ilibrary.org/agriculture-and-food/data/oecd-agriculture-statistics/oecd-fao-agricultural-outlook-edition-2023_3f870a2b-en | AC15: 45352
A16: China | B16: =+Ethanol!B15+Biodiesel!B15 -> 2290.0925 | C16: =+Ethanol!C15+Biodiesel!C15 -> 2374.5548 | D16: =+Ethanol!D15+Biodiesel!D15 -> 2437.5958 | E16: =+Ethanol!E15+Biodiesel!E15 -> 2896.6975 | F16: =+Ethanol!F15+Biodiesel!F15 -> 3135.535 | G16: =+Ethanol!G15+Biodiesel!G15 -> 2877.9392 | H16: =+Ethanol!H15+Biodiesel!H15 -> 2890.6209 | I16: =+Ethanol!I15+Biodiesel!I15 -> 2738.9696 | ... X16: =+Ethanol!X15+Biodiesel!X15 -> 3237.7701 | Y16: =+(X16-O16)/X16*100 -> 9.8714316 | Z16: =+X16-O16 -> 319.61427 | AA16: OECD-FAO Agricultural Outlook | AB16: https://www.oecd-ilibrary.org/agriculture-and-food/data/oecd-agriculture-statistics/oecd-fao-agricultural-outlook-edition-2023_3f870a2b-en | AC16: 45352
A17: Indonesia | B17: =+Ethanol!B16+Biodiesel!B16 -> 100.6605 | C17: =+Ethanol!C16+Biodiesel!C16 -> 133.1572 | D17: =+Ethanol!D16+Biodiesel!D16 -> 217.96565 | E17: =+Ethanol!E16+Biodiesel!E16 -> 308.05812 | F17: =+Ethanol!F16+Biodiesel!F16 -> 517.04095 | G17: =+Ethanol!G16+Biodiesel!G16 -> 268.69221 | H17: =+Ethanol!H16+Biodiesel!H16 -> 831.7041 | I17: =+Ethanol!I16+Biodiesel!I16 -> 715.45575 | ... X17: =+Ethanol!X16+Biodiesel!X16 -> 3246.7979 | Y17: =+(X17-O17)/X17*100 -> 12.961048 | Z17: =+X17-O17 -> 420.81902 | AA17: OECD-FAO Agricultural Outlook | AB17: https://www.oecd-ilibrary.org/agriculture-and-food/data/oecd-agriculture-statistics/oecd-fao-agricultural-outlook-edition-2023_3f870a2b-en | AC17: 45352
A18: UK | B18: =+Ethanol!B17+Biodiesel!B17 -> 422.85601 | C18: =+Ethanol!C17+Biodiesel!C17 -> 370.05812 | D18: =+Ethanol!D17+Biodiesel!D17 -> 397.74108 | E18: =+Ethanol!E17+Biodiesel!E17 -> 422.2325 | F18: =+Ethanol!F17+Biodiesel!F17 -> 399.45575 | G18: =+Ethanol!G17+Biodiesel!G17 -> 365.90489 | H18: =+Ethanol!H17+Biodiesel!H17 -> 421.03567 | I18: =+Ethanol!I17+Biodiesel!I17 -> 418.80053 | ... X18: =+Ethanol!X17+Biodiesel!X17 -> 737.51651 | Y18: =+(X18-O18)/X18*100 -> 11.709475 | Z18: =+X18-O18 -> 86.359313 | AA18: OECD-FAO Agricultural Outlook | AB18: https://www.oecd-ilibrary.org/agriculture-and-food/data/oecd-agriculture-statistics/oecd-fao-agricultural-outlook-edition-2023_3f870a2b-en | AC18: 45352
A19: RoW | B19: =+Ethanol!B18+Biodiesel!B18 -> 3200.8137 | C19: =+Ethanol!C18+Biodiesel!C18 -> 3476.1162 | D19: =+Ethanol!D18+Biodiesel!D18 -> 3757.0885 | E19: =+Ethanol!E18+Biodiesel!E18 -> 4103.4135 | F19: =+Ethanol!F18+Biodiesel!F18 -> 4596.6262 | G19: =+Ethanol!G18+Biodiesel!G18 -> 4916.1717 | H19: =+Ethanol!H18+Biodiesel!H18 -> 5208.8217 | I19: =+Ethanol!I18+Biodiesel!I18 -> 5444.2351 | ... X19: =+Ethanol!X18+Biodiesel!X18 -> 9746.7318 | Y19: =+(X19-O19)/X19*100 -> 20.690606 | Z19: =+X19-O19 -> 2016.6579 | AA19: OECD-FAO Agricultural Outlook | AB19: https://www.oecd-ilibrary.org/agriculture-and-food/data/oecd-agriculture-statistics/oecd-fao-agricultural-outlook-edition-2023_3f870a2b-en | AC19: 45352
A20: World | B20: =+Ethanol!B19+Biodiesel!B19 -> 31590.164 | C20: =+Ethanol!C19+Biodiesel!C19 -> 32404.774 | D20: =+Ethanol!D19+Biodiesel!D19 -> 33290.024 | E20: =+Ethanol!E19+Biodiesel!E19 -> 36118.386 | F20: =+Ethanol!F19+Biodiesel!F19 -> 38589.844 | G20: =+Ethanol!G19+Biodiesel!G19 -> 40140.499 | H20: =+Ethanol!H19+Biodiesel!H19 -> 41557.696 | I20: =+Ethanol!I19+Biodiesel!I19 -> 42001.654 | ... X20: =+Ethanol!X19+Biodiesel!X19 -> 57575.02 | Y20: =+(X20-O20)/X20*100 -> 11.823967 | Z20: =+X20-O20 -> 6807.6513 | AA20: OECD-FAO Agricultural Outlook | AB20: https://www.oecd-ilibrary.org/agriculture-and-food/data/oecd-agriculture-statistics/oecd-fao-agricultural-outlook-edition-2023_3f870a2b-en | AC20: 45352
A21: Biofuels Imports (million gallons) | B21: 2010 | C21: 2011 | D21: 2012 | E21: 2013 | F21: 2014 | G21: 2015 | H21: 2016 | I21: 2017 | J21: 2018 | K21: 2019 | L21: 2020 | M21: 2021 | N21: 2022 | O21: 2023 | P21: 2024 | Q21: 2025 | R21: 2026 | S21: 2027 | T21: 2028 | U21: 2029 | V21: 2030 | W21: 2031 | X21: 2032 | Y21: % | AA21: Source | AB21: URL | AC21: Retrieve Date
A22: United States | B22: =+Ethanol!B21+Biodiesel!B21 -> 175.60634 | C22: =+Ethanol!C21+Biodiesel!C21 -> 342.70277 | D22: =+Ethanol!D21+Biodiesel!D21 -> 701.09643 | E22: =+Ethanol!E21+Biodiesel!E21 -> 1017.1255 | F22: =+Ethanol!F21+Biodiesel!F21 -> 548.19551 | G22: =+Ethanol!G21+Biodiesel!G21 -> 866.1638 | H22: =+Ethanol!H21+Biodiesel!H21 -> 1095.9419 | I22: =+Ethanol!I21+Biodiesel!I21 -> 853.7041 | ... X22: =+Ethanol!X21+Biodiesel!X21 -> 618.17701 | Y22: =+(X22-O22)/X22*100 -> -9.4029404 | Z22: =+X22-O22 -> -58.126816 | AA22: OECD-FAO Agricultural Outlook | AB22: https://www.oecd-ilibrary.org/agriculture-and-food/data/oecd-agriculture-statistics/oecd-fao-agricultural-outlook-edition-2023_3f870a2b-en | AC22: 45352
A23: Brazil | B23: =+Ethanol!B22+Biodiesel!B22 -> 22.55218 | C23: =+Ethanol!C22+Biodiesel!C22 -> 308.61559 | D23: =+Ethanol!D22+Biodiesel!D22 -> 144.14795 | E23: =+Ethanol!E22+Biodiesel!E22 -> 34.797886 | F23: =+Ethanol!F22+Biodiesel!F22 -> 119.41876 | G23: =+Ethanol!G22+Biodiesel!G22 -> 135.49538 | H23: =+Ethanol!H22+Biodiesel!H22 -> 220.51255 | I23: =+Ethanol!I22+Biodiesel!I22 -> 482.33554 | ... X23: =+Ethanol!X22+Biodiesel!X22 -> 72.549538 | Y23: =+(X23-O23)/X23*100 -> 14.683176 | Z23: =+X23-O23 -> 10.652576 | AA23: OECD-FAO Agricultural Outlook | AB23: https://www.oecd-ilibrary.org/agriculture-and-food/data/oecd-agriculture-statistics/oecd-fao-agricultural-outlook-edition-2023_3f870a2b-en | AC23: 45352
A24: European Union | B24: =+Ethanol!B23+Biodiesel!B23 -> 705.97094 | C24: =+Ethanol!C23+Biodiesel!C23 -> 989.09908 | D24: =+Ethanol!D23+Biodiesel!D23 -> 989.45046 | E24: =+Ethanol!E23+Biodiesel!E23 -> 660.33554 | F24: =+Ethanol!F23+Biodiesel!F23 -> 474.22721 | G24: =+Ethanol!G23+Biodiesel!G23 -> 459.26288 | H24: =+Ethanol!H23+Biodiesel!H23 -> 528.27741 | I24: =+Ethanol!I23+Biodiesel!I23 -> 715.00925 | ... X24: =+Ethanol!X23+Biodiesel!X23 -> 1073.5403 | Y24: =+(X24-O24)/X24*100 -> -3.4697971 | Z24: =+X24-O24 -> -37.24967 | AA24: OECD-FAO Agricultural Outlook | AB24: https://www.oecd-ilibrary.org/agriculture-and-food/data/oecd-agriculture-statistics/oecd-fao-agricultural-outlook-edition-2023_3f870a2b-en | AC24: 45352
A25: Canada | B25: =+Ethanol!B24+Biodiesel!B24 -> 185.73316 | C25: =+Ethanol!C24+Biodiesel!C24 -> 298.01849 | D25: =+Ethanol!D24+Biodiesel!D24 -> 313.60634 | E25: =+Ethanol!E24+Biodiesel!E24 -> 350.06605 | F25: =+Ethanol!F24+Biodiesel!F24 -> 430.64729 | G25: =+Ethanol!G24+Biodiesel!G24 -> 462.08719 | H25: =+Ethanol!H24+Biodiesel!H24 -> 496.69749 | I25: =+Ethanol!I24+Biodiesel!I24 -> 518.09775 | ... X25: =+Ethanol!X24+Biodiesel!X24 -> 1063.2734 | Y25: =+(X25-O25)/X25*100 -> 44.1487 | Z25: =+X25-O25 -> 469.4214 | AA25: OECD-FAO Agricultural Outlook | AB25: https://www.oecd-ilibrary.org/agriculture-and-food/data/oecd-agriculture-statistics/oecd-fao-agricultural-outlook-edition-2023_3f870a2b-en | AC25: 45352
A26: China | B26: =+Ethanol!B25+Biodiesel!B25 -> 0.95640687 | C26: =+Ethanol!C25+Biodiesel!C25 -> 1.321004 | D26: =+Ethanol!D25+Biodiesel!D25 -> 16.908851 | E26: =+Ethanol!E25+Biodiesel!E25 -> 236.45971 | F26: =+Ethanol!F25+Biodiesel!F25 -> 278.65258 | G26: =+Ethanol!G25+Biodiesel!G25 -> 190.22457 | H26: =+Ethanol!H25+Biodiesel!H25 -> 237.25231 | I26: =+Ethanol!I25+Biodiesel!I25 -> 11.360634 | ... X26: =+Ethanol!X25+Biodiesel!X25 -> 185.77807 | Y26: =+(X26-O26)/X26*100 -> 6.081033 | Z26: =+X26-O26 -> 11.297226 | AA26: OECD-FAO Agricultural Outlook | AB26: https://www.oecd-ilibrary.org/agriculture-and-food/data/oecd-agriculture-statistics/oecd-fao-agricultural-outlook-edition-2023_3f870a2b-en | AC26: 45352
A27: Indonesia | B27: =+Ethanol!B26+Biodiesel!B26 -> 0.079260238 | C27: =+Ethanol!C26+Biodiesel!C26 -> 0.18494055 | D27: =+Ethanol!D26+Biodiesel!D26 -> 0.81902246 | E27: =+Ethanol!E26+Biodiesel!E26 -> 0.1321004 | F27: =+Ethanol!F26+Biodiesel!F26 -> 0.26420079 | G27: =+Ethanol!G26+Biodiesel!G26 -> 0.10568032 | H27: =+Ethanol!H26+Biodiesel!H26 -> 0.58124174 | I27: =+Ethanol!I26+Biodiesel!I26 -> 1.2681638 | ... X27: =+Ethanol!X26+Biodiesel!X26 -> 8.9299868 | Y27: =+(X27-O27)/X27*100 -> 0 | Z27: =+X27-O27 -> 0 | AA27: OECD-FAO Agricultural Outlook | AB27: https://www.oecd-ilibrary.org/agriculture-and-food/data/oecd-agriculture-statistics/oecd-fao-agricultural-outlook-edition-2023_3f870a2b-en | AC27: 45352
A28: UK | B28: =+Ethanol!B27+Biodiesel!B27 -> 257.65125 | C28: =+Ethanol!C27+Biodiesel!C27 -> 217.07266 | D28: =+Ethanol!D27+Biodiesel!D27 -> 238.46764 | E28: =+Ethanol!E27+Biodiesel!E27 -> 264.77147 | F28: =+Ethanol!F27+Biodiesel!F27 -> 199.36856 | G28: =+Ethanol!G27+Biodiesel!G27 -> 218.29062 | H28: =+Ethanol!H27+Biodiesel!H27 -> 214.25363 | I28: =+Ethanol!I27+Biodiesel!I27 -> 216.72655 | ... X28: =+Ethanol!X27+Biodiesel!X27 -> 422.76882 | Y28: =+(X28-O28)/X28*100 -> 11.95928 | Z28: =+X28-O28 -> 50.560106 | AA28: OECD-FAO Agricultural Outlook | AB28: https://www.oecd-ilibrary.org/agriculture-and-food/data/oecd-agriculture-statistics/oecd-fao-agricultural-outlook-edition-2023_3f870a2b-en | AC28: 45352
A29: RoW | B29: =+Ethanol!B28+Biodiesel!B28 -> 812.4465 | C29: =+Ethanol!C28+Biodiesel!C28 -> 811.17569 | D29: =+Ethanol!D28+Biodiesel!D28 -> 956.30647 | E29: =+Ethanol!E28+Biodiesel!E28 -> 1034.605 | F29: =+Ethanol!F28+Biodiesel!F28 -> 1125.4584 | G29: =+Ethanol!G28+Biodiesel!G28 -> 1179.1255 | H29: =+Ethanol!H28+Biodiesel!H28 -> 1294.7213 | I29: =+Ethanol!I28+Biodiesel!I28 -> 1423.8547 | ... X29: =+Ethanol!X28+Biodiesel!X28 -> 1608.9643 | Y29: =+(X29-O29)/X29*100 -> -0.62808604 | Z29: =+X29-O29 -> -10.10568 | AA29: OECD-FAO Agricultural Outlook | AB29: https://www.oecd-ilibrary.org/agriculture-and-food/data/oecd-agriculture-statistics/oecd-fao-agricultural-outlook-edition-2023_3f870a2b-en | AC29: 45352
A30: World | B30: =+Ethanol!B29+Biodiesel!B29 -> 2160.996 | C30: =+Ethanol!C29+Biodiesel!C29 -> 2968.1902 | D30: =+Ethanol!D29+Biodiesel!D29 -> 3360.8032 | E30: =+Ethanol!E29+Biodiesel!E29 -> 3598.2933 | F30: =+Ethanol!F29+Biodiesel!F29 -> 3176.2325 | G30: =+Ethanol!G29+Biodiesel!G29 -> 3510.7556 | H30: =+Ethanol!H29+Biodiesel!H29 -> 4088.2378 | I30: =+Ethanol!I29+Biodiesel!I29 -> 4222.3567 | ... X30: =+Ethanol!X29+Biodiesel!X29 -> 5053.9815 | Y30: =+(X30-O30)/X30*100 -> 8.6357487 | Z30: =+X30-O30 -> 436.44914 | AA30: OECD-FAO Agricultural Outlook | AB30: https://www.oecd-ilibrary.org/agriculture-and-food/data/oecd-agriculture-statistics/oecd-fao-agricultural-outlook-edition-2023_3f870a2b-en | AC30: 45352
A31: Biofuels Exports (million gallons) | B31: 2010 | C31: 2011 | D31: 2012 | E31: 2013 | F31: 2014 | G31: 2015 | H31: 2016 | I31: 2017 | J31: 2018 | K31: 2019 | L31: 2020 | M31: 2021 | N31: 2022 | O31: 2023 | P31: 2024 | Q31: 2025 | R31: 2026 | S31: 2027 | T31: 2028 | U31: 2029 | V31: 2030 | W31: 2031 | X31: 2032 | AA31: Source | AB31: URL | AC31: Retrieve Date
A32: United States | B32: =+Ethanol!B30+Biodiesel!B30 -> 521.38441 | C32: =+Ethanol!C30+Biodiesel!C30 -> 1269.498 | D32: =+Ethanol!D30+Biodiesel!D30 -> 855.6539 | E32: =+Ethanol!E30+Biodiesel!E30 -> 806.09511 | F32: =+Ethanol!F30+Biodiesel!F30 -> 922.70806 | G32: =+Ethanol!G30+Biodiesel!G30 -> 1020.79 | H32: =+Ethanol!H30+Biodiesel!H30 -> 1281.1757 | I32: =+Ethanol!I30+Biodiesel!I30 -> 1536.7133 | ... X32: =+Ethanol!X30+Biodiesel!X30 -> 2085.6856 | Y32: =+(X32-O32)/X32*100 -> 22.449559 | Z32: =+X32-O32 -> 468.22721 | AA32: OECD-FAO Agricultural Outlook | AB32: https://www.oecd-ilibrary.org/agriculture-and-food/data/oecd-agriculture-statistics/oecd-fao-agricultural-outlook-edition-2023_3f870a2b-en | AC32: 45352
A33: Brazil | B33: =+Ethanol!B31+Biodiesel!B31 -> 553.13078 | C33: =+Ethanol!C31+Biodiesel!C31 -> 520.46499 | D33: =+Ethanol!D31+Biodiesel!D31 -> 807.21004 | E33: =+Ethanol!E31+Biodiesel!E31 -> 780.86394 | F33: =+Ethanol!F31+Biodiesel!F31 -> 379.89432 | G33: =+Ethanol!G31+Biodiesel!G31 -> 496.49141 | H33: =+Ethanol!H31+Biodiesel!H31 -> 472.65522 | I33: =+Ethanol!I31+Biodiesel!I31 -> 367.27873 | ... X33: =+Ethanol!X31+Biodiesel!X31 -> 468.32232 | Y33: =+(X33-O33)/X33*100 -> -14.664899 | Z33: =+X33-O33 -> -68.678996 | AA33: OECD-FAO Agricultural Outlook | AB33: https://www.oecd-ilibrary.org/agriculture-and-food/data/oecd-agriculture-statistics/oecd-fao-agricultural-outlook-edition-2023_3f870a2b-en | AC33: 45352
A34: European Union | B34: =+Ethanol!B32+Biodiesel!B32 -> 279.33686 | C34: =+Ethanol!C32+Biodiesel!C32 -> 266.65522 | D34: =+Ethanol!D32+Biodiesel!D32 -> 217.11229 | E34: =+Ethanol!E32+Biodiesel!E32 -> 391.07266 | F34: =+Ethanol!F32+Biodiesel!F32 -> 384.94584 | G34: =+Ethanol!G32+Biodiesel!G32 -> 387.07266 | H34: =+Ethanol!H32+Biodiesel!H32 -> 417.0251 | I34: =+Ethanol!I32+Biodiesel!I32 -> 444.44914 | ... X34: =+Ethanol!X32+Biodiesel!X32 -> 422.80053 | Y34: =+(X34-O34)/X34*100 -> 21.610323 | Z34: =+X34-O34 -> 91.36856 | AA34: OECD-FAO Agricultural Outlook | AB34: https://www.oecd-ilibrary.org/agriculture-and-food/data/oecd-agriculture-statistics/oecd-fao-agricultural-outlook-edition-2023_3f870a2b-en | AC34: 45352
A35: Canada | B35: =+Ethanol!B33+Biodiesel!B33 -> 53.896962 | C35: =+Ethanol!C33+Biodiesel!C33 -> 41.479524 | D35: =+Ethanol!D33+Biodiesel!D33 -> 41.215324 | E35: =+Ethanol!E33+Biodiesel!E33 -> 56.53897 | F35: =+Ethanol!F33+Biodiesel!F33 -> 103.03831 | G35: =+Ethanol!G33+Biodiesel!G33 -> 88.507266 | H35: =+Ethanol!H33+Biodiesel!H33 -> 125.75958 | I35: =+Ethanol!I33+Biodiesel!I33 -> 134.214 | ... X35: =+Ethanol!X33+Biodiesel!X33 -> 142.73712 | Y35: =+(X35-O35)/X35*100 -> 22.130086 | Z35: =+X35-O35 -> 31.587847 | AA35: OECD-FAO Agricultural Outlook | AB35: https://www.oecd-ilibrary.org/agriculture-and-food/data/oecd-agriculture-statistics/oecd-fao-agricultural-outlook-edition-2023_3f870a2b-en | AC35: 45352
A36: China | B36: =+Ethanol!B34+Biodiesel!B34 -> 41.22325 | C36: =+Ethanol!C34+Biodiesel!C34 -> 11.450462 | D36: =+Ethanol!D34+Biodiesel!D34 -> 11.889036 | E36: =+Ethanol!E34+Biodiesel!E34 -> 10.568032 | F36: =+Ethanol!F34+Biodiesel!F34 -> 20.07926 | G36: =+Ethanol!G34+Biodiesel!G34 -> 13.738441 | H36: =+Ethanol!H34+Biodiesel!H34 -> 28.982827 | I36: =+Ethanol!I34+Biodiesel!I34 -> 86.393659 | ... X36: =+Ethanol!X34+Biodiesel!X34 -> 414.59974 | Y36: =+(X36-O36)/X36*100 -> -34.511171 | Z36: =+X36-O36 -> -143.08322 | AA36: OECD-FAO Agricultural Outlook | AB36: https://www.oecd-ilibrary.org/agriculture-and-food/data/oecd-agriculture-statistics/oecd-fao-agricultural-outlook-edition-2023_3f870a2b-en | AC36: 45352
A37: Indonesia | B37: =+Ethanol!B35+Biodiesel!B35 -> 161.95509 | C37: =+Ethanol!C35+Biodiesel!C35 -> 398.15059 | D37: =+Ethanol!D35+Biodiesel!D35 -> 441.321 | E37: =+Ethanol!E35+Biodiesel!E35 -> 537.19947 | F37: =+Ethanol!F35+Biodiesel!F35 -> 438.12417 | G37: =+Ethanol!G35+Biodiesel!G35 -> 104.67635 | H37: =+Ethanol!H35+Biodiesel!H35 -> 144.46499 | I37: =+Ethanol!I35+Biodiesel!I35 -> 66.287979 | ... X37: =+Ethanol!X35+Biodiesel!X35 -> 92.377807 | Y37: =+(X37-O37)/X37*100 -> 18.801659 | Z37: =+X37-O37 -> 17.36856 | AA37: OECD-FAO Agricultural Outlook | AB37: https://www.oecd-ilibrary.org/agriculture-and-food/data/oecd-agriculture-statistics/oecd-fao-agricultural-outlook-edition-2023_3f870a2b-en | AC37: 45352
A38: UK | B38: =+Ethanol!B36+Biodiesel!B36 -> 44.53897 | C38: =+Ethanol!C36+Biodiesel!C36 -> 47.307794 | D38: =+Ethanol!D36+Biodiesel!D36 -> 54.290621 | E38: =+Ethanol!E36+Biodiesel!E36 -> 38.354029 | F38: =+Ethanol!F36+Biodiesel!F36 -> 98.398943 | G38: =+Ethanol!G36+Biodiesel!G36 -> 85.215324 | H38: =+Ethanol!H36+Biodiesel!H36 -> 117.98679 | I38: =+Ethanol!I36+Biodiesel!I36 -> 161.26816 | ... X38: =+Ethanol!X36+Biodiesel!X36 -> 98.483487 | Y38: =+(X38-O38)/X38*100 -> 7.04743 | Z38: =+X38-O38 -> 6.9405548 | AA38: OECD-FAO Agricultural Outlook | AB38: https://www.oecd-ilibrary.org/agriculture-and-food/data/oecd-agriculture-statistics/oecd-fao-agricultural-outlook-edition-2023_3f870a2b-en | AC38: 45352
A39: RoW | B39: =+Ethanol!B37+Biodiesel!B37 -> 886.90621 | C39: =+Ethanol!C37+Biodiesel!C37 -> 985.4214 | D39: =+Ethanol!D37+Biodiesel!D37 -> 1239.4082 | E39: =+Ethanol!E37+Biodiesel!E37 -> 1307.5324 | F39: =+Ethanol!F37+Biodiesel!F37 -> 1343.2444 | G39: =+Ethanol!G37+Biodiesel!G37 -> 1035.0172 | H39: =+Ethanol!H37+Biodiesel!H37 -> 1283.7834 | I39: =+Ethanol!I37+Biodiesel!I37 -> 1310.4993 | ... X39: =+Ethanol!X37+Biodiesel!X37 -> 1328.9749 | Y39: =+(X39-O39)/X39*100 -> 2.4619446 | Z39: =+X39-O39 -> 32.718626 | AA39: OECD-FAO Agricultural Outlook | AB39: https://www.oecd-ilibrary.org/agriculture-and-food/data/oecd-agriculture-statistics/oecd-fao-agricultural-outlook-edition-2023_3f870a2b-en | AC39: 45352
A40: World | B40: =+Ethanol!B38+Biodiesel!B38 -> 2542.3725 | C40: =+Ethanol!C38+Biodiesel!C38 -> 3540.428 | D40: =+Ethanol!D38+Biodiesel!D38 -> 3668.1004 | E40: =+Ethanol!E38+Biodiesel!E38 -> 3928.2246 | F40: =+Ethanol!F38+Biodiesel!F38 -> 3690.4333 | G40: =+Ethanol!G38+Biodiesel!G38 -> 3231.5086 | H40: =+Ethanol!H38+Biodiesel!H38 -> 3871.8336 | I40: =+Ethanol!I38+Biodiesel!I38 -> 4107.1044 | ... X40: =+Ethanol!X38+Biodiesel!X38 -> 5053.9815 | Y40: =+(X40-O40)/X40*100 -> 8.6357487 | Z40: =+X40-O40 -> 436.44914 | AA40: OECD-FAO Agricultural Outlook | AB40: https://www.oecd-ilibrary.org/agriculture-and-food/data/oecd-agriculture-statistics/oecd-fao-agricultural-outlook-edition-2023_3f870a2b-en | AC40: 45352
A41: Biofuels direct and indirect jobs (thousand jobs) | B41: 2010 | C41: 2011 | D41: 2012 | E41: 2013 | F41: 2014 | G41: 2015 | H41: 2016 | I41: 2017 | J41: 2018 | K41: 2019 | L41: 2020 | M41: 2021 | N41: 2022 | O41: 2023 | P41: 2024 | Q41: 2025 | R41: 2026 | S41: 2027 | T41: 2028 | U41: 2029 | V41: 2030 | W41: 2031 | X41: 2032 | AA41: Source | AB41: URL | AC41: Retrieve Date
A42: China | D42: 24 | E42: 24 | F42: 71 | G42: 71 | H42: 51 | I42: 51 | J42: 51 | K42: 51 | L42: 51 | M42: 51 | N42: 55 | O42: 60 | AA42: IRENA | AB42: https://www.irena.org/Data/View-data-by-topic/Benefits/Renewable-Energy-Employment-by-Country | AC42: 45352
A43: Brazil | D43: 804 | E43: 820 | F43: 845 | G43: 821 | H43: 783 | I43: 795 | J43: 832 | K43: 839 | L43: 871 | M43: 863 | N43: 856.15 | O43: 994 | AA43: IRENA | AB43: https://www.irena.org/Data/View-data-by-topic/Benefits/Renewable-Energy-Employment-by-Country | AC43: 45352
A44: United States | D44: 217 | E44: 236 | F44: 282 | G44: 277 | H44: 283.7 | I44: 299 | J44: 311 | K44: 297 | L44: 271 | M44: 322.6 | N44: 359.709 | O44: 342 | AA44: IRENA | AB44: https://www.irena.org/Data/View-data-by-topic/Benefits/Renewable-Energy-Employment-by-Country | AC44: 45352
A45: European Union | D45: 109 | E45: 111 | F45: 98 | G45: 105 | H45: 93 | I45: 200 | J45: 208 | K45: 239 | L45: 229 | M45: 141.6 | N45: 148.3 | O45: 150 | AA45: IRENA | AB45: https://www.irena.org/Data/View-data-by-topic/Benefits/Renewable-Energy-Employment-by-Country | AC45: 45352
A46: Indonesia | F46: 223 | G46: 94.8 | H46: 154.3 | I46: 180 | J46: 237 | K46: 494.4 | L46: 475 | M46: 555.9 | N46: 619.03 | O46: 798.6 | AA46: IRENA | AB46: https://www.irena.org/Data/View-data-by-topic/Benefits/Renewable-Energy-Employment-by-Country | AC46: 45352
A47: Canada | N47: 1.3 | AA47: IRENA | AB47: https://www.irena.org/Data/View-data-by-topic/Benefits/Renewable-Energy-Employment-by-Country | AC47: 45352
A48: UK | N48: 13.196 | AA48: IRENA | AB48: https://www.irena.org/Data/View-data-by-topic/Benefits/Renewable-Energy-Employment-by-Country | AC48: 45352
A49: RoW | D49: =+D50-SUM(D42:D48) -> 225 | E49: =+E50-SUM(E42:E48) -> 262 | F49: =+F50-SUM(F42:F48) -> 269 | G49: =+G50-SUM(G42:G48) -> 309.2 | H49: =+H50-SUM(H42:H48) -> 359 | I49: =+I50-SUM(I42:I48) -> 405 | J49: =+J50-SUM(J42:J48) -> 361 | K49: =+K50-SUM(K42:K48) -> 554.6 | ... O49: =+O50-SUM(O42:O48) -> 458.4 | AA49: IRENA | AB49: https://www.irena.org/Data/View-data-by-topic/Benefits/Renewable-Energy-Employment-by-Country | AC49: 45352
A50: World | D50: 1379 | E50: 1453 | F50: 1788 | G50: 1678 | H50: 1724 | I50: 1930 | J50: 2000 | K50: 2475 | L50: 2411 | M50: 2421 | N50: 2490 | O50: 2803 | AA50: IRENA | AB50: https://www.irena.org/Data/View-data-by-topic/Benefits/Renewable-Energy-Employment-by-Country | AC50: 45352
A51: Biofuels price (US Dollars per gallon) | B51: 2010 | C51: 2011 | D51: 2012 | E51: 2013 | F51: 2014 | G51: 2015 | H51: 2016 | I51: 2017 | J51: 2018 | K51: 2019 | L51: 2020 | M51: 2021 | N51: 2022 | O51: 2023 | P51: 2024 | Q51: 2025 | R51: 2026 | S51: 2027 | T51: 2028 | U51: 2029 | V51: 2030 | W51: 2031 | X51: 2032 | AA51: Source | AB51: URL | AC51: Retrieve Date
A52: Ethanol | B52: 1.9812849 | C52: 2.7735718 | D52: 2.4790667 | E52: 2.5642385 | F52: 2.3795103 | G52: 1.7023 | H52: 1.6962434 | I52: 1.6527111 | J52: 1.4918311 | K52: 1.5153006 | L52: 1.4350499 | M52: 2.4571113 | N52: 2.6781794 | O52: 2.1504929 | P52: 1.977878 | Q52: 1.9975622 | R52: 2.0221674 | S52: 2.0418515 | T52: 2.0562361 | U52: 2.0766773 | V52: 2.1024181 | W52: 2.1277804 | X52: 2.1489787 | AA52: OECD-FAO Agricultural Outlook | AB52: https://www.oecd-ilibrary.org/agriculture-and-food/data/oecd-agriculture-statistics/oecd-fao-agricultural-outlook-edition-2023_3f870a2b-en | AC52: 45352
A53: Biodiesel and Renewable Diesel | B53: 3.5654801 | C53: 5.0300562 | D53: 4.4705722 | E53: 4.2676741 | F53: 3.6483806 | G53: 2.8969762 | H53: 3.0941962 | I53: 3.372424 | J53: 3.2444771 | K53: 3.1233439 | L53: 3.216465 | M53: 5.661463 | N53: 7.1078691 | O53: 5.6970459 | P53: 4.9172509 | Q53: 5.0981936 | R53: 5.2030495 | S53: 5.3393244 | T53: 5.4570507 | U53: 5.5524431 | V53: 5.6671411 | W53: 5.7837318 | X53: 5.9082719 | AA53: OECD-FAO Agricultural Outlook | AB53: https://www.oecd-ilibrary.org/agriculture-and-food/data/oecd-agriculture-statistics/oecd-fao-agricultural-outlook-edition-2023_3f870a2b-en | AC53: 45352
A54: Demand in billion litres per year | B54: 2010 | C54: 2011 | D54: 2012 | E54: 2013 | F54: 2014 | G54: 2015 | H54: 2016 | I54: 2017 | J54: 2018 | K54: 2019 | L54: 2020 | M54: 2021 | N54: 2022 | O54: 2023 | P54: 2024 | Q54: 2025 | R54: 2026 | S54: 2027 | T54: 2028 | U54: 2029 | V54: 2030 | W54: 2031 | X54: 2032 | AA54: Source | AB54: URL | AC54: Retrieve Date
A55: Ethanol | H55: 97.8 | I55: 99.8 | J55: 104.6 | K55: 109.6 | L55: 98 | M55: 103.6 | N55: 105.7 | O55: 108.2 | P55: 110.9 | Q55: 112.3 | R55: 114.1 | S55: 115.5 | T55: 117.5 | AA55: IEA | AB55: https://www.iea.org/reports/renewables-2023/transport-biofuels | AC55: 45352
A56: Biodiesel | H56: 33.3 | I56: 34 | J56: 38.3 | K56: 42.9 | L56: 45.1 | M56: 44.2 | N56: 45.1 | O56: 48 | P56: 50.2 | Q56: 52 | R56: 52.3 | S56: 52.5 | T56: 52.9 | AA56: IEA | AB56: https://www.iea.org/reports/renewables-2023/transport-biofuels | AC56: 45352
A57: Renewable diesel | H57: 4 | I57: 4.9 | J57: 4.8 | K57: 6 | L57: 7.1 | M57: 10.2 | N57: 13.3 | O57: 18.6 | P57: 18.9 | Q57: 21.7 | R57: 23.2 | S57: 25.1 | T57: 26.4 | AA57: IEA | AB57: https://www.iea.org/reports/renewables-2023/transport-biofuels | AC57: 45352
A58: Biojet fuel | H58: 0 | I58: 0 | J58: 0 | K58: 0 | L58: 0 | M58: 0 | N58: 0.2 | O58: 0.6 | P58: 1.8 | Q58: 2.7 | R58: 3.5 | S58: 4.4 | T58: 5.2 | AA58: IEA | AB58: https://www.iea.org/reports/renewables-2023/transport-biofuels | AC58: 45352
A59: Demand in billion litres per year | N59: 2017-2022 | O59: 2023 | P59: 2024 | Q59: 2025 | R59: 2026 | S59: 2027 | T59: 2023-2028 | U59: 2029 | V59: 2030 | W59: 2031 | X59: 2032 | AA59: Source | AB59: URL | AC59: Retrieve Date
A60: Europe | N60: 9 | T60: 4.6 | AA60: IEA | AB60: https://www.iea.org/reports/renewables-2023/transport-biofuels | AC60: 45352
A61: United States | N61: 1.5 | T61: 4.3 | AA61: IEA | AB61: https://www.iea.org/reports/renewables-2023/transport-biofuels | AC61: 45352
A62: Other advanced | N62: 0.8 | P62: =+P52-N52 -> -0.70030132 | Q62: =+P62/N52 -> -0.2614841 | T62: 2.2 | AA62: IEA | AB62: https://www.iea.org/reports/renewables-2023/transport-biofuels | AC62: 45352
A63: Brazil | N63: 3.3 | P63: =+P53-N53 -> -2.1906182 | Q63: =+P63/N53 -> -0.3081962 | T63: 15.7 | AA63: IEA | AB63: https://www.iea.org/reports/renewables-2023/transport-biofuels | AC63: 45352
A64: Indonesia | N64: 7.8 | T64: 4.1 | AA64: IEA | AB64: https://www.iea.org/reports/renewables-2023/transport-biofuels | AC64: 45352
A65: India | N65: 4 | T65: 2.6 | AA65: IEA | AB65: https://www.iea.org/reports/renewables-2023/transport-biofuels | AC65: 45352
A66: Other emerging | N66: 2.8 | T66: 4.7 | AA66: IEA | AB66: https://www.iea.org/reports/renewables-2023/transport-biofuels | AC66: 45352
A67: Advanced economies | N67: =+N60+N61+N62 -> 11.3 | T67: =+T60+T61+T62 -> 11.1 | AA67: IEA | AB67: https://www.iea.org/reports/renewables-2023/transport-biofuels | AC67: 45352
A68: Emerging economies | N68: =+N63+N64+N65+N66 -> 17.9 | T68: =+T63+T64+T65+T66 -> 27.1 | AA68: IEA | AB68: https://www.iea.org/reports/renewables-2023/transport-biofuels | AC68: 45352
A164: Advanced Economies | B164: Europe | C164: 9
A165: Advanced Economies | B165: United States | C165: 1.5
A166: Advanced Economies | B166: Other advanced | C166: 0.8
A167: Emerginf Economies | B167: Brazil | C167: 3.3
A168: Emerginf Economies | B168: Indonesia | C168: 7.8
A169: Emerginf Economies | B169: India | C169: 4
A170: Emerginf Economies | B170: Other emerging | C170: 2.8
B173: 2023
A174: USA P | B174: =O2 -> 19086.277
A175: RoW P | B175: =O10-O2 -> 31663.614
A176: USA C | B176: =O12 -> 18155.157
A177: RoW C | B177: =O20-O12 -> 32612.211
A178: USA E | B178: =O32 -> 1617.4584
A179: RoW E | B179: =O40-O32 -> 3000.074

Sheet Trade
A1: Origin | B1: Destination | C1: Million Gallons | D1: Commodity
A2: United States | B2: Canada | C2: 625.632 | D2: Ethanol
A3: United States | B3: United Kingdom | C3: 160.062 | D3: Ethanol
A4: United States | B4: Netherlands | C4: 114.324 | D4: Ethanol
A5: United States | B5: Korea | C5: 99.456 | D5: Ethanol
A6: United States | B6: India | C6: 83.874 | D6: Ethanol
A7: United States | B7: Colombia | C7: 72.828 | D7: Ethanol
A8: United States | B8: Mexico | C8: 52.836 | D8: Ethanol
A9: United States | B9: Peru | C9: 47.208 | D9: Ethanol
A10: United States | B10: Philippines | C10: 29.904 | D10: Ethanol
A11: United States | B11: Jamaica | C11: 25.788 | D11: Ethanol
A12: United States | B12: RoW | C12: 96.684 | D12: Ethanol
A13: United States | B13: Canada | C13: 230.664 | D13: Biodiesel
... A31: Brazil | B31: Row | C31: 83.031637 | D31: Ethanol

Sheet Bioplastics
A1: Bioplastics
